Workbook

Sheet 🏠 DASHBOARD
A1: 🏦 SAMICIOUS MICROFINANCE ENTERPRISE v16.0
A2: =TEXT(TODAY(),"dddd, mmmm d, yyyy")&" | 10-Agent | Formula-Only | Zero VBA | " -> Saturday, April 25, 2026 | 10-Agent | Formula-Only | Zero VBA |
B4: TOTAL SAVINGS (GHS) | D4: TOTAL WITHDRAWALS | F4: CUSTOMERS | H4: LOAN PORTFOLIO | J4: TOP-UPS
B5: =IFERROR(SUM(DB_Savings!F:F),0) -> 0 | D5: =IFERROR(SUM(DB_Withdrawals!G:G),0) -> 0 | F5: =IFERROR(COUNTA(DB_Customers!A:A)-3,0) -> 500 | H5: =IFERROR(SUM(DB_Loans!E:E),0) -> 0 | J5: =IFERROR(COUNTA('LOAN TOPUP'!B:B)-4,0) -> -3
A6: 🟡 YELLOW = Enter your data | 🔵 BLUE = Auto-computed — DO NOT EDIT | 🔒 WRONG CODE = Agent code mismatch — check code in System_Config
B7: 📋 NEW ACCOUNT | D7: 🗄️ DATABASE | F7: 🏦 MANAGER DASHBOARD | H7: 📊 REPORTS | J7: 🔗 LOAN TOP-UP
B8: 💰 SAVINGS DB | D8: 🏧 WITHDRAWALS DB | F8: 🏦 LOANS DB | H8: ⚙️ SYSTEM CONFIG | J8: 👥 AGENTS DB
A10: ⚡ FULLY AUTOMATED • 10 Agents • 4-Digit Code Security (FIXED BUG v16) • GHS 10 Min Balance • Real-Time DB Sync • Multi-Year • 🔵 Blue = System-Controlled • 🟡 Yellow = User Input • Zero VBA

Sheet DEVELOPER
A1: 🏦 SAMICIOUS MICROFINANCE
A2: ENTERPRISE MANAGEMENT SYSTEM | Developer Information
A4: ABOUT THE DEVELOPER
A6: THIS SAMICIOUS MICROFINANCE MANAGEMENT SYSTEM WAS DESIGNED AND DEVELOPED BY
A7: FRANK ABBAN
A8: IT CONSULTANT
A10: 📞 FOR ALL ENQUIRIES, KINDLY REACH OUT USING ANY OF THE CONTACT NUMBERS BELOW:
A12: 📱 0241911273
A14: 📱 0207530771
A16: 📋 Select any number above → Ctrl+C to copy
A20: SAMICIOUS MICROFINANCE v16.0 | Formula-Driven Architecture | No VBA

Sheet ACKNOWLEDGEMENT
A1: 🏦 SAMICIOUS MICROFINANCE
A2: ENTERPRISE MANAGEMENT SYSTEM | Official Documentation
A4: ACKNOWLEDGEMENT
B6: I give all glory to the Almighty God for His grace, strength, and wisdom that have guided me throughout this journey. Without Him, this work would not have been possible.
B8: I sincerely appreciate Dr. Gabriel Annan, Lecturer at the University of Cape Coast (UCC), for his mentorship, guidance, and invaluable support throughout the development of this system.
B10: I am deeply grateful to Rev. Ebenezer Asibu Dadzie for his spiritual guidance, encouragement, and prayers, which strengthened me greatly.
B12: Special thanks to Mr. Addu Gyamfi, CEO of Samicious Microfinance, for his trust and confidence in my ability to serve as the IT Consultant for this project.
B14: To my beloved wife and children, your patience, sacrifices, and unwavering support have been invaluable. Your love continues to inspire me.
B16: Through your collective support, this vision has been successfully realized.
A18: 📖 BIBLICAL SUPPORT
B20: "I can do all things through Christ who strengthens me."
B22: — Philippians 4:13
A24: A M E N

Sheet 🏦 MANAGER DASHBOARD
A1: 🏦 SAMICIOUS MICROFINANCE — MANAGER COMMAND CENTER v16.0
A2: =UPPER(TEXT(TODAY(),"DDDD, DD MMMM YYYY"))&" | 10 Agents | Real-Time | Formula Engine | Zero VBA" -> SATURDAY, 25 APRIL 2026 | 10 Agents | Real-Time | Formula Engine | Zero VBA
B4: TOTAL SAVINGS (GHS) | D4: TOTAL WITHDRAWALS | F4: NET FLOW (GHS) | H4: CUSTOMERS | J4: LOAN PORTFOLIO | L4: ACTIVE TOP-UPS
B5: =IFERROR(SUM(DB_Savings!$F:$F),0) -> 0 | D5: =IFERROR(SUM(DB_Withdrawals!$G:$G),0) -> 0 | F5: =B5-D5 -> 0 | H5: =IFERROR(COUNTA(DB_Customers!A:A)-3,0) -> 500 | J5: =IFERROR(SUM(DB_Loans!$E:$E),0) -> 0 | L5: =IFERROR(COUNTA('LOAN TOPUP'!B:B)-4,0) -> -3
A7: 📊 REAL-TIME AGENT PERFORMANCE TRACKER
A8: Agent | B8: Today Savings | C8: Today Withdrawals | D8: Net Today | E8: Txns Today | F8: MTD Savings | G8: Active Customers | H8: Target | I8: % Target
A9: Agent 01 | B9: =IFERROR(SUMIFS(DB_Savings!$F:$F,DB_Savings!$D:$D,"Agent 01",DB_Savings!$E:$E,TODAY()),0) -> 0 | C9: =IFERROR(SUMIFS(DB_Withdrawals!$G:$G,DB_Withdrawals!$I:$I,"Agent 01",DB_Withdrawals!$E:$E,TODAY()),0) -> 0 | D9: =B9-C9 -> 0 | E9: =IFERROR(COUNTIFS(DB_Savings!$D:$D,"Agent 01",DB_Savings!$E:$E,TODAY()),0) -> 0 | F9: =IFERROR(SUMIF(DB_Savings!$D:$D,"Agent 01",DB_Savings!$F:$F),0) -> 0 | G9: =IFERROR(COUNTIF(DB_Customers!$G:$G,"Agent 01"),0) -> 0 | H9: 5000 | I9: =IFERROR(B9/H9,0) -> 0
A10: Agent 02 | B10: =IFERROR(SUMIFS(DB_Savings!$F:$F,DB_Savings!$D:$D,"Agent 02",DB_Savings!$E:$E,TODAY()),0) -> 0 | C10: =IFERROR(SUMIFS(DB_Withdrawals!$G:$G,DB_Withdrawals!$I:$I,"Agent 02",DB_Withdrawals!$E:$E,TODAY()),0) -> 0 | D10: =B10-C10 -> 0 | E10: =IFERROR(COUNTIFS(DB_Savings!$D:$D,"Agent 02",DB_Savings!$E:$E,TODAY()),0) -> 0 | F10: =IFERROR(SUMIF(DB_Savings!$D:$D,"Agent 02",DB_Savings!$F:$F),0) -> 0 | G10: =IFERROR(COUNTIF(DB_Customers!$G:$G,"Agent 02"),0) -> 0 | H10: 5000 | I10: =IFERROR(B10/H10,0) -> 0
A11: Agent 03 | B11: =IFERROR(SUMIFS(DB_Savings!$F:$F,DB_Savings!$D:$D,"Agent 03",DB_Savings!$E:$E,TODAY()),0) -> 0 | C11: =IFERROR(SUMIFS(DB_Withdrawals!$G:$G,DB_Withdrawals!$I:$I,"Agent 03",DB_Withdrawals!$E:$E,TODAY()),0) -> 0 | D11: =B11-C11 -> 0 | E11: =IFERROR(COUNTIFS(DB_Savings!$D:$D,"Agent 03",DB_Savings!$E:$E,TODAY()),0) -> 0 | F11: =IFERROR(SUMIF(DB_Savings!$D:$D,"Agent 03",DB_Savings!$F:$F),0) -> 0 | G11: =IFERROR(COUNTIF(DB_Customers!$G:$G,"Agent 03"),0) -> 0 | H11: 5000 | I11: =IFERROR(B11/H11,0) -> 0
A12: Agent 04 | B12: =IFERROR(SUMIFS(DB_Savings!$F:$F,DB_Savings!$D:$D,"Agent 04",DB_Savings!$E:$E,TODAY()),0) -> 0 | C12: =IFERROR(SUMIFS(DB_Withdrawals!$G:$G,DB_Withdrawals!$I:$I,"Agent 04",DB_Withdrawals!$E:$E,TODAY()),0) -> 0 | D12: =B12-C12 -> 0 | E12: =IFERROR(COUNTIFS(DB_Savings!$D:$D,"Agent 04",DB_Savings!$E:$E,TODAY()),0) -> 0 | F12: =IFERROR(SUMIF(DB_Savings!$D:$D,"Agent 04",DB_Savings!$F:$F),0) -> 0 | G12: =IFERROR(COUNTIF(DB_Customers!$G:$G,"Agent 04"),0) -> 0 | H12: 5000 | I12: =IFERROR(B12/H12,0) -> 0
A13: Agent 05 | B13: =IFERROR(SUMIFS(DB_Savings!$F:$F,DB_Savings!$D:$D,"Agent 05",DB_Savings!$E:$E,TODAY()),0) -> 0 | C13: =IFERROR(SUMIFS(DB_Withdrawals!$G:$G,DB_Withdrawals!$I:$I,"Agent 05",DB_Withdrawals!$E:$E,TODAY()),0) -> 0 | D13: =B13-C13 -> 0 | E13: =IFERROR(COUNTIFS(DB_Savings!$D:$D,"Agent 05",DB_Savings!$E:$E,TODAY()),0) -> 0 | F13: =IFERROR(SUMIF(DB_Savings!$D:$D,"Agent 05",DB_Savings!$F:$F),0) -> 0 | G13: =IFERROR(COUNTIF(DB_Customers!$G:$G,"Agent 05"),0) -> 0 | H13: 5000 | I13: =IFERROR(B13/H13,0) -> 0
A14: Agent 06 | B14: =IFERROR(SUMIFS(DB_Savings!$F:$F,DB_Savings!$D:$D,"Agent 06",DB_Savings!$E:$E,TODAY()),0) -> 0 | C14: =IFERROR(SUMIFS(DB_Withdrawals!$G:$G,DB_Withdrawals!$I:$I,"Agent 06",DB_Withdrawals!$E:$E,TODAY()),0) -> 0 | D14: =B14-C14 -> 0 | E14: =IFERROR(COUNTIFS(DB_Savings!$D:$D,"Agent 06",DB_Savings!$E:$E,TODAY()),0) -> 0 | F14: =IFERROR(SUMIF(DB_Savings!$D:$D,"Agent 06",DB_Savings!$F:$F),0) -> 0 | G14: =IFERROR(COUNTIF(DB_Customers!$G:$G,"Agent 06"),0) -> 0 | H14: 5000 | I14: =IFERROR(B14/H14,0) -> 0
A15: Agent 07 | B15: =IFERROR(SUMIFS(DB_Savings!$F:$F,DB_Savings!$D:$D,"Agent 07",DB_Savings!$E:$E,TODAY()),0) -> 0 | C15: =IFERROR(SUMIFS(DB_Withdrawals!$G:$G,DB_Withdrawals!$I:$I,"Agent 07",DB_Withdrawals!$E:$E,TODAY()),0) -> 0 | D15: =B15-C15 -> 0 | E15: =IFERROR(COUNTIFS(DB_Savings!$D:$D,"Agent 07",DB_Savings!$E:$E,TODAY()),0) -> 0 | F15: =IFERROR(SUMIF(DB_Savings!$D:$D,"Agent 07",DB_Savings!$F:$F),0) -> 0 | G15: =IFERROR(COUNTIF(DB_Customers!$G:$G,"Agent 07"),0) -> 0 | H15: 5000 | I15: =IFERROR(B15/H15,0) -> 0
A16: Agent 08 | B16: =IFERROR(SUMIFS(DB_Savings!$F:$F,DB_Savings!$D:$D,"Agent 08",DB_Savings!$E:$E,TODAY()),0) -> 0 | C16: =IFERROR(SUMIFS(DB_Withdrawals!$G:$G,DB_Withdrawals!$I:$I,"Agent 08",DB_Withdrawals!$E:$E,TODAY()),0) -> 0 | D16: =B16-C16 -> 0 | E16: =IFERROR(COUNTIFS(DB_Savings!$D:$D,"Agent 08",DB_Savings!$E:$E,TODAY()),0) -> 0 | F16: =IFERROR(SUMIF(DB_Savings!$D:$D,"Agent 08",DB_Savings!$F:$F),0) -> 0 | G16: =IFERROR(COUNTIF(DB_Customers!$G:$G,"Agent 08"),0) -> 0 | H16: 5000 | I16: =IFERROR(B16/H16,0) -> 0
A17: Agent 09 | B17: =IFERROR(SUMIFS(DB_Savings!$F:$F,DB_Savings!$D:$D,"Agent 09",DB_Savings!$E:$E,TODAY()),0) -> 0 | C17: =IFERROR(SUMIFS(DB_Withdrawals!$G:$G,DB_Withdrawals!$I:$I,"Agent 09",DB_Withdrawals!$E:$E,TODAY()),0) -> 0 | D17: =B17-C17 -> 0 | E17: =IFERROR(COUNTIFS(DB_Savings!$D:$D,"Agent 09",DB_Savings!$E:$E,TODAY()),0) -> 0 | F17: =IFERROR(SUMIF(DB_Savings!$D:$D,"Agent 09",DB_Savings!$F:$F),0) -> 0 | G17: =IFERROR(COUNTIF(DB_Customers!$G:$G,"Agent 09"),0) -> 0 | H17: 5000 | I17: =IFERROR(B17/H17,0) -> 0
A18: Agent 10 | B18: =IFERROR(SUMIFS(DB_Savings!$F:$F,DB_Savings!$D:$D,"Agent 10",DB_Savings!$E:$E,TODAY()),0) -> 0 | C18: =IFERROR(SUMIFS(DB_Withdrawals!$G:$G,DB_Withdrawals!$I:$I,"Agent 10",DB_Withdrawals!$E:$E,TODAY()),0) -> 0 | D18: =B18-C18 -> 0 | E18: =IFERROR(COUNTIFS(DB_Savings!$D:$D,"Agent 10",DB_Savings!$E:$E,TODAY()),0) -> 0 | F18: =IFERROR(SUMIF(DB_Savings!$D:$D,"Agent 10",DB_Savings!$F:$F),0) -> 0 | G18: =IFERROR(COUNTIF(DB_Customers!$G:$G,"Agent 10"),0) -> 0 | H18: 5000 | I18: =IFERROR(B18/H18,0) -> 0
A19: TOTALS | B19: =SUM(B9:B18) -> 0 | C19: =SUM(C9:C18) -> 0 | D19: =SUM(D9:D18) -> 0 | E19: =SUM(E9:E18) -> 0 | F19: =SUM(F9:F18) -> 0 | G19: =SUM(G9:G18) -> 0 | H19: =SUM(H9:H18) -> 50000 | I19: =IFERROR(B19/H19,0) -> 0

Sheet NEW ACCOUNT
A1: 👤 NEW CUSTOMER ACCOUNT REGISTRATION
A2: ✅ AUTOMATED — Type customer details in 🟡 YELLOW cells. Account Number (col A) and Date (col I) are 🔵 BLUE = auto-generated. DATABASE reads this table live. No copy-paste. No buttons.
A3: ⚠️ GHS 10.00 MINIMUM OPENING BALANCE ENFORCED | Accounts below GHS 10 are flagged ⚠️ Below Min Balance
A4: Account No. | B4: Customer Name | C4: Date of Birth | D4: Phone Number | E4: Location | F4: Occupation | G4: Assigned Agent | H4: Opening Balance (GHS) | I4: Date Registered | J4: Status
A5: =IF(B5="","","ACC"&TEXT(ROW()-4,"0000")) | I5: =IF(B5="","",TEXT(TODAY(),"dd/mm/yyyy")) | J5: =IF(B5="","",IF(ISNUMBER(H5),IF(H5>=10,"✅ Active","⚠️ Below Min Balance"),"Pending"))
A6: =IF(B6="","","ACC"&TEXT(ROW()-4,"0000")) | I6: =IF(B6="","",TEXT(TODAY(),"dd/mm/yyyy")) | J6: =IF(B6="","",IF(ISNUMBER(H6),IF(H6>=10,"✅ Active","⚠️ Below Min Balance"),"Pending"))
A7: =IF(B7="","","ACC"&TEXT(ROW()-4,"0000")) | I7: =IF(B7="","",TEXT(TODAY(),"dd/mm/yyyy")) | J7: =IF(B7="","",IF(ISNUMBER(H7),IF(H7>=10,"✅ Active","⚠️ Below Min Balance"),"Pending"))
A8: =IF(B8="","","ACC"&TEXT(ROW()-4,"0000")) | I8: =IF(B8="","",TEXT(TODAY(),"dd/mm/yyyy")) | J8: =IF(B8="","",IF(ISNUMBER(H8),IF(H8>=10,"✅ Active","⚠️ Below Min Balance"),"Pending"))
A9: =IF(B9="","","ACC"&TEXT(ROW()-4,"0000")) | I9: =IF(B9="","",TEXT(TODAY(),"dd/mm/yyyy")) | J9: =IF(B9="","",IF(ISNUMBER(H9),IF(H9>=10,"✅ Active","⚠️ Below Min Balance"),"Pending"))
A10: =IF(B10="","","ACC"&TEXT(ROW()-4,"0000")) | I10: =IF(B10="","",TEXT(TODAY(),"dd/mm/yyyy")) | J10: =IF(B10="","",IF(ISNUMBER(H10),IF(H10>=10,"✅ Active","⚠️ Below Min Balance"),"Pending"))
A11: =IF(B11="","","ACC"&TEXT(ROW()-4,"0000")) | I11: =IF(B11="","",TEXT(TODAY(),"dd/mm/yyyy")) | J11: =IF(B11="","",IF(ISNUMBER(H11),IF(H11>=10,"✅ Active","⚠️ Below Min Balance"),"Pending"))
A12: =IF(B12="","","ACC"&TEXT(ROW()-4,"0000")) | I12: =IF(B12="","",TEXT(TODAY(),"dd/mm/yyyy")) | J12: =IF(B12="","",IF(ISNUMBER(H12),IF(H12>=10,"✅ Active","⚠️ Below Min Balance"),"Pending"))
A13: =IF(B13="","","ACC"&TEXT(ROW()-4,"0000")) | I13: =IF(B13="","",TEXT(TODAY(),"dd/mm/yyyy")) | J13: =IF(B13="","",IF(ISNUMBER(H13),IF(H13>=10,"✅ Active","⚠️ Below Min Balance"),"Pending"))
A14: =IF(B14="","","ACC"&TEXT(ROW()-4,"0000")) | I14: =IF(B14="","",TEXT(TODAY(),"dd/mm/yyyy")) | J14: =IF(B14="","",IF(ISNUMBER(H14),IF(H14>=10,"✅ Active","⚠️ Below Min Balance"),"Pending"))
A15: =IF(B15="","","ACC"&TEXT(ROW()-4,"0000")) | I15: =IF(B15="","",TEXT(TODAY(),"dd/mm/yyyy")) | J15: =IF(B15="","",IF(ISNUMBER(H15),IF(H15>=10,"✅ Active","⚠️ Below Min Balance"),"Pending"))
A16: =IF(B16="","","ACC"&TEXT(ROW()-4,"0000")) | I16: =IF(B16="","",TEXT(TODAY(),"dd/mm/yyyy")) | J16: =IF(B16="","",IF(ISNUMBER(H16),IF(H16>=10,"✅ Active","⚠️ Below Min Balance"),"Pending"))
... A504: =IF(B504="","","ACC"&TEXT(ROW()-4,"0000")) | I504: =IF(B504="","",TEXT(TODAY(),"dd/mm/yyyy")) | J504: =IF(B504="","",IF(ISNUMBER(H504),IF(H504>=10,"✅ Active","⚠️ Below Min Balance"),"Pending"))
A506: 🟡 Yellow = Enter data here | 🔵 Blue = Auto-generated (DO NOT EDIT)

Sheet DB_Customers
A1: 🗄️ CUSTOMER DATABASE — Central Source of Truth (All columns formula-driven, READ-ONLY)
A2: 🔵 ALL CELLS AUTO-COMPUTED — Do NOT type here. Columns A–J mirror NEW ACCOUNT. Columns K–N computed from all transactions.
A3: Account No. | B3: Full Name | C3: Date of Birth | D3: Phone Number | E3: Location | F3: Occupation | G3: Assigned Agent | H3: Opening Balance (GHS) | I3: Date Registered | J3: Status | K3: Total Savings (GHS) | L3: Total Withdrawals (GHS) | M3: Current Balance (GHS) | N3: Withdrawable Balance (GHS)
A4: ='NEW ACCOUNT'!A5 | B4: =IF('NEW ACCOUNT'!A5="","",'NEW ACCOUNT'!B5) | C4: =IF('NEW ACCOUNT'!A5="","",'NEW ACCOUNT'!C5) | D4: =IF('NEW ACCOUNT'!A5="","",'NEW ACCOUNT'!D5) | E4: =IF('NEW ACCOUNT'!A5="","",'NEW ACCOUNT'!E5) | F4: =IF('NEW ACCOUNT'!A5="","",'NEW ACCOUNT'!F5) | G4: =IF('NEW ACCOUNT'!A5="","",'NEW ACCOUNT'!G5) | H4: =IF('NEW ACCOUNT'!A5="","",'NEW ACCOUNT'!H5) | I4: =IF('NEW ACCOUNT'!A5="","",'NEW ACCOUNT'!I5) | J4: =IF('NEW ACCOUNT'!A5="","",'NEW ACCOUNT'!J5) | K4: =IFERROR(IF(A4="","",SUMIF(DB_Savings!$A:$A,A4,DB_Savings!$F:$F)),"") | L4: =IFERROR(IF(A4="","",SUMIF(DB_Withdrawals!$A:$A,A4,DB_Withdrawals!$G:$G)),"") | M4: =IFERROR(IF(A4="","",IFERROR(VALUE(H4),0)+IFERROR(SUMIF(DB_Savings!$A:$A,A4,DB_Savings!$F:$F),0)-IFERROR(SUMIF(DB_Withdrawals!$A:$A,A4,DB_Withdrawals!$G:$G),0)),"") | N4: =IFERROR(IF(A4="","",MAX(0,M4-System_Config!$B$9)),"")
A5: ='NEW ACCOUNT'!A6 | B5: =IF('NEW ACCOUNT'!A6="","",'NEW ACCOUNT'!B6) | C5: =IF('NEW ACCOUNT'!A6="","",'NEW ACCOUNT'!C6) | D5: =IF('NEW ACCOUNT'!A6="","",'NEW ACCOUNT'!D6) | E5: =IF('NEW ACCOUNT'!A6="","",'NEW ACCOUNT'!E6) | F5: =IF('NEW ACCOUNT'!A6="","",'NEW ACCOUNT'!F6) | G5: =IF('NEW ACCOUNT'!A6="","",'NEW ACCOUNT'!G6) | H5: =IF('NEW ACCOUNT'!A6="","",'NEW ACCOUNT'!H6) | I5: =IF('NEW ACCOUNT'!A6="","",'NEW ACCOUNT'!I6) | J5: =IF('NEW ACCOUNT'!A6="","",'NEW ACCOUNT'!J6) | K5: =IFERROR(IF(A5="","",SUMIF(DB_Savings!$A:$A,A5,DB_Savings!$F:$F)),"") | L5: =IFERROR(IF(A5="","",SUMIF(DB_Withdrawals!$A:$A,A5,DB_Withdrawals!$G:$G)),"") | M5: =IFERROR(IF(A5="","",IFERROR(VALUE(H5),0)+IFERROR(SUMIF(DB_Savings!$A:$A,A5,DB_Savings!$F:$F),0)-IFERROR(SUMIF(DB_Withdrawals!$A:$A,A5,DB_Withdrawals!$G:$G),0)),"") | N5: =IFERROR(IF(A5="","",MAX(0,M5-System_Config!$B$9)),"")
A6: ='NEW ACCOUNT'!A7 | B6: =IF('NEW ACCOUNT'!A7="","",'NEW ACCOUNT'!B7) | C6: =IF('NEW ACCOUNT'!A7="","",'NEW ACCOUNT'!C7) | D6: =IF('NEW ACCOUNT'!A7="","",'NEW ACCOUNT'!D7) | E6: =IF('NEW ACCOUNT'!A7="","",'NEW ACCOUNT'!E7) | F6: =IF('NEW ACCOUNT'!A7="","",'NEW ACCOUNT'!F7) | G6: =IF('NEW ACCOUNT'!A7="","",'NEW ACCOUNT'!G7) | H6: =IF('NEW ACCOUNT'!A7="","",'NEW ACCOUNT'!H7) | I6: =IF('NEW ACCOUNT'!A7="","",'NEW ACCOUNT'!I7) | J6: =IF('NEW ACCOUNT'!A7="","",'NEW ACCOUNT'!J7) | K6: =IFERROR(IF(A6="","",SUMIF(DB_Savings!$A:$A,A6,DB_Savings!$F:$F)),"") | L6: =IFERROR(IF(A6="","",SUMIF(DB_Withdrawals!$A:$A,A6,DB_Withdrawals!$G:$G)),"") | M6: =IFERROR(IF(A6="","",IFERROR(VALUE(H6),0)+IFERROR(SUMIF(DB_Savings!$A:$A,A6,DB_Savings!$F:$F),0)-IFERROR(SUMIF(DB_Withdrawals!$A:$A,A6,DB_Withdrawals!$G:$G),0)),"") | N6: =IFERROR(IF(A6="","",MAX(0,M6-System_Config!$B$9)),"")
A7: ='NEW ACCOUNT'!A8 | B7: =IF('NEW ACCOUNT'!A8="","",'NEW ACCOUNT'!B8) | C7: =IF('NEW ACCOUNT'!A8="","",'NEW ACCOUNT'!C8) | D7: =IF('NEW ACCOUNT'!A8="","",'NEW ACCOUNT'!D8) | E7: =IF('NEW ACCOUNT'!A8="","",'NEW ACCOUNT'!E8) | F7: =IF('NEW ACCOUNT'!A8="","",'NEW ACCOUNT'!F8) | G7: =IF('NEW ACCOUNT'!A8="","",'NEW ACCOUNT'!G8) | H7: =IF('NEW ACCOUNT'!A8="","",'NEW ACCOUNT'!H8) | I7: =IF('NEW ACCOUNT'!A8="","",'NEW ACCOUNT'!I8) | J7: =IF('NEW ACCOUNT'!A8="","",'NEW ACCOUNT'!J8) | K7: =IFERROR(IF(A7="","",SUMIF(DB_Savings!$A:$A,A7,DB_Savings!$F:$F)),"") | L7: =IFERROR(IF(A7="","",SUMIF(DB_Withdrawals!$A:$A,A7,DB_Withdrawals!$G:$G)),"") | M7: =IFERROR(IF(A7="","",IFERROR(VALUE(H7),0)+IFERROR(SUMIF(DB_Savings!$A:$A,A7,DB_Savings!$F:$F),0)-IFERROR(SUMIF(DB_Withdrawals!$A:$A,A7,DB_Withdrawals!$G:$G),0)),"") | N7: =IFERROR(IF(A7="","",MAX(0,M7-System_Config!$B$9)),"")
A8: ='NEW ACCOUNT'!A9 | B8: =IF('NEW ACCOUNT'!A9="","",'NEW ACCOUNT'!B9) | C8: =IF('NEW ACCOUNT'!A9="","",'NEW ACCOUNT'!C9) | D8: =IF('NEW ACCOUNT'!A9="","",'NEW ACCOUNT'!D9) | E8: =IF('NEW ACCOUNT'!A9="","",'NEW ACCOUNT'!E9) | F8: =IF('NEW ACCOUNT'!A9="","",'NEW ACCOUNT'!F9) | G8: =IF('NEW ACCOUNT'!A9="","",'NEW ACCOUNT'!G9) | H8: =IF('NEW ACCOUNT'!A9="","",'NEW ACCOUNT'!H9) | I8: =IF('NEW ACCOUNT'!A9="","",'NEW ACCOUNT'!I9) | J8: =IF('NEW ACCOUNT'!A9="","",'NEW ACCOUNT'!J9) | K8: =IFERROR(IF(A8="","",SUMIF(DB_Savings!$A:$A,A8,DB_Savings!$F:$F)),"") | L8: =IFERROR(IF(A8="","",SUMIF(DB_Withdrawals!$A:$A,A8,DB_Withdrawals!$G:$G)),"") | M8: =IFERROR(IF(A8="","",IFERROR(VALUE(H8),0)+IFERROR(SUMIF(DB_Savings!$A:$A,A8,DB_Savings!$F:$F),0)-IFERROR(SUMIF(DB_Withdrawals!$A:$A,A8,DB_Withdrawals!$G:$G),0)),"") | N8: =IFERROR(IF(A8="","",MAX(0,M8-System_Config!$B$9)),"")
A9: ='NEW ACCOUNT'!A10 | B9: =IF('NEW ACCOUNT'!A10="","",'NEW ACCOUNT'!B10) | C9: =IF('NEW ACCOUNT'!A10="","",'NEW ACCOUNT'!C10) | D9: =IF('NEW ACCOUNT'!A10="","",'NEW ACCOUNT'!D10) | E9: =IF('NEW ACCOUNT'!A10="","",'NEW ACCOUNT'!E10) | F9: =IF('NEW ACCOUNT'!A10="","",'NEW ACCOUNT'!F10) | G9: =IF('NEW ACCOUNT'!A10="","",'NEW ACCOUNT'!G10) | H9: =IF('NEW ACCOUNT'!A10="","",'NEW ACCOUNT'!H10) | I9: =IF('NEW ACCOUNT'!A10="","",'NEW ACCOUNT'!I10) | J9: =IF('NEW ACCOUNT'!A10="","",'NEW ACCOUNT'!J10) | K9: =IFERROR(IF(A9="","",SUMIF(DB_Savings!$A:$A,A9,DB_Savings!$F:$F)),"") | L9: =IFERROR(IF(A9="","",SUMIF(DB_Withdrawals!$A:$A,A9,DB_Withdrawals!$G:$G)),"") | M9: =IFERROR(IF(A9="","",IFERROR(VALUE(H9),0)+IFERROR(SUMIF(DB_Savings!$A:$A,A9,DB_Savings!$F:$F),0)-IFERROR(SUMIF(DB_Withdrawals!$A:$A,A9,DB_Withdrawals!$G:$G),0)),"") | N9: =IFERROR(IF(A9="","",MAX(0,M9-System_Config!$B$9)),"")
A10: ='NEW ACCOUNT'!A11 | B10: =IF('NEW ACCOUNT'!A11="","",'NEW ACCOUNT'!B11) | C10: =IF('NEW ACCOUNT'!A11="","",'NEW ACCOUNT'!C11) | D10: =IF('NEW ACCOUNT'!A11="","",'NEW ACCOUNT'!D11) | E10: =IF('NEW ACCOUNT'!A11="","",'NEW ACCOUNT'!E11) | F10: =IF('NEW ACCOUNT'!A11="","",'NEW ACCOUNT'!F11) | G10: =IF('NEW ACCOUNT'!A11="","",'NEW ACCOUNT'!G11) | H10: =IF('NEW ACCOUNT'!A11="","",'NEW ACCOUNT'!H11) | I10: =IF('NEW ACCOUNT'!A11="","",'NEW ACCOUNT'!I11) | J10: =IF('NEW ACCOUNT'!A11="","",'NEW ACCOUNT'!J11) | K10: =IFERROR(IF(A10="","",SUMIF(DB_Savings!$A:$A,A10,DB_Savings!$F:$F)),"") | L10: =IFERROR(IF(A10="","",SUMIF(DB_Withdrawals!$A:$A,A10,DB_Withdrawals!$G:$G)),"") | M10: =IFERROR(IF(A10="","",IFERROR(VALUE(H10),0)+IFERROR(SUMIF(DB_Savings!$A:$A,A10,DB_Savings!$F:$F),0)-IFERROR(SUMIF(DB_Withdrawals!$A:$A,A10,DB_Withdrawals!$G:$G),0)),"") | N10: =IFERROR(IF(A10="","",MAX(0,M10-System_Config!$B$9)),"")
A11: ='NEW ACCOUNT'!A12 | B11: =IF('NEW ACCOUNT'!A12="","",'NEW ACCOUNT'!B12) | C11: =IF('NEW ACCOUNT'!A12="","",'NEW ACCOUNT'!C12) | D11: =IF('NEW ACCOUNT'!A12="","",'NEW ACCOUNT'!D12) | E11: =IF('NEW ACCOUNT'!A12="","",'NEW ACCOUNT'!E12) | F11: =IF('NEW ACCOUNT'!A12="","",'NEW ACCOUNT'!F12) | G11: =IF('NEW ACCOUNT'!A12="","",'NEW ACCOUNT'!G12) | H11: =IF('NEW ACCOUNT'!A12="","",'NEW ACCOUNT'!H12) | I11: =IF('NEW ACCOUNT'!A12="","",'NEW ACCOUNT'!I12) | J11: =IF('NEW ACCOUNT'!A12="","",'NEW ACCOUNT'!J12) | K11: =IFERROR(IF(A11="","",SUMIF(DB_Savings!$A:$A,A11,DB_Savings!$F:$F)),"") | L11: =IFERROR(IF(A11="","",SUMIF(DB_Withdrawals!$A:$A,A11,DB_Withdrawals!$G:$G)),"") | M11: =IFERROR(IF(A11="","",IFERROR(VALUE(H11),0)+IFERROR(SUMIF(DB_Savings!$A:$A,A11,DB_Savings!$F:$F),0)-IFERROR(SUMIF(DB_Withdrawals!$A:$A,A11,DB_Withdrawals!$G:$G),0)),"") | N11: =IFERROR(IF(A11="","",MAX(0,M11-System_Config!$B$9)),"")
A12: ='NEW ACCOUNT'!A13 | B12: =IF('NEW ACCOUNT'!A13="","",'NEW ACCOUNT'!B13) | C12: =IF('NEW ACCOUNT'!A13="","",'NEW ACCOUNT'!C13) | D12: =IF('NEW ACCOUNT'!A13="","",'NEW ACCOUNT'!D13) | E12: =IF('NEW ACCOUNT'!A13="","",'NEW ACCOUNT'!E13) | F12: =IF('NEW ACCOUNT'!A13="","",'NEW ACCOUNT'!F13) | G12: =IF('NEW ACCOUNT'!A13="","",'NEW ACCOUNT'!G13) | H12: =IF('NEW ACCOUNT'!A13="","",'NEW ACCOUNT'!H13) | I12: =IF('NEW ACCOUNT'!A13="","",'NEW ACCOUNT'!I13) | J12: =IF('NEW ACCOUNT'!A13="","",'NEW ACCOUNT'!J13) | K12: =IFERROR(IF(A12="","",SUMIF(DB_Savings!$A:$A,A12,DB_Savings!$F:$F)),"") | L12: =IFERROR(IF(A12="","",SUMIF(DB_Withdrawals!$A:$A,A12,DB_Withdrawals!$G:$G)),"") | M12: =IFERROR(IF(A12="","",IFERROR(VALUE(H12),0)+IFERROR(SUMIF(DB_Savings!$A:$A,A12,DB_Savings!$F:$F),0)-IFERROR(SUMIF(DB_Withdrawals!$A:$A,A12,DB_Withdrawals!$G:$G),0)),"") | N12: =IFERROR(IF(A12="","",MAX(0,M12-System_Config!$B$9)),"")
A13: ='NEW ACCOUNT'!A14 | B13: =IF('NEW ACCOUNT'!A14="","",'NEW ACCOUNT'!B14) | C13: =IF('NEW ACCOUNT'!A14="","",'NEW ACCOUNT'!C14) | D13: =IF('NEW ACCOUNT'!A14="","",'NEW ACCOUNT'!D14) | E13: =IF('NEW ACCOUNT'!A14="","",'NEW ACCOUNT'!E14) | F13: =IF('NEW ACCOUNT'!A14="","",'NEW ACCOUNT'!F14) | G13: =IF('NEW ACCOUNT'!A14="","",'NEW ACCOUNT'!G14) | H13: =IF('NEW ACCOUNT'!A14="","",'NEW ACCOUNT'!H14) | I13: =IF('NEW ACCOUNT'!A14="","",'NEW ACCOUNT'!I14) | J13: =IF('NEW ACCOUNT'!A14="","",'NEW ACCOUNT'!J14) | K13: =IFERROR(IF(A13="","",SUMIF(DB_Savings!$A:$A,A13,DB_Savings!$F:$F)),"") | L13: =IFERROR(IF(A13="","",SUMIF(DB_Withdrawals!$A:$A,A13,DB_Withdrawals!$G:$G)),"") | M13: =IFERROR(IF(A13="","",IFERROR(VALUE(H13),0)+IFERROR(SUMIF(DB_Savings!$A:$A,A13,DB_Savings!$F:$F),0)-IFERROR(SUMIF(DB_Withdrawals!$A:$A,A13,DB_Withdrawals!$G:$G),0)),"") | N13: =IFERROR(IF(A13="","",MAX(0,M13-System_Config!$B$9)),"")
A14: ='NEW ACCOUNT'!A15 | B14: =IF('NEW ACCOUNT'!A15="","",'NEW ACCOUNT'!B15) | C14: =IF('NEW ACCOUNT'!A15="","",'NEW ACCOUNT'!C15) | D14: =IF('NEW ACCOUNT'!A15="","",'NEW ACCOUNT'!D15) | E14: =IF('NEW ACCOUNT'!A15="","",'NEW ACCOUNT'!E15) | F14: =IF('NEW ACCOUNT'!A15="","",'NEW ACCOUNT'!F15) | G14: =IF('NEW ACCOUNT'!A15="","",'NEW ACCOUNT'!G15) | H14: =IF('NEW ACCOUNT'!A15="","",'NEW ACCOUNT'!H15) | I14: =IF('NEW ACCOUNT'!A15="","",'NEW ACCOUNT'!I15) | J14: =IF('NEW ACCOUNT'!A15="","",'NEW ACCOUNT'!J15) | K14: =IFERROR(IF(A14="","",SUMIF(DB_Savings!$A:$A,A14,DB_Savings!$F:$F)),"") | L14: =IFERROR(IF(A14="","",SUMIF(DB_Withdrawals!$A:$A,A14,DB_Withdrawals!$G:$G)),"") | M14: =IFERROR(IF(A14="","",IFERROR(VALUE(H14),0)+IFERROR(SUMIF(DB_Savings!$A:$A,A14,DB_Savings!$F:$F),0)-IFERROR(SUMIF(DB_Withdrawals!$A:$A,A14,DB_Withdrawals!$G:$G),0)),"") | N14: =IFERROR(IF(A14="","",MAX(0,M14-System_Config!$B$9)),"")
A15: ='NEW ACCOUNT'!A16 | B15: =IF('NEW ACCOUNT'!A16="","",'NEW ACCOUNT'!B16) | C15: =IF('NEW ACCOUNT'!A16="","",'NEW ACCOUNT'!C16) | D15: =IF('NEW ACCOUNT'!A16="","",'NEW ACCOUNT'!D16) | E15: =IF('NEW ACCOUNT'!A16="","",'NEW ACCOUNT'!E16) | F15: =IF('NEW ACCOUNT'!A16="","",'NEW ACCOUNT'!F16) | G15: =IF('NEW ACCOUNT'!A16="","",'NEW ACCOUNT'!G16) | H15: =IF('NEW ACCOUNT'!A16="","",'NEW ACCOUNT'!H16) | I15: =IF('NEW ACCOUNT'!A16="","",'NEW ACCOUNT'!I16) | J15: =IF('NEW ACCOUNT'!A16="","",'NEW ACCOUNT'!J16) | K15: =IFERROR(IF(A15="","",SUMIF(DB_Savings!$A:$A,A15,DB_Savings!$F:$F)),"") | L15: =IFERROR(IF(A15="","",SUMIF(DB_Withdrawals!$A:$A,A15,DB_Withdrawals!$G:$G)),"") | M15: =IFERROR(IF(A15="","",IFERROR(VALUE(H15),0)+IFERROR(SUMIF(DB_Savings!$A:$A,A15,DB_Savings!$F:$F),0)-IFERROR(SUMIF(DB_Withdrawals!$A:$A,A15,DB_Withdrawals!$G:$G),0)),"") | N15: =IFERROR(IF(A15="","",MAX(0,M15-System_Config!$B$9)),"")
... A503: ='NEW ACCOUNT'!A504 | B503: =IF('NEW ACCOUNT'!A504="","",'NEW ACCOUNT'!B504) | C503: =IF('NEW ACCOUNT'!A504="","",'NEW ACCOUNT'!C504) | D503: =IF('NEW ACCOUNT'!A504="","",'NEW ACCOUNT'!D504) | E503: =IF('NEW ACCOUNT'!A504="","",'NEW ACCOUNT'!E504) | F503: =IF('NEW ACCOUNT'!A504="","",'NEW ACCOUNT'!F504) | G503: =IF('NEW ACCOUNT'!A504="","",'NEW ACCOUNT'!G504) | H503: =IF('NEW ACCOUNT'!A504="","",'NEW ACCOUNT'!H504) | I503: =IF('NEW ACCOUNT'!A504="","",'NEW ACCOUNT'!I504) | J503: =IF('NEW ACCOUNT'!A504="","",'NEW ACCOUNT'!J504) | K503: =IFERROR(IF(A503="","",SUMIF(DB_Savings!$A:$A,A503,DB_Savings!$F:$F)),"") | L503: =IFERROR(IF(A503="","",SUMIF(DB_Withdrawals!$A:$A,A503,DB_Withdrawals!$G:$G)),"") | M503: =IFERROR(IF(A503="","",IFERROR(VALUE(H503),0)+IFERROR(SUMIF(DB_Savings!$A:$A,A503,DB_Savings!$F:$F),0)-IFERROR(SUMIF(DB_Withdrawals!$A:$A,A503,DB_Withdrawals!$G:$G),0)),"") | N503: =IFERROR(IF(A503="","",MAX(0,M503-System_Config!$B$9)),"")

Sheet DB_Savings
A1: 💰 SAVINGS DATABASE — All 10 Agents Combined (Formula-Driven, READ-ONLY)
A2: 🔵 DO NOT ENTER DATA HERE — This sheet auto-aggregates from all Agent Savings sheets. Rows 4–203 = Agent 01, 204–403 = Agent 02, …, 1804–2003 = Agent 10.
A3: Account_No | B3: Transaction_ID | C3: Customer_Name | D3: Agent | E3: Date | F3: Amount_GHS | G3: New_Balance | H3: Status | I3: Saved_At | J3: Notes | K3: Year
A4: =IF(Agent01_Savings!A9="","",Agent01_Savings!A9) | B4: =IF(Agent01_Savings!A9="","","SV"&TEXT(4-3,"0000")&"-"&TEXT(TODAY(),"YYYYMMDD")) | C4: =IF(Agent01_Savings!A9="","",Agent01_Savings!B9) | D4: =IF(Agent01_Savings!A9="","",Agent01_Savings!G9) | E4: =IF(Agent01_Savings!A9="","",Agent01_Savings!D9) | F4: =IF(Agent01_Savings!A9="","",Agent01_Savings!E9) | G4: =IF(Agent01_Savings!A9="","",Agent01_Savings!F9) | H4: =IF(Agent01_Savings!A9="","",Agent01_Savings!I9) | I4: =IF(Agent01_Savings!A9="","",Agent01_Savings!J9) | J4: =IF(Agent01_Savings!A9="","",Agent01_Savings!K9) | K4: =IFERROR(IF(Agent01_Savings!A9="","",YEAR(Agent01_Savings!D9)),"")
A5: =IF(Agent01_Savings!A10="","",Agent01_Savings!A10) | B5: =IF(Agent01_Savings!A10="","","SV"&TEXT(5-3,"0000")&"-"&TEXT(TODAY(),"YYYYMMDD")) | C5: =IF(Agent01_Savings!A10="","",Agent01_Savings!B10) | D5: =IF(Agent01_Savings!A10="","",Agent01_Savings!G10) | E5: =IF(Agent01_Savings!A10="","",Agent01_Savings!D10) | F5: =IF(Agent01_Savings!A10="","",Agent01_Savings!E10) | G5: =IF(Agent01_Savings!A10="","",Agent01_Savings!F10) | H5: =IF(Agent01_Savings!A10="","",Agent01_Savings!I10) | I5: =IF(Agent01_Savings!A10="","",Agent01_Savings!J10) | J5: =IF(Agent01_Savings!A10="","",Agent01_Savings!K10) | K5: =IFERROR(IF(Agent01_Savings!A10="","",YEAR(Agent01_Savings!D10)),"")
A6: =IF(Agent01_Savings!A11="","",Agent01_Savings!A11) | B6: =IF(Agent01_Savings!A11="","","SV"&TEXT(6-3,"0000")&"-"&TEXT(TODAY(),"YYYYMMDD")) | C6: =IF(Agent01_Savings!A11="","",Agent01_Savings!B11) | D6: =IF(Agent01_Savings!A11="","",Agent01_Savings!G11) | E6: =IF(Agent01_Savings!A11="","",Agent01_Savings!D11) | F6: =IF(Agent01_Savings!A11="","",Agent01_Savings!E11) | G6: =IF(Agent01_Savings!A11="","",Agent01_Savings!F11) | H6: =IF(Agent01_Savings!A11="","",Agent01_Savings!I11) | I6: =IF(Agent01_Savings!A11="","",Agent01_Savings!J11) | J6: =IF(Agent01_Savings!A11="","",Agent01_Savings!K11) | K6: =IFERROR(IF(Agent01_Savings!A11="","",YEAR(Agent01_Savings!D11)),"")
A7: =IF(Agent01_Savings!A12="","",Agent01_Savings!A12) | B7: =IF(Agent01_Savings!A12="","","SV"&TEXT(7-3,"0000")&"-"&TEXT(TODAY(),"YYYYMMDD")) | C7: =IF(Agent01_Savings!A12="","",Agent01_Savings!B12) | D7: =IF(Agent01_Savings!A12="","",Agent01_Savings!G12) | E7: =IF(Agent01_Savings!A12="","",Agent01_Savings!D12) | F7: =IF(Agent01_Savings!A12="","",Agent01_Savings!E12) | G7: =IF(Agent01_Savings!A12="","",Agent01_Savings!F12) | H7: =IF(Agent01_Savings!A12="","",Agent01_Savings!I12) | I7: =IF(Agent01_Savings!A12="","",Agent01_Savings!J12) | J7: =IF(Agent01_Savings!A12="","",Agent01_Savings!K12) | K7: =IFERROR(IF(Agent01_Savings!A12="","",YEAR(Agent01_Savings!D12)),"")
A8: =IF(Agent01_Savings!A13="","",Agent01_Savings!A13) | B8: =IF(Agent01_Savings!A13="","","SV"&TEXT(8-3,"0000")&"-"&TEXT(TODAY(),"YYYYMMDD")) | C8: =IF(Agent01_Savings!A13="","",Agent01_Savings!B13) | D8: =IF(Agent01_Savings!A13="","",Agent01_Savings!G13) | E8: =IF(Agent01_Savings!A13="","",Agent01_Savings!D13) | F8: =IF(Agent01_Savings!A13="","",Agent01_Savings!E13) | G8: =IF(Agent01_Savings!A13="","",Agent01_Savings!F13) | H8: =IF(Agent01_Savings!A13="","",Agent01_Savings!I13) | I8: =IF(Agent01_Savings!A13="","",Agent01_Savings!J13) | J8: =IF(Agent01_Savings!A13="","",Agent01_Savings!K13) | K8: =IFERROR(IF(Agent01_Savings!A13="","",YEAR(Agent01_Savings!D13)),"")
A9: =IF(Agent01_Savings!A14="","",Agent01_Savings!A14) | B9: =IF(Agent01_Savings!A14="","","SV"&TEXT(9-3,"0000")&"-"&TEXT(TODAY(),"YYYYMMDD")) | C9: =IF(Agent01_Savings!A14="","",Agent01_Savings!B14) | D9: =IF(Agent01_Savings!A14="","",Agent01_Savings!G14) | E9: =IF(Agent01_Savings!A14="","",Agent01_Savings!D14) | F9: =IF(Agent01_Savings!A14="","",Agent01_Savings!E14) | G9: =IF(Agent01_Savings!A14="","",Agent01_Savings!F14) | H9: =IF(Agent01_Savings!A14="","",Agent01_Savings!I14) | I9: =IF(Agent01_Savings!A14="","",Agent01_Savings!J14) | J9: =IF(Agent01_Savings!A14="","",Agent01_Savings!K14) | K9: =IFERROR(IF(Agent01_Savings!A14="","",YEAR(Agent01_Savings!D14)),"")
A10: =IF(Agent01_Savings!A15="","",Agent01_Savings!A15) | B10: =IF(Agent01_Savings!A15="","","SV"&TEXT(10-3,"0000")&"-"&TEXT(TODAY(),"YYYYMMDD")) | C10: =IF(Agent01_Savings!A15="","",Agent01_Savings!B15) | D10: =IF(Agent01_Savings!A15="","",Agent01_Savings!G15) | E10: =IF(Agent01_Savings!A15="","",Agent01_Savings!D15) | F10: =IF(Agent01_Savings!A15="","",Agent01_Savings!E15) | G10: =IF(Agent01_Savings!A15="","",Agent01_Savings!F15) | H10: =IF(Agent01_Savings!A15="","",Agent01_Savings!I15) | I10: =IF(Agent01_Savings!A15="","",Agent01_Savings!J15) | J10: =IF(Agent01_Savings!A15="","",Agent01_Savings!K15) | K10: =IFERROR(IF(Agent01_Savings!A15="","",YEAR(Agent01_Savings!D15)),"")
A11: =IF(Agent01_Savings!A16="","",Agent01_Savings!A16) | B11: =IF(Agent01_Savings!A16="","","SV"&TEXT(11-3,"0000")&"-"&TEXT(TODAY(),"YYYYMMDD")) | C11: =IF(Agent01_Savings!A16="","",Agent01_Savings!B16) | D11: =IF(Agent01_Savings!A16="","",Agent01_Savings!G16) | E11: =IF(Agent01_Savings!A16="","",Agent01_Savings!D16) | F11: =IF(Agent01_Savings!A16="","",Agent01_Savings!E16) | G11: =IF(Agent01_Savings!A16="","",Agent01_Savings!F16) | H11: =IF(Agent01_Savings!A16="","",Agent01_Savings!I16) | I11: =IF(Agent01_Savings!A16="","",Agent01_Savings!J16) | J11: =IF(Agent01_Savings!A16="","",Agent01_Savings!K16) | K11: =IFERROR(IF(Agent01_Savings!A16="","",YEAR(Agent01_Savings!D16)),"")
A12: =IF(Agent01_Savings!A17="","",Agent01_Savings!A17) | B12: =IF(Agent01_Savings!A17="","","SV"&TEXT(12-3,"0000")&"-"&TEXT(TODAY(),"YYYYMMDD")) | C12: =IF(Agent01_Savings!A17="","",Agent01_Savings!B17) | D12: =IF(Agent01_Savings!A17="","",Agent01_Savings!G17) | E12: =IF(Agent01_Savings!A17="","",Agent01_Savings!D17) | F12: =IF(Agent01_Savings!A17="","",Agent01_Savings!E17) | G12: =IF(Agent01_Savings!A17="","",Agent01_Savings!F17) | H12: =IF(Agent01_Savings!A17="","",Agent01_Savings!I17) | I12: =IF(Agent01_Savings!A17="","",Agent01_Savings!J17) | J12: =IF(Agent01_Savings!A17="","",Agent01_Savings!K17) | K12: =IFERROR(IF(Agent01_Savings!A17="","",YEAR(Agent01_Savings!D17)),"")
A13: =IF(Agent01_Savings!A18="","",Agent01_Savings!A18) | B13: =IF(Agent01_Savings!A18="","","SV"&TEXT(13-3,"0000")&"-"&TEXT(TODAY(),"YYYYMMDD")) | C13: =IF(Agent01_Savings!A18="","",Agent01_Savings!B18) | D13: =IF(Agent01_Savings!A18="","",Agent01_Savings!G18) | E13: =IF(Agent01_Savings!A18="","",Agent01_Savings!D18) | F13: =IF(Agent01_Savings!A18="","",Agent01_Savings!E18) | G13: =IF(Agent01_Savings!A18="","",Agent01_Savings!F18) | H13: =IF(Agent01_Savings!A18="","",Agent01_Savings!I18) | I13: =IF(Agent01_Savings!A18="","",Agent01_Savings!J18) | J13: =IF(Agent01_Savings!A18="","",Agent01_Savings!K18) | K13: =IFERROR(IF(Agent01_Savings!A18="","",YEAR(Agent01_Savings!D18)),"")
A14: =IF(Agent01_Savings!A19="","",Agent01_Savings!A19) | B14: =IF(Agent01_Savings!A19="","","SV"&TEXT(14-3,"0000")&"-"&TEXT(TODAY(),"YYYYMMDD")) | C14: =IF(Agent01_Savings!A19="","",Agent01_Savings!B19) | D14: =IF(Agent01_Savings!A19="","",Agent01_Savings!G19) | E14: =IF(Agent01_Savings!A19="","",Agent01_Savings!D19) | F14: =IF(Agent01_Savings!A19="","",Agent01_Savings!E19) | G14: =IF(Agent01_Savings!A19="","",Agent01_Savings!F19) | H14: =IF(Agent01_Savings!A19="","",Agent01_Savings!I19) | I14: =IF(Agent01_Savings!A19="","",Agent01_Savings!J19) | J14: =IF(Agent01_Savings!A19="","",Agent01_Savings!K19) | K14: =IFERROR(IF(Agent01_Savings!A19="","",YEAR(Agent01_Savings!D19)),"")
A15: =IF(Agent01_Savings!A20="","",Agent01_Savings!A20) | B15: =IF(Agent01_Savings!A20="","","SV"&TEXT(15-3,"0000")&"-"&TEXT(TODAY(),"YYYYMMDD")) | C15: =IF(Agent01_Savings!A20="","",Agent01_Savings!B20) | D15: =IF(Agent01_Savings!A20="","",Agent01_Savings!G20) | E15: =IF(Agent01_Savings!A20="","",Agent01_Savings!D20) | F15: =IF(Agent01_Savings!A20="","",Agent01_Savings!E20) | G15: =IF(Agent01_Savings!A20="","",Agent01_Savings!F20) | H15: =IF(Agent01_Savings!A20="","",Agent01_Savings!I20) | I15: =IF(Agent01_Savings!A20="","",Agent01_Savings!J20) | J15: =IF(Agent01_Savings!A20="","",Agent01_Savings!K20) | K15: =IFERROR(IF(Agent01_Savings!A20="","",YEAR(Agent01_Savings!D20)),"")
A16: =IF(Agent01_Savings!A21="","",Agent01_Savings!A21) | B16: =IF(Agent01_Savings!A21="","","SV"&TEXT(16-3,"0000")&"-"&TEXT(TODAY(),"YYYYMMDD")) | C16: =IF(Agent01_Savings!A21="","",Agent01_Savings!B21) | D16: =IF(Agent01_Savings!A21="","",Agent01_Savings!G21) | E16: =IF(Agent01_Savings!A21="","",Agent01_Savings!D21) | F16: =IF(Agent01_Savings!A21="","",Agent01_Savings!E21) | G16: =IF(Agent01_Savings!A21="","",Agent01_Savings!F21) | H16: =IF(Agent01_Savings!A21="","",Agent01_Savings!I21) | I16: =IF(Agent01_Savings!A21="","",Agent01_Savings!J21) | J16: =IF(Agent01_Savings!A21="","",Agent01_Savings!K21) | K16: =IFERROR(IF(Agent01_Savings!A21="","",YEAR(Agent01_Savings!D21)),"")
A17: =IF(Agent01_Savings!A22="","",Agent01_Savings!A22) | B17: =IF(Agent01_Savings!A22="","","SV"&TEXT(17-3,"0000")&"-"&TEXT(TODAY(),"YYYYMMDD")) | C17: =IF(Agent01_Savings!A22="","",Agent01_Savings!B22) | D17: =IF(Agent01_Savings!A22="","",Agent01_Savings!G22) | E17: =IF(Agent01_Savings!A22="","",Agent01_Savings!D22) | F17: =IF(Agent01_Savings!A22="","",Agent01_Savings!E22) | G17: =IF(Agent01_Savings!A22="","",Agent01_Savings!F22) | H17: =IF(Agent01_Savings!A22="","",Agent01_Savings!I22) | I17: =IF(Agent01_Savings!A22="","",Agent01_Savings!J22) | J17: =IF(Agent01_Savings!A22="","",Agent01_Savings!K22) | K17: =IFERROR(IF(Agent01_Savings!A22="","",YEAR(Agent01_Savings!D22)),"")
A18: =IF(Agent01_Savings!A23="","",Agent01_Savings!A23) | B18: =IF(Agent01_Savings!A23="","","SV"&TEXT(18-3,"0000")&"-"&TEXT(TODAY(),"YYYYMMDD")) | C18: =IF(Agent01_Savings!A23="","",Agent01_Savings!B23) | D18: =IF(Agent01_Savings!A23="","",Agent01_Savings!G23) | E18: =IF(Agent01_Savings!A23="","",Agent01_Savings!D23) | F18: =IF(Agent01_Savings!A23="","",Agent01_Savings!E23) | G18: =IF(Agent01_Savings!A23="","",Agent01_Savings!F23) | H18: =IF(Agent01_Savings!A23="","",Agent01_Savings!I23) | I18: =IF(Agent01_Savings!A23="","",Agent01_Savings!J23) | J18: =IF(Agent01_Savings!A23="","",Agent01_Savings!K23) | K18: =IFERROR(IF(Agent01_Savings!A23="","",YEAR(Agent01_Savings!D23)),"")
A19: =IF(Agent01_Savings!A24="","",Agent01_Savings!A24) | B19: =IF(Agent01_Savings!A24="","","SV"&TEXT(19-3,"0000")&"-"&TEXT(TODAY(),"YYYYMMDD")) | C19: =IF(Agent01_Savings!A24="","",Agent01_Savings!B24) | D19: =IF(Agent01_Savings!A24="","",Agent01_Savings!G24) | E19: =IF(Agent01_Savings!A24="","",Agent01_Savings!D24) | F19: =IF(Agent01_Savings!A24="","",Agent01_Savings!E24) | G19: =IF(Agent01_Savings!A24="","",Agent01_Savings!F24) | H19: =IF(Agent01_Savings!A24="","",Agent01_Savings!I24) | I19: =IF(Agent01_Savings!A24="","",Agent01_Savings!J24) | J19: =IF(Agent01_Savings!A24="","",Agent01_Savings!K24) | K19: =IFERROR(IF(Agent01_Savings!A24="","",YEAR(Agent01_Savings!D24)),"")
A20: =IF(Agent01_Savings!A25="","",Agent01_Savings!A25) | B20: =IF(Agent01_Savings!A25="","","SV"&TEXT(20-3,"0000")&"-"&TEXT(TODAY(),"YYYYMMDD")) | C20: =IF(Agent01_Savings!A25="","",Agent01_Savings!B25) | D20: =IF(Agent01_Savings!A25="","",Agent01_Savings!G25) | E20: =IF(Agent01_Savings!A25="","",Agent01_Savings!D25) | F20: =IF(Agent01_Savings!A25="","",Agent01_Savings!E25) | G20: =IF(Agent01_Savings!A25="","",Agent01_Savings!F25) | H20: =IF(Agent01_Savings!A25="","",Agent01_Savings!I25) | I20: =IF(Agent01_Savings!A25="","",Agent01_Savings!J25) | J20: =IF(Agent01_Savings!A25="","",Agent01_Savings!K25) | K20: =IFERROR(IF(Agent01_Savings!A25="","",YEAR(Agent01_Savings!D25)),"")
A21: =IF(Agent01_Savings!A26="","",Agent01_Savings!A26) | B21: =IF(Agent01_Savings!A26="","","SV"&TEXT(21-3,"0000")&"-"&TEXT(TODAY(),"YYYYMMDD")) | C21: =IF(Agent01_Savings!A26="","",Agent01_Savings!B26) | D21: =IF(Agent01_Savings!A26="","",Agent01_Savings!G26) | E21: =IF(Agent01_Savings!A26="","",Agent01_Savings!D26) | F21: =IF(Agent01_Savings!A26="","",Agent01_Savings!E26) | G21: =IF(Agent01_Savings!A26="","",Agent01_Savings!F26) | H21: =IF(Agent01_Savings!A26="","",Agent01_Savings!I26) | I21: =IF(Agent01_Savings!A26="","",Agent01_Savings!J26) | J21: =IF(Agent01_Savings!A26="","",Agent01_Savings!K26) | K21: =IFERROR(IF(Agent01_Savings!A26="","",YEAR(Agent01_Savings!D26)),"")
A22: =IF(Agent01_Savings!A27="","",Agent01_Savings!A27) | B22: =IF(Agent01_Savings!A27="","","SV"&TEXT(22-3,"0000")&"-"&TEXT(TODAY(),"YYYYMMDD")) | C22: =IF(Agent01_Savings!A27="","",Agent01_Savings!B27) | D22: =IF(Agent01_Savings!A27="","",Agent01_Savings!G27) | E22: =IF(Agent01_Savings!A27="","",Agent01_Savings!D27) | F22: =IF(Agent01_Savings!A27="","",Agent01_Savings!E27) | G22: =IF(Agent01_Savings!A27="","",Agent01_Savings!F27) | H22: =IF(Agent01_Savings!A27="","",Agent01_Savings!I27) | I22: =IF(Agent01_Savings!A27="","",Agent01_Savings!J27) | J22: =IF(Agent01_Savings!A27="","",Agent01_Savings!K27) | K22: =IFERROR(IF(Agent01_Savings!A27="","",YEAR(Agent01_Savings!D27)),"")
A23: =IF(Agent01_Savings!A28="","",Agent01_Savings!A28) | B23: =IF(Agent01_Savings!A28="","","SV"&TEXT(23-3,"0000")&"-"&TEXT(TODAY(),"YYYYMMDD")) | C23: =IF(Agent01_Savings!A28="","",Agent01_Savings!B28) | D23: =IF(Agent01_Savings!A28="","",Agent01_Savings!G28) | E23: =IF(Agent01_Savings!A28="","",Agent01_Savings!D28) | F23: =IF(Agent01_Savings!A28="","",Agent01_Savings!E28) | G23: =IF(Agent01_Savings!A28="","",Agent01_Savings!F28) | H23: =IF(Agent01_Savings!A28="","",Agent01_Savings!I28) | I23: =IF(Agent01_Savings!A28="","",Agent01_Savings!J28) | J23: =IF(Agent01_Savings!A28="","",Agent01_Savings!K28) | K23: =IFERROR(IF(Agent01_Savings!A28="","",YEAR(Agent01_Savings!D28)),"")
A24: =IF(Agent01_Savings!A29="","",Agent01_Savings!A29) | B24: =IF(Agent01_Savings!A29="","","SV"&TEXT(24-3,"0000")&"-"&TEXT(TODAY(),"YYYYMMDD")) | C24: =IF(Agent01_Savings!A29="","",Agent01_Savings!B29) | D24: =IF(Agent01_Savings!A29="","",Agent01_Savings!G29) | E24: =IF(Agent01_Savings!A29="","",Agent01_Savings!D29) | F24: =IF(Agent01_Savings!A29="","",Agent01_Savings!E29) | G24: =IF(Agent01_Savings!A29="","",Agent01_Savings!F29) | H24: =IF(Agent01_Savings!A29="","",Agent01_Savings!I29) | I24: =IF(Agent01_Savings!A29="","",Agent01_Savings!J29) | J24: =IF(Agent01_Savings!A29="","",Agent01_Savings!K29) | K24: =IFERROR(IF(Agent01_Savings!A29="","",YEAR(Agent01_Savings!D29)),"")
A25: =IF(Agent01_Savings!A30="","",Agent01_Savings!A30) | B25: =IF(Agent01_Savings!A30="","","SV"&TEXT(25-3,"0000")&"-"&TEXT(TODAY(),"YYYYMMDD")) | C25: =IF(Agent01_Savings!A30="","",Agent01_Savings!B30) | D25: =IF(Agent01_Savings!A30="","",Agent01_Savings!G30) | E25: =IF(Agent01_Savings!A30="","",Agent01_Savings!D30) | F25: =IF(Agent01_Savings!A30="","",Agent01_Savings!E30) | G25: =IF(Agent01_Savings!A30="","",Agent01_Savings!F30) | H25: =IF(Agent01_Savings!A30="","",Agent01_Savings!I30) | I25: =IF(Agent01_Savings!A30="","",Agent01_Savings!J30) | J25: =IF(Agent01_Savings!A30="","",Agent01_Savings!K30) | K25: =IFERROR(IF(Agent01_Savings!A30="","",YEAR(Agent01_Savings!D30)),"")
A26: =IF(Agent01_Savings!A31="","",Agent01_Savings!A31) | B26: =IF(Agent01_Savings!A31="","","SV"&TEXT(26-3,"0000")&"-"&TEXT(TODAY(),"YYYYMMDD")) | C26: =IF(Agent01_Savings!A31="","",Agent01_Savings!B31) | D26: =IF(Agent01_Savings!A31="","",Agent01_Savings!G31) | E26: =IF(Agent01_Savings!A31="","",Agent01_Savings!D31) | F26: =IF(Agent01_Savings!A31="","",Agent01_Savings!E31) | G26: =IF(Agent01_Savings!A31="","",Agent01_Savings!F31) | H26: =IF(Agent01_Savings!A31="","",Agent01_Savings!I31) | I26: =IF(Agent01_Savings!A31="","",Agent01_Savings!J31) | J26: =IF(Agent01_Savings!A31="","",Agent01_Savings!K31) | K26: =IFERROR(IF(Agent01_Savings!A31="","",YEAR(Agent01_Savings!D31)),"")
A27: =IF(Agent01_Savings!A32="","",Agent01_Savings!A32) | B27: =IF(Agent01_Savings!A32="","","SV"&TEXT(27-3,"0000")&"-"&TEXT(TODAY(),"YYYYMMDD")) | C27: =IF(Agent01_Savings!A32="","",Agent01_Savings!B32) | D27: =IF(Agent01_Savings!A32="","",Agent01_Savings!G32) | E27: =IF(Agent01_Savings!A32="","",Agent01_Savings!D32) | F27: =IF(Agent01_Savings!A32="","",Agent01_Savings!E32) | G27: =IF(Agent01_Savings!A32="","",Agent01_Savings!F32) | H27: =IF(Agent01_Savings!A32="","",Agent01_Savings!I32) | I27: =IF(Agent01_Savings!A32="","",Agent01_Savings!J32) | J27: =IF(Agent01_Savings!A32="","",Agent01_Savings!K32) | K27: =IFERROR(IF(Agent01_Savings!A32="","",YEAR(Agent01_Savings!D32)),"")
A28: =IF(Agent01_Savings!A33="","",Agent01_Savings!A33) | B28: =IF(Agent01_Savings!A33="","","SV"&TEXT(28-3,"0000")&"-"&TEXT(TODAY(),"YYYYMMDD")) | C28: =IF(Agent01_Savings!A33="","",Agent01_Savings!B33) | D28: =IF(Agent01_Savings!A33="","",Agent01_Savings!G33) | E28: =IF(Agent01_Savings!A33="","",Agent01_Savings!D33) | F28: =IF(Agent01_Savings!A33="","",Agent01_Savings!E33) | G28: =IF(Agent01_Savings!A33="","",Agent01_Savings!F33) | H28: =IF(Agent01_Savings!A33="","",Agent01_Savings!I33) | I28: =IF(Agent01_Savings!A33="","",Agent01_Savings!J33) | J28: =IF(Agent01_Savings!A33="","",Agent01_Savings!K33) | K28: =IFERROR(IF(Agent01_Savings!A33="","",YEAR(Agent01_Savings!D33)),"")
A29: =IF(Agent01_Savings!A34="","",Agent01_Savings!A34) | B29: =IF(Agent01_Savings!A34="","","SV"&TEXT(29-3,"0000")&"-"&TEXT(TODAY(),"YYYYMMDD")) | C29: =IF(Agent01_Savings!A34="","",Agent01_Savings!B34) | D29: =IF(Agent01_Savings!A34="","",Agent01_Savings!G34) | E29: =IF(Agent01_Savings!A34="","",Agent01_Savings!D34) | F29: =IF(Agent01_Savings!A34="","",Agent01_Savings!E34) | G29: =IF(Agent01_Savings!A34="","",Agent01_Savings!F34) | H29: =IF(Agent01_Savings!A34="","",Agent01_Savings!I34) | I29: =IF(Agent01_Savings!A34="","",Agent01_Savings!J34) | J29: =IF(Agent01_Savings!A34="","",Agent01_Savings!K34) | K29: =IFERROR(IF(Agent01_Savings!A34="","",YEAR(Agent01_Savings!D34)),"")
A30: =IF(Agent01_Savings!A35="","",Agent01_Savings!A35) | B30: =IF(Agent01_Savings!A35="","","SV"&TEXT(30-3,"0000")&"-"&TEXT(TODAY(),"YYYYMMDD")) | C30: =IF(Agent01_Savings!A35="","",Agent01_Savings!B35) | D30: =IF(Agent01_Savings!A35="","",Agent01_Savings!G35) | E30: =IF(Agent01_Savings!A35="","",Agent01_Savings!D35) | F30: =IF(Agent01_Savings!A35="","",Agent01_Savings!E35) | G30: =IF(Agent01_Savings!A35="","",Agent01_Savings!F35) | H30: =IF(Agent01_Savings!A35="","",Agent01_Savings!I35) | I30: =IF(Agent01_Savings!A35="","",Agent01_Savings!J35) | J30: =IF(Agent01_Savings!A35="","",Agent01_Savings!K35) | K30: =IFERROR(IF(Agent01_Savings!A35="","",YEAR(Agent01_Savings!D35)),"")
A31: =IF(Agent01_Savings!A36="","",Agent01_Savings!A36) | B31: =IF(Agent01_Savings!A36="","","SV"&TEXT(31-3,"0000")&"-"&TEXT(TODAY(),"YYYYMMDD")) | C31: =IF(Agent01_Savings!A36="","",Agent01_Savings!B36) | D31: =IF(Agent01_Savings!A36="","",Agent01_Savings!G36) | E31: =IF(Agent01_Savings!A36="","",Agent01_Savings!D36) | F31: =IF(Agent01_Savings!A36="","",Agent01_Savings!E36) | G31: =IF(Agent01_Savings!A36="","",Agent01_Savings!F36) | H31: =IF(Agent01_Savings!A36="","",Agent01_Savings!I36) | I31: =IF(Agent01_Savings!A36="","",Agent01_Savings!J36) | J31: =IF(Agent01_Savings!A36="","",Agent01_Savings!K36) | K31: =IFERROR(IF(Agent01_Savings!A36="","",YEAR(Agent01_Savings!D36)),"")
A32: =IF(Agent01_Savings!A37="","",Agent01_Savings!A37) | B32: =IF(Agent01_Savings!A37="","","SV"&TEXT(32-3,"0000")&"-"&TEXT(TODAY(),"YYYYMMDD")) | C32: =IF(Agent01_Savings!A37="","",Agent01_Savings!B37) | D32: =IF(Agent01_Savings!A37="","",Agent01_Savings!G37) | E32: =IF(Agent01_Savings!A37="","",Agent01_Savings!D37) | F32: =IF(Agent01_Savings!A37="","",Agent01_Savings!E37) | G32: =IF(Agent01_Savings!A37="","",Agent01_Savings!F37) | H32: =IF(Agent01_Savings!A37="","",Agent01_Savings!I37) | I32: =IF(Agent01_Savings!A37="","",Agent01_Savings!J37) | J32: =IF(Agent01_Savings!A37="","",Agent01_Savings!K37) | K32: =IFERROR(IF(Agent01_Savings!A37="","",YEAR(Agent01_Savings!D37)),"")
A33: =IF(Agent01_Savings!A38="","",Agent01_Savings!A38) | B33: =IF(Agent01_Savings!A38="","","SV"&TEXT(33-3,"0000")&"-"&TEXT(TODAY(),"YYYYMMDD")) | C33: =IF(Agent01_Savings!A38="","",Agent01_Savings!B38) | D33: =IF(Agent01_Savings!A38="","",Agent01_Savings!G38) | E33: =IF(Agent01_Savings!A38="","",Agent01_Savings!D38) | F33: =IF(Agent01_Savings!A38="","",Agent01_Savings!E38) | G33: =IF(Agent01_Savings!A38="","",Agent01_Savings!F38) | H33: =IF(Agent01_Savings!A38="","",Agent01_Savings!I38) | I33: =IF(Agent01_Savings!A38="","",Agent01_Savings!J38) | J33: =IF(Agent01_Savings!A38="","",Agent01_Savings!K38) | K33: =IFERROR(IF(Agent01_Savings!A38="","",YEAR(Agent01_Savings!D38)),"")
A34: =IF(Agent01_Savings!A39="","",Agent01_Savings!A39) | B34: =IF(Agent01_Savings!A39="","","SV"&TEXT(34-3,"0000")&"-"&TEXT(TODAY(),"YYYYMMDD")) | C34: =IF(Agent01_Savings!A39="","",Agent01_Savings!B39) | D34: =IF(Agent01_Savings!A39="","",Agent01_Savings!G39) | E34: =IF(Agent01_Savings!A39="","",Agent01_Savings!D39) | F34: =IF(Agent01_Savings!A39="","",Agent01_Savings!E39) | G34: =IF(Agent01_Savings!A39="","",Agent01_Savings!F39) | H34: =IF(Agent01_Savings!A39="","",Agent01_Savings!I39) | I34: =IF(Agent01_Savings!A39="","",Agent01_Savings!J39) | J34: =IF(Agent01_Savings!A39="","",Agent01_Savings!K39) | K34: =IFERROR(IF(Agent01_Savings!A39="","",YEAR(Agent01_Savings!D39)),"")
A35: =IF(Agent01_Savings!A40="","",Agent01_Savings!A40) | B35: =IF(Agent01_Savings!A40="","","SV"&TEXT(35-3,"0000")&"-"&TEXT(TODAY(),"YYYYMMDD")) | C35: =IF(Agent01_Savings!A40="","",Agent01_Savings!B40) | D35: =IF(Agent01_Savings!A40="","",Agent01_Savings!G40) | E35: =IF(Agent01_Savings!A40="","",Agent01_Savings!D40) | F35: =IF(Agent01_Savings!A40="","",Agent01_Savings!E40) | G35: =IF(Agent01_Savings!A40="","",Agent01_Savings!F40) | H35: =IF(Agent01_Savings!A40="","",Agent01_Savings!I40) | I35: =IF(Agent01_Savings!A40="","",Agent01_Savings!J40) | J35: =IF(Agent01_Savings!A40="","",Agent01_Savings!K40) | K35: =IFERROR(IF(Agent01_Savings!A40="","",YEAR(Agent01_Savings!D40)),"")
A36: =IF(Agent01_Savings!A41="","",Agent01_Savings!A41) | B36: =IF(Agent01_Savings!A41="","","SV"&TEXT(36-3,"0000")&"-"&TEXT(TODAY(),"YYYYMMDD")) | C36: =IF(Agent01_Savings!A41="","",Agent01_Savings!B41) | D36: =IF(Agent01_Savings!A41="","",Agent01_Savings!G41) | E36: =IF(Agent01_Savings!A41="","",Agent01_Savings!D41) | F36: =IF(Agent01_Savings!A41="","",Agent01_Savings!E41) | G36: =IF(Agent01_Savings!A41="","",Agent01_Savings!F41) | H36: =IF(Agent01_Savings!A41="","",Agent01_Savings!I41) | I36: =IF(Agent01_Savings!A41="","",Agent01_Savings!J41) | J36: =IF(Agent01_Savings!A41="","",Agent01_Savings!K41) | K36: =IFERROR(IF(Agent01_Savings!A41="","",YEAR(Agent01_Savings!D41)),"")
A37: =IF(Agent01_Savings!A42="","",Agent01_Savings!A42) | B37: =IF(Agent01_Savings!A42="","","SV"&TEXT(37-3,"0000")&"-"&TEXT(TODAY(),"YYYYMMDD")) | C37: =IF(Agent01_Savings!A42="","",Agent01_Savings!B42) | D37: =IF(Agent01_Savings!A42="","",Agent01_Savings!G42) | E37: =IF(Agent01_Savings!A42="","",Agent01_Savings!D42) | F37: =IF(Agent01_Savings!A42="","",Agent01_Savings!E42) | G37: =IF(Agent01_Savings!A42="","",Agent01_Savings!F42) | H37: =IF(Agent01_Savings!A42="","",Agent01_Savings!I42) | I37: =IF(Agent01_Savings!A42="","",Agent01_Savings!J42) | J37: =IF(Agent01_Savings!A42="","",Agent01_Savings!K42) | K37: =IFERROR(IF(Agent01_Savings!A42="","",YEAR(Agent01_Savings!D42)),"")
A38: =IF(Agent01_Savings!A43="","",Agent01_Savings!A43) | B38: =IF(Agent01_Savings!A43="","","SV"&TEXT(38-3,"0000")&"-"&TEXT(TODAY(),"YYYYMMDD")) | C38: =IF(Agent01_Savings!A43="","",Agent01_Savings!B43) | D38: =IF(Agent01_Savings!A43="","",Agent01_Savings!G43) | E38: =IF(Agent01_Savings!A43="","",Agent01_Savings!D43) | F38: =IF(Agent01_Savings!A43="","",Agent01_Savings!E43) | G38: =IF(Agent01_Savings!A43="","",Agent01_Savings!F43) | H38: =IF(Agent01_Savings!A43="","",Agent01_Savings!I43) | I38: =IF(Agent01_Savings!A43="","",Agent01_Savings!J43) | J38: =IF(Agent01_Savings!A43="","",Agent01_Savings!K43) | K38: =IFERROR(IF(Agent01_Savings!A43="","",YEAR(Agent01_Savings!D43)),"")
A39: =IF(Agent01_Savings!A44="","",Agent01_Savings!A44) | B39: =IF(Agent01_Savings!A44="","","SV"&TEXT(39-3,"0000")&"-"&TEXT(TODAY(),"YYYYMMDD")) | C39: =IF(Agent01_Savings!A44="","",Agent01_Savings!B44) | D39: =IF(Agent01_Savings!A44="","",Agent01_Savings!G44) | E39: =IF(Agent01_Savings!A44="","",Agent01_Savings!D44) | F39: =IF(Agent01_Savings!A44="","",Agent01_Savings!E44) | G39: =IF(Agent01_Savings!A44="","",Agent01_Savings!F44) | H39: =IF(Agent01_Savings!A44="","",Agent01_Savings!I44) | I39: =IF(Agent01_Savings!A44="","",Agent01_Savings!J44) | J39: =IF(Agent01_Savings!A44="","",Agent01_Savings!K44) | K39: =IFERROR(IF(Agent01_Savings!A44="","",YEAR(Agent01_Savings!D44)),"")
A40: =IF(Agent01_Savings!A45="","",Agent01_Savings!A45) | B40: =IF(Agent01_Savings!A45="","","SV"&TEXT(40-3,"0000")&"-"&TEXT(TODAY(),"YYYYMMDD")) | C40: =IF(Agent01_Savings!A45="","",Agent01_Savings!B45) | D40: =IF(Agent01_Savings!A45="","",Agent01_Savings!G45) | E40: =IF(Agent01_Savings!A45="","",Agent01_Savings!D45) | F40: =IF(Agent01_Savings!A45="","",Agent01_Savings!E45) | G40: =IF(Agent01_Savings!A45="","",Agent01_Savings!F45) | H40: =IF(Agent01_Savings!A45="","",Agent01_Savings!I45) | I40: =IF(Agent01_Savings!A45="","",Agent01_Savings!J45) | J40: =IF(Agent01_Savings!A45="","",Agent01_Savings!K45) | K40: =IFERROR(IF(Agent01_Savings!A45="","",YEAR(Agent01_Savings!D45)),"")
A41: =IF(Agent01_Savings!A46="","",Agent01_Savings!A46) | B41: =IF(Agent01_Savings!A46="","","SV"&TEXT(41-3,"0000")&"-"&TEXT(TODAY(),"YYYYMMDD")) | C41: =IF(Agent01_Savings!A46="","",Agent01_Savings!B46) | D41: =IF(Agent01_Savings!A46="","",Agent01_Savings!G46) | E41: =IF(Agent01_Savings!A46="","",Agent01_Savings!D46) | F41: =IF(Agent01_Savings!A46="","",Agent01_Savings!E46) | G41: =IF(Agent01_Savings!A46="","",Agent01_Savings!F46) | H41: =IF(Agent01_Savings!A46="","",Agent01_Savings!I46) | I41: =IF(Agent01_Savings!A46="","",Agent01_Savings!J46) | J41: =IF(Agent01_Savings!A46="","",Agent01_Savings!K46) | K41: =IFERROR(IF(Agent01_Savings!A46="","",YEAR(Agent01_Savings!D46)),"")
A42: =IF(Agent01_Savings!A47="","",Agent01_Savings!A47) | B42: =IF(Agent01_Savings!A47="","","SV"&TEXT(42-3,"0000")&"-"&TEXT(TODAY(),"YYYYMMDD")) | C42: =IF(Agent01_Savings!A47="","",Agent01_Savings!B47) | D42: =IF(Agent01_Savings!A47="","",Agent01_Savings!G47) | E42: =IF(Agent01_Savings!A47="","",Agent01_Savings!D47) | F42: =IF(Agent01_Savings!A47="","",Agent01_Savings!E47) | G42: =IF(Agent01_Savings!A47="","",Agent01_Savings!F47) | H42: =IF(Agent01_Savings!A47="","",Agent01_Savings!I47) | I42: =IF(Agent01_Savings!A47="","",Agent01_Savings!J47) | J42: =IF(Agent01_Savings!A47="","",Agent01_Savings!K47) | K42: =IFERROR(IF(Agent01_Savings!A47="","",YEAR(Agent01_Savings!D47)),"")
A43: =IF(Agent01_Savings!A48="","",Agent01_Savings!A48) | B43: =IF(Agent01_Savings!A48="","","SV"&TEXT(43-3,"0000")&"-"&TEXT(TODAY(),"YYYYMMDD")) | C43: =IF(Agent01_Savings!A48="","",Agent01_Savings!B48) | D43: =IF(Agent01_Savings!A48="","",Agent01_Savings!G48) | E43: =IF(Agent01_Savings!A48="","",Agent01_Savings!D48) | F43: =IF(Agent01_Savings!A48="","",Agent01_Savings!E48) | G43: =IF(Agent01_Savings!A48="","",Agent01_Savings!F48) | H43: =IF(Agent01_Savings!A48="","",Agent01_Savings!I48) | I43: =IF(Agent01_Savings!A48="","",Agent01_Savings!J48) | J43: =IF(Agent01_Savings!A48="","",Agent01_Savings!K48) | K43: =IFERROR(IF(Agent01_Savings!A48="","",YEAR(Agent01_Savings!D48)),"")
A44: =IF(Agent01_Savings!A49="","",Agent01_Savings!A49) | B44: =IF(Agent01_Savings!A49="","","SV"&TEXT(44-3,"0000")&"-"&TEXT(TODAY(),"YYYYMMDD")) | C44: =IF(Agent01_Savings!A49="","",Agent01_Savings!B49) | D44: =IF(Agent01_Savings!A49="","",Agent01_Savings!G49) | E44: =IF(Agent01_Savings!A49="","",Agent01_Savings!D49) | F44: =IF(Agent01_Savings!A49="","",Agent01_Savings!E49) | G44: =IF(Agent01_Savings!A49="","",Agent01_Savings!F49) | H44: =IF(Agent01_Savings!A49="","",Agent01_Savings!I49) | I44: =IF(Agent01_Savings!A49="","",Agent01_Savings!J49) | J44: =IF(Agent01_Savings!A49="","",Agent01_Savings!K49) | K44: =IFERROR(IF(Agent01_Savings!A49="","",YEAR(Agent01_Savings!D49)),"")
A45: =IF(Agent01_Savings!A50="","",Agent01_Savings!A50) | B45: =IF(Agent01_Savings!A50="","","SV"&TEXT(45-3,"0000")&"-"&TEXT(TODAY(),"YYYYMMDD")) | C45: =IF(Agent01_Savings!A50="","",Agent01_Savings!B50) | D45: =IF(Agent01_Savings!A50="","",Agent01_Savings!G50) | E45: =IF(Agent01_Savings!A50="","",Agent01_Savings!D50) | F45: =IF(Agent01_Savings!A50="","",Agent01_Savings!E50) | G45: =IF(Agent01_Savings!A50="","",Agent01_Savings!F50) | H45: =IF(Agent01_Savings!A50="","",Agent01_Savings!I50) | I45: =IF(Agent01_Savings!A50="","",Agent01_Savings!J50) | J45: =IF(Agent01_Savings!A50="","",Agent01_Savings!K50) | K45: =IFERROR(IF(Agent01_Savings!A50="","",YEAR(Agent01_Savings!D50)),"")
A46: =IF(Agent01_Savings!A51="","",Agent01_Savings!A51) | B46: =IF(Agent01_Savings!A51="","","SV"&TEXT(46-3,"0000")&"-"&TEXT(TODAY(),"YYYYMMDD")) | C46: =IF(Agent01_Savings!A51="","",Agent01_Savings!B51) | D46: =IF(Agent01_Savings!A51="","",Agent01_Savings!G51) | E46: =IF(Agent01_Savings!A51="","",Agent01_Savings!D51) | F46: =IF(Agent01_Savings!A51="","",Agent01_Savings!E51) | G46: =IF(Agent01_Savings!A51="","",Agent01_Savings!F51) | H46: =IF(Agent01_Savings!A51="","",Agent01_Savings!I51) | I46: =IF(Agent01_Savings!A51="","",Agent01_Savings!J51) | J46: =IF(Agent01_Savings!A51="","",Agent01_Savings!K51) | K46: =IFERROR(IF(Agent01_Savings!A51="","",YEAR(Agent01_Savings!D51)),"")
A47: =IF(Agent01_Savings!A52="","",Agent01_Savings!A52) | B47: =IF(Agent01_Savings!A52="","","SV"&TEXT(47-3,"0000")&"-"&TEXT(TODAY(),"YYYYMMDD")) | C47: =IF(Agent01_Savings!A52="","",Agent01_Savings!B52) | D47: =IF(Agent01_Savings!A52="","",Agent01_Savings!G52) | E47: =IF(Agent01_Savings!A52="","",Agent01_Savings!D52) | F47: =IF(Agent01_Savings!A52="","",Agent01_Savings!E52) | G47: =IF(Agent01_Savings!A52="","",Agent01_Savings!F52) | H47: =IF(Agent01_Savings!A52="","",Agent01_Savings!I52) | I47: =IF(Agent01_Savings!A52="","",Agent01_Savings!J52) | J47: =IF(Agent01_Savings!A52="","",Agent01_Savings!K52) | K47: =IFERROR(IF(Agent01_Savings!A52="","",YEAR(Agent01_Savings!D52)),"")
A48: =IF(Agent01_Savings!A53="","",Agent01_Savings!A53) | B48: =IF(Agent01_Savings!A53="","","SV"&TEXT(48-3,"0000")&"-"&TEXT(TODAY(),"YYYYMMDD")) | C48: =IF(Agent01_Savings!A53="","",Agent01_Savings!B53) | D48: =IF(Agent01_Savings!A53="","",Agent01_Savings!G53) | E48: =IF(Agent01_Savings!A53="","",Agent01_Savings!D53) | F48: =IF(Agent01_Savings!A53="","",Agent01_Savings!E53) | G48: =IF(Agent01_Savings!A53="","",Agent01_Savings!F53) | H48: =IF(Agent01_Savings!A53="","",Agent01_Savings!I53) | I48: =IF(Agent01_Savings!A53="","",Agent01_Savings!J53) | J48: =IF(Agent01_Savings!A53="","",Agent01_Savings!K53) | K48: =IFERROR(IF(Agent01_Savings!A53="","",YEAR(Agent01_Savings!D53)),"")
A49: =IF(Agent01_Savings!A54="","",Agent01_Savings!A54) | B49: =IF(Agent01_Savings!A54="","","SV"&TEXT(49-3,"0000")&"-"&TEXT(TODAY(),"YYYYMMDD")) | C49: =IF(Agent01_Savings!A54="","",Agent01_Savings!B54) | D49: =IF(Agent01_Savings!A54="","",Agent01_Savings!G54) | E49: =IF(Agent01_Savings!A54="","",Agent01_Savings!D54) | F49: =IF(Agent01_Savings!A54="","",Agent01_Savings!E54) | G49: =IF(Agent01_Savings!A54="","",Agent01_Savings!F54) | H49: =IF(Agent01_Savings!A54="","",Agent01_Savings!I54) | I49: =IF(Agent01_Savings!A54="","",Agent01_Savings!J54) | J49: =IF(Agent01_Savings!A54="","",Agent01_Savings!K54) | K49: =IFERROR(IF(Agent01_Savings!A54="","",YEAR(Agent01_Savings!D54)),"")
A50: =IF(Agent01_Savings!A55="","",Agent01_Savings!A55) | B50: =IF(Agent01_Savings!A55="","","SV"&TEXT(50-3,"0000")&"-"&TEXT(TODAY(),"YYYYMMDD")) | C50: =IF(Agent01_Savings!A55="","",Agent01_Savings!B55) | D50: =IF(Agent01_Savings!A55="","",Agent01_Savings!G55) | E50: =IF(Agent01_Savings!A55="","",Agent01_Savings!D55) | F50: =IF(Agent01_Savings!A55="","",Agent01_Savings!E55) | G50: =IF(Agent01_Savings!A55="","",Agent01_Savings!F55) | H50: =IF(Agent01_Savings!A55="","",Agent01_Savings!I55) | I50: =IF(Agent01_Savings!A55="","",Agent01_Savings!J55) | J50: =IF(Agent01_Savings!A55="","",Agent01_Savings!K55) | K50: =IFERROR(IF(Agent01_Savings!A55="","",YEAR(Agent01_Savings!D55)),"")
A51: =IF(Agent01_Savings!A56="","",Agent01_Savings!A56) | B51: =IF(Agent01_Savings!A56="","","SV"&TEXT(51-3,"0000")&"-"&TEXT(TODAY(),"YYYYMMDD")) | C51: =IF(Agent01_Savings!A56="","",Agent01_Savings!B56) | D51: =IF(Agent01_Savings!A56="","",Agent01_Savings!G56) | E51: =IF(Agent01_Savings!A56="","",Agent01_Savings!D56) | F51: =IF(Agent01_Savings!A56="","",Agent01_Savings!E56) | G51: =IF(Agent01_Savings!A56="","",Agent01_Savings!F56) | H51: =IF(Agent01_Savings!A56="","",Agent01_Savings!I56) | I51: =IF(Agent01_Savings!A56="","",Agent01_Savings!J56) | J51: =IF(Agent01_Savings!A56="","",Agent01_Savings!K56) | K51: =IFERROR(IF(Agent01_Savings!A56="","",YEAR(Agent01_Savings!D56)),"")
A52: =IF(Agent01_Savings!A57="","",Agent01_Savings!A57) | B52: =IF(Agent01_Savings!A57="","","SV"&TEXT(52-3,"0000")&"-"&TEXT(TODAY(),"YYYYMMDD")) | C52: =IF(Agent01_Savings!A57="","",Agent01_Savings!B57) | D52: =IF(Agent01_Savings!A57="","",Agent01_Savings!G57) | E52: =IF(Agent01_Savings!A57="","",Agent01_Savings!D57) | F52: =IF(Agent01_Savings!A57="","",Agent01_Savings!E57) | G52: =IF(Agent01_Savings!A57="","",Agent01_Savings!F57) | H52: =IF(Agent01_Savings!A57="","",Agent01_Savings!I57) | I52: =IF(Agent01_Savings!A57="","",Agent01_Savings!J57) | J52: =IF(Agent01_Savings!A57="","",Agent01_Savings!K57) | K52: =IFERROR(IF(Agent01_Savings!A57="","",YEAR(Agent01_Savings!D57)),"")
A53: =IF(Agent01_Savings!A58="","",Agent01_Savings!A58) | B53: =IF(Agent01_Savings!A58="","","SV"&TEXT(53-3,"0000")&"-"&TEXT(TODAY(),"YYYYMMDD")) | C53: =IF(Agent01_Savings!A58="","",Agent01_Savings!B58) | D53: =IF(Agent01_Savings!A58="","",Agent01_Savings!G58) | E53: =IF(Agent01_Savings!A58="","",Agent01_Savings!D58) | F53: =IF(Agent01_Savings!A58="","",Agent01_Savings!E58) | G53: =IF(Agent01_Savings!A58="","",Agent01_Savings!F58) | H53: =IF(Agent01_Savings!A58="","",Agent01_Savings!I58) | I53: =IF(Agent01_Savings!A58="","",Agent01_Savings!J58) | J53: =IF(Agent01_Savings!A58="","",Agent01_Savings!K58) | K53: =IFERROR(IF(Agent01_Savings!A58="","",YEAR(Agent01_Savings!D58)),"")
A54: =IF(Agent01_Savings!A59="","",Agent01_Savings!A59) | B54: =IF(Agent01_Savings!A59="","","SV"&TEXT(54-3,"0000")&"-"&TEXT(TODAY(),"YYYYMMDD")) | C54: =IF(Agent01_Savings!A59="","",Agent01_Savings!B59) | D54: =IF(Agent01_Savings!A59="","",Agent01_Savings!G59) | E54: =IF(Agent01_Savings!A59="","",Agent01_Savings!D59) | F54: =IF(Agent01_Savings!A59="","",Agent01_Savings!E59) | G54: =IF(Agent01_Savings!A59="","",Agent01_Savings!F59) | H54: =IF(Agent01_Savings!A59="","",Agent01_Savings!I59) | I54: =IF(Agent01_Savings!A59="","",Agent01_Savings!J59) | J54: =IF(Agent01_Savings!A59="","",Agent01_Savings!K59) | K54: =IFERROR(IF(Agent01_Savings!A59="","",YEAR(Agent01_Savings!D59)),"")
A55: =IF(Agent01_Savings!A60="","",Agent01_Savings!A60) | B55: =IF(Agent01_Savings!A60="","","SV"&TEXT(55-3,"0000")&"-"&TEXT(TODAY(),"YYYYMMDD")) | C55: =IF(Agent01_Savings!A60="","",Agent01_Savings!B60) | D55: =IF(Agent01_Savings!A60="","",Agent01_Savings!G60) | E55: =IF(Agent01_Savings!A60="","",Agent01_Savings!D60) | F55: =IF(Agent01_Savings!A60="","",Agent01_Savings!E60) | G55: =IF(Agent01_Savings!A60="","",Agent01_Savings!F60) | H55: =IF(Agent01_Savings!A60="","",Agent01_Savings!I60) | I55: =IF(Agent01_Savings!A60="","",Agent01_Savings!J60) | J55: =IF(Agent01_Savings!A60="","",Agent01_Savings!K60) | K55: =IFERROR(IF(Agent01_Savings!A60="","",YEAR(Agent01_Savings!D60)),"")
A56: =IF(Agent01_Savings!A61="","",Agent01_Savings!A61) | B56: =IF(Agent01_Savings!A61="","","SV"&TEXT(56-3,"0000")&"-"&TEXT(TODAY(),"YYYYMMDD")) | C56: =IF(Agent01_Savings!A61="","",Agent01_Savings!B61) | D56: =IF(Agent01_Savings!A61="","",Agent01_Savings!G61) | E56: =IF(Agent01_Savings!A61="","",Agent01_Savings!D61) | F56: =IF(Agent01_Savings!A61="","",Agent01_Savings!E61) | G56: =IF(Agent01_Savings!A61="","",Agent01_Savings!F61) | H56: =IF(Agent01_Savings!A61="","",Agent01_Savings!I61) | I56: =IF(Agent01_Savings!A61="","",Agent01_Savings!J61) | J56: =IF(Agent01_Savings!A61="","",Agent01_Savings!K61) | K56: =IFERROR(IF(Agent01_Savings!A61="","",YEAR(Agent01_Savings!D61)),"")
A57: =IF(Agent01_Savings!A62="","",Agent01_Savings!A62) | B57: =IF(Agent01_Savings!A62="","","SV"&TEXT(57-3,"0000")&"-"&TEXT(TODAY(),"YYYYMMDD")) | C57: =IF(Agent01_Savings!A62="","",Agent01_Savings!B62) | D57: =IF(Agent01_Savings!A62="","",Agent01_Savings!G62) | E57: =IF(Agent01_Savings!A62="","",Agent01_Savings!D62) | F57: =IF(Agent01_Savings!A62="","",Agent01_Savings!E62) | G57: =IF(Agent01_Savings!A62="","",Agent01_Savings!F62) | H57: =IF(Agent01_Savings!A62="","",Agent01_Savings!I62) | I57: =IF(Agent01_Savings!A62="","",Agent01_Savings!J62) | J57: =IF(Agent01_Savings!A62="","",Agent01_Savings!K62) | K57: =IFERROR(IF(Agent01_Savings!A62="","",YEAR(Agent01_Savings!D62)),"")
A58: =IF(Agent01_Savings!A63="","",Agent01_Savings!A63) | B58: =IF(Agent01_Savings!A63="","","SV"&TEXT(58-3,"0000")&"-"&TEXT(TODAY(),"YYYYMMDD")) | C58: =IF(Agent01_Savings!A63="","",Agent01_Savings!B63) | D58: =IF(Agent01_Savings!A63="","",Agent01_Savings!G63) | E58: =IF(Agent01_Savings!A63="","",Agent01_Savings!D63) | F58: =IF(Agent01_Savings!A63="","",Agent01_Savings!E63) | G58: =IF(Agent01_Savings!A63="","",Agent01_Savings!F63) | H58: =IF(Agent01_Savings!A63="","",Agent01_Savings!I63) | I58: =IF(Agent01_Savings!A63="","",Agent01_Savings!J63) | J58: =IF(Agent01_Savings!A63="","",Agent01_Savings!K63) | K58: =IFERROR(IF(Agent01_Savings!A63="","",YEAR(Agent01_Savings!D63)),"")
A59: =IF(Agent01_Savings!A64="","",Agent01_Savings!A64) | B59: =IF(Agent01_Savings!A64="","","SV"&TEXT(59-3,"0000")&"-"&TEXT(TODAY(),"YYYYMMDD")) | C59: =IF(Agent01_Savings!A64="","",Agent01_Savings!B64) | D59: =IF(Agent01_Savings!A64="","",Agent01_Savings!G64) | E59: =IF(Agent01_Savings!A64="","",Agent01_Savings!D64) | F59: =IF(Agent01_Savings!A64="","",Agent01_Savings!E64) | G59: =IF(Agent01_Savings!A64="","",Agent01_Savings!F64) | H59: =IF(Agent01_Savings!A64="","",Agent01_Savings!I64) | I59: =IF(Agent01_Savings!A64="","",Agent01_Savings!J64) | J59: =IF(Agent01_Savings!A64="","",Agent01_Savings!K64) | K59: =IFERROR(IF(Agent01_Savings!A64="","",YEAR(Agent01_Savings!D64)),"")
A60: =IF(Agent01_Savings!A65="","",Agent01_Savings!A65) | B60: =IF(Agent01_Savings!A65="","","SV"&TEXT(60-3,"0000")&"-"&TEXT(TODAY(),"YYYYMMDD")) | C60: =IF(Agent01_Savings!A65="","",Agent01_Savings!B65) | D60: =IF(Agent01_Savings!A65="","",Agent01_Savings!G65) | E60: =IF(Agent01_Savings!A65="","",Agent01_Savings!D65) | F60: =IF(Agent01_Savings!A65="","",Agent01_Savings!E65) | G60: =IF(Agent01_Savings!A65="","",Agent01_Savings!F65) | H60: =IF(Agent01_Savings!A65="","",Agent01_Savings!I65) | I60: =IF(Agent01_Savings!A65="","",Agent01_Savings!J65) | J60: =IF(Agent01_Savings!A65="","",Agent01_Savings!K65) | K60: =IFERROR(IF(Agent01_Savings!A65="","",YEAR(Agent01_Savings!D65)),"")
A61: =IF(Agent01_Savings!A66="","",Agent01_Savings!A66) | B61: =IF(Agent01_Savings!A66="","","SV"&TEXT(61-3,"0000")&"-"&TEXT(TODAY(),"YYYYMMDD")) | C61: =IF(Agent01_Savings!A66="","",Agent01_Savings!B66) | D61: =IF(Agent01_Savings!A66="","",Agent01_Savings!G66) | E61: =IF(Agent01_Savings!A66="","",Agent01_Savings!D66) | F61: =IF(Agent01_Savings!A66="","",Agent01_Savings!E66) | G61: =IF(Agent01_Savings!A66="","",Agent01_Savings!F66) | H61: =IF(Agent01_Savings!A66="","",Agent01_Savings!I66) | I61: =IF(Agent01_Savings!A66="","",Agent01_Savings!J66) | J61: =IF(Agent01_Savings!A66="","",Agent01_Savings!K66) | K61: =IFERROR(IF(Agent01_Savings!A66="","",YEAR(Agent01_Savings!D66)),"")
A62: =IF(Agent01_Savings!A67="","",Agent01_Savings!A67) | B62: =IF(Agent01_Savings!A67="","","SV"&TEXT(62-3,"0000")&"-"&TEXT(TODAY(),"YYYYMMDD")) | C62: =IF(Agent01_Savings!A67="","",Agent01_Savings!B67) | D62: =IF(Agent01_Savings!A67="","",Agent01_Savings!G67) | E62: =IF(Agent01_Savings!A67="","",Agent01_Savings!D67) | F62: =IF(Agent01_Savings!A67="","",Agent01_Savings!E67) | G62: =IF(Agent01_Savings!A67="","",Agent01_Savings!F67) | H62: =IF(Agent01_Savings!A67="","",Agent01_Savings!I67) | I62: =IF(Agent01_Savings!A67="","",Agent01_Savings!J67) | J62: =IF(Agent01_Savings!A67="","",Agent01_Savings!K67) | K62: =IFERROR(IF(Agent01_Savings!A67="","",YEAR(Agent01_Savings!D67)),"")
A63: =IF(Agent01_Savings!A68="","",Agent01_Savings!A68) | B63: =IF(Agent01_Savings!A68="","","SV"&TEXT(63-3,"0000")&"-"&TEXT(TODAY(),"YYYYMMDD")) | C63: =IF(Agent01_Savings!A68="","",Agent01_Savings!B68) | D63: =IF(Agent01_Savings!A68="","",Agent01_Savings!G68) | E63: =IF(Agent01_Savings!A68="","",Agent01_Savings!D68) | F63: =IF(Agent01_Savings!A68="","",Agent01_Savings!E68) | G63: =IF(Agent01_Savings!A68="","",Agent01_Savings!F68) | H63: =IF(Agent01_Savings!A68="","",Agent01_Savings!I68) | I63: =IF(Agent01_Savings!A68="","",Agent01_Savings!J68) | J63: =IF(Agent01_Savings!A68="","",Agent01_Savings!K68) | K63: =IFERROR(IF(Agent01_Savings!A68="","",YEAR(Agent01_Savings!D68)),"")
A64: =IF(Agent01_Savings!A69="","",Agent01_Savings!A69) | B64: =IF(Agent01_Savings!A69="","","SV"&TEXT(64-3,"0000")&"-"&TEXT(TODAY(),"YYYYMMDD")) | C64: =IF(Agent01_Savings!A69="","",Agent01_Savings!B69) | D64: =IF(Agent01_Savings!A69="","",Agent01_Savings!G69) | E64: =IF(Agent01_Savings!A69="","",Agent01_Savings!D69) | F64: =IF(Agent01_Savings!A69="","",Agent01_Savings!E69) | G64: =IF(Agent01_Savings!A69="","",Agent01_Savings!F69) | H64: =IF(Agent01_Savings!A69="","",Agent01_Savings!I69) | I64: =IF(Agent01_Savings!A69="","",Agent01_Savings!J69) | J64: =IF(Agent01_Savings!A69="","",Agent01_Savings!K69) | K64: =IFERROR(IF(Agent01_Savings!A69="","",YEAR(Agent01_Savings!D69)),"")
A65: =IF(Agent01_Savings!A70="","",Agent01_Savings!A70) | B65: =IF(Agent01_Savings!A70="","","SV"&TEXT(65-3,"0000")&"-"&TEXT(TODAY(),"YYYYMMDD")) | C65: =IF(Agent01_Savings!A70="","",Agent01_Savings!B70) | D65: =IF(Agent01_Savings!A70="","",Agent01_Savings!G70) | E65: =IF(Agent01_Savings!A70="","",Agent01_Savings!D70) | F65: =IF(Agent01_Savings!A70="","",Agent01_Savings!E70) | G65: =IF(Agent01_Savings!A70="","",Agent01_Savings!F70) | H65: =IF(Agent01_Savings!A70="","",Agent01_Savings!I70) | I65: =IF(Agent01_Savings!A70="","",Agent01_Savings!J70) | J65: =IF(Agent01_Savings!A70="","",Agent01_Savings!K70) | K65: =IFERROR(IF(Agent01_Savings!A70="","",YEAR(Agent01_Savings!D70)),"")
A66: =IF(Agent01_Savings!A71="","",Agent01_Savings!A71) | B66: =IF(Agent01_Savings!A71="","","SV"&TEXT(66-3,"0000")&"-"&TEXT(TODAY(),"YYYYMMDD")) | C66: =IF(Agent01_Savings!A71="","",Agent01_Savings!B71) | D66: =IF(Agent01_Savings!A71="","",Agent01_Savings!G71) | E66: =IF(Agent01_Savings!A71="","",Agent01_Savings!D71) | F66: =IF(Agent01_Savings!A71="","",Agent01_Savings!E71) | G66: =IF(Agent01_Savings!A71="","",Agent01_Savings!F71) | H66: =IF(Agent01_Savings!A71="","",Agent01_Savings!I71) | I66: =IF(Agent01_Savings!A71="","",Agent01_Savings!J71) | J66: =IF(Agent01_Savings!A71="","",Agent01_Savings!K71) | K66: =IFERROR(IF(Agent01_Savings!A71="","",YEAR(Agent01_Savings!D71)),"")
A67: =IF(Agent01_Savings!A72="","",Agent01_Savings!A72) | B67: =IF(Agent01_Savings!A72="","","SV"&TEXT(67-3,"0000")&"-"&TEXT(TODAY(),"YYYYMMDD")) | C67: =IF(Agent01_Savings!A72="","",Agent01_Savings!B72) | D67: =IF(Agent01_Savings!A72="","",Agent01_Savings!G72) | E67: =IF(Agent01_Savings!A72="","",Agent01_Savings!D72) | F67: =IF(Agent01_Savings!A72="","",Agent01_Savings!E72) | G67: =IF(Agent01_Savings!A72="","",Agent01_Savings!F72) | H67: =IF(Agent01_Savings!A72="","",Agent01_Savings!I72) | I67: =IF(Agent01_Savings!A72="","",Agent01_Savings!J72) | J67: =IF(Agent01_Savings!A72="","",Agent01_Savings!K72) | K67: =IFERROR(IF(Agent01_Savings!A72="","",YEAR(Agent01_Savings!D72)),"")
A68: =IF(Agent01_Savings!A73="","",Agent01_Savings!A73) | B68: =IF(Agent01_Savings!A73="","","SV"&TEXT(68-3,"0000")&"-"&TEXT(TODAY(),"YYYYMMDD")) | C68: =IF(Agent01_Savings!A73="","",Agent01_Savings!B73) | D68: =IF(Agent01_Savings!A73="","",Agent01_Savings!G73) | E68: =IF(Agent01_Savings!A73="","",Agent01_Savings!D73) | F68: =IF(Agent01_Savings!A73="","",Agent01_Savings!E73) | G68: =IF(Agent01_Savings!A73="","",Agent01_Savings!F73) | H68: =IF(Agent01_Savings!A73="","",Agent01_Savings!I73) | I68: =IF(Agent01_Savings!A73="","",Agent01_Savings!J73) | J68: =IF(Agent01_Savings!A73="","",Agent01_Savings!K73) | K68: =IFERROR(IF(Agent01_Savings!A73="","",YEAR(Agent01_Savings!D73)),"")
A69: =IF(Agent01_Savings!A74="","",Agent01_Savings!A74) | B69: =IF(Agent01_Savings!A74="","","SV"&TEXT(69-3,"0000")&"-"&TEXT(TODAY(),"YYYYMMDD")) | C69: =IF(Agent01_Savings!A74="","",Agent01_Savings!B74) | D69: =IF(Agent01_Savings!A74="","",Agent01_Savings!G74) | E69: =IF(Agent01_Savings!A74="","",Agent01_Savings!D74) | F69: =IF(Agent01_Savings!A74="","",Agent01_Savings!E74) | G69: =IF(Agent01_Savings!A74="","",Agent01_Savings!F74) | H69: =IF(Agent01_Savings!A74="","",Agent01_Savings!I74) | I69: =IF(Agent01_Savings!A74="","",Agent01_Savings!J74) | J69: =IF(Agent01_Savings!A74="","",Agent01_Savings!K74) | K69: =IFERROR(IF(Agent01_Savings!A74="","",YEAR(Agent01_Savings!D74)),"")
A70: =IF(Agent01_Savings!A75="","",Agent01_Savings!A75) | B70: =IF(Agent01_Savings!A75="","","SV"&TEXT(70-3,"0000")&"-"&TEXT(TODAY(),"YYYYMMDD")) | C70: =IF(Agent01_Savings!A75="","",Agent01_Savings!B75) | D70: =IF(Agent01_Savings!A75="","",Agent01_Savings!G75) | E70: =IF(Agent01_Savings!A75="","",Agent01_Savings!D75) | F70: =IF(Agent01_Savings!A75="","",Agent01_Savings!E75) | G70: =IF(Agent01_Savings!A75="","",Agent01_Savings!F75) | H70: =IF(Agent01_Savings!A75="","",Agent01_Savings!I75) | I70: =IF(Agent01_Savings!A75="","",Agent01_Savings!J75) | J70: =IF(Agent01_Savings!A75="","",Agent01_Savings!K75) | K70: =IFERROR(IF(Agent01_Savings!A75="","",YEAR(Agent01_Savings!D75)),"")
A71: =IF(Agent01_Savings!A76="","",Agent01_Savings!A76) | B71: =IF(Agent01_Savings!A76="","","SV"&TEXT(71-3,"0000")&"-"&TEXT(TODAY(),"YYYYMMDD")) | C71: =IF(Agent01_Savings!A76="","",Agent01_Savings!B76) | D71: =IF(Agent01_Savings!A76="","",Agent01_Savings!G76) | E71: =IF(Agent01_Savings!A76="","",Agent01_Savings!D76) | F71: =IF(Agent01_Savings!A76="","",Agent01_Savings!E76) | G71: =IF(Agent01_Savings!A76="","",Agent01_Savings!F76) | H71: =IF(Agent01_Savings!A76="","",Agent01_Savings!I76) | I71: =IF(Agent01_Savings!A76="","",Agent01_Savings!J76) | J71: =IF(Agent01_Savings!A76="","",Agent01_Savings!K76) | K71: =IFERROR(IF(Agent01_Savings!A76="","",YEAR(Agent01_Savings!D76)),"")
A72: =IF(Agent01_Savings!A77="","",Agent01_Savings!A77) | B72: =IF(Agent01_Savings!A77="","","SV"&TEXT(72-3,"0000")&"-"&TEXT(TODAY(),"YYYYMMDD")) | C72: =IF(Agent01_Savings!A77="","",Agent01_Savings!B77) | D72: =IF(Agent01_Savings!A77="","",Agent01_Savings!G77) | E72: =IF(Agent01_Savings!A77="","",Agent01_Savings!D77) | F72: =IF(Agent01_Savings!A77="","",Agent01_Savings!E77) | G72: =IF(Agent01_Savings!A77="","",Agent01_Savings!F77) | H72: =IF(Agent01_Savings!A77="","",Agent01_Savings!I77) | I72: =IF(Agent01_Savings!A77="","",Agent01_Savings!J77) | J72: =IF(Agent01_Savings!A77="","",Agent01_Savings!K77) | K72: =IFERROR(IF(Agent01_Savings!A77="","",YEAR(Agent01_Savings!D77)),"")
A73: =IF(Agent01_Savings!A78="","",Agent01_Savings!A78) | B73: =IF(Agent01_Savings!A78="","","SV"&TEXT(73-3,"0000")&"-"&TEXT(TODAY(),"YYYYMMDD")) | C73: =IF(Agent01_Savings!A78="","",Agent01_Savings!B78) | D73: =IF(Agent01_Savings!A78="","",Agent01_Savings!G78) | E73: =IF(Agent01_Savings!A78="","",Agent01_Savings!D78) | F73: =IF(Agent01_Savings!A78="","",Agent01_Savings!E78) | G73: =IF(Agent01_Savings!A78="","",Agent01_Savings!F78) | H73: =IF(Agent01_Savings!A78="","",Agent01_Savings!I78) | I73: =IF(Agent01_Savings!A78="","",Agent01_Savings!J78) | J73: =IF(Agent01_Savings!A78="","",Agent01_Savings!K78) | K73: =IFERROR(IF(Agent01_Savings!A78="","",YEAR(Agent01_Savings!D78)),"")
A74: =IF(Agent01_Savings!A79="","",Agent01_Savings!A79) | B74: =IF(Agent01_Savings!A79="","","SV"&TEXT(74-3,"0000")&"-"&TEXT(TODAY(),"YYYYMMDD")) | C74: =IF(Agent01_Savings!A79="","",Agent01_Savings!B79) | D74: =IF(Agent01_Savings!A79="","",Agent01_Savings!G79) | E74: =IF(Agent01_Savings!A79="","",Agent01_Savings!D79) | F74: =IF(Agent01_Savings!A79="","",Agent01_Savings!E79) | G74: =IF(Agent01_Savings!A79="","",Agent01_Savings!F79) | H74: =IF(Agent01_Savings!A79="","",Agent01_Savings!I79) | I74: =IF(Agent01_Savings!A79="","",Agent01_Savings!J79) | J74: =IF(Agent01_Savings!A79="","",Agent01_Savings!K79) | K74: =IFERROR(IF(Agent01_Savings!A79="","",YEAR(Agent01_Savings!D79)),"")
A75: =IF(Agent01_Savings!A80="","",Agent01_Savings!A80) | B75: =IF(Agent01_Savings!A80="","","SV"&TEXT(75-3,"0000")&"-"&TEXT(TODAY(),"YYYYMMDD")) | C75: =IF(Agent01_Savings!A80="","",Agent01_Savings!B80) | D75: =IF(Agent01_Savings!A80="","",Agent01_Savings!G80) | E75: =IF(Agent01_Savings!A80="","",Agent01_Savings!D80) | F75: =IF(Agent01_Savings!A80="","",Agent01_Savings!E80) | G75: =IF(Agent01_Savings!A80="","",Agent01_Savings!F80) | H75: =IF(Agent01_Savings!A80="","",Agent01_Savings!I80) | I75: =IF(Agent01_Savings!A80="","",Agent01_Savings!J80) | J75: =IF(Agent01_Savings!A80="","",Agent01_Savings!K80) | K75: =IFERROR(IF(Agent01_Savings!A80="","",YEAR(Agent01_Savings!D80)),"")
A76: =IF(Agent01_Savings!A81="","",Agent01_Savings!A81) | B76: =IF(Agent01_Savings!A81="","","SV"&TEXT(76-3,"0000")&"-"&TEXT(TODAY(),"YYYYMMDD")) | C76: =IF(Agent01_Savings!A81="","",Agent01_Savings!B81) | D76: =IF(Agent01_Savings!A81="","",Agent01_Savings!G81) | E76: =IF(Agent01_Savings!A81="","",Agent01_Savings!D81) | F76: =IF(Agent01_Savings!A81="","",Agent01_Savings!E81) | G76: =IF(Agent01_Savings!A81="","",Agent01_Savings!F81) | H76: =IF(Agent01_Savings!A81="","",Agent01_Savings!I81) | I76: =IF(Agent01_Savings!A81="","",Agent01_Savings!J81) | J76: =IF(Agent01_Savings!A81="","",Agent01_Savings!K81) | K76: =IFERROR(IF(Agent01_Savings!A81="","",YEAR(Agent01_Savings!D81)),"")
A77: =IF(Agent01_Savings!A82="","",Agent01_Savings!A82) | B77: =IF(Agent01_Savings!A82="","","SV"&TEXT(77-3,"0000")&"-"&TEXT(TODAY(),"YYYYMMDD")) | C77: =IF(Agent01_Savings!A82="","",Agent01_Savings!B82) | D77: =IF(Agent01_Savings!A82="","",Agent01_Savings!G82) | E77: =IF(Agent01_Savings!A82="","",Agent01_Savings!D82) | F77: =IF(Agent01_Savings!A82="","",Agent01_Savings!E82) | G77: =IF(Agent01_Savings!A82="","",Agent01_Savings!F82) | H77: =IF(Agent01_Savings!A82="","",Agent01_Savings!I82) | I77: =IF(Agent01_Savings!A82="","",Agent01_Savings!J82) | J77: =IF(Agent01_Savings!A82="","",Agent01_Savings!K82) | K77: =IFERROR(IF(Agent01_Savings!A82="","",YEAR(Agent01_Savings!D82)),"")
A78: =IF(Agent01_Savings!A83="","",Agent01_Savings!A83) | B78: =IF(Agent01_Savings!A83="","","SV"&TEXT(78-3,"0000")&"-"&TEXT(TODAY(),"YYYYMMDD")) | C78: =IF(Agent01_Savings!A83="","",Agent01_Savings!B83) | D78: =IF(Agent01_Savings!A83="","",Agent01_Savings!G83) | E78: =IF(Agent01_Savings!A83="","",Agent01_Savings!D83) | F78: =IF(Agent01_Savings!A83="","",Agent01_Savings!E83) | G78: =IF(Agent01_Savings!A83="","",Agent01_Savings!F83) | H78: =IF(Agent01_Savings!A83="","",Agent01_Savings!I83) | I78: =IF(Agent01_Savings!A83="","",Agent01_Savings!J83) | J78: =IF(Agent01_Savings!A83="","",Agent01_Savings!K83) | K78: =IFERROR(IF(Agent01_Savings!A83="","",YEAR(Agent01_Savings!D83)),"")
A79: =IF(Agent01_Savings!A84="","",Agent01_Savings!A84) | B79: =IF(Agent01_Savings!A84="","","SV"&TEXT(79-3,"0000")&"-"&TEXT(TODAY(),"YYYYMMDD")) | C79: =IF(Agent01_Savings!A84="","",Agent01_Savings!B84) | D79: =IF(Agent01_Savings!A84="","",Agent01_Savings!G84) | E79: =IF(Agent01_Savings!A84="","",Agent01_Savings!D84) | F79: =IF(Agent01_Savings!A84="","",Agent01_Savings!E84) | G79: =IF(Agent01_Savings!A84="","",Agent01_Savings!F84) | H79: =IF(Agent01_Savings!A84="","",Agent01_Savings!I84) | I79: =IF(Agent01_Savings!A84="","",Agent01_Savings!J84) | J79: =IF(Agent01_Savings!A84="","",Agent01_Savings!K84) | K79: =IFERROR(IF(Agent01_Savings!A84="","",YEAR(Agent01_Savings!D84)),"")
A80: =IF(Agent01_Savings!A85="","",Agent01_Savings!A85) | B80: =IF(Agent01_Savings!A85="","","SV"&TEXT(80-3,"0000")&"-"&TEXT(TODAY(),"YYYYMMDD")) | C80: =IF(Agent01_Savings!A85="","",Agent01_Savings!B85) | D80: =IF(Agent01_Savings!A85="","",Agent01_Savings!G85) | E80: =IF(Agent01_Savings!A85="","",Agent01_Savings!D85) | F80: =IF(Agent01_Savings!A85="","",Agent01_Savings!E85) | G80: =IF(Agent01_Savings!A85="","",Agent01_Savings!F85) | H80: =IF(Agent01_Savings!A85="","",Agent01_Savings!I85) | I80: =IF(Agent01_Savings!A85="","",Agent01_Savings!J85) | J80: =IF(Agent01_Savings!A85="","",Agent01_Savings!K85) | K80: =IFERROR(IF(Agent01_Savings!A85="","",YEAR(Agent01_Savings!D85)),"")
A81: =IF(Agent01_Savings!A86="","",Agent01_Savings!A86) | B81: =IF(Agent01_Savings!A86="","","SV"&TEXT(81-3,"0000")&"-"&TEXT(TODAY(),"YYYYMMDD")) | C81: =IF(Agent01_Savings!A86="","",Agent01_Savings!B86) | D81: =IF(Agent01_Savings!A86="","",Agent01_Savings!G86) | E81: =IF(Agent01_Savings!A86="","",Agent01_Savings!D86) | F81: =IF(Agent01_Savings!A86="","",Agent01_Savings!E86) | G81: =IF(Agent01_Savings!A86="","",Agent01_Savings!F86) | H81: =IF(Agent01_Savings!A86="","",Agent01_Savings!I86) | I81: =IF(Agent01_Savings!A86="","",Agent01_Savings!J86) | J81: =IF(Agent01_Savings!A86="","",Agent01_Savings!K86) | K81: =IFERROR(IF(Agent01_Savings!A86="","",YEAR(Agent01_Savings!D86)),"")
A82: =IF(Agent01_Savings!A87="","",Agent01_Savings!A87) | B82: =IF(Agent01_Savings!A87="","","SV"&TEXT(82-3,"0000")&"-"&TEXT(TODAY(),"YYYYMMDD")) | C82: =IF(Agent01_Savings!A87="","",Agent01_Savings!B87) | D82: =IF(Agent01_Savings!A87="","",Agent01_Savings!G87) | E82: =IF(Agent01_Savings!A87="","",Agent01_Savings!D87) | F82: =IF(Agent01_Savings!A87="","",Agent01_Savings!E87) | G82: =IF(Agent01_Savings!A87="","",Agent01_Savings!F87) | H82: =IF(Agent01_Savings!A87="","",Agent01_Savings!I87) | I82: =IF(Agent01_Savings!A87="","",Agent01_Savings!J87) | J82: =IF(Agent01_Savings!A87="","",Agent01_Savings!K87) | K82: =IFERROR(IF(Agent01_Savings!A87="","",YEAR(Agent01_Savings!D87)),"")
A83: =IF(Agent01_Savings!A88="","",Agent01_Savings!A88) | B83: =IF(Agent01_Savings!A88="","","SV"&TEXT(83-3,"0000")&"-"&TEXT(TODAY(),"YYYYMMDD")) | C83: =IF(Agent01_Savings!A88="","",Agent01_Savings!B88) | D83: =IF(Agent01_Savings!A88="","",Agent01_Savings!G88) | E83: =IF(Agent01_Savings!A88="","",Agent01_Savings!D88) | F83: =IF(Agent01_Savings!A88="","",Agent01_Savings!E88) | G83: =IF(Agent01_Savings!A88="","",Agent01_Savings!F88) | H83: =IF(Agent01_Savings!A88="","",Agent01_Savings!I88) | I83: =IF(Agent01_Savings!A88="","",Agent01_Savings!J88) | J83: =IF(Agent01_Savings!A88="","",Agent01_Savings!K88) | K83: =IFERROR(IF(Agent01_Savings!A88="","",YEAR(Agent01_Savings!D88)),"")
A84: =IF(Agent01_Savings!A89="","",Agent01_Savings!A89) | B84: =IF(Agent01_Savings!A89="","","SV"&TEXT(84-3,"0000")&"-"&TEXT(TODAY(),"YYYYMMDD")) | C84: =IF(Agent01_Savings!A89="","",Agent01_Savings!B89) | D84: =IF(Agent01_Savings!A89="","",Agent01_Savings!G89) | E84: =IF(Agent01_Savings!A89="","",Agent01_Savings!D89) | F84: =IF(Agent01_Savings!A89="","",Agent01_Savings!E89) | G84: =IF(Agent01_Savings!A89="","",Agent01_Savings!F89) | H84: =IF(Agent01_Savings!A89="","",Agent01_Savings!I89) | I84: =IF(Agent01_Savings!A89="","",Agent01_Savings!J89) | J84: =IF(Agent01_Savings!A89="","",Agent01_Savings!K89) | K84: =IFERROR(IF(Agent01_Savings!A89="","",YEAR(Agent01_Savings!D89)),"")
A85: =IF(Agent01_Savings!A90="","",Agent01_Savings!A90) | B85: =IF(Agent01_Savings!A90="","","SV"&TEXT(85-3,"0000")&"-"&TEXT(TODAY(),"YYYYMMDD")) | C85: =IF(Agent01_Savings!A90="","",Agent01_Savings!B90) | D85: =IF(Agent01_Savings!A90="","",Agent01_Savings!G90) | E85: =IF(Agent01_Savings!A90="","",Agent01_Savings!D90) | F85: =IF(Agent01_Savings!A90="","",Agent01_Savings!E90) | G85: =IF(Agent01_Savings!A90="","",Agent01_Savings!F90) | H85: =IF(Agent01_Savings!A90="","",Agent01_Savings!I90) | I85: =IF(Agent01_Savings!A90="","",Agent01_Savings!J90) | J85: =IF(Agent01_Savings!A90="","",Agent01_Savings!K90) | K85: =IFERROR(IF(Agent01_Savings!A90="","",YEAR(Agent01_Savings!D90)),"")
A86: =IF(Agent01_Savings!A91="","",Agent01_Savings!A91) | B86: =IF(Agent01_Savings!A91="","","SV"&TEXT(86-3,"0000")&"-"&TEXT(TODAY(),"YYYYMMDD")) | C86: =IF(Agent01_Savings!A91="","",Agent01_Savings!B91) | D86: =IF(Agent01_Savings!A91="","",Agent01_Savings!G91) | E86: =IF(Agent01_Savings!A91="","",Agent01_Savings!D91) | F86: =IF(Agent01_Savings!A91="","",Agent01_Savings!E91) | G86: =IF(Agent01_Savings!A91="","",Agent01_Savings!F91) | H86: =IF(Agent01_Savings!A91="","",Agent01_Savings!I91) | I86: =IF(Agent01_Savings!A91="","",Agent01_Savings!J91) | J86: =IF(Agent01_Savings!A91="","",Agent01_Savings!K91) | K86: =IFERROR(IF(Agent01_Savings!A91="","",YEAR(Agent01_Savings!D91)),"")
A87: =IF(Agent01_Savings!A92="","",Agent01_Savings!A92) | B87: =IF(Agent01_Savings!A92="","","SV"&TEXT(87-3,"0000")&"-"&TEXT(TODAY(),"YYYYMMDD")) | C87: =IF(Agent01_Savings!A92="","",Agent01_Savings!B92) | D87: =IF(Agent01_Savings!A92="","",Agent01_Savings!G92) | E87: =IF(Agent01_Savings!A92="","",Agent01_Savings!D92) | F87: =IF(Agent01_Savings!A92="","",Agent01_Savings!E92) | G87: =IF(Agent01_Savings!A92="","",Agent01_Savings!F92) | H87: =IF(Agent01_Savings!A92="","",Agent01_Savings!I92) | I87: =IF(Agent01_Savings!A92="","",Agent01_Savings!J92) | J87: =IF(Agent01_Savings!A92="","",Agent01_Savings!K92) | K87: =IFERROR(IF(Agent01_Savings!A92="","",YEAR(Agent01_Savings!D92)),"")
A88: =IF(Agent01_Savings!A93="","",Agent01_Savings!A93) | B88: =IF(Agent01_Savings!A93="","","SV"&TEXT(88-3,"0000")&"-"&TEXT(TODAY(),"YYYYMMDD")) | C88: =IF(Agent01_Savings!A93="","",Agent01_Savings!B93) | D88: =IF(Agent01_Savings!A93="","",Agent01_Savings!G93) | E88: =IF(Agent01_Savings!A93="","",Agent01_Savings!D93) | F88: =IF(Agent01_Savings!A93="","",Agent01_Savings!E93) | G88: =IF(Agent01_Savings!A93="","",Agent01_Savings!F93) | H88: =IF(Agent01_Savings!A93="","",Agent01_Savings!I93) | I88: =IF(Agent01_Savings!A93="","",Agent01_Savings!J93) | J88: =IF(Agent01_Savings!A93="","",Agent01_Savings!K93) | K88: =IFERROR(IF(Agent01_Savings!A93="","",YEAR(Agent01_Savings!D93)),"")
A89: =IF(Agent01_Savings!A94="","",Agent01_Savings!A94) | B89: =IF(Agent01_Savings!A94="","","SV"&TEXT(89-3,"0000")&"-"&TEXT(TODAY(),"YYYYMMDD")) | C89: =IF(Agent01_Savings!A94="","",Agent01_Savings!B94) | D89: =IF(Agent01_Savings!A94="","",Agent01_Savings!G94) | E89: =IF(Agent01_Savings!A94="","",Agent01_Savings!D94) | F89: =IF(Agent01_Savings!A94="","",Agent01_Savings!E94) | G89: =IF(Agent01_Savings!A94="","",Agent01_Savings!F94) | H89: =IF(Agent01_Savings!A94="","",Agent01_Savings!I94) | I89: =IF(Agent01_Savings!A94="","",Agent01_Savings!J94) | J89: =IF(Agent01_Savings!A94="","",Agent01_Savings!K94) | K89: =IFERROR(IF(Agent01_Savings!A94="","",YEAR(Agent01_Savings!D94)),"")
A90: =IF(Agent01_Savings!A95="","",Agent01_Savings!A95) | B90: =IF(Agent01_Savings!A95="","","SV"&TEXT(90-3,"0000")&"-"&TEXT(TODAY(),"YYYYMMDD")) | C90: =IF(Agent01_Savings!A95="","",Agent01_Savings!B95) | D90: =IF(Agent01_Savings!A95="","",Agent01_Savings!G95) | E90: =IF(Agent01_Savings!A95="","",Agent01_Savings!D95) | F90: =IF(Agent01_Savings!A95="","",Agent01_Savings!E95) | G90: =IF(Agent01_Savings!A95="","",Agent01_Savings!F95) | H90: =IF(Agent01_Savings!A95="","",Agent01_Savings!I95) | I90: =IF(Agent01_Savings!A95="","",Agent01_Savings!J95) | J90: =IF(Agent01_Savings!A95="","",Agent01_Savings!K95) | K90: =IFERROR(IF(Agent01_Savings!A95="","",YEAR(Agent01_Savings!D95)),"")
A91: =IF(Agent01_Savings!A96="","",Agent01_Savings!A96) | B91: =IF(Agent01_Savings!A96="","","SV"&TEXT(91-3,"0000")&"-"&TEXT(TODAY(),"YYYYMMDD")) | C91: =IF(Agent01_Savings!A96="","",Agent01_Savings!B96) | D91: =IF(Agent01_Savings!A96="","",Agent01_Savings!G96) | E91: =IF(Agent01_Savings!A96="","",Agent01_Savings!D96) | F91: =IF(Agent01_Savings!A96="","",Agent01_Savings!E96) | G91: =IF(Agent01_Savings!A96="","",Agent01_Savings!F96) | H91: =IF(Agent01_Savings!A96="","",Agent01_Savings!I96) | I91: =IF(Agent01_Savings!A96="","",Agent01_Savings!J96) | J91: =IF(Agent01_Savings!A96="","",Agent01_Savings!K96) | K91: =IFERROR(IF(Agent01_Savings!A96="","",YEAR(Agent01_Savings!D96)),"")
A92: =IF(Agent01_Savings!A97="","",Agent01_Savings!A97) | B92: =IF(Agent01_Savings!A97="","","SV"&TEXT(92-3,"0000")&"-"&TEXT(TODAY(),"YYYYMMDD")) | C92: =IF(Agent01_Savings!A97="","",Agent01_Savings!B97) | D92: =IF(Agent01_Savings!A97="","",Agent01_Savings!G97) | E92: =IF(Agent01_Savings!A97="","",Agent01_Savings!D97) | F92: =IF(Agent01_Savings!A97="","",Agent01_Savings!E97) | G92: =IF(Agent01_Savings!A97="","",Agent01_Savings!F97) | H92: =IF(Agent01_Savings!A97="","",Agent01_Savings!I97) | I92: =IF(Agent01_Savings!A97="","",Agent01_Savings!J97) | J92: =IF(Agent01_Savings!A97="","",Agent01_Savings!K97) | K92: =IFERROR(IF(Agent01_Savings!A97="","",YEAR(Agent01_Savings!D97)),"")
A93: =IF(Agent01_Savings!A98="","",Agent01_Savings!A98) | B93: =IF(Agent01_Savings!A98="","","SV"&TEXT(93-3,"0000")&"-"&TEXT(TODAY(),"YYYYMMDD")) | C93: =IF(Agent01_Savings!A98="","",Agent01_Savings!B98) | D93: =IF(Agent01_Savings!A98="","",Agent01_Savings!G98) | E93: =IF(Agent01_Savings!A98="","",Agent01_Savings!D98) | F93: =IF(Agent01_Savings!A98="","",Agent01_Savings!E98) | G93: =IF(Agent01_Savings!A98="","",Agent01_Savings!F98) | H93: =IF(Agent01_Savings!A98="","",Agent01_Savings!I98) | I93: =IF(Agent01_Savings!A98="","",Agent01_Savings!J98) | J93: =IF(Agent01_Savings!A98="","",Agent01_Savings!K98) | K93: =IFERROR(IF(Agent01_Savings!A98="","",YEAR(Agent01_Savings!D98)),"")
A94: =IF(Agent01_Savings!A99="","",Agent01_Savings!A99) | B94: =IF(Agent01_Savings!A99="","","SV"&TEXT(94-3,"0000")&"-"&TEXT(TODAY(),"YYYYMMDD")) | C94: =IF(Agent01_Savings!A99="","",Agent01_Savings!B99) | D94: =IF(Agent01_Savings!A99="","",Agent01_Savings!G99) | E94: =IF(Agent01_Savings!A99="","",Agent01_Savings!D99) | F94: =IF(Agent01_Savings!A99="","",Agent01_Savings!E99) | G94: =IF(Agent01_Savings!A99="","",Agent01_Savings!F99) | H94: =IF(Agent01_Savings!A99="","",Agent01_Savings!I99) | I94: =IF(Agent01_Savings!A99="","",Agent01_Savings!J99) | J94: =IF(Agent01_Savings!A99="","",Agent01_Savings!K99) | K94: =IFERROR(IF(Agent01_Savings!A99="","",YEAR(Agent01_Savings!D99)),"")
A95: =IF(Agent01_Savings!A100="","",Agent01_Savings!A100) | B95: =IF(Agent01_Savings!A100="","","SV"&TEXT(95-3,"0000")&"-"&TEXT(TODAY(),"YYYYMMDD")) | C95: =IF(Agent01_Savings!A100="","",Agent01_Savings!B100) | D95: =IF(Agent01_Savings!A100="","",Agent01_Savings!G100) | E95: =IF(Agent01_Savings!A100="","",Agent01_Savings!D100) | F95: =IF(Agent01_Savings!A100="","",Agent01_Savings!E100) | G95: =IF(Agent01_Savings!A100="","",Agent01_Savings!F100) | H95: =IF(Agent01_Savings!A100="","",Agent01_Savings!I100) | I95: =IF(Agent01_Savings!A100="","",Agent01_Savings!J100) | J95: =IF(Agent01_Savings!A100="","",Agent01_Savings!K100) | K95: =IFERROR(IF(Agent01_Savings!A100="","",YEAR(Agent01_Savings!D100)),"")
A96: =IF(Agent01_Savings!A101="","",Agent01_Savings!A101) | B96: =IF(Agent01_Savings!A101="","","SV"&TEXT(96-3,"0000")&"-"&TEXT(TODAY(),"YYYYMMDD")) | C96: =IF(Agent01_Savings!A101="","",Agent01_Savings!B101) | D96: =IF(Agent01_Savings!A101="","",Agent01_Savings!G101) | E96: =IF(Agent01_Savings!A101="","",Agent01_Savings!D101) | F96: =IF(Agent01_Savings!A101="","",Agent01_Savings!E101) | G96: =IF(Agent01_Savings!A101="","",Agent01_Savings!F101) | H96: =IF(Agent01_Savings!A101="","",Agent01_Savings!I101) | I96: =IF(Agent01_Savings!A101="","",Agent01_Savings!J101) | J96: =IF(Agent01_Savings!A101="","",Agent01_Savings!K101) | K96: =IFERROR(IF(Agent01_Savings!A101="","",YEAR(Agent01_Savings!D101)),"")
A97: =IF(Agent01_Savings!A102="","",Agent01_Savings!A102) | B97: =IF(Agent01_Savings!A102="","","SV"&TEXT(97-3,"0000")&"-"&TEXT(TODAY(),"YYYYMMDD")) | C97: =IF(Agent01_Savings!A102="","",Agent01_Savings!B102) | D97: =IF(Agent01_Savings!A102="","",Agent01_Savings!G102) | E97: =IF(Agent01_Savings!A102="","",Agent01_Savings!D102) | F97: =IF(Agent01_Savings!A102="","",Agent01_Savings!E102) | G97: =IF(Agent01_Savings!A102="","",Agent01_Savings!F102) | H97: =IF(Agent01_Savings!A102="","",Agent01_Savings!I102) | I97: =IF(Agent01_Savings!A102="","",Agent01_Savings!J102) | J97: =IF(Agent01_Savings!A102="","",Agent01_Savings!K102) | K97: =IFERROR(IF(Agent01_Savings!A102="","",YEAR(Agent01_Savings!D102)),"")
A98: =IF(Agent01_Savings!A103="","",Agent01_Savings!A103) | B98: =IF(Agent01_Savings!A103="","","SV"&TEXT(98-3,"0000")&"-"&TEXT(TODAY(),"YYYYMMDD")) | C98: =IF(Agent01_Savings!A103="","",Agent01_Savings!B103) | D98: =IF(Agent01_Savings!A103="","",Agent01_Savings!G103) | E98: =IF(Agent01_Savings!A103="","",Agent01_Savings!D103) | F98: =IF(Agent01_Savings!A103="","",Agent01_Savings!E103) | G98: =IF(Agent01_Savings!A103="","",Agent01_Savings!F103) | H98: =IF(Agent01_Savings!A103="","",Agent01_Savings!I103) | I98: =IF(Agent01_Savings!A103="","",Agent01_Savings!J103) | J98: =IF(Agent01_Savings!A103="","",Agent01_Savings!K103) | K98: =IFERROR(IF(Agent01_Savings!A103="","",YEAR(Agent01_Savings!D103)),"")
A99: =IF(Agent01_Savings!A104="","",Agent01_Savings!A104) | B99: =IF(Agent01_Savings!A104="","","SV"&TEXT(99-3,"0000")&"-"&TEXT(TODAY(),"YYYYMMDD")) | C99: =IF(Agent01_Savings!A104="","",Agent01_Savings!B104) | D99: =IF(Agent01_Savings!A104="","",Agent01_Savings!G104) | E99: =IF(Agent01_Savings!A104="","",Agent01_Savings!D104) | F99: =IF(Agent01_Savings!A104="","",Agent01_Savings!E104) | G99: =IF(Agent01_Savings!A104="","",Agent01_Savings!F104) | H99: =IF(Agent01_Savings!A104="","",Agent01_Savings!I104) | I99: =IF(Agent01_Savings!A104="","",Agent01_Savings!J104) | J99: =IF(Agent01_Savings!A104="","",Agent01_Savings!K104) | K99: =IFERROR(IF(Agent01_Savings!A104="","",YEAR(Agent01_Savings!D104)),"")
A100: =IF(Agent01_Savings!A105="","",Agent01_Savings!A105) | B100: =IF(Agent01_Savings!A105="","","SV"&TEXT(100-3,"0000")&"-"&TEXT(TODAY(),"YYYYMMDD")) | C100: =IF(Agent01_Savings!A105="","",Agent01_Savings!B105) | D100: =IF(Agent01_Savings!A105="","",Agent01_Savings!G105) | E100: =IF(Agent01_Savings!A105="","",Agent01_Savings!D105) | F100: =IF(Agent01_Savings!A105="","",Agent01_Savings!E105) | G100: =IF(Agent01_Savings!A105="","",Agent01_Savings!F105) | H100: =IF(Agent01_Savings!A105="","",Agent01_Savings!I105) | I100: =IF(Agent01_Savings!A105="","",Agent01_Savings!J105) | J100: =IF(Agent01_Savings!A105="","",Agent01_Savings!K105) | K100: =IFERROR(IF(Agent01_Savings!A105="","",YEAR(Agent01_Savings!D105)),"")
...

Sheet DB_Withdrawals
A1: 🏧 WITHDRAWALS DATABASE — All 10 Agents Combined (Formula-Driven, READ-ONLY)
A2: 🔵 DO NOT ENTER DATA HERE — auto-aggregates from all Agent Withdrawal sheets. Rows 4–203=Agent01, 204–403=Agent02 … 1804–2003=Agent10.
A3: Account_No | B3: Transaction_ID | C3: Customer_Name | D3: Balance_Before | E3: Date | F3: Authorized_By | G3: Withdrawal_Amt_GHS | H3: New_Balance_GHS | I3: Agent | J3: Status | K3: Saved_At | L3: Min_Bal_Compliant | M3: Year
A4: =IF(Agent01_Withdrawals!A9="","",Agent01_Withdrawals!A9) | B4: =IF(Agent01_Withdrawals!A9="","","WD"&TEXT(4-3,"0000")&"-"&TEXT(TODAY(),"YYYYMMDD")) | C4: =IF(Agent01_Withdrawals!A9="","",Agent01_Withdrawals!B9) | D4: =IF(Agent01_Withdrawals!A9="","",Agent01_Withdrawals!C9) | E4: =IF(Agent01_Withdrawals!A9="","",Agent01_Withdrawals!D9) | F4: =IF(Agent01_Withdrawals!A9="","",Agent01_Withdrawals!F9) | G4: =IF(Agent01_Withdrawals!A9="","",Agent01_Withdrawals!E9) | H4: =IF(Agent01_Withdrawals!A9="","",Agent01_Withdrawals!G9) | I4: =IF(Agent01_Withdrawals!A9="","",Agent01_Withdrawals!H9) | J4: =IF(Agent01_Withdrawals!A9="","",Agent01_Withdrawals!J9) | K4: =IF(Agent01_Withdrawals!A9="","",Agent01_Withdrawals!K9) | L4: =IF(G4="","",IF(D4-G4>=System_Config!$B$9,"✅ OK","⚠️ BREACH")) | M4: =IFERROR(IF(Agent01_Withdrawals!A9="","",YEAR(Agent01_Withdrawals!D9)),"")
A5: =IF(Agent01_Withdrawals!A10="","",Agent01_Withdrawals!A10) | B5: =IF(Agent01_Withdrawals!A10="","","WD"&TEXT(5-3,"0000")&"-"&TEXT(TODAY(),"YYYYMMDD")) | C5: =IF(Agent01_Withdrawals!A10="","",Agent01_Withdrawals!B10) | D5: =IF(Agent01_Withdrawals!A10="","",Agent01_Withdrawals!C10) | E5: =IF(Agent01_Withdrawals!A10="","",Agent01_Withdrawals!D10) | F5: =IF(Agent01_Withdrawals!A10="","",Agent01_Withdrawals!F10) | G5: =IF(Agent01_Withdrawals!A10="","",Agent01_Withdrawals!E10) | H5: =IF(Agent01_Withdrawals!A10="","",Agent01_Withdrawals!G10) | I5: =IF(Agent01_Withdrawals!A10="","",Agent01_Withdrawals!H10) | J5: =IF(Agent01_Withdrawals!A10="","",Agent01_Withdrawals!J10) | K5: =IF(Agent01_Withdrawals!A10="","",Agent01_Withdrawals!K10) | L5: =IF(G5="","",IF(D5-G5>=System_Config!$B$9,"✅ OK","⚠️ BREACH")) | M5: =IFERROR(IF(Agent01_Withdrawals!A10="","",YEAR(Agent01_Withdrawals!D10)),"")
A6: =IF(Agent01_Withdrawals!A11="","",Agent01_Withdrawals!A11) | B6: =IF(Agent01_Withdrawals!A11="","","WD"&TEXT(6-3,"0000")&"-"&TEXT(TODAY(),"YYYYMMDD")) | C6: =IF(Agent01_Withdrawals!A11="","",Agent01_Withdrawals!B11) | D6: =IF(Agent01_Withdrawals!A11="","",Agent01_Withdrawals!C11) | E6: =IF(Agent01_Withdrawals!A11="","",Agent01_Withdrawals!D11) | F6: =IF(Agent01_Withdrawals!A11="","",Agent01_Withdrawals!F11) | G6: =IF(Agent01_Withdrawals!A11="","",Agent01_Withdrawals!E11) | H6: =IF(Agent01_Withdrawals!A11="","",Agent01_Withdrawals!G11) | I6: =IF(Agent01_Withdrawals!A11="","",Agent01_Withdrawals!H11) | J6: =IF(Agent01_Withdrawals!A11="","",Agent01_Withdrawals!J11) | K6: =IF(Agent01_Withdrawals!A11="","",Agent01_Withdrawals!K11) | L6: =IF(G6="","",IF(D6-G6>=System_Config!$B$9,"✅ OK","⚠️ BREACH")) | M6: =IFERROR(IF(Agent01_Withdrawals!A11="","",YEAR(Agent01_Withdrawals!D11)),"")
A7: =IF(Agent01_Withdrawals!A12="","",Agent01_Withdrawals!A12) | B7: =IF(Agent01_Withdrawals!A12="","","WD"&TEXT(7-3,"0000")&"-"&TEXT(TODAY(),"YYYYMMDD")) | C7: =IF(Agent01_Withdrawals!A12="","",Agent01_Withdrawals!B12) | D7: =IF(Agent01_Withdrawals!A12="","",Agent01_Withdrawals!C12) | E7: =IF(Agent01_Withdrawals!A12="","",Agent01_Withdrawals!D12) | F7: =IF(Agent01_Withdrawals!A12="","",Agent01_Withdrawals!F12) | G7: =IF(Agent01_Withdrawals!A12="","",Agent01_Withdrawals!E12) | H7: =IF(Agent01_Withdrawals!A12="","",Agent01_Withdrawals!G12) | I7: =IF(Agent01_Withdrawals!A12="","",Agent01_Withdrawals!H12) | J7: =IF(Agent01_Withdrawals!A12="","",Agent01_Withdrawals!J12) | K7: =IF(Agent01_Withdrawals!A12="","",Agent01_Withdrawals!K12) | L7: =IF(G7="","",IF(D7-G7>=System_Config!$B$9,"✅ OK","⚠️ BREACH")) | M7: =IFERROR(IF(Agent01_Withdrawals!A12="","",YEAR(Agent01_Withdrawals!D12)),"")
A8: =IF(Agent01_Withdrawals!A13="","",Agent01_Withdrawals!A13) | B8: =IF(Agent01_Withdrawals!A13="","","WD"&TEXT(8-3,"0000")&"-"&TEXT(TODAY(),"YYYYMMDD")) | C8: =IF(Agent01_Withdrawals!A13="","",Agent01_Withdrawals!B13) | D8: =IF(Agent01_Withdrawals!A13="","",Agent01_Withdrawals!C13) | E8: =IF(Agent01_Withdrawals!A13="","",Agent01_Withdrawals!D13) | F8: =IF(Agent01_Withdrawals!A13="","",Agent01_Withdrawals!F13) | G8: =IF(Agent01_Withdrawals!A13="","",Agent01_Withdrawals!E13) | H8: =IF(Agent01_Withdrawals!A13="","",Agent01_Withdrawals!G13) | I8: =IF(Agent01_Withdrawals!A13="","",Agent01_Withdrawals!H13) | J8: =IF(Agent01_Withdrawals!A13="","",Agent01_Withdrawals!J13) | K8: =IF(Agent01_Withdrawals!A13="","",Agent01_Withdrawals!K13) | L8: =IF(G8="","",IF(D8-G8>=System_Config!$B$9,"✅ OK","⚠️ BREACH")) | M8: =IFERROR(IF(Agent01_Withdrawals!A13="","",YEAR(Agent01_Withdrawals!D13)),"")
A9: =IF(Agent01_Withdrawals!A14="","",Agent01_Withdrawals!A14) | B9: =IF(Agent01_Withdrawals!A14="","","WD"&TEXT(9-3,"0000")&"-"&TEXT(TODAY(),"YYYYMMDD")) | C9: =IF(Agent01_Withdrawals!A14="","",Agent01_Withdrawals!B14) | D9: =IF(Agent01_Withdrawals!A14="","",Agent01_Withdrawals!C14) | E9: =IF(Agent01_Withdrawals!A14="","",Agent01_Withdrawals!D14) | F9: =IF(Agent01_Withdrawals!A14="","",Agent01_Withdrawals!F14) | G9: =IF(Agent01_Withdrawals!A14="","",Agent01_Withdrawals!E14) | H9: =IF(Agent01_Withdrawals!A14="","",Agent01_Withdrawals!G14) | I9: =IF(Agent01_Withdrawals!A14="","",Agent01_Withdrawals!H14) | J9: =IF(Agent01_Withdrawals!A14="","",Agent01_Withdrawals!J14) | K9: =IF(Agent01_Withdrawals!A14="","",Agent01_Withdrawals!K14) | L9: =IF(G9="","",IF(D9-G9>=System_Config!$B$9,"✅ OK","⚠️ BREACH")) | M9: =IFERROR(IF(Agent01_Withdrawals!A14="","",YEAR(Agent01_Withdrawals!D14)),"")
A10: =IF(Agent01_Withdrawals!A15="","",Agent01_Withdrawals!A15) | B10: =IF(Agent01_Withdrawals!A15="","","WD"&TEXT(10-3,"0000")&"-"&TEXT(TODAY(),"YYYYMMDD")) | C10: =IF(Agent01_Withdrawals!A15="","",Agent01_Withdrawals!B15) | D10: =IF(Agent01_Withdrawals!A15="","",Agent01_Withdrawals!C15) | E10: =IF(Agent01_Withdrawals!A15="","",Agent01_Withdrawals!D15) | F10: =IF(Agent01_Withdrawals!A15="","",Agent01_Withdrawals!F15) | G10: =IF(Agent01_Withdrawals!A15="","",Agent01_Withdrawals!E15) | H10: =IF(Agent01_Withdrawals!A15="","",Agent01_Withdrawals!G15) | I10: =IF(Agent01_Withdrawals!A15="","",Agent01_Withdrawals!H15) | J10: =IF(Agent01_Withdrawals!A15="","",Agent01_Withdrawals!J15) | K10: =IF(Agent01_Withdrawals!A15="","",Agent01_Withdrawals!K15) | L10: =IF(G10="","",IF(D10-G10>=System_Config!$B$9,"✅ OK","⚠️ BREACH")) | M10: =IFERROR(IF(Agent01_Withdrawals!A15="","",YEAR(Agent01_Withdrawals!D15)),"")
A11: =IF(Agent01_Withdrawals!A16="","",Agent01_Withdrawals!A16) | B11: =IF(Agent01_Withdrawals!A16="","","WD"&TEXT(11-3,"0000")&"-"&TEXT(TODAY(),"YYYYMMDD")) | C11: =IF(Agent01_Withdrawals!A16="","",Agent01_Withdrawals!B16) | D11: =IF(Agent01_Withdrawals!A16="","",Agent01_Withdrawals!C16) | E11: =IF(Agent01_Withdrawals!A16="","",Agent01_Withdrawals!D16) | F11: =IF(Agent01_Withdrawals!A16="","",Agent01_Withdrawals!F16) | G11: =IF(Agent01_Withdrawals!A16="","",Agent01_Withdrawals!E16) | H11: =IF(Agent01_Withdrawals!A16="","",Agent01_Withdrawals!G16) | I11: =IF(Agent01_Withdrawals!A16="","",Agent01_Withdrawals!H16) | J11: =IF(Agent01_Withdrawals!A16="","",Agent01_Withdrawals!J16) | K11: =IF(Agent01_Withdrawals!A16="","",Agent01_Withdrawals!K16) | L11: =IF(G11="","",IF(D11-G11>=System_Config!$B$9,"✅ OK","⚠️ BREACH")) | M11: =IFERROR(IF(Agent01_Withdrawals!A16="","",YEAR(Agent01_Withdrawals!D16)),"")
A12: =IF(Agent01_Withdrawals!A17="","",Agent01_Withdrawals!A17) | B12: =IF(Agent01_Withdrawals!A17="","","WD"&TEXT(12-3,"0000")&"-"&TEXT(TODAY(),"YYYYMMDD")) | C12: =IF(Agent01_Withdrawals!A17="","",Agent01_Withdrawals!B17) | D12: =IF(Agent01_Withdrawals!A17="","",Agent01_Withdrawals!C17) | E12: =IF(Agent01_Withdrawals!A17="","",Agent01_Withdrawals!D17) | F12: =IF(Agent01_Withdrawals!A17="","",Agent01_Withdrawals!F17) | G12: =IF(Agent01_Withdrawals!A17="","",Agent01_Withdrawals!E17) | H12: =IF(Agent01_Withdrawals!A17="","",Agent01_Withdrawals!G17) | I12: =IF(Agent01_Withdrawals!A17="","",Agent01_Withdrawals!H17) | J12: =IF(Agent01_Withdrawals!A17="","",Agent01_Withdrawals!J17) | K12: =IF(Agent01_Withdrawals!A17="","",Agent01_Withdrawals!K17) | L12: =IF(G12="","",IF(D12-G12>=System_Config!$B$9,"✅ OK","⚠️ BREACH")) | M12: =IFERROR(IF(Agent01_Withdrawals!A17="","",YEAR(Agent01_Withdrawals!D17)),"")
A13: =IF(Agent01_Withdrawals!A18="","",Agent01_Withdrawals!A18) | B13: =IF(Agent01_Withdrawals!A18="","","WD"&TEXT(13-3,"0000")&"-"&TEXT(TODAY(),"YYYYMMDD")) | C13: =IF(Agent01_Withdrawals!A18="","",Agent01_Withdrawals!B18) | D13: =IF(Agent01_Withdrawals!A18="","",Agent01_Withdrawals!C18) | E13: =IF(Agent01_Withdrawals!A18="","",Agent01_Withdrawals!D18) | F13: =IF(Agent01_Withdrawals!A18="","",Agent01_Withdrawals!F18) | G13: =IF(Agent01_Withdrawals!A18="","",Agent01_Withdrawals!E18) | H13: =IF(Agent01_Withdrawals!A18="","",Agent01_Withdrawals!G18) | I13: =IF(Agent01_Withdrawals!A18="","",Agent01_Withdrawals!H18) | J13: =IF(Agent01_Withdrawals!A18="","",Agent01_Withdrawals!J18) | K13: =IF(Agent01_Withdrawals!A18="","",Agent01_Withdrawals!K18) | L13: =IF(G13="","",IF(D13-G13>=System_Config!$B$9,"✅ OK","⚠️ BREACH")) | M13: =IFERROR(IF(Agent01_Withdrawals!A18="","",YEAR(Agent01_Withdrawals!D18)),"")
A14: =IF(Agent01_Withdrawals!A19="","",Agent01_Withdrawals!A19) | B14: =IF(Agent01_Withdrawals!A19="","","WD"&TEXT(14-3,"0000")&"-"&TEXT(TODAY(),"YYYYMMDD")) | C14: =IF(Agent01_Withdrawals!A19="","",Agent01_Withdrawals!B19) | D14: =IF(Agent01_Withdrawals!A19="","",Agent01_Withdrawals!C19) | E14: =IF(Agent01_Withdrawals!A19="","",Agent01_Withdrawals!D19) | F14: =IF(Agent01_Withdrawals!A19="","",Agent01_Withdrawals!F19) | G14: =IF(Agent01_Withdrawals!A19="","",Agent01_Withdrawals!E19) | H14: =IF(Agent01_Withdrawals!A19="","",Agent01_Withdrawals!G19) | I14: =IF(Agent01_Withdrawals!A19="","",Agent01_Withdrawals!H19) | J14: =IF(Agent01_Withdrawals!A19="","",Agent01_Withdrawals!J19) | K14: =IF(Agent01_Withdrawals!A19="","",Agent01_Withdrawals!K19) | L14: =IF(G14="","",IF(D14-G14>=System_Config!$B$9,"✅ OK","⚠️ BREACH")) | M14: =IFERROR(IF(Agent01_Withdrawals!A19="","",YEAR(Agent01_Withdrawals!D19)),"")
A15: =IF(Agent01_Withdrawals!A20="","",Agent01_Withdrawals!A20) | B15: =IF(Agent01_Withdrawals!A20="","","WD"&TEXT(15-3,"0000")&"-"&TEXT(TODAY(),"YYYYMMDD")) | C15: =IF(Agent01_Withdrawals!A20="","",Agent01_Withdrawals!B20) | D15: =IF(Agent01_Withdrawals!A20="","",Agent01_Withdrawals!C20) | E15: =IF(Agent01_Withdrawals!A20="","",Agent01_Withdrawals!D20) | F15: =IF(Agent01_Withdrawals!A20="","",Agent01_Withdrawals!F20) | G15: =IF(Agent01_Withdrawals!A20="","",Agent01_Withdrawals!E20) | H15: =IF(Agent01_Withdrawals!A20="","",Agent01_Withdrawals!G20) | I15: =IF(Agent01_Withdrawals!A20="","",Agent01_Withdrawals!H20) | J15: =IF(Agent01_Withdrawals!A20="","",Agent01_Withdrawals!J20) | K15: =IF(Agent01_Withdrawals!A20="","",Agent01_Withdrawals!K20) | L15: =IF(G15="","",IF(D15-G15>=System_Config!$B$9,"✅ OK","⚠️ BREACH")) | M15: =IFERROR(IF(Agent01_Withdrawals!A20="","",YEAR(Agent01_Withdrawals!D20)),"")
A16: =IF(Agent01_Withdrawals!A21="","",Agent01_Withdrawals!A21) | B16: =IF(Agent01_Withdrawals!A21="","","WD"&TEXT(16-3,"0000")&"-"&TEXT(TODAY(),"YYYYMMDD")) | C16: =IF(Agent01_Withdrawals!A21="","",Agent01_Withdrawals!B21) | D16: =IF(Agent01_Withdrawals!A21="","",Agent01_Withdrawals!C21) | E16: =IF(Agent01_Withdrawals!A21="","",Agent01_Withdrawals!D21) | F16: =IF(Agent01_Withdrawals!A21="","",Agent01_Withdrawals!F21) | G16: =IF(Agent01_Withdrawals!A21="","",Agent01_Withdrawals!E21) | H16: =IF(Agent01_Withdrawals!A21="","",Agent01_Withdrawals!G21) | I16: =IF(Agent01_Withdrawals!A21="","",Agent01_Withdrawals!H21) | J16: =IF(Agent01_Withdrawals!A21="","",Agent01_Withdrawals!J21) | K16: =IF(Agent01_Withdrawals!A21="","",Agent01_Withdrawals!K21) | L16: =IF(G16="","",IF(D16-G16>=System_Config!$B$9,"✅ OK","⚠️ BREACH")) | M16: =IFERROR(IF(Agent01_Withdrawals!A21="","",YEAR(Agent01_Withdrawals!D21)),"")
A17: =IF(Agent01_Withdrawals!A22="","",Agent01_Withdrawals!A22) | B17: =IF(Agent01_Withdrawals!A22="","","WD"&TEXT(17-3,"0000")&"-"&TEXT(TODAY(),"YYYYMMDD")) | C17: =IF(Agent01_Withdrawals!A22="","",Agent01_Withdrawals!B22) | D17: =IF(Agent01_Withdrawals!A22="","",Agent01_Withdrawals!C22) | E17: =IF(Agent01_Withdrawals!A22="","",Agent01_Withdrawals!D22) | F17: =IF(Agent01_Withdrawals!A22="","",Agent01_Withdrawals!F22) | G17: =IF(Agent01_Withdrawals!A22="","",Agent01_Withdrawals!E22) | H17: =IF(Agent01_Withdrawals!A22="","",Agent01_Withdrawals!G22) | I17: =IF(Agent01_Withdrawals!A22="","",Agent01_Withdrawals!H22) | J17: =IF(Agent01_Withdrawals!A22="","",Agent01_Withdrawals!J22) | K17: =IF(Agent01_Withdrawals!A22="","",Agent01_Withdrawals!K22) | L17: =IF(G17="","",IF(D17-G17>=System_Config!$B$9,"✅ OK","⚠️ BREACH")) | M17: =IFERROR(IF(Agent01_Withdrawals!A22="","",YEAR(Agent01_Withdrawals!D22)),"")
A18: =IF(Agent01_Withdrawals!A23="","",Agent01_Withdrawals!A23) | B18: =IF(Agent01_Withdrawals!A23="","","WD"&TEXT(18-3,"0000")&"-"&TEXT(TODAY(),"YYYYMMDD")) | C18: =IF(Agent01_Withdrawals!A23="","",Agent01_Withdrawals!B23) | D18: =IF(Agent01_Withdrawals!A23="","",Agent01_Withdrawals!C23) | E18: =IF(Agent01_Withdrawals!A23="","",Agent01_Withdrawals!D23) | F18: =IF(Agent01_Withdrawals!A23="","",Agent01_Withdrawals!F23) | G18: =IF(Agent01_Withdrawals!A23="","",Agent01_Withdrawals!E23) | H18: =IF(Agent01_Withdrawals!A23="","",Agent01_Withdrawals!G23) | I18: =IF(Agent01_Withdrawals!A23="","",Agent01_Withdrawals!H23) | J18: =IF(Agent01_Withdrawals!A23="","",Agent01_Withdrawals!J23) | K18: =IF(Agent01_Withdrawals!A23="","",Agent01_Withdrawals!K23) | L18: =IF(G18="","",IF(D18-G18>=System_Config!$B$9,"✅ OK","⚠️ BREACH")) | M18: =IFERROR(IF(Agent01_Withdrawals!A23="","",YEAR(Agent01_Withdrawals!D23)),"")
A19: =IF(Agent01_Withdrawals!A24="","",Agent01_Withdrawals!A24) | B19: =IF(Agent01_Withdrawals!A24="","","WD"&TEXT(19-3,"0000")&"-"&TEXT(TODAY(),"YYYYMMDD")) | C19: =IF(Agent01_Withdrawals!A24="","",Agent01_Withdrawals!B24) | D19: =IF(Agent01_Withdrawals!A24="","",Agent01_Withdrawals!C24) | E19: =IF(Agent01_Withdrawals!A24="","",Agent01_Withdrawals!D24) | F19: =IF(Agent01_Withdrawals!A24="","",Agent01_Withdrawals!F24) | G19: =IF(Agent01_Withdrawals!A24="","",Agent01_Withdrawals!E24) | H19: =IF(Agent01_Withdrawals!A24="","",Agent01_Withdrawals!G24) | I19: =IF(Agent01_Withdrawals!A24="","",Agent01_Withdrawals!H24) | J19: =IF(Agent01_Withdrawals!A24="","",Agent01_Withdrawals!J24) | K19: =IF(Agent01_Withdrawals!A24="","",Agent01_Withdrawals!K24) | L19: =IF(G19="","",IF(D19-G19>=System_Config!$B$9,"✅ OK","⚠️ BREACH")) | M19: =IFERROR(IF(Agent01_Withdrawals!A24="","",YEAR(Agent01_Withdrawals!D24)),"")
A20: =IF(Agent01_Withdrawals!A25="","",Agent01_Withdrawals!A25) | B20: =IF(Agent01_Withdrawals!A25="","","WD"&TEXT(20-3,"0000")&"-"&TEXT(TODAY(),"YYYYMMDD")) | C20: =IF(Agent01_Withdrawals!A25="","",Agent01_Withdrawals!B25) | D20: =IF(Agent01_Withdrawals!A25="","",Agent01_Withdrawals!C25) | E20: =IF(Agent01_Withdrawals!A25="","",Agent01_Withdrawals!D25) | F20: =IF(Agent01_Withdrawals!A25="","",Agent01_Withdrawals!F25) | G20: =IF(Agent01_Withdrawals!A25="","",Agent01_Withdrawals!E25) | H20: =IF(Agent01_Withdrawals!A25="","",Agent01_Withdrawals!G25) | I20: =IF(Agent01_Withdrawals!A25="","",Agent01_Withdrawals!H25) | J20: =IF(Agent01_Withdrawals!A25="","",Agent01_Withdrawals!J25) | K20: =IF(Agent01_Withdrawals!A25="","",Agent01_Withdrawals!K25) | L20: =IF(G20="","",IF(D20-G20>=System_Config!$B$9,"✅ OK","⚠️ BREACH")) | M20: =IFERROR(IF(Agent01_Withdrawals!A25="","",YEAR(Agent01_Withdrawals!D25)),"")
A21: =IF(Agent01_Withdrawals!A26="","",Agent01_Withdrawals!A26) | B21: =IF(Agent01_Withdrawals!A26="","","WD"&TEXT(21-3,"0000")&"-"&TEXT(TODAY(),"YYYYMMDD")) | C21: =IF(Agent01_Withdrawals!A26="","",Agent01_Withdrawals!B26) | D21: =IF(Agent01_Withdrawals!A26="","",Agent01_Withdrawals!C26) | E21: =IF(Agent01_Withdrawals!A26="","",Agent01_Withdrawals!D26) | F21: =IF(Agent01_Withdrawals!A26="","",Agent01_Withdrawals!F26) | G21: =IF(Agent01_Withdrawals!A26="","",Agent01_Withdrawals!E26) | H21: =IF(Agent01_Withdrawals!A26="","",Agent01_Withdrawals!G26) | I21: =IF(Agent01_Withdrawals!A26="","",Agent01_Withdrawals!H26) | J21: =IF(Agent01_Withdrawals!A26="","",Agent01_Withdrawals!J26) | K21: =IF(Agent01_Withdrawals!A26="","",Agent01_Withdrawals!K26) | L21: =IF(G21="","",IF(D21-G21>=System_Config!$B$9,"✅ OK","⚠️ BREACH")) | M21: =IFERROR(IF(Agent01_Withdrawals!A26="","",YEAR(Agent01_Withdrawals!D26)),"")
A22: =IF(Agent01_Withdrawals!A27="","",Agent01_Withdrawals!A27) | B22: =IF(Agent01_Withdrawals!A27="","","WD"&TEXT(22-3,"0000")&"-"&TEXT(TODAY(),"YYYYMMDD")) | C22: =IF(Agent01_Withdrawals!A27="","",Agent01_Withdrawals!B27) | D22: =IF(Agent01_Withdrawals!A27="","",Agent01_Withdrawals!C27) | E22: =IF(Agent01_Withdrawals!A27="","",Agent01_Withdrawals!D27) | F22: =IF(Agent01_Withdrawals!A27="","",Agent01_Withdrawals!F27) | G22: =IF(Agent01_Withdrawals!A27="","",Agent01_Withdrawals!E27) | H22: =IF(Agent01_Withdrawals!A27="","",Agent01_Withdrawals!G27) | I22: =IF(Agent01_Withdrawals!A27="","",Agent01_Withdrawals!H27) | J22: =IF(Agent01_Withdrawals!A27="","",Agent01_Withdrawals!J27) | K22: =IF(Agent01_Withdrawals!A27="","",Agent01_Withdrawals!K27) | L22: =IF(G22="","",IF(D22-G22>=System_Config!$B$9,"✅ OK","⚠️ BREACH")) | M22: =IFERROR(IF(Agent01_Withdrawals!A27="","",YEAR(Agent01_Withdrawals!D27)),"")
A23: =IF(Agent01_Withdrawals!A28="","",Agent01_Withdrawals!A28) | B23: =IF(Agent01_Withdrawals!A28="","","WD"&TEXT(23-3,"0000")&"-"&TEXT(TODAY(),"YYYYMMDD")) | C23: =IF(Agent01_Withdrawals!A28="","",Agent01_Withdrawals!B28) | D23: =IF(Agent01_Withdrawals!A28="","",Agent01_Withdrawals!C28) | E23: =IF(Agent01_Withdrawals!A28="","",Agent01_Withdrawals!D28) | F23: =IF(Agent01_Withdrawals!A28="","",Agent01_Withdrawals!F28) | G23: =IF(Agent01_Withdrawals!A28="","",Agent01_Withdrawals!E28) | H23: =IF(Agent01_Withdrawals!A28="","",Agent01_Withdrawals!G28) | I23: =IF(Agent01_Withdrawals!A28="","",Agent01_Withdrawals!H28) | J23: =IF(Agent01_Withdrawals!A28="","",Agent01_Withdrawals!J28) | K23: =IF(Agent01_Withdrawals!A28="","",Agent01_Withdrawals!K28) | L23: =IF(G23="","",IF(D23-G23>=System_Config!$B$9,"✅ OK","⚠️ BREACH")) | M23: =IFERROR(IF(Agent01_Withdrawals!A28="","",YEAR(Agent01_Withdrawals!D28)),"")
A24: =IF(Agent01_Withdrawals!A29="","",Agent01_Withdrawals!A29) | B24: =IF(Agent01_Withdrawals!A29="","","WD"&TEXT(24-3,"0000")&"-"&TEXT(TODAY(),"YYYYMMDD")) | C24: =IF(Agent01_Withdrawals!A29="","",Agent01_Withdrawals!B29) | D24: =IF(Agent01_Withdrawals!A29="","",Agent01_Withdrawals!C29) | E24: =IF(Agent01_Withdrawals!A29="","",Agent01_Withdrawals!D29) | F24: =IF(Agent01_Withdrawals!A29="","",Agent01_Withdrawals!F29) | G24: =IF(Agent01_Withdrawals!A29="","",Agent01_Withdrawals!E29) | H24: =IF(Agent01_Withdrawals!A29="","",Agent01_Withdrawals!G29) | I24: =IF(Agent01_Withdrawals!A29="","",Agent01_Withdrawals!H29) | J24: =IF(Agent01_Withdrawals!A29="","",Agent01_Withdrawals!J29) | K24: =IF(Agent01_Withdrawals!A29="","",Agent01_Withdrawals!K29) | L24: =IF(G24="","",IF(D24-G24>=System_Config!$B$9,"✅ OK","⚠️ BREACH")) | M24: =IFERROR(IF(Agent01_Withdrawals!A29="","",YEAR(Agent01_Withdrawals!D29)),"")
A25: =IF(Agent01_Withdrawals!A30="","",Agent01_Withdrawals!A30) | B25: =IF(Agent01_Withdrawals!A30="","","WD"&TEXT(25-3,"0000")&"-"&TEXT(TODAY(),"YYYYMMDD")) | C25: =IF(Agent01_Withdrawals!A30="","",Agent01_Withdrawals!B30) | D25: =IF(Agent01_Withdrawals!A30="","",Agent01_Withdrawals!C30) | E25: =IF(Agent01_Withdrawals!A30="","",Agent01_Withdrawals!D30) | F25: =IF(Agent01_Withdrawals!A30="","",Agent01_Withdrawals!F30) | G25: =IF(Agent01_Withdrawals!A30="","",Agent01_Withdrawals!E30) | H25: =IF(Agent01_Withdrawals!A30="","",Agent01_Withdrawals!G30) | I25: =IF(Agent01_Withdrawals!A30="","",Agent01_Withdrawals!H30) | J25: =IF(Agent01_Withdrawals!A30="","",Agent01_Withdrawals!J30) | K25: =IF(Agent01_Withdrawals!A30="","",Agent01_Withdrawals!K30) | L25: =IF(G25="","",IF(D25-G25>=System_Config!$B$9,"✅ OK","⚠️ BREACH")) | M25: =IFERROR(IF(Agent01_Withdrawals!A30="","",YEAR(Agent01_Withdrawals!D30)),"")
A26: =IF(Agent01_Withdrawals!A31="","",Agent01_Withdrawals!A31) | B26: =IF(Agent01_Withdrawals!A31="","","WD"&TEXT(26-3,"0000")&"-"&TEXT(TODAY(),"YYYYMMDD")) | C26: =IF(Agent01_Withdrawals!A31="","",Agent01_Withdrawals!B31) | D26: =IF(Agent01_Withdrawals!A31="","",Agent01_Withdrawals!C31) | E26: =IF(Agent01_Withdrawals!A31="","",Agent01_Withdrawals!D31) | F26: =IF(Agent01_Withdrawals!A31="","",Agent01_Withdrawals!F31) | G26: =IF(Agent01_Withdrawals!A31="","",Agent01_Withdrawals!E31) | H26: =IF(Agent01_Withdrawals!A31="","",Agent01_Withdrawals!G31) | I26: =IF(Agent01_Withdrawals!A31="","",Agent01_Withdrawals!H31) | J26: =IF(Agent01_Withdrawals!A31="","",Agent01_Withdrawals!J31) | K26: =IF(Agent01_Withdrawals!A31="","",Agent01_Withdrawals!K31) | L26: =IF(G26="","",IF(D26-G26>=System_Config!$B$9,"✅ OK","⚠️ BREACH")) | M26: =IFERROR(IF(Agent01_Withdrawals!A31="","",YEAR(Agent01_Withdrawals!D31)),"")
A27: =IF(Agent01_Withdrawals!A32="","",Agent01_Withdrawals!A32) | B27: =IF(Agent01_Withdrawals!A32="","","WD"&TEXT(27-3,"0000")&"-"&TEXT(TODAY(),"YYYYMMDD")) | C27: =IF(Agent01_Withdrawals!A32="","",Agent01_Withdrawals!B32) | D27: =IF(Agent01_Withdrawals!A32="","",Agent01_Withdrawals!C32) | E27: =IF(Agent01_Withdrawals!A32="","",Agent01_Withdrawals!D32) | F27: =IF(Agent01_Withdrawals!A32="","",Agent01_Withdrawals!F32) | G27: =IF(Agent01_Withdrawals!A32="","",Agent01_Withdrawals!E32) | H27: =IF(Agent01_Withdrawals!A32="","",Agent01_Withdrawals!G32) | I27: =IF(Agent01_Withdrawals!A32="","",Agent01_Withdrawals!H32) | J27: =IF(Agent01_Withdrawals!A32="","",Agent01_Withdrawals!J32) | K27: =IF(Agent01_Withdrawals!A32="","",Agent01_Withdrawals!K32) | L27: =IF(G27="","",IF(D27-G27>=System_Config!$B$9,"✅ OK","⚠️ BREACH")) | M27: =IFERROR(IF(Agent01_Withdrawals!A32="","",YEAR(Agent01_Withdrawals!D32)),"")
A28: =IF(Agent01_Withdrawals!A33="","",Agent01_Withdrawals!A33) | B28: =IF(Agent01_Withdrawals!A33="","","WD"&TEXT(28-3,"0000")&"-"&TEXT(TODAY(),"YYYYMMDD")) | C28: =IF(Agent01_Withdrawals!A33="","",Agent01_Withdrawals!B33) | D28: =IF(Agent01_Withdrawals!A33="","",Agent01_Withdrawals!C33) | E28: =IF(Agent01_Withdrawals!A33="","",Agent01_Withdrawals!D33) | F28: =IF(Agent01_Withdrawals!A33="","",Agent01_Withdrawals!F33) | G28: =IF(Agent01_Withdrawals!A33="","",Agent01_Withdrawals!E33) | H28: =IF(Agent01_Withdrawals!A33="","",Agent01_Withdrawals!G33) | I28: =IF(Agent01_Withdrawals!A33="","",Agent01_Withdrawals!H33) | J28: =IF(Agent01_Withdrawals!A33="","",Agent01_Withdrawals!J33) | K28: =IF(Agent01_Withdrawals!A33="","",Agent01_Withdrawals!K33) | L28: =IF(G28="","",IF(D28-G28>=System_Config!$B$9,"✅ OK","⚠️ BREACH")) | M28: =IFERROR(IF(Agent01_Withdrawals!A33="","",YEAR(Agent01_Withdrawals!D33)),"")
A29: =IF(Agent01_Withdrawals!A34="","",Agent01_Withdrawals!A34) | B29: =IF(Agent01_Withdrawals!A34="","","WD"&TEXT(29-3,"0000")&"-"&TEXT(TODAY(),"YYYYMMDD")) | C29: =IF(Agent01_Withdrawals!A34="","",Agent01_Withdrawals!B34) | D29: =IF(Agent01_Withdrawals!A34="","",Agent01_Withdrawals!C34) | E29: =IF(Agent01_Withdrawals!A34="","",Agent01_Withdrawals!D34) | F29: =IF(Agent01_Withdrawals!A34="","",Agent01_Withdrawals!F34) | G29: =IF(Agent01_Withdrawals!A34="","",Agent01_Withdrawals!E34) | H29: =IF(Agent01_Withdrawals!A34="","",Agent01_Withdrawals!G34) | I29: =IF(Agent01_Withdrawals!A34="","",Agent01_Withdrawals!H34) | J29: =IF(Agent01_Withdrawals!A34="","",Agent01_Withdrawals!J34) | K29: =IF(Agent01_Withdrawals!A34="","",Agent01_Withdrawals!K34) | L29: =IF(G29="","",IF(D29-G29>=System_Config!$B$9,"✅ OK","⚠️ BREACH")) | M29: =IFERROR(IF(Agent01_Withdrawals!A34="","",YEAR(Agent01_Withdrawals!D34)),"")
A30: =IF(Agent01_Withdrawals!A35="","",Agent01_Withdrawals!A35) | B30: =IF(Agent01_Withdrawals!A35="","","WD"&TEXT(30-3,"0000")&"-"&TEXT(TODAY(),"YYYYMMDD")) | C30: =IF(Agent01_Withdrawals!A35="","",Agent01_Withdrawals!B35) | D30: =IF(Agent01_Withdrawals!A35="","",Agent01_Withdrawals!C35) | E30: =IF(Agent01_Withdrawals!A35="","",Agent01_Withdrawals!D35) | F30: =IF(Agent01_Withdrawals!A35="","",Agent01_Withdrawals!F35) | G30: =IF(Agent01_Withdrawals!A35="","",Agent01_Withdrawals!E35) | H30: =IF(Agent01_Withdrawals!A35="","",Agent01_Withdrawals!G35) | I30: =IF(Agent01_Withdrawals!A35="","",Agent01_Withdrawals!H35) | J30: =IF(Agent01_Withdrawals!A35="","",Agent01_Withdrawals!J35) | K30: =IF(Agent01_Withdrawals!A35="","",Agent01_Withdrawals!K35) | L30: =IF(G30="","",IF(D30-G30>=System_Config!$B$9,"✅ OK","⚠️ BREACH")) | M30: =IFERROR(IF(Agent01_Withdrawals!A35="","",YEAR(Agent01_Withdrawals!D35)),"")
A31: =IF(Agent01_Withdrawals!A36="","",Agent01_Withdrawals!A36) | B31: =IF(Agent01_Withdrawals!A36="","","WD"&TEXT(31-3,"0000")&"-"&TEXT(TODAY(),"YYYYMMDD")) | C31: =IF(Agent01_Withdrawals!A36="","",Agent01_Withdrawals!B36) | D31: =IF(Agent01_Withdrawals!A36="","",Agent01_Withdrawals!C36) | E31: =IF(Agent01_Withdrawals!A36="","",Agent01_Withdrawals!D36) | F31: =IF(Agent01_Withdrawals!A36="","",Agent01_Withdrawals!F36) | G31: =IF(Agent01_Withdrawals!A36="","",Agent01_Withdrawals!E36) | H31: =IF(Agent01_Withdrawals!A36="","",Agent01_Withdrawals!G36) | I31: =IF(Agent01_Withdrawals!A36="","",Agent01_Withdrawals!H36) | J31: =IF(Agent01_Withdrawals!A36="","",Agent01_Withdrawals!J36) | K31: =IF(Agent01_Withdrawals!A36="","",Agent01_Withdrawals!K36) | L31: =IF(G31="","",IF(D31-G31>=System_Config!$B$9,"✅ OK","⚠️ BREACH")) | M31: =IFERROR(IF(Agent01_Withdrawals!A36="","",YEAR(Agent01_Withdrawals!D36)),"")
A32: =IF(Agent01_Withdrawals!A37="","",Agent01_Withdrawals!A37) | B32: =IF(Agent01_Withdrawals!A37="","","WD"&TEXT(32-3,"0000")&"-"&TEXT(TODAY(),"YYYYMMDD")) | C32: =IF(Agent01_Withdrawals!A37="","",Agent01_Withdrawals!B37) | D32: =IF(Agent01_Withdrawals!A37="","",Agent01_Withdrawals!C37) | E32: =IF(Agent01_Withdrawals!A37="","",Agent01_Withdrawals!D37) | F32: =IF(Agent01_Withdrawals!A37="","",Agent01_Withdrawals!F37) | G32: =IF(Agent01_Withdrawals!A37="","",Agent01_Withdrawals!E37) | H32: =IF(Agent01_Withdrawals!A37="","",Agent01_Withdrawals!G37) | I32: =IF(Agent01_Withdrawals!A37="","",Agent01_Withdrawals!H37) | J32: =IF(Agent01_Withdrawals!A37="","",Agent01_Withdrawals!J37) | K32: =IF(Agent01_Withdrawals!A37="","",Agent01_Withdrawals!K37) | L32: =IF(G32="","",IF(D32-G32>=System_Config!$B$9,"✅ OK","⚠️ BREACH")) | M32: =IFERROR(IF(Agent01_Withdrawals!A37="","",YEAR(Agent01_Withdrawals!D37)),"")
A33: =IF(Agent01_Withdrawals!A38="","",Agent01_Withdrawals!A38) | B33: =IF(Agent01_Withdrawals!A38="","","WD"&TEXT(33-3,"0000")&"-"&TEXT(TODAY(),"YYYYMMDD")) | C33: =IF(Agent01_Withdrawals!A38="","",Agent01_Withdrawals!B38) | D33: =IF(Agent01_Withdrawals!A38="","",Agent01_Withdrawals!C38) | E33: =IF(Agent01_Withdrawals!A38="","",Agent01_Withdrawals!D38) | F33: =IF(Agent01_Withdrawals!A38="","",Agent01_Withdrawals!F38) | G33: =IF(Agent01_Withdrawals!A38="","",Agent01_Withdrawals!E38) | H33: =IF(Agent01_Withdrawals!A38="","",Agent01_Withdrawals!G38) | I33: =IF(Agent01_Withdrawals!A38="","",Agent01_Withdrawals!H38) | J33: =IF(Agent01_Withdrawals!A38="","",Agent01_Withdrawals!J38) | K33: =IF(Agent01_Withdrawals!A38="","",Agent01_Withdrawals!K38) | L33: =IF(G33="","",IF(D33-G33>=System_Config!$B$9,"✅ OK","⚠️ BREACH")) | M33: =IFERROR(IF(Agent01_Withdrawals!A38="","",YEAR(Agent01_Withdrawals!D38)),"")
A34: =IF(Agent01_Withdrawals!A39="","",Agent01_Withdrawals!A39) | B34: =IF(Agent01_Withdrawals!A39="","","WD"&TEXT(34-3,"0000")&"-"&TEXT(TODAY(),"YYYYMMDD")) | C34: =IF(Agent01_Withdrawals!A39="","",Agent01_Withdrawals!B39) | D34: =IF(Agent01_Withdrawals!A39="","",Agent01_Withdrawals!C39) | E34: =IF(Agent01_Withdrawals!A39="","",Agent01_Withdrawals!D39) | F34: =IF(Agent01_Withdrawals!A39="","",Agent01_Withdrawals!F39) | G34: =IF(Agent01_Withdrawals!A39="","",Agent01_Withdrawals!E39) | H34: =IF(Agent01_Withdrawals!A39="","",Agent01_Withdrawals!G39) | I34: =IF(Agent01_Withdrawals!A39="","",Agent01_Withdrawals!H39) | J34: =IF(Agent01_Withdrawals!A39="","",Agent01_Withdrawals!J39) | K34: =IF(Agent01_Withdrawals!A39="","",Agent01_Withdrawals!K39) | L34: =IF(G34="","",IF(D34-G34>=System_Config!$B$9,"✅ OK","⚠️ BREACH")) | M34: =IFERROR(IF(Agent01_Withdrawals!A39="","",YEAR(Agent01_Withdrawals!D39)),"")
A35: =IF(Agent01_Withdrawals!A40="","",Agent01_Withdrawals!A40) | B35: =IF(Agent01_Withdrawals!A40="","","WD"&TEXT(35-3,"0000")&"-"&TEXT(TODAY(),"YYYYMMDD")) | C35: =IF(Agent01_Withdrawals!A40="","",Agent01_Withdrawals!B40) | D35: =IF(Agent01_Withdrawals!A40="","",Agent01_Withdrawals!C40) | E35: =IF(Agent01_Withdrawals!A40="","",Agent01_Withdrawals!D40) | F35: =IF(Agent01_Withdrawals!A40="","",Agent01_Withdrawals!F40) | G35: =IF(Agent01_Withdrawals!A40="","",Agent01_Withdrawals!E40) | H35: =IF(Agent01_Withdrawals!A40="","",Agent01_Withdrawals!G40) | I35: =IF(Agent01_Withdrawals!A40="","",Agent01_Withdrawals!H40) | J35: =IF(Agent01_Withdrawals!A40="","",Agent01_Withdrawals!J40) | K35: =IF(Agent01_Withdrawals!A40="","",Agent01_Withdrawals!K40) | L35: =IF(G35="","",IF(D35-G35>=System_Config!$B$9,"✅ OK","⚠️ BREACH")) | M35: =IFERROR(IF(Agent01_Withdrawals!A40="","",YEAR(Agent01_Withdrawals!D40)),"")
A36: =IF(Agent01_Withdrawals!A41="","",Agent01_Withdrawals!A41) | B36: =IF(Agent01_Withdrawals!A41="","","WD"&TEXT(36-3,"0000")&"-"&TEXT(TODAY(),"YYYYMMDD")) | C36: =IF(Agent01_Withdrawals!A41="","",Agent01_Withdrawals!B41) | D36: =IF(Agent01_Withdrawals!A41="","",Agent01_Withdrawals!C41) | E36: =IF(Agent01_Withdrawals!A41="","",Agent01_Withdrawals!D41) | F36: =IF(Agent01_Withdrawals!A41="","",Agent01_Withdrawals!F41) | G36: =IF(Agent01_Withdrawals!A41="","",Agent01_Withdrawals!E41) | H36: =IF(Agent01_Withdrawals!A41="","",Agent01_Withdrawals!G41) | I36: =IF(Agent01_Withdrawals!A41="","",Agent01_Withdrawals!H41) | J36: =IF(Agent01_Withdrawals!A41="","",Agent01_Withdrawals!J41) | K36: =IF(Agent01_Withdrawals!A41="","",Agent01_Withdrawals!K41) | L36: =IF(G36="","",IF(D36-G36>=System_Config!$B$9,"✅ OK","⚠️ BREACH")) | M36: =IFERROR(IF(Agent01_Withdrawals!A41="","",YEAR(Agent01_Withdrawals!D41)),"")
A37: =IF(Agent01_Withdrawals!A42="","",Agent01_Withdrawals!A42) | B37: =IF(Agent01_Withdrawals!A42="","","WD"&TEXT(37-3,"0000")&"-"&TEXT(TODAY(),"YYYYMMDD")) | C37: =IF(Agent01_Withdrawals!A42="","",Agent01_Withdrawals!B42) | D37: =IF(Agent01_Withdrawals!A42="","",Agent01_Withdrawals!C42) | E37: =IF(Agent01_Withdrawals!A42="","",Agent01_Withdrawals!D42) | F37: =IF(Agent01_Withdrawals!A42="","",Agent01_Withdrawals!F42) | G37: =IF(Agent01_Withdrawals!A42="","",Agent01_Withdrawals!E42) | H37: =IF(Agent01_Withdrawals!A42="","",Agent01_Withdrawals!G42) | I37: =IF(Agent01_Withdrawals!A42="","",Agent01_Withdrawals!H42) | J37: =IF(Agent01_Withdrawals!A42="","",Agent01_Withdrawals!J42) | K37: =IF(Agent01_Withdrawals!A42="","",Agent01_Withdrawals!K42) | L37: =IF(G37="","",IF(D37-G37>=System_Config!$B$9,"✅ OK","⚠️ BREACH")) | M37: =IFERROR(IF(Agent01_Withdrawals!A42="","",YEAR(Agent01_Withdrawals!D42)),"")
A38: =IF(Agent01_Withdrawals!A43="","",Agent01_Withdrawals!A43) | B38: =IF(Agent01_Withdrawals!A43="","","WD"&TEXT(38-3,"0000")&"-"&TEXT(TODAY(),"YYYYMMDD")) | C38: =IF(Agent01_Withdrawals!A43="","",Agent01_Withdrawals!B43) | D38: =IF(Agent01_Withdrawals!A43="","",Agent01_Withdrawals!C43) | E38: =IF(Agent01_Withdrawals!A43="","",Agent01_Withdrawals!D43) | F38: =IF(Agent01_Withdrawals!A43="","",Agent01_Withdrawals!F43) | G38: =IF(Agent01_Withdrawals!A43="","",Agent01_Withdrawals!E43) | H38: =IF(Agent01_Withdrawals!A43="","",Agent01_Withdrawals!G43) | I38: =IF(Agent01_Withdrawals!A43="","",Agent01_Withdrawals!H43) | J38: =IF(Agent01_Withdrawals!A43="","",Agent01_Withdrawals!J43) | K38: =IF(Agent01_Withdrawals!A43="","",Agent01_Withdrawals!K43) | L38: =IF(G38="","",IF(D38-G38>=System_Config!$B$9,"✅ OK","⚠️ BREACH")) | M38: =IFERROR(IF(Agent01_Withdrawals!A43="","",YEAR(Agent01_Withdrawals!D43)),"")
A39: =IF(Agent01_Withdrawals!A44="","",Agent01_Withdrawals!A44) | B39: =IF(Agent01_Withdrawals!A44="","","WD"&TEXT(39-3,"0000")&"-"&TEXT(TODAY(),"YYYYMMDD")) | C39: =IF(Agent01_Withdrawals!A44="","",Agent01_Withdrawals!B44) | D39: =IF(Agent01_Withdrawals!A44="","",Agent01_Withdrawals!C44) | E39: =IF(Agent01_Withdrawals!A44="","",Agent01_Withdrawals!D44) | F39: =IF(Agent01_Withdrawals!A44="","",Agent01_Withdrawals!F44) | G39: =IF(Agent01_Withdrawals!A44="","",Agent01_Withdrawals!E44) | H39: =IF(Agent01_Withdrawals!A44="","",Agent01_Withdrawals!G44) | I39: =IF(Agent01_Withdrawals!A44="","",Agent01_Withdrawals!H44) | J39: =IF(Agent01_Withdrawals!A44="","",Agent01_Withdrawals!J44) | K39: =IF(Agent01_Withdrawals!A44="","",Agent01_Withdrawals!K44) | L39: =IF(G39="","",IF(D39-G39>=System_Config!$B$9,"✅ OK","⚠️ BREACH")) | M39: =IFERROR(IF(Agent01_Withdrawals!A44="","",YEAR(Agent01_Withdrawals!D44)),"")
A40: =IF(Agent01_Withdrawals!A45="","",Agent01_Withdrawals!A45) | B40: =IF(Agent01_Withdrawals!A45="","","WD"&TEXT(40-3,"0000")&"-"&TEXT(TODAY(),"YYYYMMDD")) | C40: =IF(Agent01_Withdrawals!A45="","",Agent01_Withdrawals!B45) | D40: =IF(Agent01_Withdrawals!A45="","",Agent01_Withdrawals!C45) | E40: =IF(Agent01_Withdrawals!A45="","",Agent01_Withdrawals!D45) | F40: =IF(Agent01_Withdrawals!A45="","",Agent01_Withdrawals!F45) | G40: =IF(Agent01_Withdrawals!A45="","",Agent01_Withdrawals!E45) | H40: =IF(Agent01_Withdrawals!A45="","",Agent01_Withdrawals!G45) | I40: =IF(Agent01_Withdrawals!A45="","",Agent01_Withdrawals!H45) | J40: =IF(Agent01_Withdrawals!A45="","",Agent01_Withdrawals!J45) | K40: =IF(Agent01_Withdrawals!A45="","",Agent01_Withdrawals!K45) | L40: =IF(G40="","",IF(D40-G40>=System_Config!$B$9,"✅ OK","⚠️ BREACH")) | M40: =IFERROR(IF(Agent01_Withdrawals!A45="","",YEAR(Agent01_Withdrawals!D45)),"")
A41: =IF(Agent01_Withdrawals!A46="","",Agent01_Withdrawals!A46) | B41: =IF(Agent01_Withdrawals!A46="","","WD"&TEXT(41-3,"0000")&"-"&TEXT(TODAY(),"YYYYMMDD")) | C41: =IF(Agent01_Withdrawals!A46="","",Agent01_Withdrawals!B46) | D41: =IF(Agent01_Withdrawals!A46="","",Agent01_Withdrawals!C46) | E41: =IF(Agent01_Withdrawals!A46="","",Agent01_Withdrawals!D46) | F41: =IF(Agent01_Withdrawals!A46="","",Agent01_Withdrawals!F46) | G41: =IF(Agent01_Withdrawals!A46="","",Agent01_Withdrawals!E46) | H41: =IF(Agent01_Withdrawals!A46="","",Agent01_Withdrawals!G46) | I41: =IF(Agent01_Withdrawals!A46="","",Agent01_Withdrawals!H46) | J41: =IF(Agent01_Withdrawals!A46="","",Agent01_Withdrawals!J46) | K41: =IF(Agent01_Withdrawals!A46="","",Agent01_Withdrawals!K46) | L41: =IF(G41="","",IF(D41-G41>=System_Config!$B$9,"✅ OK","⚠️ BREACH")) | M41: =IFERROR(IF(Agent01_Withdrawals!A46="","",YEAR(Agent01_Withdrawals!D46)),"")
A42: =IF(Agent01_Withdrawals!A47="","",Agent01_Withdrawals!A47) | B42: =IF(Agent01_Withdrawals!A47="","","WD"&TEXT(42-3,"0000")&"-"&TEXT(TODAY(),"YYYYMMDD")) | C42: =IF(Agent01_Withdrawals!A47="","",Agent01_Withdrawals!B47) | D42: =IF(Agent01_Withdrawals!A47="","",Agent01_Withdrawals!C47) | E42: =IF(Agent01_Withdrawals!A47="","",Agent01_Withdrawals!D47) | F42: =IF(Agent01_Withdrawals!A47="","",Agent01_Withdrawals!F47) | G42: =IF(Agent01_Withdrawals!A47="","",Agent01_Withdrawals!E47) | H42: =IF(Agent01_Withdrawals!A47="","",Agent01_Withdrawals!G47) | I42: =IF(Agent01_Withdrawals!A47="","",Agent01_Withdrawals!H47) | J42: =IF(Agent01_Withdrawals!A47="","",Agent01_Withdrawals!J47) | K42: =IF(Agent01_Withdrawals!A47="","",Agent01_Withdrawals!K47) | L42: =IF(G42="","",IF(D42-G42>=System_Config!$B$9,"✅ OK","⚠️ BREACH")) | M42: =IFERROR(IF(Agent01_Withdrawals!A47="","",YEAR(Agent01_Withdrawals!D47)),"")
A43: =IF(Agent01_Withdrawals!A48="","",Agent01_Withdrawals!A48) | B43: =IF(Agent01_Withdrawals!A48="","","WD"&TEXT(43-3,"0000")&"-"&TEXT(TODAY(),"YYYYMMDD")) | C43: =IF(Agent01_Withdrawals!A48="","",Agent01_Withdrawals!B48) | D43: =IF(Agent01_Withdrawals!A48="","",Agent01_Withdrawals!C48) | E43: =IF(Agent01_Withdrawals!A48="","",Agent01_Withdrawals!D48) | F43: =IF(Agent01_Withdrawals!A48="","",Agent01_Withdrawals!F48) | G43: =IF(Agent01_Withdrawals!A48="","",Agent01_Withdrawals!E48) | H43: =IF(Agent01_Withdrawals!A48="","",Agent01_Withdrawals!G48) | I43: =IF(Agent01_Withdrawals!A48="","",Agent01_Withdrawals!H48) | J43: =IF(Agent01_Withdrawals!A48="","",Agent01_Withdrawals!J48) | K43: =IF(Agent01_Withdrawals!A48="","",Agent01_Withdrawals!K48) | L43: =IF(G43="","",IF(D43-G43>=System_Config!$B$9,"✅ OK","⚠️ BREACH")) | M43: =IFERROR(IF(Agent01_Withdrawals!A48="","",YEAR(Agent01_Withdrawals!D48)),"")
A44: =IF(Agent01_Withdrawals!A49="","",Agent01_Withdrawals!A49) | B44: =IF(Agent01_Withdrawals!A49="","","WD"&TEXT(44-3,"0000")&"-"&TEXT(TODAY(),"YYYYMMDD")) | C44: =IF(Agent01_Withdrawals!A49="","",Agent01_Withdrawals!B49) | D44: =IF(Agent01_Withdrawals!A49="","",Agent01_Withdrawals!C49) | E44: =IF(Agent01_Withdrawals!A49="","",Agent01_Withdrawals!D49) | F44: =IF(Agent01_Withdrawals!A49="","",Agent01_Withdrawals!F49) | G44: =IF(Agent01_Withdrawals!A49="","",Agent01_Withdrawals!E49) | H44: =IF(Agent01_Withdrawals!A49="","",Agent01_Withdrawals!G49) | I44: =IF(Agent01_Withdrawals!A49="","",Agent01_Withdrawals!H49) | J44: =IF(Agent01_Withdrawals!A49="","",Agent01_Withdrawals!J49) | K44: =IF(Agent01_Withdrawals!A49="","",Agent01_Withdrawals!K49) | L44: =IF(G44="","",IF(D44-G44>=System_Config!$B$9,"✅ OK","⚠️ BREACH")) | M44: =IFERROR(IF(Agent01_Withdrawals!A49="","",YEAR(Agent01_Withdrawals!D49)),"")
A45: =IF(Agent01_Withdrawals!A50="","",Agent01_Withdrawals!A50) | B45: =IF(Agent01_Withdrawals!A50="","","WD"&TEXT(45-3,"0000")&"-"&TEXT(TODAY(),"YYYYMMDD")) | C45: =IF(Agent01_Withdrawals!A50="","",Agent01_Withdrawals!B50) | D45: =IF(Agent01_Withdrawals!A50="","",Agent01_Withdrawals!C50) | E45: =IF(Agent01_Withdrawals!A50="","",Agent01_Withdrawals!D50) | F45: =IF(Agent01_Withdrawals!A50="","",Agent01_Withdrawals!F50) | G45: =IF(Agent01_Withdrawals!A50="","",Agent01_Withdrawals!E50) | H45: =IF(Agent01_Withdrawals!A50="","",Agent01_Withdrawals!G50) | I45: =IF(Agent01_Withdrawals!A50="","",Agent01_Withdrawals!H50) | J45: =IF(Agent01_Withdrawals!A50="","",Agent01_Withdrawals!J50) | K45: =IF(Agent01_Withdrawals!A50="","",Agent01_Withdrawals!K50) | L45: =IF(G45="","",IF(D45-G45>=System_Config!$B$9,"✅ OK","⚠️ BREACH")) | M45: =IFERROR(IF(Agent01_Withdrawals!A50="","",YEAR(Agent01_Withdrawals!D50)),"")
A46: =IF(Agent01_Withdrawals!A51="","",Agent01_Withdrawals!A51) | B46: =IF(Agent01_Withdrawals!A51="","","WD"&TEXT(46-3,"0000")&"-"&TEXT(TODAY(),"YYYYMMDD")) | C46: =IF(Agent01_Withdrawals!A51="","",Agent01_Withdrawals!B51) | D46: =IF(Agent01_Withdrawals!A51="","",Agent01_Withdrawals!C51) | E46: =IF(Agent01_Withdrawals!A51="","",Agent01_Withdrawals!D51) | F46: =IF(Agent01_Withdrawals!A51="","",Agent01_Withdrawals!F51) | G46: =IF(Agent01_Withdrawals!A51="","",Agent01_Withdrawals!E51) | H46: =IF(Agent01_Withdrawals!A51="","",Agent01_Withdrawals!G51) | I46: =IF(Agent01_Withdrawals!A51="","",Agent01_Withdrawals!H51) | J46: =IF(Agent01_Withdrawals!A51="","",Agent01_Withdrawals!J51) | K46: =IF(Agent01_Withdrawals!A51="","",Agent01_Withdrawals!K51) | L46: =IF(G46="","",IF(D46-G46>=System_Config!$B$9,"✅ OK","⚠️ BREACH")) | M46: =IFERROR(IF(Agent01_Withdrawals!A51="","",YEAR(Agent01_Withdrawals!D51)),"")
A47: =IF(Agent01_Withdrawals!A52="","",Agent01_Withdrawals!A52) | B47: =IF(Agent01_Withdrawals!A52="","","WD"&TEXT(47-3,"0000")&"-"&TEXT(TODAY(),"YYYYMMDD")) | C47: =IF(Agent01_Withdrawals!A52="","",Agent01_Withdrawals!B52) | D47: =IF(Agent01_Withdrawals!A52="","",Agent01_Withdrawals!C52) | E47: =IF(Agent01_Withdrawals!A52="","",Agent01_Withdrawals!D52) | F47: =IF(Agent01_Withdrawals!A52="","",Agent01_Withdrawals!F52) | G47: =IF(Agent01_Withdrawals!A52="","",Agent01_Withdrawals!E52) | H47: =IF(Agent01_Withdrawals!A52="","",Agent01_Withdrawals!G52) | I47: =IF(Agent01_Withdrawals!A52="","",Agent01_Withdrawals!H52) | J47: =IF(Agent01_Withdrawals!A52="","",Agent01_Withdrawals!J52) | K47: =IF(Agent01_Withdrawals!A52="","",Agent01_Withdrawals!K52) | L47: =IF(G47="","",IF(D47-G47>=System_Config!$B$9,"✅ OK","⚠️ BREACH")) | M47: =IFERROR(IF(Agent01_Withdrawals!A52="","",YEAR(Agent01_Withdrawals!D52)),"")
A48: =IF(Agent01_Withdrawals!A53="","",Agent01_Withdrawals!A53) | B48: =IF(Agent01_Withdrawals!A53="","","WD"&TEXT(48-3,"0000")&"-"&TEXT(TODAY(),"YYYYMMDD")) | C48: =IF(Agent01_Withdrawals!A53="","",Agent01_Withdrawals!B53) | D48: =IF(Agent01_Withdrawals!A53="","",Agent01_Withdrawals!C53) | E48: =IF(Agent01_Withdrawals!A53="","",Agent01_Withdrawals!D53) | F48: =IF(Agent01_Withdrawals!A53="","",Agent01_Withdrawals!F53) | G48: =IF(Agent01_Withdrawals!A53="","",Agent01_Withdrawals!E53) | H48: =IF(Agent01_Withdrawals!A53="","",Agent01_Withdrawals!G53) | I48: =IF(Agent01_Withdrawals!A53="","",Agent01_Withdrawals!H53) | J48: =IF(Agent01_Withdrawals!A53="","",Agent01_Withdrawals!J53) | K48: =IF(Agent01_Withdrawals!A53="","",Agent01_Withdrawals!K53) | L48: =IF(G48="","",IF(D48-G48>=System_Config!$B$9,"✅ OK","⚠️ BREACH")) | M48: =IFERROR(IF(Agent01_Withdrawals!A53="","",YEAR(Agent01_Withdrawals!D53)),"")
A49: =IF(Agent01_Withdrawals!A54="","",Agent01_Withdrawals!A54) | B49: =IF(Agent01_Withdrawals!A54="","","WD"&TEXT(49-3,"0000")&"-"&TEXT(TODAY(),"YYYYMMDD")) | C49: =IF(Agent01_Withdrawals!A54="","",Agent01_Withdrawals!B54) | D49: =IF(Agent01_Withdrawals!A54="","",Agent01_Withdrawals!C54) | E49: =IF(Agent01_Withdrawals!A54="","",Agent01_Withdrawals!D54) | F49: =IF(Agent01_Withdrawals!A54="","",Agent01_Withdrawals!F54) | G49: =IF(Agent01_Withdrawals!A54="","",Agent01_Withdrawals!E54) | H49: =IF(Agent01_Withdrawals!A54="","",Agent01_Withdrawals!G54) | I49: =IF(Agent01_Withdrawals!A54="","",Agent01_Withdrawals!H54) | J49: =IF(Agent01_Withdrawals!A54="","",Agent01_Withdrawals!J54) | K49: =IF(Agent01_Withdrawals!A54="","",Agent01_Withdrawals!K54) | L49: =IF(G49="","",IF(D49-G49>=System_Config!$B$9,"✅ OK","⚠️ BREACH")) | M49: =IFERROR(IF(Agent01_Withdrawals!A54="","",YEAR(Agent01_Withdrawals!D54)),"")
A50: =IF(Agent01_Withdrawals!A55="","",Agent01_Withdrawals!A55) | B50: =IF(Agent01_Withdrawals!A55="","","WD"&TEXT(50-3,"0000")&"-"&TEXT(TODAY(),"YYYYMMDD")) | C50: =IF(Agent01_Withdrawals!A55="","",Agent01_Withdrawals!B55) | D50: =IF(Agent01_Withdrawals!A55="","",Agent01_Withdrawals!C55) | E50: =IF(Agent01_Withdrawals!A55="","",Agent01_Withdrawals!D55) | F50: =IF(Agent01_Withdrawals!A55="","",Agent01_Withdrawals!F55) | G50: =IF(Agent01_Withdrawals!A55="","",Agent01_Withdrawals!E55) | H50: =IF(Agent01_Withdrawals!A55="","",Agent01_Withdrawals!G55) | I50: =IF(Agent01_Withdrawals!A55="","",Agent01_Withdrawals!H55) | J50: =IF(Agent01_Withdrawals!A55="","",Agent01_Withdrawals!J55) | K50: =IF(Agent01_Withdrawals!A55="","",Agent01_Withdrawals!K55) | L50: =IF(G50="","",IF(D50-G50>=System_Config!$B$9,"✅ OK","⚠️ BREACH")) | M50: =IFERROR(IF(Agent01_Withdrawals!A55="","",YEAR(Agent01_Withdrawals!D55)),"")
A51: =IF(Agent01_Withdrawals!A56="","",Agent01_Withdrawals!A56) | B51: =IF(Agent01_Withdrawals!A56="","","WD"&TEXT(51-3,"0000")&"-"&TEXT(TODAY(),"YYYYMMDD")) | C51: =IF(Agent01_Withdrawals!A56="","",Agent01_Withdrawals!B56) | D51: =IF(Agent01_Withdrawals!A56="","",Agent01_Withdrawals!C56) | E51: =IF(Agent01_Withdrawals!A56="","",Agent01_Withdrawals!D56) | F51: =IF(Agent01_Withdrawals!A56="","",Agent01_Withdrawals!F56) | G51: =IF(Agent01_Withdrawals!A56="","",Agent01_Withdrawals!E56) | H51: =IF(Agent01_Withdrawals!A56="","",Agent01_Withdrawals!G56) | I51: =IF(Agent01_Withdrawals!A56="","",Agent01_Withdrawals!H56) | J51: =IF(Agent01_Withdrawals!A56="","",Agent01_Withdrawals!J56) | K51: =IF(Agent01_Withdrawals!A56="","",Agent01_Withdrawals!K56) | L51: =IF(G51="","",IF(D51-G51>=System_Config!$B$9,"✅ OK","⚠️ BREACH")) | M51: =IFERROR(IF(Agent01_Withdrawals!A56="","",YEAR(Agent01_Withdrawals!D56)),"")
A52: =IF(Agent01_Withdrawals!A57="","",Agent01_Withdrawals!A57) | B52: =IF(Agent01_Withdrawals!A57="","","WD"&TEXT(52-3,"0000")&"-"&TEXT(TODAY(),"YYYYMMDD")) | C52: =IF(Agent01_Withdrawals!A57="","",Agent01_Withdrawals!B57) | D52: =IF(Agent01_Withdrawals!A57="","",Agent01_Withdrawals!C57) | E52: =IF(Agent01_Withdrawals!A57="","",Agent01_Withdrawals!D57) | F52: =IF(Agent01_Withdrawals!A57="","",Agent01_Withdrawals!F57) | G52: =IF(Agent01_Withdrawals!A57="","",Agent01_Withdrawals!E57) | H52: =IF(Agent01_Withdrawals!A57="","",Agent01_Withdrawals!G57) | I52: =IF(Agent01_Withdrawals!A57="","",Agent01_Withdrawals!H57) | J52: =IF(Agent01_Withdrawals!A57="","",Agent01_Withdrawals!J57) | K52: =IF(Agent01_Withdrawals!A57="","",Agent01_Withdrawals!K57) | L52: =IF(G52="","",IF(D52-G52>=System_Config!$B$9,"✅ OK","⚠️ BREACH")) | M52: =IFERROR(IF(Agent01_Withdrawals!A57="","",YEAR(Agent01_Withdrawals!D57)),"")
A53: =IF(Agent01_Withdrawals!A58="","",Agent01_Withdrawals!A58) | B53: =IF(Agent01_Withdrawals!A58="","","WD"&TEXT(53-3,"0000")&"-"&TEXT(TODAY(),"YYYYMMDD")) | C53: =IF(Agent01_Withdrawals!A58="","",Agent01_Withdrawals!B58) | D53: =IF(Agent01_Withdrawals!A58="","",Agent01_Withdrawals!C58) | E53: =IF(Agent01_Withdrawals!A58="","",Agent01_Withdrawals!D58) | F53: =IF(Agent01_Withdrawals!A58="","",Agent01_Withdrawals!F58) | G53: =IF(Agent01_Withdrawals!A58="","",Agent01_Withdrawals!E58) | H53: =IF(Agent01_Withdrawals!A58="","",Agent01_Withdrawals!G58) | I53: =IF(Agent01_Withdrawals!A58="","",Agent01_Withdrawals!H58) | J53: =IF(Agent01_Withdrawals!A58="","",Agent01_Withdrawals!J58) | K53: =IF(Agent01_Withdrawals!A58="","",Agent01_Withdrawals!K58) | L53: =IF(G53="","",IF(D53-G53>=System_Config!$B$9,"✅ OK","⚠️ BREACH")) | M53: =IFERROR(IF(Agent01_Withdrawals!A58="","",YEAR(Agent01_Withdrawals!D58)),"")
A54: =IF(Agent01_Withdrawals!A59="","",Agent01_Withdrawals!A59) | B54: =IF(Agent01_Withdrawals!A59="","","WD"&TEXT(54-3,"0000")&"-"&TEXT(TODAY(),"YYYYMMDD")) | C54: =IF(Agent01_Withdrawals!A59="","",Agent01_Withdrawals!B59) | D54: =IF(Agent01_Withdrawals!A59="","",Agent01_Withdrawals!C59) | E54: =IF(Agent01_Withdrawals!A59="","",Agent01_Withdrawals!D59) | F54: =IF(Agent01_Withdrawals!A59="","",Agent01_Withdrawals!F59) | G54: =IF(Agent01_Withdrawals!A59="","",Agent01_Withdrawals!E59) | H54: =IF(Agent01_Withdrawals!A59="","",Agent01_Withdrawals!G59) | I54: =IF(Agent01_Withdrawals!A59="","",Agent01_Withdrawals!H59) | J54: =IF(Agent01_Withdrawals!A59="","",Agent01_Withdrawals!J59) | K54: =IF(Agent01_Withdrawals!A59="","",Agent01_Withdrawals!K59) | L54: =IF(G54="","",IF(D54-G54>=System_Config!$B$9,"✅ OK","⚠️ BREACH")) | M54: =IFERROR(IF(Agent01_Withdrawals!A59="","",YEAR(Agent01_Withdrawals!D59)),"")
A55: =IF(Agent01_Withdrawals!A60="","",Agent01_Withdrawals!A60) | B55: =IF(Agent01_Withdrawals!A60="","","WD"&TEXT(55-3,"0000")&"-"&TEXT(TODAY(),"YYYYMMDD")) | C55: =IF(Agent01_Withdrawals!A60="","",Agent01_Withdrawals!B60) | D55: =IF(Agent01_Withdrawals!A60="","",Agent01_Withdrawals!C60) | E55: =IF(Agent01_Withdrawals!A60="","",Agent01_Withdrawals!D60) | F55: =IF(Agent01_Withdrawals!A60="","",Agent01_Withdrawals!F60) | G55: =IF(Agent01_Withdrawals!A60="","",Agent01_Withdrawals!E60) | H55: =IF(Agent01_Withdrawals!A60="","",Agent01_Withdrawals!G60) | I55: =IF(Agent01_Withdrawals!A60="","",Agent01_Withdrawals!H60) | J55: =IF(Agent01_Withdrawals!A60="","",Agent01_Withdrawals!J60) | K55: =IF(Agent01_Withdrawals!A60="","",Agent01_Withdrawals!K60) | L55: =IF(G55="","",IF(D55-G55>=System_Config!$B$9,"✅ OK","⚠️ BREACH")) | M55: =IFERROR(IF(Agent01_Withdrawals!A60="","",YEAR(Agent01_Withdrawals!D60)),"")
A56: =IF(Agent01_Withdrawals!A61="","",Agent01_Withdrawals!A61) | B56: =IF(Agent01_Withdrawals!A61="","","WD"&TEXT(56-3,"0000")&"-"&TEXT(TODAY(),"YYYYMMDD")) | C56: =IF(Agent01_Withdrawals!A61="","",Agent01_Withdrawals!B61) | D56: =IF(Agent01_Withdrawals!A61="","",Agent01_Withdrawals!C61) | E56: =IF(Agent01_Withdrawals!A61="","",Agent01_Withdrawals!D61) | F56: =IF(Agent01_Withdrawals!A61="","",Agent01_Withdrawals!F61) | G56: =IF(Agent01_Withdrawals!A61="","",Agent01_Withdrawals!E61) | H56: =IF(Agent01_Withdrawals!A61="","",Agent01_Withdrawals!G61) | I56: =IF(Agent01_Withdrawals!A61="","",Agent01_Withdrawals!H61) | J56: =IF(Agent01_Withdrawals!A61="","",Agent01_Withdrawals!J61) | K56: =IF(Agent01_Withdrawals!A61="","",Agent01_Withdrawals!K61) | L56: =IF(G56="","",IF(D56-G56>=System_Config!$B$9,"✅ OK","⚠️ BREACH")) | M56: =IFERROR(IF(Agent01_Withdrawals!A61="","",YEAR(Agent01_Withdrawals!D61)),"")
A57: =IF(Agent01_Withdrawals!A62="","",Agent01_Withdrawals!A62) | B57: =IF(Agent01_Withdrawals!A62="","","WD"&TEXT(57-3,"0000")&"-"&TEXT(TODAY(),"YYYYMMDD")) | C57: =IF(Agent01_Withdrawals!A62="","",Agent01_Withdrawals!B62) | D57: =IF(Agent01_Withdrawals!A62="","",Agent01_Withdrawals!C62) | E57: =IF(Agent01_Withdrawals!A62="","",Agent01_Withdrawals!D62) | F57: =IF(Agent01_Withdrawals!A62="","",Agent01_Withdrawals!F62) | G57: =IF(Agent01_Withdrawals!A62="","",Agent01_Withdrawals!E62) | H57: =IF(Agent01_Withdrawals!A62="","",Agent01_Withdrawals!G62) | I57: =IF(Agent01_Withdrawals!A62="","",Agent01_Withdrawals!H62) | J57: =IF(Agent01_Withdrawals!A62="","",Agent01_Withdrawals!J62) | K57: =IF(Agent01_Withdrawals!A62="","",Agent01_Withdrawals!K62) | L57: =IF(G57="","",IF(D57-G57>=System_Config!$B$9,"✅ OK","⚠️ BREACH")) | M57: =IFERROR(IF(Agent01_Withdrawals!A62="","",YEAR(Agent01_Withdrawals!D62)),"")
A58: =IF(Agent01_Withdrawals!A63="","",Agent01_Withdrawals!A63) | B58: =IF(Agent01_Withdrawals!A63="","","WD"&TEXT(58-3,"0000")&"-"&TEXT(TODAY(),"YYYYMMDD")) | C58: =IF(Agent01_Withdrawals!A63="","",Agent01_Withdrawals!B63) | D58: =IF(Agent01_Withdrawals!A63="","",Agent01_Withdrawals!C63) | E58: =IF(Agent01_Withdrawals!A63="","",Agent01_Withdrawals!D63) | F58: =IF(Agent01_Withdrawals!A63="","",Agent01_Withdrawals!F63) | G58: =IF(Agent01_Withdrawals!A63="","",Agent01_Withdrawals!E63) | H58: =IF(Agent01_Withdrawals!A63="","",Agent01_Withdrawals!G63) | I58: =IF(Agent01_Withdrawals!A63="","",Agent01_Withdrawals!H63) | J58: =IF(Agent01_Withdrawals!A63="","",Agent01_Withdrawals!J63) | K58: =IF(Agent01_Withdrawals!A63="","",Agent01_Withdrawals!K63) | L58: =IF(G58="","",IF(D58-G58>=System_Config!$B$9,"✅ OK","⚠️ BREACH")) | M58: =IFERROR(IF(Agent01_Withdrawals!A63="","",YEAR(Agent01_Withdrawals!D63)),"")
A59: =IF(Agent01_Withdrawals!A64="","",Agent01_Withdrawals!A64) | B59: =IF(Agent01_Withdrawals!A64="","","WD"&TEXT(59-3,"0000")&"-"&TEXT(TODAY(),"YYYYMMDD")) | C59: =IF(Agent01_Withdrawals!A64="","",Agent01_Withdrawals!B64) | D59: =IF(Agent01_Withdrawals!A64="","",Agent01_Withdrawals!C64) | E59: =IF(Agent01_Withdrawals!A64="","",Agent01_Withdrawals!D64) | F59: =IF(Agent01_Withdrawals!A64="","",Agent01_Withdrawals!F64) | G59: =IF(Agent01_Withdrawals!A64="","",Agent01_Withdrawals!E64) | H59: =IF(Agent01_Withdrawals!A64="","",Agent01_Withdrawals!G64) | I59: =IF(Agent01_Withdrawals!A64="","",Agent01_Withdrawals!H64) | J59: =IF(Agent01_Withdrawals!A64="","",Agent01_Withdrawals!J64) | K59: =IF(Agent01_Withdrawals!A64="","",Agent01_Withdrawals!K64) | L59: =IF(G59="","",IF(D59-G59>=System_Config!$B$9,"✅ OK","⚠️ BREACH")) | M59: =IFERROR(IF(Agent01_Withdrawals!A64="","",YEAR(Agent01_Withdrawals!D64)),"")
A60: =IF(Agent01_Withdrawals!A65="","",Agent01_Withdrawals!A65) | B60: =IF(Agent01_Withdrawals!A65="","","WD"&TEXT(60-3,"0000")&"-"&TEXT(TODAY(),"YYYYMMDD")) | C60: =IF(Agent01_Withdrawals!A65="","",Agent01_Withdrawals!B65) | D60: =IF(Agent01_Withdrawals!A65="","",Agent01_Withdrawals!C65) | E60: =IF(Agent01_Withdrawals!A65="","",Agent01_Withdrawals!D65) | F60: =IF(Agent01_Withdrawals!A65="","",Agent01_Withdrawals!F65) | G60: =IF(Agent01_Withdrawals!A65="","",Agent01_Withdrawals!E65) | H60: =IF(Agent01_Withdrawals!A65="","",Agent01_Withdrawals!G65) | I60: =IF(Agent01_Withdrawals!A65="","",Agent01_Withdrawals!H65) | J60: =IF(Agent01_Withdrawals!A65="","",Agent01_Withdrawals!J65) | K60: =IF(Agent01_Withdrawals!A65="","",Agent01_Withdrawals!K65) | L60: =IF(G60="","",IF(D60-G60>=System_Config!$B$9,"✅ OK","⚠️ BREACH")) | M60: =IFERROR(IF(Agent01_Withdrawals!A65="","",YEAR(Agent01_Withdrawals!D65)),"")
A61: =IF(Agent01_Withdrawals!A66="","",Agent01_Withdrawals!A66) | B61: =IF(Agent01_Withdrawals!A66="","","WD"&TEXT(61-3,"0000")&"-"&TEXT(TODAY(),"YYYYMMDD")) | C61: =IF(Agent01_Withdrawals!A66="","",Agent01_Withdrawals!B66) | D61: =IF(Agent01_Withdrawals!A66="","",Agent01_Withdrawals!C66) | E61: =IF(Agent01_Withdrawals!A66="","",Agent01_Withdrawals!D66) | F61: =IF(Agent01_Withdrawals!A66="","",Agent01_Withdrawals!F66) | G61: =IF(Agent01_Withdrawals!A66="","",Agent01_Withdrawals!E66) | H61: =IF(Agent01_Withdrawals!A66="","",Agent01_Withdrawals!G66) | I61: =IF(Agent01_Withdrawals!A66="","",Agent01_Withdrawals!H66) | J61: =IF(Agent01_Withdrawals!A66="","",Agent01_Withdrawals!J66) | K61: =IF(Agent01_Withdrawals!A66="","",Agent01_Withdrawals!K66) | L61: =IF(G61="","",IF(D61-G61>=System_Config!$B$9,"✅ OK","⚠️ BREACH")) | M61: =IFERROR(IF(Agent01_Withdrawals!A66="","",YEAR(Agent01_Withdrawals!D66)),"")
A62: =IF(Agent01_Withdrawals!A67="","",Agent01_Withdrawals!A67) | B62: =IF(Agent01_Withdrawals!A67="","","WD"&TEXT(62-3,"0000")&"-"&TEXT(TODAY(),"YYYYMMDD")) | C62: =IF(Agent01_Withdrawals!A67="","",Agent01_Withdrawals!B67) | D62: =IF(Agent01_Withdrawals!A67="","",Agent01_Withdrawals!C67) | E62: =IF(Agent01_Withdrawals!A67="","",Agent01_Withdrawals!D67) | F62: =IF(Agent01_Withdrawals!A67="","",Agent01_Withdrawals!F67) | G62: =IF(Agent01_Withdrawals!A67="","",Agent01_Withdrawals!E67) | H62: =IF(Agent01_Withdrawals!A67="","",Agent01_Withdrawals!G67) | I62: =IF(Agent01_Withdrawals!A67="","",Agent01_Withdrawals!H67) | J62: =IF(Agent01_Withdrawals!A67="","",Agent01_Withdrawals!J67) | K62: =IF(Agent01_Withdrawals!A67="","",Agent01_Withdrawals!K67) | L62: =IF(G62="","",IF(D62-G62>=System_Config!$B$9,"✅ OK","⚠️ BREACH")) | M62: =IFERROR(IF(Agent01_Withdrawals!A67="","",YEAR(Agent01_Withdrawals!D67)),"")
A63: =IF(Agent01_Withdrawals!A68="","",Agent01_Withdrawals!A68) | B63: =IF(Agent01_Withdrawals!A68="","","WD"&TEXT(63-3,"0000")&"-"&TEXT(TODAY(),"YYYYMMDD")) | C63: =IF(Agent01_Withdrawals!A68="","",Agent01_Withdrawals!B68) | D63: =IF(Agent01_Withdrawals!A68="","",Agent01_Withdrawals!C68) | E63: =IF(Agent01_Withdrawals!A68="","",Agent01_Withdrawals!D68) | F63: =IF(Agent01_Withdrawals!A68="","",Agent01_Withdrawals!F68) | G63: =IF(Agent01_Withdrawals!A68="","",Agent01_Withdrawals!E68) | H63: =IF(Agent01_Withdrawals!A68="","",Agent01_Withdrawals!G68) | I63: =IF(Agent01_Withdrawals!A68="","",Agent01_Withdrawals!H68) | J63: =IF(Agent01_Withdrawals!A68="","",Agent01_Withdrawals!J68) | K63: =IF(Agent01_Withdrawals!A68="","",Agent01_Withdrawals!K68) | L63: =IF(G63="","",IF(D63-G63>=System_Config!$B$9,"✅ OK","⚠️ BREACH")) | M63: =IFERROR(IF(Agent01_Withdrawals!A68="","",YEAR(Agent01_Withdrawals!D68)),"")
A64: =IF(Agent01_Withdrawals!A69="","",Agent01_Withdrawals!A69) | B64: =IF(Agent01_Withdrawals!A69="","","WD"&TEXT(64-3,"0000")&"-"&TEXT(TODAY(),"YYYYMMDD")) | C64: =IF(Agent01_Withdrawals!A69="","",Agent01_Withdrawals!B69) | D64: =IF(Agent01_Withdrawals!A69="","",Agent01_Withdrawals!C69) | E64: =IF(Agent01_Withdrawals!A69="","",Agent01_Withdrawals!D69) | F64: =IF(Agent01_Withdrawals!A69="","",Agent01_Withdrawals!F69) | G64: =IF(Agent01_Withdrawals!A69="","",Agent01_Withdrawals!E69) | H64: =IF(Agent01_Withdrawals!A69="","",Agent01_Withdrawals!G69) | I64: =IF(Agent01_Withdrawals!A69="","",Agent01_Withdrawals!H69) | J64: =IF(Agent01_Withdrawals!A69="","",Agent01_Withdrawals!J69) | K64: =IF(Agent01_Withdrawals!A69="","",Agent01_Withdrawals!K69) | L64: =IF(G64="","",IF(D64-G64>=System_Config!$B$9,"✅ OK","⚠️ BREACH")) | M64: =IFERROR(IF(Agent01_Withdrawals!A69="","",YEAR(Agent01_Withdrawals!D69)),"")
A65: =IF(Agent01_Withdrawals!A70="","",Agent01_Withdrawals!A70) | B65: =IF(Agent01_Withdrawals!A70="","","WD"&TEXT(65-3,"0000")&"-"&TEXT(TODAY(),"YYYYMMDD")) | C65: =IF(Agent01_Withdrawals!A70="","",Agent01_Withdrawals!B70) | D65: =IF(Agent01_Withdrawals!A70="","",Agent01_Withdrawals!C70) | E65: =IF(Agent01_Withdrawals!A70="","",Agent01_Withdrawals!D70) | F65: =IF(Agent01_Withdrawals!A70="","",Agent01_Withdrawals!F70) | G65: =IF(Agent01_Withdrawals!A70="","",Agent01_Withdrawals!E70) | H65: =IF(Agent01_Withdrawals!A70="","",Agent01_Withdrawals!G70) | I65: =IF(Agent01_Withdrawals!A70="","",Agent01_Withdrawals!H70) | J65: =IF(Agent01_Withdrawals!A70="","",Agent01_Withdrawals!J70) | K65: =IF(Agent01_Withdrawals!A70="","",Agent01_Withdrawals!K70) | L65: =IF(G65="","",IF(D65-G65>=System_Config!$B$9,"✅ OK","⚠️ BREACH")) | M65: =IFERROR(IF(Agent01_Withdrawals!A70="","",YEAR(Agent01_Withdrawals!D70)),"")
A66: =IF(Agent01_Withdrawals!A71="","",Agent01_Withdrawals!A71) | B66: =IF(Agent01_Withdrawals!A71="","","WD"&TEXT(66-3,"0000")&"-"&TEXT(TODAY(),"YYYYMMDD")) | C66: =IF(Agent01_Withdrawals!A71="","",Agent01_Withdrawals!B71) | D66: =IF(Agent01_Withdrawals!A71="","",Agent01_Withdrawals!C71) | E66: =IF(Agent01_Withdrawals!A71="","",Agent01_Withdrawals!D71) | F66: =IF(Agent01_Withdrawals!A71="","",Agent01_Withdrawals!F71) | G66: =IF(Agent01_Withdrawals!A71="","",Agent01_Withdrawals!E71) | H66: =IF(Agent01_Withdrawals!A71="","",Agent01_Withdrawals!G71) | I66: =IF(Agent01_Withdrawals!A71="","",Agent01_Withdrawals!H71) | J66: =IF(Agent01_Withdrawals!A71="","",Agent01_Withdrawals!J71) | K66: =IF(Agent01_Withdrawals!A71="","",Agent01_Withdrawals!K71) | L66: =IF(G66="","",IF(D66-G66>=System_Config!$B$9,"✅ OK","⚠️ BREACH")) | M66: =IFERROR(IF(Agent01_Withdrawals!A71="","",YEAR(Agent01_Withdrawals!D71)),"")
A67: =IF(Agent01_Withdrawals!A72="","",Agent01_Withdrawals!A72) | B67: =IF(Agent01_Withdrawals!A72="","","WD"&TEXT(67-3,"0000")&"-"&TEXT(TODAY(),"YYYYMMDD")) | C67: =IF(Agent01_Withdrawals!A72="","",Agent01_Withdrawals!B72) | D67: =IF(Agent01_Withdrawals!A72="","",Agent01_Withdrawals!C72) | E67: =IF(Agent01_Withdrawals!A72="","",Agent01_Withdrawals!D72) | F67: =IF(Agent01_Withdrawals!A72="","",Agent01_Withdrawals!F72) | G67: =IF(Agent01_Withdrawals!A72="","",Agent01_Withdrawals!E72) | H67: =IF(Agent01_Withdrawals!A72="","",Agent01_Withdrawals!G72) | I67: =IF(Agent01_Withdrawals!A72="","",Agent01_Withdrawals!H72) | J67: =IF(Agent01_Withdrawals!A72="","",Agent01_Withdrawals!J72) | K67: =IF(Agent01_Withdrawals!A72="","",Agent01_Withdrawals!K72) | L67: =IF(G67="","",IF(D67-G67>=System_Config!$B$9,"✅ OK","⚠️ BREACH")) | M67: =IFERROR(IF(Agent01_Withdrawals!A72="","",YEAR(Agent01_Withdrawals!D72)),"")
A68: =IF(Agent01_Withdrawals!A73="","",Agent01_Withdrawals!A73) | B68: =IF(Agent01_Withdrawals!A73="","","WD"&TEXT(68-3,"0000")&"-"&TEXT(TODAY(),"YYYYMMDD")) | C68: =IF(Agent01_Withdrawals!A73="","",Agent01_Withdrawals!B73) | D68: =IF(Agent01_Withdrawals!A73="","",Agent01_Withdrawals!C73) | E68: =IF(Agent01_Withdrawals!A73="","",Agent01_Withdrawals!D73) | F68: =IF(Agent01_Withdrawals!A73="","",Agent01_Withdrawals!F73) | G68: =IF(Agent01_Withdrawals!A73="","",Agent01_Withdrawals!E73) | H68: =IF(Agent01_Withdrawals!A73="","",Agent01_Withdrawals!G73) | I68: =IF(Agent01_Withdrawals!A73="","",Agent01_Withdrawals!H73) | J68: =IF(Agent01_Withdrawals!A73="","",Agent01_Withdrawals!J73) | K68: =IF(Agent01_Withdrawals!A73="","",Agent01_Withdrawals!K73) | L68: =IF(G68="","",IF(D68-G68>=System_Config!$B$9,"✅ OK","⚠️ BREACH")) | M68: =IFERROR(IF(Agent01_Withdrawals!A73="","",YEAR(Agent01_Withdrawals!D73)),"")
A69: =IF(Agent01_Withdrawals!A74="","",Agent01_Withdrawals!A74) | B69: =IF(Agent01_Withdrawals!A74="","","WD"&TEXT(69-3,"0000")&"-"&TEXT(TODAY(),"YYYYMMDD")) | C69: =IF(Agent01_Withdrawals!A74="","",Agent01_Withdrawals!B74) | D69: =IF(Agent01_Withdrawals!A74="","",Agent01_Withdrawals!C74) | E69: =IF(Agent01_Withdrawals!A74="","",Agent01_Withdrawals!D74) | F69: =IF(Agent01_Withdrawals!A74="","",Agent01_Withdrawals!F74) | G69: =IF(Agent01_Withdrawals!A74="","",Agent01_Withdrawals!E74) | H69: =IF(Agent01_Withdrawals!A74="","",Agent01_Withdrawals!G74) | I69: =IF(Agent01_Withdrawals!A74="","",Agent01_Withdrawals!H74) | J69: =IF(Agent01_Withdrawals!A74="","",Agent01_Withdrawals!J74) | K69: =IF(Agent01_Withdrawals!A74="","",Agent01_Withdrawals!K74) | L69: =IF(G69="","",IF(D69-G69>=System_Config!$B$9,"✅ OK","⚠️ BREACH")) | M69: =IFERROR(IF(Agent01_Withdrawals!A74="","",YEAR(Agent01_Withdrawals!D74)),"")
A70: =IF(Agent01_Withdrawals!A75="","",Agent01_Withdrawals!A75) | B70: =IF(Agent01_Withdrawals!A75="","","WD"&TEXT(70-3,"0000")&"-"&TEXT(TODAY(),"YYYYMMDD")) | C70: =IF(Agent01_Withdrawals!A75="","",Agent01_Withdrawals!B75) | D70: =IF(Agent01_Withdrawals!A75="","",Agent01_Withdrawals!C75) | E70: =IF(Agent01_Withdrawals!A75="","",Agent01_Withdrawals!D75) | F70: =IF(Agent01_Withdrawals!A75="","",Agent01_Withdrawals!F75) | G70: =IF(Agent01_Withdrawals!A75="","",Agent01_Withdrawals!E75) | H70: =IF(Agent01_Withdrawals!A75="","",Agent01_Withdrawals!G75) | I70: =IF(Agent01_Withdrawals!A75="","",Agent01_Withdrawals!H75) | J70: =IF(Agent01_Withdrawals!A75="","",Agent01_Withdrawals!J75) | K70: =IF(Agent01_Withdrawals!A75="","",Agent01_Withdrawals!K75) | L70: =IF(G70="","",IF(D70-G70>=System_Config!$B$9,"✅ OK","⚠️ BREACH")) | M70: =IFERROR(IF(Agent01_Withdrawals!A75="","",YEAR(Agent01_Withdrawals!D75)),"")
A71: =IF(Agent01_Withdrawals!A76="","",Agent01_Withdrawals!A76) | B71: =IF(Agent01_Withdrawals!A76="","","WD"&TEXT(71-3,"0000")&"-"&TEXT(TODAY(),"YYYYMMDD")) | C71: =IF(Agent01_Withdrawals!A76="","",Agent01_Withdrawals!B76) | D71: =IF(Agent01_Withdrawals!A76="","",Agent01_Withdrawals!C76) | E71: =IF(Agent01_Withdrawals!A76="","",Agent01_Withdrawals!D76) | F71: =IF(Agent01_Withdrawals!A76="","",Agent01_Withdrawals!F76) | G71: =IF(Agent01_Withdrawals!A76="","",Agent01_Withdrawals!E76) | H71: =IF(Agent01_Withdrawals!A76="","",Agent01_Withdrawals!G76) | I71: =IF(Agent01_Withdrawals!A76="","",Agent01_Withdrawals!H76) | J71: =IF(Agent01_Withdrawals!A76="","",Agent01_Withdrawals!J76) | K71: =IF(Agent01_Withdrawals!A76="","",Agent01_Withdrawals!K76) | L71: =IF(G71="","",IF(D71-G71>=System_Config!$B$9,"✅ OK","⚠️ BREACH")) | M71: =IFERROR(IF(Agent01_Withdrawals!A76="","",YEAR(Agent01_Withdrawals!D76)),"")
A72: =IF(Agent01_Withdrawals!A77="","",Agent01_Withdrawals!A77) | B72: =IF(Agent01_Withdrawals!A77="","","WD"&TEXT(72-3,"0000")&"-"&TEXT(TODAY(),"YYYYMMDD")) | C72: =IF(Agent01_Withdrawals!A77="","",Agent01_Withdrawals!B77) | D72: =IF(Agent01_Withdrawals!A77="","",Agent01_Withdrawals!C77) | E72: =IF(Agent01_Withdrawals!A77="","",Agent01_Withdrawals!D77) | F72: =IF(Agent01_Withdrawals!A77="","",Agent01_Withdrawals!F77) | G72: =IF(Agent01_Withdrawals!A77="","",Agent01_Withdrawals!E77) | H72: =IF(Agent01_Withdrawals!A77="","",Agent01_Withdrawals!G77) | I72: =IF(Agent01_Withdrawals!A77="","",Agent01_Withdrawals!H77) | J72: =IF(Agent01_Withdrawals!A77="","",Agent01_Withdrawals!J77) | K72: =IF(Agent01_Withdrawals!A77="","",Agent01_Withdrawals!K77) | L72: =IF(G72="","",IF(D72-G72>=System_Config!$B$9,"✅ OK","⚠️ BREACH")) | M72: =IFERROR(IF(Agent01_Withdrawals!A77="","",YEAR(Agent01_Withdrawals!D77)),"")
A73: =IF(Agent01_Withdrawals!A78="","",Agent01_Withdrawals!A78) | B73: =IF(Agent01_Withdrawals!A78="","","WD"&TEXT(73-3,"0000")&"-"&TEXT(TODAY(),"YYYYMMDD")) | C73: =IF(Agent01_Withdrawals!A78="","",Agent01_Withdrawals!B78) | D73: =IF(Agent01_Withdrawals!A78="","",Agent01_Withdrawals!C78) | E73: =IF(Agent01_Withdrawals!A78="","",Agent01_Withdrawals!D78) | F73: =IF(Agent01_Withdrawals!A78="","",Agent01_Withdrawals!F78) | G73: =IF(Agent01_Withdrawals!A78="","",Agent01_Withdrawals!E78) | H73: =IF(Agent01_Withdrawals!A78="","",Agent01_Withdrawals!G78) | I73: =IF(Agent01_Withdrawals!A78="","",Agent01_Withdrawals!H78) | J73: =IF(Agent01_Withdrawals!A78="","",Agent01_Withdrawals!J78) | K73: =IF(Agent01_Withdrawals!A78="","",Agent01_Withdrawals!K78) | L73: =IF(G73="","",IF(D73-G73>=System_Config!$B$9,"✅ OK","⚠️ BREACH")) | M73: =IFERROR(IF(Agent01_Withdrawals!A78="","",YEAR(Agent01_Withdrawals!D78)),"")
A74: =IF(Agent01_Withdrawals!A79="","",Agent01_Withdrawals!A79) | B74: =IF(Agent01_Withdrawals!A79="","","WD"&TEXT(74-3,"0000")&"-"&TEXT(TODAY(),"YYYYMMDD")) | C74: =IF(Agent01_Withdrawals!A79="","",Agent01_Withdrawals!B79) | D74: =IF(Agent01_Withdrawals!A79="","",Agent01_Withdrawals!C79) | E74: =IF(Agent01_Withdrawals!A79="","",Agent01_Withdrawals!D79) | F74: =IF(Agent01_Withdrawals!A79="","",Agent01_Withdrawals!F79) | G74: =IF(Agent01_Withdrawals!A79="","",Agent01_Withdrawals!E79) | H74: =IF(Agent01_Withdrawals!A79="","",Agent01_Withdrawals!G79) | I74: =IF(Agent01_Withdrawals!A79="","",Agent01_Withdrawals!H79) | J74: =IF(Agent01_Withdrawals!A79="","",Agent01_Withdrawals!J79) | K74: =IF(Agent01_Withdrawals!A79="","",Agent01_Withdrawals!K79) | L74: =IF(G74="","",IF(D74-G74>=System_Config!$B$9,"✅ OK","⚠️ BREACH")) | M74: =IFERROR(IF(Agent01_Withdrawals!A79="","",YEAR(Agent01_Withdrawals!D79)),"")
A75: =IF(Agent01_Withdrawals!A80="","",Agent01_Withdrawals!A80) | B75: =IF(Agent01_Withdrawals!A80="","","WD"&TEXT(75-3,"0000")&"-"&TEXT(TODAY(),"YYYYMMDD")) | C75: =IF(Agent01_Withdrawals!A80="","",Agent01_Withdrawals!B80) | D75: =IF(Agent01_Withdrawals!A80="","",Agent01_Withdrawals!C80) | E75: =IF(Agent01_Withdrawals!A80="","",Agent01_Withdrawals!D80) | F75: =IF(Agent01_Withdrawals!A80="","",Agent01_Withdrawals!F80) | G75: =IF(Agent01_Withdrawals!A80="","",Agent01_Withdrawals!E80) | H75: =IF(Agent01_Withdrawals!A80="","",Agent01_Withdrawals!G80) | I75: =IF(Agent01_Withdrawals!A80="","",Agent01_Withdrawals!H80) | J75: =IF(Agent01_Withdrawals!A80="","",Agent01_Withdrawals!J80) | K75: =IF(Agent01_Withdrawals!A80="","",Agent01_Withdrawals!K80) | L75: =IF(G75="","",IF(D75-G75>=System_Config!$B$9,"✅ OK","⚠️ BREACH")) | M75: =IFERROR(IF(Agent01_Withdrawals!A80="","",YEAR(Agent01_Withdrawals!D80)),"")
A76: =IF(Agent01_Withdrawals!A81="","",Agent01_Withdrawals!A81) | B76: =IF(Agent01_Withdrawals!A81="","","WD"&TEXT(76-3,"0000")&"-"&TEXT(TODAY(),"YYYYMMDD")) | C76: =IF(Agent01_Withdrawals!A81="","",Agent01_Withdrawals!B81) | D76: =IF(Agent01_Withdrawals!A81="","",Agent01_Withdrawals!C81) | E76: =IF(Agent01_Withdrawals!A81="","",Agent01_Withdrawals!D81) | F76: =IF(Agent01_Withdrawals!A81="","",Agent01_Withdrawals!F81) | G76: =IF(Agent01_Withdrawals!A81="","",Agent01_Withdrawals!E81) | H76: =IF(Agent01_Withdrawals!A81="","",Agent01_Withdrawals!G81) | I76: =IF(Agent01_Withdrawals!A81="","",Agent01_Withdrawals!H81) | J76: =IF(Agent01_Withdrawals!A81="","",Agent01_Withdrawals!J81) | K76: =IF(Agent01_Withdrawals!A81="","",Agent01_Withdrawals!K81) | L76: =IF(G76="","",IF(D76-G76>=System_Config!$B$9,"✅ OK","⚠️ BREACH")) | M76: =IFERROR(IF(Agent01_Withdrawals!A81="","",YEAR(Agent01_Withdrawals!D81)),"")
A77: =IF(Agent01_Withdrawals!A82="","",Agent01_Withdrawals!A82) | B77: =IF(Agent01_Withdrawals!A82="","","WD"&TEXT(77-3,"0000")&"-"&TEXT(TODAY(),"YYYYMMDD")) | C77: =IF(Agent01_Withdrawals!A82="","",Agent01_Withdrawals!B82) | D77: =IF(Agent01_Withdrawals!A82="","",Agent01_Withdrawals!C82) | E77: =IF(Agent01_Withdrawals!A82="","",Agent01_Withdrawals!D82) | F77: =IF(Agent01_Withdrawals!A82="","",Agent01_Withdrawals!F82) | G77: =IF(Agent01_Withdrawals!A82="","",Agent01_Withdrawals!E82) | H77: =IF(Agent01_Withdrawals!A82="","",Agent01_Withdrawals!G82) | I77: =IF(Agent01_Withdrawals!A82="","",Agent01_Withdrawals!H82) | J77: =IF(Agent01_Withdrawals!A82="","",Agent01_Withdrawals!J82) | K77: =IF(Agent01_Withdrawals!A82="","",Agent01_Withdrawals!K82) | L77: =IF(G77="","",IF(D77-G77>=System_Config!$B$9,"✅ OK","⚠️ BREACH")) | M77: =IFERROR(IF(Agent01_Withdrawals!A82="","",YEAR(Agent01_Withdrawals!D82)),"")
A78: =IF(Agent01_Withdrawals!A83="","",Agent01_Withdrawals!A83) | B78: =IF(Agent01_Withdrawals!A83="","","WD"&TEXT(78-3,"0000")&"-"&TEXT(TODAY(),"YYYYMMDD")) | C78: =IF(Agent01_Withdrawals!A83="","",Agent01_Withdrawals!B83) | D78: =IF(Agent01_Withdrawals!A83="","",Agent01_Withdrawals!C83) | E78: =IF(Agent01_Withdrawals!A83="","",Agent01_Withdrawals!D83) | F78: =IF(Agent01_Withdrawals!A83="","",Agent01_Withdrawals!F83) | G78: =IF(Agent01_Withdrawals!A83="","",Agent01_Withdrawals!E83) | H78: =IF(Agent01_Withdrawals!A83="","",Agent01_Withdrawals!G83) | I78: =IF(Agent01_Withdrawals!A83="","",Agent01_Withdrawals!H83) | J78: =IF(Agent01_Withdrawals!A83="","",Agent01_Withdrawals!J83) | K78: =IF(Agent01_Withdrawals!A83="","",Agent01_Withdrawals!K83) | L78: =IF(G78="","",IF(D78-G78>=System_Config!$B$9,"✅ OK","⚠️ BREACH")) | M78: =IFERROR(IF(Agent01_Withdrawals!A83="","",YEAR(Agent01_Withdrawals!D83)),"")
A79: =IF(Agent01_Withdrawals!A84="","",Agent01_Withdrawals!A84) | B79: =IF(Agent01_Withdrawals!A84="","","WD"&TEXT(79-3,"0000")&"-"&TEXT(TODAY(),"YYYYMMDD")) | C79: =IF(Agent01_Withdrawals!A84="","",Agent01_Withdrawals!B84) | D79: =IF(Agent01_Withdrawals!A84="","",Agent01_Withdrawals!C84) | E79: =IF(Agent01_Withdrawals!A84="","",Agent01_Withdrawals!D84) | F79: =IF(Agent01_Withdrawals!A84="","",Agent01_Withdrawals!F84) | G79: =IF(Agent01_Withdrawals!A84="","",Agent01_Withdrawals!E84) | H79: =IF(Agent01_Withdrawals!A84="","",Agent01_Withdrawals!G84) | I79: =IF(Agent01_Withdrawals!A84="","",Agent01_Withdrawals!H84) | J79: =IF(Agent01_Withdrawals!A84="","",Agent01_Withdrawals!J84) | K79: =IF(Agent01_Withdrawals!A84="","",Agent01_Withdrawals!K84) | L79: =IF(G79="","",IF(D79-G79>=System_Config!$B$9,"✅ OK","⚠️ BREACH")) | M79: =IFERROR(IF(Agent01_Withdrawals!A84="","",YEAR(Agent01_Withdrawals!D84)),"")
A80: =IF(Agent01_Withdrawals!A85="","",Agent01_Withdrawals!A85) | B80: =IF(Agent01_Withdrawals!A85="","","WD"&TEXT(80-3,"0000")&"-"&TEXT(TODAY(),"YYYYMMDD")) | C80: =IF(Agent01_Withdrawals!A85="","",Agent01_Withdrawals!B85) | D80: =IF(Agent01_Withdrawals!A85="","",Agent01_Withdrawals!C85) | E80: =IF(Agent01_Withdrawals!A85="","",Agent01_Withdrawals!D85) | F80: =IF(Agent01_Withdrawals!A85="","",Agent01_Withdrawals!F85) | G80: =IF(Agent01_Withdrawals!A85="","",Agent01_Withdrawals!E85) | H80: =IF(Agent01_Withdrawals!A85="","",Agent01_Withdrawals!G85) | I80: =IF(Agent01_Withdrawals!A85="","",Agent01_Withdrawals!H85) | J80: =IF(Agent01_Withdrawals!A85="","",Agent01_Withdrawals!J85) | K80: =IF(Agent01_Withdrawals!A85="","",Agent01_Withdrawals!K85) | L80: =IF(G80="","",IF(D80-G80>=System_Config!$B$9,"✅ OK","⚠️ BREACH")) | M80: =IFERROR(IF(Agent01_Withdrawals!A85="","",YEAR(Agent01_Withdrawals!D85)),"")
A81: =IF(Agent01_Withdrawals!A86="","",Agent01_Withdrawals!A86) | B81: =IF(Agent01_Withdrawals!A86="","","WD"&TEXT(81-3,"0000")&"-"&TEXT(TODAY(),"YYYYMMDD")) | C81: =IF(Agent01_Withdrawals!A86="","",Agent01_Withdrawals!B86) | D81: =IF(Agent01_Withdrawals!A86="","",Agent01_Withdrawals!C86) | E81: =IF(Agent01_Withdrawals!A86="","",Agent01_Withdrawals!D86) | F81: =IF(Agent01_Withdrawals!A86="","",Agent01_Withdrawals!F86) | G81: =IF(Agent01_Withdrawals!A86="","",Agent01_Withdrawals!E86) | H81: =IF(Agent01_Withdrawals!A86="","",Agent01_Withdrawals!G86) | I81: =IF(Agent01_Withdrawals!A86="","",Agent01_Withdrawals!H86) | J81: =IF(Agent01_Withdrawals!A86="","",Agent01_Withdrawals!J86) | K81: =IF(Agent01_Withdrawals!A86="","",Agent01_Withdrawals!K86) | L81: =IF(G81="","",IF(D81-G81>=System_Config!$B$9,"✅ OK","⚠️ BREACH")) | M81: =IFERROR(IF(Agent01_Withdrawals!A86="","",YEAR(Agent01_Withdrawals!D86)),"")
A82: =IF(Agent01_Withdrawals!A87="","",Agent01_Withdrawals!A87) | B82: =IF(Agent01_Withdrawals!A87="","","WD"&TEXT(82-3,"0000")&"-"&TEXT(TODAY(),"YYYYMMDD")) | C82: =IF(Agent01_Withdrawals!A87="","",Agent01_Withdrawals!B87) | D82: =IF(Agent01_Withdrawals!A87="","",Agent01_Withdrawals!C87) | E82: =IF(Agent01_Withdrawals!A87="","",Agent01_Withdrawals!D87) | F82: =IF(Agent01_Withdrawals!A87="","",Agent01_Withdrawals!F87) | G82: =IF(Agent01_Withdrawals!A87="","",Agent01_Withdrawals!E87) | H82: =IF(Agent01_Withdrawals!A87="","",Agent01_Withdrawals!G87) | I82: =IF(Agent01_Withdrawals!A87="","",Agent01_Withdrawals!H87) | J82: =IF(Agent01_Withdrawals!A87="","",Agent01_Withdrawals!J87) | K82: =IF(Agent01_Withdrawals!A87="","",Agent01_Withdrawals!K87) | L82: =IF(G82="","",IF(D82-G82>=System_Config!$B$9,"✅ OK","⚠️ BREACH")) | M82: =IFERROR(IF(Agent01_Withdrawals!A87="","",YEAR(Agent01_Withdrawals!D87)),"")
A83: =IF(Agent01_Withdrawals!A88="","",Agent01_Withdrawals!A88) | B83: =IF(Agent01_Withdrawals!A88="","","WD"&TEXT(83-3,"0000")&"-"&TEXT(TODAY(),"YYYYMMDD")) | C83: =IF(Agent01_Withdrawals!A88="","",Agent01_Withdrawals!B88) | D83: =IF(Agent01_Withdrawals!A88="","",Agent01_Withdrawals!C88) | E83: =IF(Agent01_Withdrawals!A88="","",Agent01_Withdrawals!D88) | F83: =IF(Agent01_Withdrawals!A88="","",Agent01_Withdrawals!F88) | G83: =IF(Agent01_Withdrawals!A88="","",Agent01_Withdrawals!E88) | H83: =IF(Agent01_Withdrawals!A88="","",Agent01_Withdrawals!G88) | I83: =IF(Agent01_Withdrawals!A88="","",Agent01_Withdrawals!H88) | J83: =IF(Agent01_Withdrawals!A88="","",Agent01_Withdrawals!J88) | K83: =IF(Agent01_Withdrawals!A88="","",Agent01_Withdrawals!K88) | L83: =IF(G83="","",IF(D83-G83>=System_Config!$B$9,"✅ OK","⚠️ BREACH")) | M83: =IFERROR(IF(Agent01_Withdrawals!A88="","",YEAR(Agent01_Withdrawals!D88)),"")
A84: =IF(Agent01_Withdrawals!A89="","",Agent01_Withdrawals!A89) | B84: =IF(Agent01_Withdrawals!A89="","","WD"&TEXT(84-3,"0000")&"-"&TEXT(TODAY(),"YYYYMMDD")) | C84: =IF(Agent01_Withdrawals!A89="","",Agent01_Withdrawals!B89) | D84: =IF(Agent01_Withdrawals!A89="","",Agent01_Withdrawals!C89) | E84: =IF(Agent01_Withdrawals!A89="","",Agent01_Withdrawals!D89) | F84: =IF(Agent01_Withdrawals!A89="","",Agent01_Withdrawals!F89) | G84: =IF(Agent01_Withdrawals!A89="","",Agent01_Withdrawals!E89) | H84: =IF(Agent01_Withdrawals!A89="","",Agent01_Withdrawals!G89) | I84: =IF(Agent01_Withdrawals!A89="","",Agent01_Withdrawals!H89) | J84: =IF(Agent01_Withdrawals!A89="","",Agent01_Withdrawals!J89) | K84: =IF(Agent01_Withdrawals!A89="","",Agent01_Withdrawals!K89) | L84: =IF(G84="","",IF(D84-G84>=System_Config!$B$9,"✅ OK","⚠️ BREACH")) | M84: =IFERROR(IF(Agent01_Withdrawals!A89="","",YEAR(Agent01_Withdrawals!D89)),"")
A85: =IF(Agent01_Withdrawals!A90="","",Agent01_Withdrawals!A90) | B85: =IF(Agent01_Withdrawals!A90="","","WD"&TEXT(85-3,"0000")&"-"&TEXT(TODAY(),"YYYYMMDD")) | C85: =IF(Agent01_Withdrawals!A90="","",Agent01_Withdrawals!B90) | D85: =IF(Agent01_Withdrawals!A90="","",Agent01_Withdrawals!C90) | E85: =IF(Agent01_Withdrawals!A90="","",Agent01_Withdrawals!D90) | F85: =IF(Agent01_Withdrawals!A90="","",Agent01_Withdrawals!F90) | G85: =IF(Agent01_Withdrawals!A90="","",Agent01_Withdrawals!E90) | H85: =IF(Agent01_Withdrawals!A90="","",Agent01_Withdrawals!G90) | I85: =IF(Agent01_Withdrawals!A90="","",Agent01_Withdrawals!H90) | J85: =IF(Agent01_Withdrawals!A90="","",Agent01_Withdrawals!J90) | K85: =IF(Agent01_Withdrawals!A90="","",Agent01_Withdrawals!K90) | L85: =IF(G85="","",IF(D85-G85>=System_Config!$B$9,"✅ OK","⚠️ BREACH")) | M85: =IFERROR(IF(Agent01_Withdrawals!A90="","",YEAR(Agent01_Withdrawals!D90)),"")
A86: =IF(Agent01_Withdrawals!A91="","",Agent01_Withdrawals!A91) | B86: =IF(Agent01_Withdrawals!A91="","","WD"&TEXT(86-3,"0000")&"-"&TEXT(TODAY(),"YYYYMMDD")) | C86: =IF(Agent01_Withdrawals!A91="","",Agent01_Withdrawals!B91) | D86: =IF(Agent01_Withdrawals!A91="","",Agent01_Withdrawals!C91) | E86: =IF(Agent01_Withdrawals!A91="","",Agent01_Withdrawals!D91) | F86: =IF(Agent01_Withdrawals!A91="","",Agent01_Withdrawals!F91) | G86: =IF(Agent01_Withdrawals!A91="","",Agent01_Withdrawals!E91) | H86: =IF(Agent01_Withdrawals!A91="","",Agent01_Withdrawals!G91) | I86: =IF(Agent01_Withdrawals!A91="","",Agent01_Withdrawals!H91) | J86: =IF(Agent01_Withdrawals!A91="","",Agent01_Withdrawals!J91) | K86: =IF(Agent01_Withdrawals!A91="","",Agent01_Withdrawals!K91) | L86: =IF(G86="","",IF(D86-G86>=System_Config!$B$9,"✅ OK","⚠️ BREACH")) | M86: =IFERROR(IF(Agent01_Withdrawals!A91="","",YEAR(Agent01_Withdrawals!D91)),"")
A87: =IF(Agent01_Withdrawals!A92="","",Agent01_Withdrawals!A92) | B87: =IF(Agent01_Withdrawals!A92="","","WD"&TEXT(87-3,"0000")&"-"&TEXT(TODAY(),"YYYYMMDD")) | C87: =IF(Agent01_Withdrawals!A92="","",Agent01_Withdrawals!B92) | D87: =IF(Agent01_Withdrawals!A92="","",Agent01_Withdrawals!C92) | E87: =IF(Agent01_Withdrawals!A92="","",Agent01_Withdrawals!D92) | F87: =IF(Agent01_Withdrawals!A92="","",Agent01_Withdrawals!F92) | G87: =IF(Agent01_Withdrawals!A92="","",Agent01_Withdrawals!E92) | H87: =IF(Agent01_Withdrawals!A92="","",Agent01_Withdrawals!G92) | I87: =IF(Agent01_Withdrawals!A92="","",Agent01_Withdrawals!H92) | J87: =IF(Agent01_Withdrawals!A92="","",Agent01_Withdrawals!J92) | K87: =IF(Agent01_Withdrawals!A92="","",Agent01_Withdrawals!K92) | L87: =IF(G87="","",IF(D87-G87>=System_Config!$B$9,"✅ OK","⚠️ BREACH")) | M87: =IFERROR(IF(Agent01_Withdrawals!A92="","",YEAR(Agent01_Withdrawals!D92)),"")
A88: =IF(Agent01_Withdrawals!A93="","",Agent01_Withdrawals!A93) | B88: =IF(Agent01_Withdrawals!A93="","","WD"&TEXT(88-3,"0000")&"-"&TEXT(TODAY(),"YYYYMMDD")) | C88: =IF(Agent01_Withdrawals!A93="","",Agent01_Withdrawals!B93) | D88: =IF(Agent01_Withdrawals!A93="","",Agent01_Withdrawals!C93) | E88: =IF(Agent01_Withdrawals!A93="","",Agent01_Withdrawals!D93) | F88: =IF(Agent01_Withdrawals!A93="","",Agent01_Withdrawals!F93) | G88: =IF(Agent01_Withdrawals!A93="","",Agent01_Withdrawals!E93) | H88: =IF(Agent01_Withdrawals!A93="","",Agent01_Withdrawals!G93) | I88: =IF(Agent01_Withdrawals!A93="","",Agent01_Withdrawals!H93) | J88: =IF(Agent01_Withdrawals!A93="","",Agent01_Withdrawals!J93) | K88: =IF(Agent01_Withdrawals!A93="","",Agent01_Withdrawals!K93) | L88: =IF(G88="","",IF(D88-G88>=System_Config!$B$9,"✅ OK","⚠️ BREACH")) | M88: =IFERROR(IF(Agent01_Withdrawals!A93="","",YEAR(Agent01_Withdrawals!D93)),"")
A89: =IF(Agent01_Withdrawals!A94="","",Agent01_Withdrawals!A94) | B89: =IF(Agent01_Withdrawals!A94="","","WD"&TEXT(89-3,"0000")&"-"&TEXT(TODAY(),"YYYYMMDD")) | C89: =IF(Agent01_Withdrawals!A94="","",Agent01_Withdrawals!B94) | D89: =IF(Agent01_Withdrawals!A94="","",Agent01_Withdrawals!C94) | E89: =IF(Agent01_Withdrawals!A94="","",Agent01_Withdrawals!D94) | F89: =IF(Agent01_Withdrawals!A94="","",Agent01_Withdrawals!F94) | G89: =IF(Agent01_Withdrawals!A94="","",Agent01_Withdrawals!E94) | H89: =IF(Agent01_Withdrawals!A94="","",Agent01_Withdrawals!G94) | I89: =IF(Agent01_Withdrawals!A94="","",Agent01_Withdrawals!H94) | J89: =IF(Agent01_Withdrawals!A94="","",Agent01_Withdrawals!J94) | K89: =IF(Agent01_Withdrawals!A94="","",Agent01_Withdrawals!K94) | L89: =IF(G89="","",IF(D89-G89>=System_Config!$B$9,"✅ OK","⚠️ BREACH")) | M89: =IFERROR(IF(Agent01_Withdrawals!A94="","",YEAR(Agent01_Withdrawals!D94)),"")
A90: =IF(Agent01_Withdrawals!A95="","",Agent01_Withdrawals!A95) | B90: =IF(Agent01_Withdrawals!A95="","","WD"&TEXT(90-3,"0000")&"-"&TEXT(TODAY(),"YYYYMMDD")) | C90: =IF(Agent01_Withdrawals!A95="","",Agent01_Withdrawals!B95) | D90: =IF(Agent01_Withdrawals!A95="","",Agent01_Withdrawals!C95) | E90: =IF(Agent01_Withdrawals!A95="","",Agent01_Withdrawals!D95) | F90: =IF(Agent01_Withdrawals!A95="","",Agent01_Withdrawals!F95) | G90: =IF(Agent01_Withdrawals!A95="","",Agent01_Withdrawals!E95) | H90: =IF(Agent01_Withdrawals!A95="","",Agent01_Withdrawals!G95) | I90: =IF(Agent01_Withdrawals!A95="","",Agent01_Withdrawals!H95) | J90: =IF(Agent01_Withdrawals!A95="","",Agent01_Withdrawals!J95) | K90: =IF(Agent01_Withdrawals!A95="","",Agent01_Withdrawals!K95) | L90: =IF(G90="","",IF(D90-G90>=System_Config!$B$9,"✅ OK","⚠️ BREACH")) | M90: =IFERROR(IF(Agent01_Withdrawals!A95="","",YEAR(Agent01_Withdrawals!D95)),"")
A91: =IF(Agent01_Withdrawals!A96="","",Agent01_Withdrawals!A96) | B91: =IF(Agent01_Withdrawals!A96="","","WD"&TEXT(91-3,"0000")&"-"&TEXT(TODAY(),"YYYYMMDD")) | C91: =IF(Agent01_Withdrawals!A96="","",Agent01_Withdrawals!B96) | D91: =IF(Agent01_Withdrawals!A96="","",Agent01_Withdrawals!C96) | E91: =IF(Agent01_Withdrawals!A96="","",Agent01_Withdrawals!D96) | F91: =IF(Agent01_Withdrawals!A96="","",Agent01_Withdrawals!F96) | G91: =IF(Agent01_Withdrawals!A96="","",Agent01_Withdrawals!E96) | H91: =IF(Agent01_Withdrawals!A96="","",Agent01_Withdrawals!G96) | I91: =IF(Agent01_Withdrawals!A96="","",Agent01_Withdrawals!H96) | J91: =IF(Agent01_Withdrawals!A96="","",Agent01_Withdrawals!J96) | K91: =IF(Agent01_Withdrawals!A96="","",Agent01_Withdrawals!K96) | L91: =IF(G91="","",IF(D91-G91>=System_Config!$B$9,"✅ OK","⚠️ BREACH")) | M91: =IFERROR(IF(Agent01_Withdrawals!A96="","",YEAR(Agent01_Withdrawals!D96)),"")
A92: =IF(Agent01_Withdrawals!A97="","",Agent01_Withdrawals!A97) | B92: =IF(Agent01_Withdrawals!A97="","","WD"&TEXT(92-3,"0000")&"-"&TEXT(TODAY(),"YYYYMMDD")) | C92: =IF(Agent01_Withdrawals!A97="","",Agent01_Withdrawals!B97) | D92: =IF(Agent01_Withdrawals!A97="","",Agent01_Withdrawals!C97) | E92: =IF(Agent01_Withdrawals!A97="","",Agent01_Withdrawals!D97) | F92: =IF(Agent01_Withdrawals!A97="","",Agent01_Withdrawals!F97) | G92: =IF(Agent01_Withdrawals!A97="","",Agent01_Withdrawals!E97) | H92: =IF(Agent01_Withdrawals!A97="","",Agent01_Withdrawals!G97) | I92: =IF(Agent01_Withdrawals!A97="","",Agent01_Withdrawals!H97) | J92: =IF(Agent01_Withdrawals!A97="","",Agent01_Withdrawals!J97) | K92: =IF(Agent01_Withdrawals!A97="","",Agent01_Withdrawals!K97) | L92: =IF(G92="","",IF(D92-G92>=System_Config!$B$9,"✅ OK","⚠️ BREACH")) | M92: =IFERROR(IF(Agent01_Withdrawals!A97="","",YEAR(Agent01_Withdrawals!D97)),"")
A93: =IF(Agent01_Withdrawals!A98="","",Agent01_Withdrawals!A98) | B93: =IF(Agent01_Withdrawals!A98="","","WD"&TEXT(93-3,"0000")&"-"&TEXT(TODAY(),"YYYYMMDD")) | C93: =IF(Agent01_Withdrawals!A98="","",Agent01_Withdrawals!B98) | D93: =IF(Agent01_Withdrawals!A98="","",Agent01_Withdrawals!C98) | E93: =IF(Agent01_Withdrawals!A98="","",Agent01_Withdrawals!D98) | F93: =IF(Agent01_Withdrawals!A98="","",Agent01_Withdrawals!F98) | G93: =IF(Agent01_Withdrawals!A98="","",Agent01_Withdrawals!E98) | H93: =IF(Agent01_Withdrawals!A98="","",Agent01_Withdrawals!G98) | I93: =IF(Agent01_Withdrawals!A98="","",Agent01_Withdrawals!H98) | J93: =IF(Agent01_Withdrawals!A98="","",Agent01_Withdrawals!J98) | K93: =IF(Agent01_Withdrawals!A98="","",Agent01_Withdrawals!K98) | L93: =IF(G93="","",IF(D93-G93>=System_Config!$B$9,"✅ OK","⚠️ BREACH")) | M93: =IFERROR(IF(Agent01_Withdrawals!A98="","",YEAR(Agent01_Withdrawals!D98)),"")
A94: =IF(Agent01_Withdrawals!A99="","",Agent01_Withdrawals!A99) | B94: =IF(Agent01_Withdrawals!A99="","","WD"&TEXT(94-3,"0000")&"-"&TEXT(TODAY(),"YYYYMMDD")) | C94: =IF(Agent01_Withdrawals!A99="","",Agent01_Withdrawals!B99) | D94: =IF(Agent01_Withdrawals!A99="","",Agent01_Withdrawals!C99) | E94: =IF(Agent01_Withdrawals!A99="","",Agent01_Withdrawals!D99) | F94: =IF(Agent01_Withdrawals!A99="","",Agent01_Withdrawals!F99) | G94: =IF(Agent01_Withdrawals!A99="","",Agent01_Withdrawals!E99) | H94: =IF(Agent01_Withdrawals!A99="","",Agent01_Withdrawals!G99) | I94: =IF(Agent01_Withdrawals!A99="","",Agent01_Withdrawals!H99) | J94: =IF(Agent01_Withdrawals!A99="","",Agent01_Withdrawals!J99) | K94: =IF(Agent01_Withdrawals!A99="","",Agent01_Withdrawals!K99) | L94: =IF(G94="","",IF(D94-G94>=System_Config!$B$9,"✅ OK","⚠️ BREACH")) | M94: =IFERROR(IF(Agent01_Withdrawals!A99="","",YEAR(Agent01_Withdrawals!D99)),"")
A95: =IF(Agent01_Withdrawals!A100="","",Agent01_Withdrawals!A100) | B95: =IF(Agent01_Withdrawals!A100="","","WD"&TEXT(95-3,"0000")&"-"&TEXT(TODAY(),"YYYYMMDD")) | C95: =IF(Agent01_Withdrawals!A100="","",Agent01_Withdrawals!B100) | D95: =IF(Agent01_Withdrawals!A100="","",Agent01_Withdrawals!C100) | E95: =IF(Agent01_Withdrawals!A100="","",Agent01_Withdrawals!D100) | F95: =IF(Agent01_Withdrawals!A100="","",Agent01_Withdrawals!F100) | G95: =IF(Agent01_Withdrawals!A100="","",Agent01_Withdrawals!E100) | H95: =IF(Agent01_Withdrawals!A100="","",Agent01_Withdrawals!G100) | I95: =IF(Agent01_Withdrawals!A100="","",Agent01_Withdrawals!H100) | J95: =IF(Agent01_Withdrawals!A100="","",Agent01_Withdrawals!J100) | K95: =IF(Agent01_Withdrawals!A100="","",Agent01_Withdrawals!K100) | L95: =IF(G95="","",IF(D95-G95>=System_Config!$B$9,"✅ OK","⚠️ BREACH")) | M95: =IFERROR(IF(Agent01_Withdrawals!A100="","",YEAR(Agent01_Withdrawals!D100)),"")
A96: =IF(Agent01_Withdrawals!A101="","",Agent01_Withdrawals!A101) | B96: =IF(Agent01_Withdrawals!A101="","","WD"&TEXT(96-3,"0000")&"-"&TEXT(TODAY(),"YYYYMMDD")) | C96: =IF(Agent01_Withdrawals!A101="","",Agent01_Withdrawals!B101) | D96: =IF(Agent01_Withdrawals!A101="","",Agent01_Withdrawals!C101) | E96: =IF(Agent01_Withdrawals!A101="","",Agent01_Withdrawals!D101) | F96: =IF(Agent01_Withdrawals!A101="","",Agent01_Withdrawals!F101) | G96: =IF(Agent01_Withdrawals!A101="","",Agent01_Withdrawals!E101) | H96: =IF(Agent01_Withdrawals!A101="","",Agent01_Withdrawals!G101) | I96: =IF(Agent01_Withdrawals!A101="","",Agent01_Withdrawals!H101) | J96: =IF(Agent01_Withdrawals!A101="","",Agent01_Withdrawals!J101) | K96: =IF(Agent01_Withdrawals!A101="","",Agent01_Withdrawals!K101) | L96: =IF(G96="","",IF(D96-G96>=System_Config!$B$9,"✅ OK","⚠️ BREACH")) | M96: =IFERROR(IF(Agent01_Withdrawals!A101="","",YEAR(Agent01_Withdrawals!D101)),"")
A97: =IF(Agent01_Withdrawals!A102="","",Agent01_Withdrawals!A102) | B97: =IF(Agent01_Withdrawals!A102="","","WD"&TEXT(97-3,"0000")&"-"&TEXT(TODAY(),"YYYYMMDD")) | C97: =IF(Agent01_Withdrawals!A102="","",Agent01_Withdrawals!B102) | D97: =IF(Agent01_Withdrawals!A102="","",Agent01_Withdrawals!C102) | E97: =IF(Agent01_Withdrawals!A102="","",Agent01_Withdrawals!D102) | F97: =IF(Agent01_Withdrawals!A102="","",Agent01_Withdrawals!F102) | G97: =IF(Agent01_Withdrawals!A102="","",Agent01_Withdrawals!E102) | H97: =IF(Agent01_Withdrawals!A102="","",Agent01_Withdrawals!G102) | I97: =IF(Agent01_Withdrawals!A102="","",Agent01_Withdrawals!H102) | J97: =IF(Agent01_Withdrawals!A102="","",Agent01_Withdrawals!J102) | K97: =IF(Agent01_Withdrawals!A102="","",Agent01_Withdrawals!K102) | L97: =IF(G97="","",IF(D97-G97>=System_Config!$B$9,"✅ OK","⚠️ BREACH")) | M97: =IFERROR(IF(Agent01_Withdrawals!A102="","",YEAR(Agent01_Withdrawals!D102)),"")
A98: =IF(Agent01_Withdrawals!A103="","",Agent01_Withdrawals!A103) | B98: =IF(Agent01_Withdrawals!A103="","","WD"&TEXT(98-3,"0000")&"-"&TEXT(TODAY(),"YYYYMMDD")) | C98: =IF(Agent01_Withdrawals!A103="","",Agent01_Withdrawals!B103) | D98: =IF(Agent01_Withdrawals!A103="","",Agent01_Withdrawals!C103) | E98: =IF(Agent01_Withdrawals!A103="","",Agent01_Withdrawals!D103) | F98: =IF(Agent01_Withdrawals!A103="","",Agent01_Withdrawals!F103) | G98: =IF(Agent01_Withdrawals!A103="","",Agent01_Withdrawals!E103) | H98: =IF(Agent01_Withdrawals!A103="","",Agent01_Withdrawals!G103) | I98: =IF(Agent01_Withdrawals!A103="","",Agent01_Withdrawals!H103) | J98: =IF(Agent01_Withdrawals!A103="","",Agent01_Withdrawals!J103) | K98: =IF(Agent01_Withdrawals!A103="","",Agent01_Withdrawals!K103) | L98: =IF(G98="","",IF(D98-G98>=System_Config!$B$9,"✅ OK","⚠️ BREACH")) | M98: =IFERROR(IF(Agent01_Withdrawals!A103="","",YEAR(Agent01_Withdrawals!D103)),"")
A99: =IF(Agent01_Withdrawals!A104="","",Agent01_Withdrawals!A104) | B99: =IF(Agent01_Withdrawals!A104="","","WD"&TEXT(99-3,"0000")&"-"&TEXT(TODAY(),"YYYYMMDD")) | C99: =IF(Agent01_Withdrawals!A104="","",Agent01_Withdrawals!B104) | D99: =IF(Agent01_Withdrawals!A104="","",Agent01_Withdrawals!C104) | E99: =IF(Agent01_Withdrawals!A104="","",Agent01_Withdrawals!D104) | F99: =IF(Agent01_Withdrawals!A104="","",Agent01_Withdrawals!F104) | G99: =IF(Agent01_Withdrawals!A104="","",Agent01_Withdrawals!E104) | H99: =IF(Agent01_Withdrawals!A104="","",Agent01_Withdrawals!G104) | I99: =IF(Agent01_Withdrawals!A104="","",Agent01_Withdrawals!H104) | J99: =IF(Agent01_Withdrawals!A104="","",Agent01_Withdrawals!J104) | K99: =IF(Agent01_Withdrawals!A104="","",Agent01_Withdrawals!K104) | L99: =IF(G99="","",IF(D99-G99>=System_Config!$B$9,"✅ OK","⚠️ BREACH")) | M99: =IFERROR(IF(Agent01_Withdrawals!A104="","",YEAR(Agent01_Withdrawals!D104)),"")
A100: =IF(Agent01_Withdrawals!A105="","",Agent01_Withdrawals!A105) | B100: =IF(Agent01_Withdrawals!A105="","","WD"&TEXT(100-3,"0000")&"-"&TEXT(TODAY(),"YYYYMMDD")) | C100: =IF(Agent01_Withdrawals!A105="","",Agent01_Withdrawals!B105) | D100: =IF(Agent01_Withdrawals!A105="","",Agent01_Withdrawals!C105) | E100: =IF(Agent01_Withdrawals!A105="","",Agent01_Withdrawals!D105) | F100: =IF(Agent01_Withdrawals!A105="","",Agent01_Withdrawals!F105) | G100: =IF(Agent01_Withdrawals!A105="","",Agent01_Withdrawals!E105) | H100: =IF(Agent01_Withdrawals!A105="","",Agent01_Withdrawals!G105) | I100: =IF(Agent01_Withdrawals!A105="","",Agent01_Withdrawals!H105) | J100: =IF(Agent01_Withdrawals!A105="","",Agent01_Withdrawals!J105) | K100: =IF(Agent01_Withdrawals!A105="","",Agent01_Withdrawals!K105) | L100: =IF(G100="","",IF(D100-G100>=System_Config!$B$9,"✅ OK","⚠️ BREACH")) | M100: =IFERROR(IF(Agent01_Withdrawals!A105="","",YEAR(Agent01_Withdrawals!D105)),"")
...

Sheet DB_Loans
A1: 🏦 LOANS DATABASE — All 10 Agents Combined (Formula-Driven, READ-ONLY)
A2: 🔵 DO NOT ENTER DATA HERE — auto-aggregates from all Agent Loan sheets.
A3: Loan_ID | B3: Account_No | C3: Customer_Name | D3: Request_Date | E3: Loan_Amount | F3: Purpose | G3: Months | H3: Rate_% | I3: Total_Repayable | J3: Monthly_Install | K3: Status | L3: Agent | M3: Year
A4: =IF(Agent01_Loans!B14="","",Agent01_Loans!A14) | B4: =IF(Agent01_Loans!B14="","",Agent01_Loans!B14) | C4: =IF(Agent01_Loans!B14="","",Agent01_Loans!C14) | D4: =IF(Agent01_Loans!B14="","",Agent01_Loans!D14) | E4: =IF(Agent01_Loans!B14="","",Agent01_Loans!E14) | F4: =IF(Agent01_Loans!B14="","",Agent01_Loans!F14) | G4: =IF(Agent01_Loans!B14="","",Agent01_Loans!G14) | H4: =IF(Agent01_Loans!B14="","",Agent01_Loans!H14) | I4: =IF(Agent01_Loans!B14="","",Agent01_Loans!I14) | J4: =IF(Agent01_Loans!B14="","",Agent01_Loans!J14) | K4: =IF(Agent01_Loans!B14="","",Agent01_Loans!K14) | L4: =IF(Agent01_Loans!B14="","",Agent01_Loans!L14) | M4: =IFERROR(IF(Agent01_Loans!B14="","",YEAR(Agent01_Loans!D14)),"")
A5: =IF(Agent01_Loans!B15="","",Agent01_Loans!A15) | B5: =IF(Agent01_Loans!B15="","",Agent01_Loans!B15) | C5: =IF(Agent01_Loans!B15="","",Agent01_Loans!C15) | D5: =IF(Agent01_Loans!B15="","",Agent01_Loans!D15) | E5: =IF(Agent01_Loans!B15="","",Agent01_Loans!E15) | F5: =IF(Agent01_Loans!B15="","",Agent01_Loans!F15) | G5: =IF(Agent01_Loans!B15="","",Agent01_Loans!G15) | H5: =IF(Agent01_Loans!B15="","",Agent01_Loans!H15) | I5: =IF(Agent01_Loans!B15="","",Agent01_Loans!I15) | J5: =IF(Agent01_Loans!B15="","",Agent01_Loans!J15) | K5: =IF(Agent01_Loans!B15="","",Agent01_Loans!K15) | L5: =IF(Agent01_Loans!B15="","",Agent01_Loans!L15) | M5: =IFERROR(IF(Agent01_Loans!B15="","",YEAR(Agent01_Loans!D15)),"")
A6: =IF(Agent01_Loans!B16="","",Agent01_Loans!A16) | B6: =IF(Agent01_Loans!B16="","",Agent01_Loans!B16) | C6: =IF(Agent01_Loans!B16="","",Agent01_Loans!C16) | D6: =IF(Agent01_Loans!B16="","",Agent01_Loans!D16) | E6: =IF(Agent01_Loans!B16="","",Agent01_Loans!E16) | F6: =IF(Agent01_Loans!B16="","",Agent01_Loans!F16) | G6: =IF(Agent01_Loans!B16="","",Agent01_Loans!G16) | H6: =IF(Agent01_Loans!B16="","",Agent01_Loans!H16) | I6: =IF(Agent01_Loans!B16="","",Agent01_Loans!I16) | J6: =IF(Agent01_Loans!B16="","",Agent01_Loans!J16) | K6: =IF(Agent01_Loans!B16="","",Agent01_Loans!K16) | L6: =IF(Agent01_Loans!B16="","",Agent01_Loans!L16) | M6: =IFERROR(IF(Agent01_Loans!B16="","",YEAR(Agent01_Loans!D16)),"")
A7: =IF(Agent01_Loans!B17="","",Agent01_Loans!A17) | B7: =IF(Agent01_Loans!B17="","",Agent01_Loans!B17) | C7: =IF(Agent01_Loans!B17="","",Agent01_Loans!C17) | D7: =IF(Agent01_Loans!B17="","",Agent01_Loans!D17) | E7: =IF(Agent01_Loans!B17="","",Agent01_Loans!E17) | F7: =IF(Agent01_Loans!B17="","",Agent01_Loans!F17) | G7: =IF(Agent01_Loans!B17="","",Agent01_Loans!G17) | H7: =IF(Agent01_Loans!B17="","",Agent01_Loans!H17) | I7: =IF(Agent01_Loans!B17="","",Agent01_Loans!I17) | J7: =IF(Agent01_Loans!B17="","",Agent01_Loans!J17) | K7: =IF(Agent01_Loans!B17="","",Agent01_Loans!K17) | L7: =IF(Agent01_Loans!B17="","",Agent01_Loans!L17) | M7: =IFERROR(IF(Agent01_Loans!B17="","",YEAR(Agent01_Loans!D17)),"")
A8: =IF(Agent01_Loans!B18="","",Agent01_Loans!A18) | B8: =IF(Agent01_Loans!B18="","",Agent01_Loans!B18) | C8: =IF(Agent01_Loans!B18="","",Agent01_Loans!C18) | D8: =IF(Agent01_Loans!B18="","",Agent01_Loans!D18) | E8: =IF(Agent01_Loans!B18="","",Agent01_Loans!E18) | F8: =IF(Agent01_Loans!B18="","",Agent01_Loans!F18) | G8: =IF(Agent01_Loans!B18="","",Agent01_Loans!G18) | H8: =IF(Agent01_Loans!B18="","",Agent01_Loans!H18) | I8: =IF(Agent01_Loans!B18="","",Agent01_Loans!I18) | J8: =IF(Agent01_Loans!B18="","",Agent01_Loans!J18) | K8: =IF(Agent01_Loans!B18="","",Agent01_Loans!K18) | L8: =IF(Agent01_Loans!B18="","",Agent01_Loans!L18) | M8: =IFERROR(IF(Agent01_Loans!B18="","",YEAR(Agent01_Loans!D18)),"")
A9: =IF(Agent01_Loans!B19="","",Agent01_Loans!A19) | B9: =IF(Agent01_Loans!B19="","",Agent01_Loans!B19) | C9: =IF(Agent01_Loans!B19="","",Agent01_Loans!C19) | D9: =IF(Agent01_Loans!B19="","",Agent01_Loans!D19) | E9: =IF(Agent01_Loans!B19="","",Agent01_Loans!E19) | F9: =IF(Agent01_Loans!B19="","",Agent01_Loans!F19) | G9: =IF(Agent01_Loans!B19="","",Agent01_Loans!G19) | H9: =IF(Agent01_Loans!B19="","",Agent01_Loans!H19) | I9: =IF(Agent01_Loans!B19="","",Agent01_Loans!I19) | J9: =IF(Agent01_Loans!B19="","",Agent01_Loans!J19) | K9: =IF(Agent01_Loans!B19="","",Agent01_Loans!K19) | L9: =IF(Agent01_Loans!B19="","",Agent01_Loans!L19) | M9: =IFERROR(IF(Agent01_Loans!B19="","",YEAR(Agent01_Loans!D19)),"")
A10: =IF(Agent01_Loans!B20="","",Agent01_Loans!A20) | B10: =IF(Agent01_Loans!B20="","",Agent01_Loans!B20) | C10: =IF(Agent01_Loans!B20="","",Agent01_Loans!C20) | D10: =IF(Agent01_Loans!B20="","",Agent01_Loans!D20) | E10: =IF(Agent01_Loans!B20="","",Agent01_Loans!E20) | F10: =IF(Agent01_Loans!B20="","",Agent01_Loans!F20) | G10: =IF(Agent01_Loans!B20="","",Agent01_Loans!G20) | H10: =IF(Agent01_Loans!B20="","",Agent01_Loans!H20) | I10: =IF(Agent01_Loans!B20="","",Agent01_Loans!I20) | J10: =IF(Agent01_Loans!B20="","",Agent01_Loans!J20) | K10: =IF(Agent01_Loans!B20="","",Agent01_Loans!K20) | L10: =IF(Agent01_Loans!B20="","",Agent01_Loans!L20) | M10: =IFERROR(IF(Agent01_Loans!B20="","",YEAR(Agent01_Loans!D20)),"")
A11: =IF(Agent01_Loans!B21="","",Agent01_Loans!A21) | B11: =IF(Agent01_Loans!B21="","",Agent01_Loans!B21) | C11: =IF(Agent01_Loans!B21="","",Agent01_Loans!C21) | D11: =IF(Agent01_Loans!B21="","",Agent01_Loans!D21) | E11: =IF(Agent01_Loans!B21="","",Agent01_Loans!E21) | F11: =IF(Agent01_Loans!B21="","",Agent01_Loans!F21) | G11: =IF(Agent01_Loans!B21="","",Agent01_Loans!G21) | H11: =IF(Agent01_Loans!B21="","",Agent01_Loans!H21) | I11: =IF(Agent01_Loans!B21="","",Agent01_Loans!I21) | J11: =IF(Agent01_Loans!B21="","",Agent01_Loans!J21) | K11: =IF(Agent01_Loans!B21="","",Agent01_Loans!K21) | L11: =IF(Agent01_Loans!B21="","",Agent01_Loans!L21) | M11: =IFERROR(IF(Agent01_Loans!B21="","",YEAR(Agent01_Loans!D21)),"")
A12: =IF(Agent01_Loans!B22="","",Agent01_Loans!A22) | B12: =IF(Agent01_Loans!B22="","",Agent01_Loans!B22) | C12: =IF(Agent01_Loans!B22="","",Agent01_Loans!C22) | D12: =IF(Agent01_Loans!B22="","",Agent01_Loans!D22) | E12: =IF(Agent01_Loans!B22="","",Agent01_Loans!E22) | F12: =IF(Agent01_Loans!B22="","",Agent01_Loans!F22) | G12: =IF(Agent01_Loans!B22="","",Agent01_Loans!G22) | H12: =IF(Agent01_Loans!B22="","",Agent01_Loans!H22) | I12: =IF(Agent01_Loans!B22="","",Agent01_Loans!I22) | J12: =IF(Agent01_Loans!B22="","",Agent01_Loans!J22) | K12: =IF(Agent01_Loans!B22="","",Agent01_Loans!K22) | L12: =IF(Agent01_Loans!B22="","",Agent01_Loans!L22) | M12: =IFERROR(IF(Agent01_Loans!B22="","",YEAR(Agent01_Loans!D22)),"")
A13: =IF(Agent01_Loans!B23="","",Agent01_Loans!A23) | B13: =IF(Agent01_Loans!B23="","",Agent01_Loans!B23) | C13: =IF(Agent01_Loans!B23="","",Agent01_Loans!C23) | D13: =IF(Agent01_Loans!B23="","",Agent01_Loans!D23) | E13: =IF(Agent01_Loans!B23="","",Agent01_Loans!E23) | F13: =IF(Agent01_Loans!B23="","",Agent01_Loans!F23) | G13: =IF(Agent01_Loans!B23="","",Agent01_Loans!G23) | H13: =IF(Agent01_Loans!B23="","",Agent01_Loans!H23) | I13: =IF(Agent01_Loans!B23="","",Agent01_Loans!I23) | J13: =IF(Agent01_Loans!B23="","",Agent01_Loans!J23) | K13: =IF(Agent01_Loans!B23="","",Agent01_Loans!K23) | L13: =IF(Agent01_Loans!B23="","",Agent01_Loans!L23) | M13: =IFERROR(IF(Agent01_Loans!B23="","",YEAR(Agent01_Loans!D23)),"")
A14: =IF(Agent01_Loans!B24="","",Agent01_Loans!A24) | B14: =IF(Agent01_Loans!B24="","",Agent01_Loans!B24) | C14: =IF(Agent01_Loans!B24="","",Agent01_Loans!C24) | D14: =IF(Agent01_Loans!B24="","",Agent01_Loans!D24) | E14: =IF(Agent01_Loans!B24="","",Agent01_Loans!E24) | F14: =IF(Agent01_Loans!B24="","",Agent01_Loans!F24) | G14: =IF(Agent01_Loans!B24="","",Agent01_Loans!G24) | H14: =IF(Agent01_Loans!B24="","",Agent01_Loans!H24) | I14: =IF(Agent01_Loans!B24="","",Agent01_Loans!I24) | J14: =IF(Agent01_Loans!B24="","",Agent01_Loans!J24) | K14: =IF(Agent01_Loans!B24="","",Agent01_Loans!K24) | L14: =IF(Agent01_Loans!B24="","",Agent01_Loans!L24) | M14: =IFERROR(IF(Agent01_Loans!B24="","",YEAR(Agent01_Loans!D24)),"")
A15: =IF(Agent01_Loans!B25="","",Agent01_Loans!A25) | B15: =IF(Agent01_Loans!B25="","",Agent01_Loans!B25) | C15: =IF(Agent01_Loans!B25="","",Agent01_Loans!C25) | D15: =IF(Agent01_Loans!B25="","",Agent01_Loans!D25) | E15: =IF(Agent01_Loans!B25="","",Agent01_Loans!E25) | F15: =IF(Agent01_Loans!B25="","",Agent01_Loans!F25) | G15: =IF(Agent01_Loans!B25="","",Agent01_Loans!G25) | H15: =IF(Agent01_Loans!B25="","",Agent01_Loans!H25) | I15: =IF(Agent01_Loans!B25="","",Agent01_Loans!I25) | J15: =IF(Agent01_Loans!B25="","",Agent01_Loans!J25) | K15: =IF(Agent01_Loans!B25="","",Agent01_Loans!K25) | L15: =IF(Agent01_Loans!B25="","",Agent01_Loans!L25) | M15: =IFERROR(IF(Agent01_Loans!B25="","",YEAR(Agent01_Loans!D25)),"")
... A203: =IF(Agent01_Loans!B213="","",Agent01_Loans!A213) | B203: =IF(Agent01_Loans!B213="","",Agent01_Loans!B213) | C203: =IF(Agent01_Loans!B213="","",Agent01_Loans!C213) | D203: =IF(Agent01_Loans!B213="","",Agent01_Loans!D213) | E203: =IF(Agent01_Loans!B213="","",Agent01_Loans!E213) | F203: =IF(Agent01_Loans!B213="","",Agent01_Loans!F213) | G203: =IF(Agent01_Loans!B213="","",Agent01_Loans!G213) | H203: =IF(Agent01_Loans!B213="","",Agent01_Loans!H213) | I203: =IF(Agent01_Loans!B213="","",Agent01_Loans!I213) | J203: =IF(Agent01_Loans!B213="","",Agent01_Loans!J213) | K203: =IF(Agent01_Loans!B213="","",Agent01_Loans!K213) | L203: =IF(Agent01_Loans!B213="","",Agent01_Loans!L213) | M203: =IFERROR(IF(Agent01_Loans!B213="","",YEAR(Agent01_Loans!D213)),"")
A204: =IF(Agent02_Loans!B14="","",Agent02_Loans!A14) | B204: =IF(Agent02_Loans!B14="","",Agent02_Loans!B14) | C204: =IF(Agent02_Loans!B14="","",Agent02_Loans!C14) | D204: =IF(Agent02_Loans!B14="","",Agent02_Loans!D14) | E204: =IF(Agent02_Loans!B14="","",Agent02_Loans!E14) | F204: =IF(Agent02_Loans!B14="","",Agent02_Loans!F14) | G204: =IF(Agent02_Loans!B14="","",Agent02_Loans!G14) | H204: =IF(Agent02_Loans!B14="","",Agent02_Loans!H14) | I204: =IF(Agent02_Loans!B14="","",Agent02_Loans!I14) | J204: =IF(Agent02_Loans!B14="","",Agent02_Loans!J14) | K204: =IF(Agent02_Loans!B14="","",Agent02_Loans!K14) | L204: =IF(Agent02_Loans!B14="","",Agent02_Loans!L14) | M204: =IFERROR(IF(Agent02_Loans!B14="","",YEAR(Agent02_Loans!D14)),"")
A205: =IF(Agent02_Loans!B15="","",Agent02_Loans!A15) | B205: =IF(Agent02_Loans!B15="","",Agent02_Loans!B15) | C205: =IF(Agent02_Loans!B15="","",Agent02_Loans!C15) | D205: =IF(Agent02_Loans!B15="","",Agent02_Loans!D15) | E205: =IF(Agent02_Loans!B15="","",Agent02_Loans!E15) | F205: =IF(Agent02_Loans!B15="","",Agent02_Loans!F15) | G205: =IF(Agent02_Loans!B15="","",Agent02_Loans!G15) | H205: =IF(Agent02_Loans!B15="","",Agent02_Loans!H15) | I205: =IF(Agent02_Loans!B15="","",Agent02_Loans!I15) | J205: =IF(Agent02_Loans!B15="","",Agent02_Loans!J15) | K205: =IF(Agent02_Loans!B15="","",Agent02_Loans!K15) | L205: =IF(Agent02_Loans!B15="","",Agent02_Loans!L15) | M205: =IFERROR(IF(Agent02_Loans!B15="","",YEAR(Agent02_Loans!D15)),"")
A206: =IF(Agent02_Loans!B16="","",Agent02_Loans!A16) | B206: =IF(Agent02_Loans!B16="","",Agent02_Loans!B16) | C206: =IF(Agent02_Loans!B16="","",Agent02_Loans!C16) | D206: =IF(Agent02_Loans!B16="","",Agent02_Loans!D16) | E206: =IF(Agent02_Loans!B16="","",Agent02_Loans!E16) | F206: =IF(Agent02_Loans!B16="","",Agent02_Loans!F16) | G206: =IF(Agent02_Loans!B16="","",Agent02_Loans!G16) | H206: =IF(Agent02_Loans!B16="","",Agent02_Loans!H16) | I206: =IF(Agent02_Loans!B16="","",Agent02_Loans!I16) | J206: =IF(Agent02_Loans!B16="","",Agent02_Loans!J16) | K206: =IF(Agent02_Loans!B16="","",Agent02_Loans!K16) | L206: =IF(Agent02_Loans!B16="","",Agent02_Loans!L16) | M206: =IFERROR(IF(Agent02_Loans!B16="","",YEAR(Agent02_Loans!D16)),"")
A207: =IF(Agent02_Loans!B17="","",Agent02_Loans!A17) | B207: =IF(Agent02_Loans!B17="","",Agent02_Loans!B17) | C207: =IF(Agent02_Loans!B17="","",Agent02_Loans!C17) | D207: =IF(Agent02_Loans!B17="","",Agent02_Loans!D17) | E207: =IF(Agent02_Loans!B17="","",Agent02_Loans!E17) | F207: =IF(Agent02_Loans!B17="","",Agent02_Loans!F17) | G207: =IF(Agent02_Loans!B17="","",Agent02_Loans!G17) | H207: =IF(Agent02_Loans!B17="","",Agent02_Loans!H17) | I207: =IF(Agent02_Loans!B17="","",Agent02_Loans!I17) | J207: =IF(Agent02_Loans!B17="","",Agent02_Loans!J17) | K207: =IF(Agent02_Loans!B17="","",Agent02_Loans!K17) | L207: =IF(Agent02_Loans!B17="","",Agent02_Loans!L17) | M207: =IFERROR(IF(Agent02_Loans!B17="","",YEAR(Agent02_Loans!D17)),"")
A208: =IF(Agent02_Loans!B18="","",Agent02_Loans!A18) | B208: =IF(Agent02_Loans!B18="","",Agent02_Loans!B18) | C208: =IF(Agent02_Loans!B18="","",Agent02_Loans!C18) | D208: =IF(Agent02_Loans!B18="","",Agent02_Loans!D18) | E208: =IF(Agent02_Loans!B18="","",Agent02_Loans!E18) | F208: =IF(Agent02_Loans!B18="","",Agent02_Loans!F18) | G208: =IF(Agent02_Loans!B18="","",Agent02_Loans!G18) | H208: =IF(Agent02_Loans!B18="","",Agent02_Loans!H18) | I208: =IF(Agent02_Loans!B18="","",Agent02_Loans!I18) | J208: =IF(Agent02_Loans!B18="","",Agent02_Loans!J18) | K208: =IF(Agent02_Loans!B18="","",Agent02_Loans!K18) | L208: =IF(Agent02_Loans!B18="","",Agent02_Loans!L18) | M208: =IFERROR(IF(Agent02_Loans!B18="","",YEAR(Agent02_Loans!D18)),"")
A209: =IF(Agent02_Loans!B19="","",Agent02_Loans!A19) | B209: =IF(Agent02_Loans!B19="","",Agent02_Loans!B19) | C209: =IF(Agent02_Loans!B19="","",Agent02_Loans!C19) | D209: =IF(Agent02_Loans!B19="","",Agent02_Loans!D19) | E209: =IF(Agent02_Loans!B19="","",Agent02_Loans!E19) | F209: =IF(Agent02_Loans!B19="","",Agent02_Loans!F19) | G209: =IF(Agent02_Loans!B19="","",Agent02_Loans!G19) | H209: =IF(Agent02_Loans!B19="","",Agent02_Loans!H19) | I209: =IF(Agent02_Loans!B19="","",Agent02_Loans!I19) | J209: =IF(Agent02_Loans!B19="","",Agent02_Loans!J19) | K209: =IF(Agent02_Loans!B19="","",Agent02_Loans!K19) | L209: =IF(Agent02_Loans!B19="","",Agent02_Loans!L19) | M209: =IFERROR(IF(Agent02_Loans!B19="","",YEAR(Agent02_Loans!D19)),"")
A210: =IF(Agent02_Loans!B20="","",Agent02_Loans!A20) | B210: =IF(Agent02_Loans!B20="","",Agent02_Loans!B20) | C210: =IF(Agent02_Loans!B20="","",Agent02_Loans!C20) | D210: =IF(Agent02_Loans!B20="","",Agent02_Loans!D20) | E210: =IF(Agent02_Loans!B20="","",Agent02_Loans!E20) | F210: =IF(Agent02_Loans!B20="","",Agent02_Loans!F20) | G210: =IF(Agent02_Loans!B20="","",Agent02_Loans!G20) | H210: =IF(Agent02_Loans!B20="","",Agent02_Loans!H20) | I210: =IF(Agent02_Loans!B20="","",Agent02_Loans!I20) | J210: =IF(Agent02_Loans!B20="","",Agent02_Loans!J20) | K210: =IF(Agent02_Loans!B20="","",Agent02_Loans!K20) | L210: =IF(Agent02_Loans!B20="","",Agent02_Loans!L20) | M210: =IFERROR(IF(Agent02_Loans!B20="","",YEAR(Agent02_Loans!D20)),"")
A211: =IF(Agent02_Loans!B21="","",Agent02_Loans!A21) | B211: =IF(Agent02_Loans!B21="","",Agent02_Loans!B21) | C211: =IF(Agent02_Loans!B21="","",Agent02_Loans!C21) | D211: =IF(Agent02_Loans!B21="","",Agent02_Loans!D21) | E211: =IF(Agent02_Loans!B21="","",Agent02_Loans!E21) | F211: =IF(Agent02_Loans!B21="","",Agent02_Loans!F21) | G211: =IF(Agent02_Loans!B21="","",Agent02_Loans!G21) | H211: =IF(Agent02_Loans!B21="","",Agent02_Loans!H21) | I211: =IF(Agent02_Loans!B21="","",Agent02_Loans!I21) | J211: =IF(Agent02_Loans!B21="","",Agent02_Loans!J21) | K211: =IF(Agent02_Loans!B21="","",Agent02_Loans!K21) | L211: =IF(Agent02_Loans!B21="","",Agent02_Loans!L21) | M211: =IFERROR(IF(Agent02_Loans!B21="","",YEAR(Agent02_Loans!D21)),"")
A212: =IF(Agent02_Loans!B22="","",Agent02_Loans!A22) | B212: =IF(Agent02_Loans!B22="","",Agent02_Loans!B22) | C212: =IF(Agent02_Loans!B22="","",Agent02_Loans!C22) | D212: =IF(Agent02_Loans!B22="","",Agent02_Loans!D22) | E212: =IF(Agent02_Loans!B22="","",Agent02_Loans!E22) | F212: =IF(Agent02_Loans!B22="","",Agent02_Loans!F22) | G212: =IF(Agent02_Loans!B22="","",Agent02_Loans!G22) | H212: =IF(Agent02_Loans!B22="","",Agent02_Loans!H22) | I212: =IF(Agent02_Loans!B22="","",Agent02_Loans!I22) | J212: =IF(Agent02_Loans!B22="","",Agent02_Loans!J22) | K212: =IF(Agent02_Loans!B22="","",Agent02_Loans!K22) | L212: =IF(Agent02_Loans!B22="","",Agent02_Loans!L22) | M212: =IFERROR(IF(Agent02_Loans!B22="","",YEAR(Agent02_Loans!D22)),"")
A213: =IF(Agent02_Loans!B23="","",Agent02_Loans!A23) | B213: =IF(Agent02_Loans!B23="","",Agent02_Loans!B23) | C213: =IF(Agent02_Loans!B23="","",Agent02_Loans!C23) | D213: =IF(Agent02_Loans!B23="","",Agent02_Loans!D23) | E213: =IF(Agent02_Loans!B23="","",Agent02_Loans!E23) | F213: =IF(Agent02_Loans!B23="","",Agent02_Loans!F23) | G213: =IF(Agent02_Loans!B23="","",Agent02_Loans!G23) | H213: =IF(Agent02_Loans!B23="","",Agent02_Loans!H23) | I213: =IF(Agent02_Loans!B23="","",Agent02_Loans!I23) | J213: =IF(Agent02_Loans!B23="","",Agent02_Loans!J23) | K213: =IF(Agent02_Loans!B23="","",Agent02_Loans!K23) | L213: =IF(Agent02_Loans!B23="","",Agent02_Loans!L23) | M213: =IFERROR(IF(Agent02_Loans!B23="","",YEAR(Agent02_Loans!D23)),"")
A214: =IF(Agent02_Loans!B24="","",Agent02_Loans!A24) | B214: =IF(Agent02_Loans!B24="","",Agent02_Loans!B24) | C214: =IF(Agent02_Loans!B24="","",Agent02_Loans!C24) | D214: =IF(Agent02_Loans!B24="","",Agent02_Loans!D24) | E214: =IF(Agent02_Loans!B24="","",Agent02_Loans!E24) | F214: =IF(Agent02_Loans!B24="","",Agent02_Loans!F24) | G214: =IF(Agent02_Loans!B24="","",Agent02_Loans!G24) | H214: =IF(Agent02_Loans!B24="","",Agent02_Loans!H24) | I214: =IF(Agent02_Loans!B24="","",Agent02_Loans!I24) | J214: =IF(Agent02_Loans!B24="","",Agent02_Loans!J24) | K214: =IF(Agent02_Loans!B24="","",Agent02_Loans!K24) | L214: =IF(Agent02_Loans!B24="","",Agent02_Loans!L24) | M214: =IFERROR(IF(Agent02_Loans!B24="","",YEAR(Agent02_Loans!D24)),"")
A215: =IF(Agent02_Loans!B25="","",Agent02_Loans!A25) | B215: =IF(Agent02_Loans!B25="","",Agent02_Loans!B25) | C215: =IF(Agent02_Loans!B25="","",Agent02_Loans!C25) | D215: =IF(Agent02_Loans!B25="","",Agent02_Loans!D25) | E215: =IF(Agent02_Loans!B25="","",Agent02_Loans!E25) | F215: =IF(Agent02_Loans!B25="","",Agent02_Loans!F25) | G215: =IF(Agent02_Loans!B25="","",Agent02_Loans!G25) | H215: =IF(Agent02_Loans!B25="","",Agent02_Loans!H25) | I215: =IF(Agent02_Loans!B25="","",Agent02_Loans!I25) | J215: =IF(Agent02_Loans!B25="","",Agent02_Loans!J25) | K215: =IF(Agent02_Loans!B25="","",Agent02_Loans!K25) | L215: =IF(Agent02_Loans!B25="","",Agent02_Loans!L25) | M215: =IFERROR(IF(Agent02_Loans!B25="","",YEAR(Agent02_Loans!D25)),"")
... A403: =IF(Agent02_Loans!B213="","",Agent02_Loans!A213) | B403: =IF(Agent02_Loans!B213="","",Agent02_Loans!B213) | C403: =IF(Agent02_Loans!B213="","",Agent02_Loans!C213) | D403: =IF(Agent02_Loans!B213="","",Agent02_Loans!D213) | E403: =IF(Agent02_Loans!B213="","",Agent02_Loans!E213) | F403: =IF(Agent02_Loans!B213="","",Agent02_Loans!F213) | G403: =IF(Agent02_Loans!B213="","",Agent02_Loans!G213) | H403: =IF(Agent02_Loans!B213="","",Agent02_Loans!H213) | I403: =IF(Agent02_Loans!B213="","",Agent02_Loans!I213) | J403: =IF(Agent02_Loans!B213="","",Agent02_Loans!J213) | K403: =IF(Agent02_Loans!B213="","",Agent02_Loans!K213) | L403: =IF(Agent02_Loans!B213="","",Agent02_Loans!L213) | M403: =IFERROR(IF(Agent02_Loans!B213="","",YEAR(Agent02_Loans!D213)),"")
A404: =IF(Agent03_Loans!B14="","",Agent03_Loans!A14) | B404: =IF(Agent03_Loans!B14="","",Agent03_Loans!B14) | C404: =IF(Agent03_Loans!B14="","",Agent03_Loans!C14) | D404: =IF(Agent03_Loans!B14="","",Agent03_Loans!D14) | E404: =IF(Agent03_Loans!B14="","",Agent03_Loans!E14) | F404: =IF(Agent03_Loans!B14="","",Agent03_Loans!F14) | G404: =IF(Agent03_Loans!B14="","",Agent03_Loans!G14) | H404: =IF(Agent03_Loans!B14="","",Agent03_Loans!H14) | I404: =IF(Agent03_Loans!B14="","",Agent03_Loans!I14) | J404: =IF(Agent03_Loans!B14="","",Agent03_Loans!J14) | K404: =IF(Agent03_Loans!B14="","",Agent03_Loans!K14) | L404: =IF(Agent03_Loans!B14="","",Agent03_Loans!L14) | M404: =IFERROR(IF(Agent03_Loans!B14="","",YEAR(Agent03_Loans!D14)),"")
