Workbook

Sheet Manager_Dashboard
A1: 🏦 SAMICIOUS MICROFINANCE — MANAGER COMMAND CENTER
A2: =UPPER(TEXT(TODAY(),"DDDD, DD MMMM YYYY"))&" | All figures auto-update from agent sheets" -> SUNDAY, 12 APRIL 2026 | All figures auto-update from agent sheets
A4: 💰 Today Savings | C4: 🏧 Today Withdrawals | E4: 📈 Net Movement | G4: 👥 Customers Served | I4: 🔔 Pending Loans | K4: ⏳ Pending KYC
A5: =Daily_Balancing!B14 -> 6570.67 | C5: =Daily_Balancing!C14 -> 0 | E5: =Daily_Balancing!D14 -> 6570.67 | G5: =Daily_Balancing!E14 -> 20 | I5: =COUNTIF(Active_Loans!K3:K200,"Pending") -> 2 | K5: =COUNTIF(Master_Customers!L2:L1000,"Pending") -> 0
A7: 📊 REAL-TIME AGENT PERFORMANCE TODAY
A8: Agent | B8: Savings (GHC) | C8: Withdrawals (GHC) | D8: Net (GHC) | E8: Customers | F8: Transactions | G8: Target GHC | H8: % of Target | I8: Status
A9: Agent01 | B9: =Daily_Balancing!B4 -> 731.47 | C9: =Daily_Balancing!C4 -> 0 | D9: =Daily_Balancing!D4 -> 731.47 | E9: =Daily_Balancing!E4 -> 2 | F9: =Daily_Balancing!F4 -> 2 | G9: 5000 | H9: =IFERROR(B9/G9,0) -> 0.146294 | I9: =Daily_Balancing!G4 -> ❌ Low
A10: Agent02 | B10: =Daily_Balancing!B5 -> 645.87 | C10: =Daily_Balancing!C5 -> 0 | D10: =Daily_Balancing!D5 -> 645.87 | E10: =Daily_Balancing!E5 -> 2 | F10: =Daily_Balancing!F5 -> 2 | G10: 5000 | H10: =IFERROR(B10/G10,0) -> 0.129174 | I10: =Daily_Balancing!G5 -> ❌ Low
A11: Agent03 | B11: =Daily_Balancing!B6 -> 498.29 | C11: =Daily_Balancing!C6 -> 0 | D11: =Daily_Balancing!D6 -> 498.29 | E11: =Daily_Balancing!E6 -> 2 | F11: =Daily_Balancing!F6 -> 2 | G11: 5000 | H11: =IFERROR(B11/G11,0) -> 0.099658 | I11: =Daily_Balancing!G6 -> ❌ Low
A12: Agent04 | B12: =Daily_Balancing!B7 -> 872.99 | C12: =Daily_Balancing!C7 -> 0 | D12: =Daily_Balancing!D7 -> 872.99 | E12: =Daily_Balancing!E7 -> 2 | F12: =Daily_Balancing!F7 -> 2 | G12: 5000 | H12: =IFERROR(B12/G12,0) -> 0.174598 | I12: =Daily_Balancing!G7 -> ❌ Low
A13: Agent05 | B13: =Daily_Balancing!B8 -> 525.86 | C13: =Daily_Balancing!C8 -> 0 | D13: =Daily_Balancing!D8 -> 525.86 | E13: =Daily_Balancing!E8 -> 2 | F13: =Daily_Balancing!F8 -> 2 | G13: 5000 | H13: =IFERROR(B13/G13,0) -> 0.105172 | I13: =Daily_Balancing!G8 -> ❌ Low
A14: Agent06 | B14: =Daily_Balancing!B9 -> 505.66 | C14: =Daily_Balancing!C9 -> 0 | D14: =Daily_Balancing!D9 -> 505.66 | E14: =Daily_Balancing!E9 -> 2 | F14: =Daily_Balancing!F9 -> 2 | G14: 5000 | H14: =IFERROR(B14/G14,0) -> 0.101132 | I14: =Daily_Balancing!G9 -> ❌ Low
A15: Agent07 | B15: =Daily_Balancing!B10 -> 642.46 | C15: =Daily_Balancing!C10 -> 0 | D15: =Daily_Balancing!D10 -> 642.46 | E15: =Daily_Balancing!E10 -> 2 | F15: =Daily_Balancing!F10 -> 2 | G15: 5000 | H15: =IFERROR(B15/G15,0) -> 0.128492 | I15: =Daily_Balancing!G10 -> ❌ Low
A16: Agent08 | B16: =Daily_Balancing!B11 -> 641.53 | C16: =Daily_Balancing!C11 -> 0 | D16: =Daily_Balancing!D11 -> 641.53 | E16: =Daily_Balancing!E11 -> 2 | F16: =Daily_Balancing!F11 -> 2 | G16: 5000 | H16: =IFERROR(B16/G16,0) -> 0.128306 | I16: =Daily_Balancing!G11 -> ❌ Low
A17: Agent09 | B17: =Daily_Balancing!B12 -> 627.62 | C17: =Daily_Balancing!C12 -> 0 | D17: =Daily_Balancing!D12 -> 627.62 | E17: =Daily_Balancing!E12 -> 2 | F17: =Daily_Balancing!F12 -> 2 | G17: 5000 | H17: =IFERROR(B17/G17,0) -> 0.125524 | I17: =Daily_Balancing!G12 -> ❌ Low
A18: Agent10 | B18: =Daily_Balancing!B13 -> 878.92 | C18: =Daily_Balancing!C13 -> 0 | D18: =Daily_Balancing!D13 -> 878.92 | E18: =Daily_Balancing!E13 -> 2 | F18: =Daily_Balancing!F13 -> 2 | G18: 5000 | H18: =IFERROR(B18/G18,0) -> 0.175784 | I18: =Daily_Balancing!G13 -> ❌ Low
A19: TOTALS | B19: =SUM(B9:B18) -> 6570.67 | C19: =SUM(C9:C18) -> 0 | D19: =SUM(D9:D18) -> 6570.67 | E19: =SUM(E9:E18) -> 20 | F19: =SUM(F9:F18) -> 20 | G19: =SUM(G9:G18) -> 50000 | H19: =IFERROR(B19/G19,0) -> 0.1314134
A21: 🔔 PENDING LOAN APPROVALS | H21: 👥 CUSTOMER STATISTICS
A22: Loan ID | B22: Account # | C22: Customer | D22: Amount (GHC) | E22: Purpose | F22: Agent | H22: Total Active Customers | K22: =COUNTIF(Master_Customers!T2:T1000,"Active") -> 20
A23: =IFERROR(INDEX(Active_Loans!A3:A200,MATCH("Pending",Active_Loans!K3:K200,0)),"") -> LN202604120002 | B23: =IFERROR(INDEX(Active_Loans!B3:B200,MATCH("Pending",Active_Loans!K3:K200,0)),"") -> SAM20240200005 | C23: =IFERROR(INDEX(Active_Loans!C3:C200,MATCH("Pending",Active_Loans!K3:K200,0)),"") -> Yaw Darko | D23: =IFERROR(INDEX(Active_Loans!E3:E200,MATCH("Pending",Active_Loans!K3:K200,0)),"") -> 5000 | E23: =IFERROR(INDEX(Active_Loans!F3:F200,MATCH("Pending",Active_Loans!K3:K200,0)),"") -> School fees | F23: =IFERROR(INDEX(Active_Loans!L3:L200,MATCH("Pending",Active_Loans!K3:K200,0)),"") -> Agent03 | H23: Total Savings Portfolio | K23: =SUM(Master_Customers!P2:P1000) -> 35770.16
H24: Total Withdrawals | K24: =SUM(Master_Customers!Q2:Q1000) -> 4561.65
H25: Total Loan Portfolio | K25: =SUM(Active_Loans!E3:E200) -> 19500
H26: Pending KYC Verifications | K26: =COUNTIF(Master_Customers!L2:L1000,"Pending") -> 0
H27: This Month New Accounts | K27: =COUNTIF(Master_Customers!K2:K1000,">="&DATE(YEAR(TODAY()),MONTH(TODAY()),1)) -> 0
A30: 🔗 QUICK NAVIGATION — Click any sheet tab below, or use Ctrl+Page Up/Down to navigate between agents
A31: 📂 Savings | B31: 🏧 Withdrawals | C31: 💳 Loans | D31: 👤 Account Opening | E31: 📊 Daily Balance | F31: 📅 Weekly | G31: 📆 Monthly | H31: 📋 Transactions | I31: 🔒 Audit

Sheet Account_Opening
A1: 👤 NEW CUSTOMER ACCOUNT OPENING FORM
A2: SAMICIOUS MICROFINANCE | Complete all required fields marked with *
A3: 🔑 SYSTEM-GENERATED ACCOUNT NUMBER WILL APPEAR BELOW AFTER SUBMISSION
A5: * First Name:
A6: * Last Name:
A7: * Ghana Card Number:
A8: * Phone Number:
A9: * Physical Address:
A10: * Occupation:
A11: * Assigned Agent:
A12: Opening Balance (GHC):
A13: 📄 KYC DOCUMENTS CHECKLIST
A14: Passport Photo uploaded: | C14: ☐ Pending
A15: Ghana Card (Front) captured: | C15: ☐ Pending
A16: Ghana Card (Back) captured: | C16: ☐ Pending
A17: Proof of Address provided: | C17: ☐ Pending
A19: ✅ GENERATED ACCOUNT NUMBER
A20: =IF(C5="","Please complete form above and click CREATE ACCOUNT","SAM"&TEXT(TODAY(),"YYYY")&TEXT(TODAY(),"MM")&"XXXXX (Auto-generated by system)") -> Please complete form above and click CREATE ACCOUNT
A21: ⚠️ After form completion, use the VBA macro "CreateNewAccount" to auto-generate account number

Sheet Agent01_Savings
A1: 💰 SAMICIOUS MICROFINANCE — AGENT01 SAVINGS
A2: Agent: Agent01 | Date: 2026-04-12 | Module: Daily Savings Collection
B3: Daily Target (GHC) | E3: Total Collected | H3: Remaining
B4: 5000 | E4: =SUMIF(I9:I1008,"SAVED",E9:E1008) -> 731.47 | H4: =IF(B4-E4<0,"TARGET MET!",B4-E4) -> 4268.53
A5: =IF(B4-E4<=0,"✅ DAILY TARGET ACHIEVED! Great work Agent01!","⏳ Collection in progress — Keep going!") -> ⏳ Collection in progress — Keep going!
A7: 📝 TRANSACTION ENTRY — Enter Account Number and Amount, then click RECORD or press Ctrl+S
A8: Account # | B8: Customer Name | C8: Current Balance | D8: Date | E8: Savings Amount | F8: New Balance | G8: Receipt # | H8: Agent | I8: Status | J8: Saved At
A9: SAM20240100001 | B9: =IF(A9="","",IFERROR(VLOOKUP(A9,Master_Customers!$A:$D,4,FALSE()),"❌ Not Found")) -> Kwame Asare | C9: =IF(A9="","",IFERROR(VLOOKUP(A9,Master_Customers!$A:$O,15,FALSE()),"")) -> 2436.65 | D9: 2026-04-12 | E9: 308.79 | F9: =IF(E9="","",IF(C9="","",C9+E9)) -> 2745.44 | H9: Agent01 | I9: SAVED | J9: 2026-04-12
A10: SAM20240100002 | B10: =IF(A10="","",IFERROR(VLOOKUP(A10,Master_Customers!$A:$D,4,FALSE()),"❌ Not Found")) -> Ama Mensah | C10: =IF(A10="","",IFERROR(VLOOKUP(A10,Master_Customers!$A:$O,15,FALSE()),"")) -> 2024.1 | D10: 2026-04-12 | E10: 422.68 | F10: =IF(E10="","",IF(C10="","",C10+E10)) -> 2446.78 | H10: Agent01 | I10: SAVED | J10: 2026-04-12
B11: =IF(A11="","",IFERROR(VLOOKUP(A11,Master_Customers!$A:$D,4,FALSE()),"❌ Not Found")) | C11: =IF(A11="","",IFERROR(VLOOKUP(A11,Master_Customers!$A:$O,15,FALSE()),"")) | F11: =IF(E11="","",IF(C11="","",C11+E11))
B12: =IF(A12="","",IFERROR(VLOOKUP(A12,Master_Customers!$A:$D,4,FALSE()),"❌ Not Found")) | C12: =IF(A12="","",IFERROR(VLOOKUP(A12,Master_Customers!$A:$O,15,FALSE()),"")) | F12: =IF(E12="","",IF(C12="","",C12+E12))
B13: =IF(A13="","",IFERROR(VLOOKUP(A13,Master_Customers!$A:$D,4,FALSE()),"❌ Not Found")) | C13: =IF(A13="","",IFERROR(VLOOKUP(A13,Master_Customers!$A:$O,15,FALSE()),"")) | F13: =IF(E13="","",IF(C13="","",C13+E13))
B14: =IF(A14="","",IFERROR(VLOOKUP(A14,Master_Customers!$A:$D,4,FALSE()),"❌ Not Found")) | C14: =IF(A14="","",IFERROR(VLOOKUP(A14,Master_Customers!$A:$O,15,FALSE()),"")) | F14: =IF(E14="","",IF(C14="","",C14+E14))
B15: =IF(A15="","",IFERROR(VLOOKUP(A15,Master_Customers!$A:$D,4,FALSE()),"❌ Not Found")) | C15: =IF(A15="","",IFERROR(VLOOKUP(A15,Master_Customers!$A:$O,15,FALSE()),"")) | F15: =IF(E15="","",IF(C15="","",C15+E15))
B16: =IF(A16="","",IFERROR(VLOOKUP(A16,Master_Customers!$A:$D,4,FALSE()),"❌ Not Found")) | C16: =IF(A16="","",IFERROR(VLOOKUP(A16,Master_Customers!$A:$O,15,FALSE()),"")) | F16: =IF(E16="","",IF(C16="","",C16+E16))
B17: =IF(A17="","",IFERROR(VLOOKUP(A17,Master_Customers!$A:$D,4,FALSE()),"❌ Not Found")) | C17: =IF(A17="","",IFERROR(VLOOKUP(A17,Master_Customers!$A:$O,15,FALSE()),"")) | F17: =IF(E17="","",IF(C17="","",C17+E17))
B18: =IF(A18="","",IFERROR(VLOOKUP(A18,Master_Customers!$A:$D,4,FALSE()),"❌ Not Found")) | C18: =IF(A18="","",IFERROR(VLOOKUP(A18,Master_Customers!$A:$O,15,FALSE()),"")) | F18: =IF(E18="","",IF(C18="","",C18+E18))
B19: =IF(A19="","",IFERROR(VLOOKUP(A19,Master_Customers!$A:$D,4,FALSE()),"❌ Not Found")) | C19: =IF(A19="","",IFERROR(VLOOKUP(A19,Master_Customers!$A:$O,15,FALSE()),"")) | F19: =IF(E19="","",IF(C19="","",C19+E19))
B20: =IF(A20="","",IFERROR(VLOOKUP(A20,Master_Customers!$A:$D,4,FALSE()),"❌ Not Found")) | C20: =IF(A20="","",IFERROR(VLOOKUP(A20,Master_Customers!$A:$O,15,FALSE()),"")) | F20: =IF(E20="","",IF(C20="","",C20+E20))
B21: =IF(A21="","",IFERROR(VLOOKUP(A21,Master_Customers!$A:$D,4,FALSE()),"❌ Not Found")) | C21: =IF(A21="","",IFERROR(VLOOKUP(A21,Master_Customers!$A:$O,15,FALSE()),"")) | F21: =IF(E21="","",IF(C21="","",C21+E21))
B22: =IF(A22="","",IFERROR(VLOOKUP(A22,Master_Customers!$A:$D,4,FALSE()),"❌ Not Found")) | C22: =IF(A22="","",IFERROR(VLOOKUP(A22,Master_Customers!$A:$O,15,FALSE()),"")) | F22: =IF(E22="","",IF(C22="","",C22+E22))
... B1008: =IF(A1008="","",IFERROR(VLOOKUP(A1008,Master_Customers!$A:$D,4,FALSE()),"❌ Not Found")) | C1008: =IF(A1008="","",IFERROR(VLOOKUP(A1008,Master_Customers!$A:$O,15,FALSE()),"")) | F1008: =IF(E1008="","",IF(C1008="","",C1008+E1008))

Sheet Agent01_Withdrawals
A1: 🏧 SAMICIOUS MICROFINANCE — AGENT01 WITHDRAWALS
A2: Agent: Agent01 | Date: 2026-04-12 | Module: Withdrawal Processing
B3: Total Withdrawals | E3: Transactions Count | H3: Avg Withdrawal
B4: =SUMIF(I9:I1008,"SAVED",E9:E1008) -> 0 | E4: =COUNTIF(I9:I1008,"SAVED") -> 0 | H4: =IFERROR(B4/E4,0) -> 0
A5: ⚠️ WITHDRAWALS MODULE — Insufficient balance will be flagged automatically
A7: 📝 TRANSACTION ENTRY — Enter Account Number and Withdrawal Amount
A8: Account # | B8: Customer Name | C8: Available Balance | D8: Date | E8: Withdrawal Amount | F8: New Balance | G8: Authorised By | H8: Agent | I8: Status | J8: Saved At
B9: =IF(A9="","",IFERROR(VLOOKUP(A9,Master_Customers!$A:$D,4,FALSE()),"❌ Not Found")) | C9: =IF(A9="","",IFERROR(VLOOKUP(A9,Master_Customers!$A:$O,15,FALSE()),"")) | F9: =IF(E9="","",IF(C9="","",IF(E9>C9,"INSUFFICIENT FUNDS",C9-E9)))
B10: =IF(A10="","",IFERROR(VLOOKUP(A10,Master_Customers!$A:$D,4,FALSE()),"❌ Not Found")) | C10: =IF(A10="","",IFERROR(VLOOKUP(A10,Master_Customers!$A:$O,15,FALSE()),"")) | F10: =IF(E10="","",IF(C10="","",IF(E10>C10,"INSUFFICIENT FUNDS",C10-E10)))
B11: =IF(A11="","",IFERROR(VLOOKUP(A11,Master_Customers!$A:$D,4,FALSE()),"❌ Not Found")) | C11: =IF(A11="","",IFERROR(VLOOKUP(A11,Master_Customers!$A:$O,15,FALSE()),"")) | F11: =IF(E11="","",IF(C11="","",IF(E11>C11,"INSUFFICIENT FUNDS",C11-E11)))
B12: =IF(A12="","",IFERROR(VLOOKUP(A12,Master_Customers!$A:$D,4,FALSE()),"❌ Not Found")) | C12: =IF(A12="","",IFERROR(VLOOKUP(A12,Master_Customers!$A:$O,15,FALSE()),"")) | F12: =IF(E12="","",IF(C12="","",IF(E12>C12,"INSUFFICIENT FUNDS",C12-E12)))
B13: =IF(A13="","",IFERROR(VLOOKUP(A13,Master_Customers!$A:$D,4,FALSE()),"❌ Not Found")) | C13: =IF(A13="","",IFERROR(VLOOKUP(A13,Master_Customers!$A:$O,15,FALSE()),"")) | F13: =IF(E13="","",IF(C13="","",IF(E13>C13,"INSUFFICIENT FUNDS",C13-E13)))
B14: =IF(A14="","",IFERROR(VLOOKUP(A14,Master_Customers!$A:$D,4,FALSE()),"❌ Not Found")) | C14: =IF(A14="","",IFERROR(VLOOKUP(A14,Master_Customers!$A:$O,15,FALSE()),"")) | F14: =IF(E14="","",IF(C14="","",IF(E14>C14,"INSUFFICIENT FUNDS",C14-E14)))
B15: =IF(A15="","",IFERROR(VLOOKUP(A15,Master_Customers!$A:$D,4,FALSE()),"❌ Not Found")) | C15: =IF(A15="","",IFERROR(VLOOKUP(A15,Master_Customers!$A:$O,15,FALSE()),"")) | F15: =IF(E15="","",IF(C15="","",IF(E15>C15,"INSUFFICIENT FUNDS",C15-E15)))
B16: =IF(A16="","",IFERROR(VLOOKUP(A16,Master_Customers!$A:$D,4,FALSE()),"❌ Not Found")) | C16: =IF(A16="","",IFERROR(VLOOKUP(A16,Master_Customers!$A:$O,15,FALSE()),"")) | F16: =IF(E16="","",IF(C16="","",IF(E16>C16,"INSUFFICIENT FUNDS",C16-E16)))
B17: =IF(A17="","",IFERROR(VLOOKUP(A17,Master_Customers!$A:$D,4,FALSE()),"❌ Not Found")) | C17: =IF(A17="","",IFERROR(VLOOKUP(A17,Master_Customers!$A:$O,15,FALSE()),"")) | F17: =IF(E17="","",IF(C17="","",IF(E17>C17,"INSUFFICIENT FUNDS",C17-E17)))
B18: =IF(A18="","",IFERROR(VLOOKUP(A18,Master_Customers!$A:$D,4,FALSE()),"❌ Not Found")) | C18: =IF(A18="","",IFERROR(VLOOKUP(A18,Master_Customers!$A:$O,15,FALSE()),"")) | F18: =IF(E18="","",IF(C18="","",IF(E18>C18,"INSUFFICIENT FUNDS",C18-E18)))
B19: =IF(A19="","",IFERROR(VLOOKUP(A19,Master_Customers!$A:$D,4,FALSE()),"❌ Not Found")) | C19: =IF(A19="","",IFERROR(VLOOKUP(A19,Master_Customers!$A:$O,15,FALSE()),"")) | F19: =IF(E19="","",IF(C19="","",IF(E19>C19,"INSUFFICIENT FUNDS",C19-E19)))
B20: =IF(A20="","",IFERROR(VLOOKUP(A20,Master_Customers!$A:$D,4,FALSE()),"❌ Not Found")) | C20: =IF(A20="","",IFERROR(VLOOKUP(A20,Master_Customers!$A:$O,15,FALSE()),"")) | F20: =IF(E20="","",IF(C20="","",IF(E20>C20,"INSUFFICIENT FUNDS",C20-E20)))
... B1008: =IF(A1008="","",IFERROR(VLOOKUP(A1008,Master_Customers!$A:$D,4,FALSE()),"❌ Not Found")) | C1008: =IF(A1008="","",IFERROR(VLOOKUP(A1008,Master_Customers!$A:$O,15,FALSE()),"")) | F1008: =IF(E1008="","",IF(C1008="","",IF(E1008>C1008,"INSUFFICIENT FUNDS",C1008-E1008)))

Sheet Agent01_Loans
A1: 🏦 SAMICIOUS MICROFINANCE — AGENT01 LOAN REQUESTS
A2: Agent: Agent01 | Interest Rate: 2.5% p/m (flat) | Min: GHC 100 | Max: GHC 50,000
A4: 🔢 LOAN CALCULATOR
A5: Loan Amount (GHC):
A6: Repayment (months):
A7: Interest Rate (%/m): | B7: 2.5
A8: Total Interest (GHC): | B8: =IF(B5="","",B5*B7/100*B6)
A9: Total Repayable (GHC): | B9: =IF(B5="","",B5+B8)
A10: Monthly Installment (GHC): | B10: =IF(B5="","",B9/B6)
A12: 📋 LOAN REQUEST SUBMISSIONS — Enter details below to submit for manager approval
A13: Loan ID | B13: Account # | C13: Customer Name | D13: Request Date | E13: Loan Amount | F13: Purpose | G13: Months | H13: Rate % | I13: Total Repayable | J13: Monthly Install | K13: Status | L13: Notes
A14: LN202604120014 | B14: SAM20240100001 | C14: Kwame Asare | D14: 2026-04-12 | E14: 1110.5 | F14: Business | G14: 6 | H14: 2.5 | I14: 1277.08 | J14: 212.85 | K14: Pending
A15: LN202604120015 | B15: SAM20240100002 | C15: Ama Mensah | D15: 2026-04-12 | E15: 7875.79 | F15: Business | G15: 6 | H15: 2.5 | I15: 9057.16 | J15: 1509.53 | K15: Pending
C16: =IF(B16="","",IFERROR(VLOOKUP(B16,Master_Customers!$A:$D,4,FALSE()),"❌ Not Found")) | I16: =IF(E16="","",E16+E16*H16/100*G16) | J16: =IFERROR(I16/G16,"")
C17: =IF(B17="","",IFERROR(VLOOKUP(B17,Master_Customers!$A:$D,4,FALSE()),"❌ Not Found")) | I17: =IF(E17="","",E17+E17*H17/100*G17) | J17: =IFERROR(I17/G17,"")
C18: =IF(B18="","",IFERROR(VLOOKUP(B18,Master_Customers!$A:$D,4,FALSE()),"❌ Not Found")) | I18: =IF(E18="","",E18+E18*H18/100*G18) | J18: =IFERROR(I18/G18,"")
C19: =IF(B19="","",IFERROR(VLOOKUP(B19,Master_Customers!$A:$D,4,FALSE()),"❌ Not Found")) | I19: =IF(E19="","",E19+E19*H19/100*G19) | J19: =IFERROR(I19/G19,"")
C20: =IF(B20="","",IFERROR(VLOOKUP(B20,Master_Customers!$A:$D,4,FALSE()),"❌ Not Found")) | I20: =IF(E20="","",E20+E20*H20/100*G20) | J20: =IFERROR(I20/G20,"")
C21: =IF(B21="","",IFERROR(VLOOKUP(B21,Master_Customers!$A:$D,4,FALSE()),"❌ Not Found")) | I21: =IF(E21="","",E21+E21*H21/100*G21) | J21: =IFERROR(I21/G21,"")
C22: =IF(B22="","",IFERROR(VLOOKUP(B22,Master_Customers!$A:$D,4,FALSE()),"❌ Not Found")) | I22: =IF(E22="","",E22+E22*H22/100*G22) | J22: =IFERROR(I22/G22,"")
C23: =IF(B23="","",IFERROR(VLOOKUP(B23,Master_Customers!$A:$D,4,FALSE()),"❌ Not Found")) | I23: =IF(E23="","",E23+E23*H23/100*G23) | J23: =IFERROR(I23/G23,"")
C24: =IF(B24="","",IFERROR(VLOOKUP(B24,Master_Customers!$A:$D,4,FALSE()),"❌ Not Found")) | I24: =IF(E24="","",E24+E24*H24/100*G24) | J24: =IFERROR(I24/G24,"")
C25: =IF(B25="","",IFERROR(VLOOKUP(B25,Master_Customers!$A:$D,4,FALSE()),"❌ Not Found")) | I25: =IF(E25="","",E25+E25*H25/100*G25) | J25: =IFERROR(I25/G25,"")
C26: =IF(B26="","",IFERROR(VLOOKUP(B26,Master_Customers!$A:$D,4,FALSE()),"❌ Not Found")) | I26: =IF(E26="","",E26+E26*H26/100*G26) | J26: =IFERROR(I26/G26,"")
C27: =IF(B27="","",IFERROR(VLOOKUP(B27,Master_Customers!$A:$D,4,FALSE()),"❌ Not Found")) | I27: =IF(E27="","",E27+E27*H27/100*G27) | J27: =IFERROR(I27/G27,"")
... C213: =IF(B213="","",IFERROR(VLOOKUP(B213,Master_Customers!$A:$D,4,FALSE()),"❌ Not Found")) | I213: =IF(E213="","",E213+E213*H213/100*G213) | J213: =IFERROR(I213/G213,"")

Sheet Agent02_Savings
A1: 💰 SAMICIOUS MICROFINANCE — AGENT02 SAVINGS
A2: Agent: Agent02 | Date: 2026-04-12 | Module: Daily Savings Collection
B3: Daily Target (GHC) | E3: Total Collected | H3: Remaining
B4: 5000 | E4: =SUMIF(I9:I1008,"SAVED",E9:E1008) -> 645.87 | H4: =IF(B4-E4<0,"TARGET MET!",B4-E4) -> 4354.13
A5: =IF(B4-E4<=0,"✅ DAILY TARGET ACHIEVED! Great work Agent02!","⏳ Collection in progress — Keep going!") -> ⏳ Collection in progress — Keep going!
A7: 📝 TRANSACTION ENTRY — Enter Account Number and Amount, then click RECORD or press Ctrl+S
A8: Account # | B8: Customer Name | C8: Current Balance | D8: Date | E8: Savings Amount | F8: New Balance | G8: Receipt # | H8: Agent | I8: Status | J8: Saved At
A9: SAM20240200003 | B9: =IF(A9="","",IFERROR(VLOOKUP(A9,Master_Customers!$A:$D,4,FALSE()),"❌ Not Found")) -> Kofi Boateng | C9: =IF(A9="","",IFERROR(VLOOKUP(A9,Master_Customers!$A:$O,15,FALSE()),"")) -> 2829.41 | D9: 2026-04-12 | E9: 311.57 | F9: =IF(E9="","",IF(C9="","",C9+E9)) -> 3140.98 | H9: Agent02 | I9: SAVED | J9: 2026-04-12
A10: SAM20240200004 | B10: =IF(A10="","",IFERROR(VLOOKUP(A10,Master_Customers!$A:$D,4,FALSE()),"❌ Not Found")) -> Abena Owusu | C10: =IF(A10="","",IFERROR(VLOOKUP(A10,Master_Customers!$A:$O,15,FALSE()),"")) -> 2942.01 | D10: 2026-04-12 | E10: 334.3 | F10: =IF(E10="","",IF(C10="","",C10+E10)) -> 3276.31 | H10: Agent02 | I10: SAVED | J10: 2026-04-12
B11: =IF(A11="","",IFERROR(VLOOKUP(A11,Master_Customers!$A:$D,4,FALSE()),"❌ Not Found")) | C11: =IF(A11="","",IFERROR(VLOOKUP(A11,Master_Customers!$A:$O,15,FALSE()),"")) | F11: =IF(E11="","",IF(C11="","",C11+E11))
B12: =IF(A12="","",IFERROR(VLOOKUP(A12,Master_Customers!$A:$D,4,FALSE()),"❌ Not Found")) | C12: =IF(A12="","",IFERROR(VLOOKUP(A12,Master_Customers!$A:$O,15,FALSE()),"")) | F12: =IF(E12="","",IF(C12="","",C12+E12))
B13: =IF(A13="","",IFERROR(VLOOKUP(A13,Master_Customers!$A:$D,4,FALSE()),"❌ Not Found")) | C13: =IF(A13="","",IFERROR(VLOOKUP(A13,Master_Customers!$A:$O,15,FALSE()),"")) | F13: =IF(E13="","",IF(C13="","",C13+E13))
B14: =IF(A14="","",IFERROR(VLOOKUP(A14,Master_Customers!$A:$D,4,FALSE()),"❌ Not Found")) | C14: =IF(A14="","",IFERROR(VLOOKUP(A14,Master_Customers!$A:$O,15,FALSE()),"")) | F14: =IF(E14="","",IF(C14="","",C14+E14))
B15: =IF(A15="","",IFERROR(VLOOKUP(A15,Master_Customers!$A:$D,4,FALSE()),"❌ Not Found")) | C15: =IF(A15="","",IFERROR(VLOOKUP(A15,Master_Customers!$A:$O,15,FALSE()),"")) | F15: =IF(E15="","",IF(C15="","",C15+E15))
B16: =IF(A16="","",IFERROR(VLOOKUP(A16,Master_Customers!$A:$D,4,FALSE()),"❌ Not Found")) | C16: =IF(A16="","",IFERROR(VLOOKUP(A16,Master_Customers!$A:$O,15,FALSE()),"")) | F16: =IF(E16="","",IF(C16="","",C16+E16))
B17: =IF(A17="","",IFERROR(VLOOKUP(A17,Master_Customers!$A:$D,4,FALSE()),"❌ Not Found")) | C17: =IF(A17="","",IFERROR(VLOOKUP(A17,Master_Customers!$A:$O,15,FALSE()),"")) | F17: =IF(E17="","",IF(C17="","",C17+E17))
B18: =IF(A18="","",IFERROR(VLOOKUP(A18,Master_Customers!$A:$D,4,FALSE()),"❌ Not Found")) | C18: =IF(A18="","",IFERROR(VLOOKUP(A18,Master_Customers!$A:$O,15,FALSE()),"")) | F18: =IF(E18="","",IF(C18="","",C18+E18))
B19: =IF(A19="","",IFERROR(VLOOKUP(A19,Master_Customers!$A:$D,4,FALSE()),"❌ Not Found")) | C19: =IF(A19="","",IFERROR(VLOOKUP(A19,Master_Customers!$A:$O,15,FALSE()),"")) | F19: =IF(E19="","",IF(C19="","",C19+E19))
B20: =IF(A20="","",IFERROR(VLOOKUP(A20,Master_Customers!$A:$D,4,FALSE()),"❌ Not Found")) | C20: =IF(A20="","",IFERROR(VLOOKUP(A20,Master_Customers!$A:$O,15,FALSE()),"")) | F20: =IF(E20="","",IF(C20="","",C20+E20))
B21: =IF(A21="","",IFERROR(VLOOKUP(A21,Master_Customers!$A:$D,4,FALSE()),"❌ Not Found")) | C21: =IF(A21="","",IFERROR(VLOOKUP(A21,Master_Customers!$A:$O,15,FALSE()),"")) | F21: =IF(E21="","",IF(C21="","",C21+E21))
B22: =IF(A22="","",IFERROR(VLOOKUP(A22,Master_Customers!$A:$D,4,FALSE()),"❌ Not Found")) | C22: =IF(A22="","",IFERROR(VLOOKUP(A22,Master_Customers!$A:$O,15,FALSE()),"")) | F22: =IF(E22="","",IF(C22="","",C22+E22))
... B1008: =IF(A1008="","",IFERROR(VLOOKUP(A1008,Master_Customers!$A:$D,4,FALSE()),"❌ Not Found")) | C1008: =IF(A1008="","",IFERROR(VLOOKUP(A1008,Master_Customers!$A:$O,15,FALSE()),"")) | F1008: =IF(E1008="","",IF(C1008="","",C1008+E1008))

Sheet Agent02_Withdrawals
A1: 🏧 SAMICIOUS MICROFINANCE — AGENT02 WITHDRAWALS
A2: Agent: Agent02 | Date: 2026-04-12 | Module: Withdrawal Processing
B3: Total Withdrawals | E3: Transactions Count | H3: Avg Withdrawal
B4: =SUMIF(I9:I1008,"SAVED",E9:E1008) -> 0 | E4: =COUNTIF(I9:I1008,"SAVED") -> 0 | H4: =IFERROR(B4/E4,0) -> 0
A5: ⚠️ WITHDRAWALS MODULE — Insufficient balance will be flagged automatically
A7: 📝 TRANSACTION ENTRY — Enter Account Number and Withdrawal Amount
A8: Account # | B8: Customer Name | C8: Available Balance | D8: Date | E8: Withdrawal Amount | F8: New Balance | G8: Authorised By | H8: Agent | I8: Status | J8: Saved At
B9: =IF(A9="","",IFERROR(VLOOKUP(A9,Master_Customers!$A:$D,4,FALSE()),"❌ Not Found")) | C9: =IF(A9="","",IFERROR(VLOOKUP(A9,Master_Customers!$A:$O,15,FALSE()),"")) | F9: =IF(E9="","",IF(C9="","",IF(E9>C9,"INSUFFICIENT FUNDS",C9-E9)))
B10: =IF(A10="","",IFERROR(VLOOKUP(A10,Master_Customers!$A:$D,4,FALSE()),"❌ Not Found")) | C10: =IF(A10="","",IFERROR(VLOOKUP(A10,Master_Customers!$A:$O,15,FALSE()),"")) | F10: =IF(E10="","",IF(C10="","",IF(E10>C10,"INSUFFICIENT FUNDS",C10-E10)))
B11: =IF(A11="","",IFERROR(VLOOKUP(A11,Master_Customers!$A:$D,4,FALSE()),"❌ Not Found")) | C11: =IF(A11="","",IFERROR(VLOOKUP(A11,Master_Customers!$A:$O,15,FALSE()),"")) | F11: =IF(E11="","",IF(C11="","",IF(E11>C11,"INSUFFICIENT FUNDS",C11-E11)))
B12: =IF(A12="","",IFERROR(VLOOKUP(A12,Master_Customers!$A:$D,4,FALSE()),"❌ Not Found")) | C12: =IF(A12="","",IFERROR(VLOOKUP(A12,Master_Customers!$A:$O,15,FALSE()),"")) | F12: =IF(E12="","",IF(C12="","",IF(E12>C12,"INSUFFICIENT FUNDS",C12-E12)))
B13: =IF(A13="","",IFERROR(VLOOKUP(A13,Master_Customers!$A:$D,4,FALSE()),"❌ Not Found")) | C13: =IF(A13="","",IFERROR(VLOOKUP(A13,Master_Customers!$A:$O,15,FALSE()),"")) | F13: =IF(E13="","",IF(C13="","",IF(E13>C13,"INSUFFICIENT FUNDS",C13-E13)))
B14: =IF(A14="","",IFERROR(VLOOKUP(A14,Master_Customers!$A:$D,4,FALSE()),"❌ Not Found")) | C14: =IF(A14="","",IFERROR(VLOOKUP(A14,Master_Customers!$A:$O,15,FALSE()),"")) | F14: =IF(E14="","",IF(C14="","",IF(E14>C14,"INSUFFICIENT FUNDS",C14-E14)))
B15: =IF(A15="","",IFERROR(VLOOKUP(A15,Master_Customers!$A:$D,4,FALSE()),"❌ Not Found")) | C15: =IF(A15="","",IFERROR(VLOOKUP(A15,Master_Customers!$A:$O,15,FALSE()),"")) | F15: =IF(E15="","",IF(C15="","",IF(E15>C15,"INSUFFICIENT FUNDS",C15-E15)))
B16: =IF(A16="","",IFERROR(VLOOKUP(A16,Master_Customers!$A:$D,4,FALSE()),"❌ Not Found")) | C16: =IF(A16="","",IFERROR(VLOOKUP(A16,Master_Customers!$A:$O,15,FALSE()),"")) | F16: =IF(E16="","",IF(C16="","",IF(E16>C16,"INSUFFICIENT FUNDS",C16-E16)))
B17: =IF(A17="","",IFERROR(VLOOKUP(A17,Master_Customers!$A:$D,4,FALSE()),"❌ Not Found")) | C17: =IF(A17="","",IFERROR(VLOOKUP(A17,Master_Customers!$A:$O,15,FALSE()),"")) | F17: =IF(E17="","",IF(C17="","",IF(E17>C17,"INSUFFICIENT FUNDS",C17-E17)))
B18: =IF(A18="","",IFERROR(VLOOKUP(A18,Master_Customers!$A:$D,4,FALSE()),"❌ Not Found")) | C18: =IF(A18="","",IFERROR(VLOOKUP(A18,Master_Customers!$A:$O,15,FALSE()),"")) | F18: =IF(E18="","",IF(C18="","",IF(E18>C18,"INSUFFICIENT FUNDS",C18-E18)))
B19: =IF(A19="","",IFERROR(VLOOKUP(A19,Master_Customers!$A:$D,4,FALSE()),"❌ Not Found")) | C19: =IF(A19="","",IFERROR(VLOOKUP(A19,Master_Customers!$A:$O,15,FALSE()),"")) | F19: =IF(E19="","",IF(C19="","",IF(E19>C19,"INSUFFICIENT FUNDS",C19-E19)))
B20: =IF(A20="","",IFERROR(VLOOKUP(A20,Master_Customers!$A:$D,4,FALSE()),"❌ Not Found")) | C20: =IF(A20="","",IFERROR(VLOOKUP(A20,Master_Customers!$A:$O,15,FALSE()),"")) | F20: =IF(E20="","",IF(C20="","",IF(E20>C20,"INSUFFICIENT FUNDS",C20-E20)))
... B1008: =IF(A1008="","",IFERROR(VLOOKUP(A1008,Master_Customers!$A:$D,4,FALSE()),"❌ Not Found")) | C1008: =IF(A1008="","",IFERROR(VLOOKUP(A1008,Master_Customers!$A:$O,15,FALSE()),"")) | F1008: =IF(E1008="","",IF(C1008="","",IF(E1008>C1008,"INSUFFICIENT FUNDS",C1008-E1008)))

Sheet Agent02_Loans
A1: 🏦 SAMICIOUS MICROFINANCE — AGENT02 LOAN REQUESTS
A2: Agent: Agent02 | Interest Rate: 2.5% p/m (flat) | Min: GHC 100 | Max: GHC 50,000
A4: 🔢 LOAN CALCULATOR
A5: Loan Amount (GHC):
A6: Repayment (months):
A7: Interest Rate (%/m): | B7: 2.5
A8: Total Interest (GHC): | B8: =IF(B5="","",B5*B7/100*B6)
A9: Total Repayable (GHC): | B9: =IF(B5="","",B5+B8)
A10: Monthly Installment (GHC): | B10: =IF(B5="","",B9/B6)
A12: 📋 LOAN REQUEST SUBMISSIONS — Enter details below to submit for manager approval
A13: Loan ID | B13: Account # | C13: Customer Name | D13: Request Date | E13: Loan Amount | F13: Purpose | G13: Months | H13: Rate % | I13: Total Repayable | J13: Monthly Install | K13: Status | L13: Notes
A14: LN202604120014 | B14: SAM20240200003 | C14: Kofi Boateng | D14: 2026-04-12 | E14: 9351.92 | F14: Business | G14: 6 | H14: 2.5 | I14: 10754.71 | J14: 1792.45 | K14: Pending
A15: LN202604120015 | B15: SAM20240200004 | C15: Abena Owusu | D15: 2026-04-12 | E15: 1586.39 | F15: Business | G15: 6 | H15: 2.5 | I15: 1824.35 | J15: 304.06 | K15: Pending
C16: =IF(B16="","",IFERROR(VLOOKUP(B16,Master_Customers!$A:$D,4,FALSE()),"❌ Not Found")) | I16: =IF(E16="","",E16+E16*H16/100*G16) | J16: =IFERROR(I16/G16,"")
C17: =IF(B17="","",IFERROR(VLOOKUP(B17,Master_Customers!$A:$D,4,FALSE()),"❌ Not Found")) | I17: =IF(E17="","",E17+E17*H17/100*G17) | J17: =IFERROR(I17/G17,"")
C18: =IF(B18="","",IFERROR(VLOOKUP(B18,Master_Customers!$A:$D,4,FALSE()),"❌ Not Found")) | I18: =IF(E18="","",E18+E18*H18/100*G18) | J18: =IFERROR(I18/G18,"")
C19: =IF(B19="","",IFERROR(VLOOKUP(B19,Master_Customers!$A:$D,4,FALSE()),"❌ Not Found")) | I19: =IF(E19="","",E19+E19*H19/100*G19) | J19: =IFERROR(I19/G19,"")
C20: =IF(B20="","",IFERROR(VLOOKUP(B20,Master_Customers!$A:$D,4,FALSE()),"❌ Not Found")) | I20: =IF(E20="","",E20+E20*H20/100*G20) | J20: =IFERROR(I20/G20,"")
C21: =IF(B21="","",IFERROR(VLOOKUP(B21,Master_Customers!$A:$D,4,FALSE()),"❌ Not Found")) | I21: =IF(E21="","",E21+E21*H21/100*G21) | J21: =IFERROR(I21/G21,"")
C22: =IF(B22="","",IFERROR(VLOOKUP(B22,Master_Customers!$A:$D,4,FALSE()),"❌ Not Found")) | I22: =IF(E22="","",E22+E22*H22/100*G22) | J22: =IFERROR(I22/G22,"")
C23: =IF(B23="","",IFERROR(VLOOKUP(B23,Master_Customers!$A:$D,4,FALSE()),"❌ Not Found")) | I23: =IF(E23="","",E23+E23*H23/100*G23) | J23: =IFERROR(I23/G23,"")
C24: =IF(B24="","",IFERROR(VLOOKUP(B24,Master_Customers!$A:$D,4,FALSE()),"❌ Not Found")) | I24: =IF(E24="","",E24+E24*H24/100*G24) | J24: =IFERROR(I24/G24,"")
C25: =IF(B25="","",IFERROR(VLOOKUP(B25,Master_Customers!$A:$D,4,FALSE()),"❌ Not Found")) | I25: =IF(E25="","",E25+E25*H25/100*G25) | J25: =IFERROR(I25/G25,"")
C26: =IF(B26="","",IFERROR(VLOOKUP(B26,Master_Customers!$A:$D,4,FALSE()),"❌ Not Found")) | I26: =IF(E26="","",E26+E26*H26/100*G26) | J26: =IFERROR(I26/G26,"")
C27: =IF(B27="","",IFERROR(VLOOKUP(B27,Master_Customers!$A:$D,4,FALSE()),"❌ Not Found")) | I27: =IF(E27="","",E27+E27*H27/100*G27) | J27: =IFERROR(I27/G27,"")
... C213: =IF(B213="","",IFERROR(VLOOKUP(B213,Master_Customers!$A:$D,4,FALSE()),"❌ Not Found")) | I213: =IF(E213="","",E213+E213*H213/100*G213) | J213: =IFERROR(I213/G213,"")

Sheet Agent03_Savings
A1: 💰 SAMICIOUS MICROFINANCE — AGENT03 SAVINGS
A2: Agent: Agent03 | Date: 2026-04-12 | Module: Daily Savings Collection
B3: Daily Target (GHC) | E3: Total Collected | H3: Remaining
B4: 5000 | E4: =SUMIF(I9:I1008,"SAVED",E9:E1008) -> 498.29 | H4: =IF(B4-E4<0,"TARGET MET!",B4-E4) -> 4501.71
A5: =IF(B4-E4<=0,"✅ DAILY TARGET ACHIEVED! Great work Agent03!","⏳ Collection in progress — Keep going!") -> ⏳ Collection in progress — Keep going!
A7: 📝 TRANSACTION ENTRY — Enter Account Number and Amount, then click RECORD or press Ctrl+S
A8: Account # | B8: Customer Name | C8: Current Balance | D8: Date | E8: Savings Amount | F8: New Balance | G8: Receipt # | H8: Agent | I8: Status | J8: Saved At
A9: SAM20240200005 | B9: =IF(A9="","",IFERROR(VLOOKUP(A9,Master_Customers!$A:$D,4,FALSE()),"❌ Not Found")) -> Yaw Darko | C9: =IF(A9="","",IFERROR(VLOOKUP(A9,Master_Customers!$A:$O,15,FALSE()),"")) -> 3808.17 | D9: 2026-04-12 | E9: 197.41 | F9: =IF(E9="","",IF(C9="","",C9+E9)) -> 4005.58 | H9: Agent03 | I9: SAVED | J9: 2026-04-12
A10: SAM20240300006 | B10: =IF(A10="","",IFERROR(VLOOKUP(A10,Master_Customers!$A:$D,4,FALSE()),"❌ Not Found")) -> Efua Kumi | C10: =IF(A10="","",IFERROR(VLOOKUP(A10,Master_Customers!$A:$O,15,FALSE()),"")) -> 1106.6 | D10: 2026-04-12 | E10: 300.88 | F10: =IF(E10="","",IF(C10="","",C10+E10)) -> 1407.48 | H10: Agent03 | I10: SAVED | J10: 2026-04-12
B11: =IF(A11="","",IFERROR(VLOOKUP(A11,Master_Customers!$A:$D,4,FALSE()),"❌ Not Found")) | C11: =IF(A11="","",IFERROR(VLOOKUP(A11,Master_Customers!$A:$O,15,FALSE()),"")) | F11: =IF(E11="","",IF(C11="","",C11+E11))
B12: =IF(A12="","",IFERROR(VLOOKUP(A12,Master_Customers!$A:$D,4,FALSE()),"❌ Not Found")) | C12: =IF(A12="","",IFERROR(VLOOKUP(A12,Master_Customers!$A:$O,15,FALSE()),"")) | F12: =IF(E12="","",IF(C12="","",C12+E12))
B13: =IF(A13="","",IFERROR(VLOOKUP(A13,Master_Customers!$A:$D,4,FALSE()),"❌ Not Found")) | C13: =IF(A13="","",IFERROR(VLOOKUP(A13,Master_Customers!$A:$O,15,FALSE()),"")) | F13: =IF(E13="","",IF(C13="","",C13+E13))
B14: =IF(A14="","",IFERROR(VLOOKUP(A14,Master_Customers!$A:$D,4,FALSE()),"❌ Not Found")) | C14: =IF(A14="","",IFERROR(VLOOKUP(A14,Master_Customers!$A:$O,15,FALSE()),"")) | F14: =IF(E14="","",IF(C14="","",C14+E14))
B15: =IF(A15="","",IFERROR(VLOOKUP(A15,Master_Customers!$A:$D,4,FALSE()),"❌ Not Found")) | C15: =IF(A15="","",IFERROR(VLOOKUP(A15,Master_Customers!$A:$O,15,FALSE()),"")) | F15: =IF(E15="","",IF(C15="","",C15+E15))
B16: =IF(A16="","",IFERROR(VLOOKUP(A16,Master_Customers!$A:$D,4,FALSE()),"❌ Not Found")) | C16: =IF(A16="","",IFERROR(VLOOKUP(A16,Master_Customers!$A:$O,15,FALSE()),"")) | F16: =IF(E16="","",IF(C16="","",C16+E16))
B17: =IF(A17="","",IFERROR(VLOOKUP(A17,Master_Customers!$A:$D,4,FALSE()),"❌ Not Found")) | C17: =IF(A17="","",IFERROR(VLOOKUP(A17,Master_Customers!$A:$O,15,FALSE()),"")) | F17: =IF(E17="","",IF(C17="","",C17+E17))
B18: =IF(A18="","",IFERROR(VLOOKUP(A18,Master_Customers!$A:$D,4,FALSE()),"❌ Not Found")) | C18: =IF(A18="","",IFERROR(VLOOKUP(A18,Master_Customers!$A:$O,15,FALSE()),"")) | F18: =IF(E18="","",IF(C18="","",C18+E18))
B19: =IF(A19="","",IFERROR(VLOOKUP(A19,Master_Customers!$A:$D,4,FALSE()),"❌ Not Found")) | C19: =IF(A19="","",IFERROR(VLOOKUP(A19,Master_Customers!$A:$O,15,FALSE()),"")) | F19: =IF(E19="","",IF(C19="","",C19+E19))
B20: =IF(A20="","",IFERROR(VLOOKUP(A20,Master_Customers!$A:$D,4,FALSE()),"❌ Not Found")) | C20: =IF(A20="","",IFERROR(VLOOKUP(A20,Master_Customers!$A:$O,15,FALSE()),"")) | F20: =IF(E20="","",IF(C20="","",C20+E20))
B21: =IF(A21="","",IFERROR(VLOOKUP(A21,Master_Customers!$A:$D,4,FALSE()),"❌ Not Found")) | C21: =IF(A21="","",IFERROR(VLOOKUP(A21,Master_Customers!$A:$O,15,FALSE()),"")) | F21: =IF(E21="","",IF(C21="","",C21+E21))
B22: =IF(A22="","",IFERROR(VLOOKUP(A22,Master_Customers!$A:$D,4,FALSE()),"❌ Not Found")) | C22: =IF(A22="","",IFERROR(VLOOKUP(A22,Master_Customers!$A:$O,15,FALSE()),"")) | F22: =IF(E22="","",IF(C22="","",C22+E22))
... B1008: =IF(A1008="","",IFERROR(VLOOKUP(A1008,Master_Customers!$A:$D,4,FALSE()),"❌ Not Found")) | C1008: =IF(A1008="","",IFERROR(VLOOKUP(A1008,Master_Customers!$A:$O,15,FALSE()),"")) | F1008: =IF(E1008="","",IF(C1008="","",C1008+E1008))

Sheet Agent03_Withdrawals
A1: 🏧 SAMICIOUS MICROFINANCE — AGENT03 WITHDRAWALS
A2: Agent: Agent03 | Date: 2026-04-12 | Module: Withdrawal Processing
B3: Total Withdrawals | E3: Transactions Count | H3: Avg Withdrawal
B4: =SUMIF(I9:I1008,"SAVED",E9:E1008) -> 0 | E4: =COUNTIF(I9:I1008,"SAVED") -> 0 | H4: =IFERROR(B4/E4,0) -> 0
A5: ⚠️ WITHDRAWALS MODULE — Insufficient balance will be flagged automatically
A7: 📝 TRANSACTION ENTRY — Enter Account Number and Withdrawal Amount
A8: Account # | B8: Customer Name | C8: Available Balance | D8: Date | E8: Withdrawal Amount | F8: New Balance | G8: Authorised By | H8: Agent | I8: Status | J8: Saved At
B9: =IF(A9="","",IFERROR(VLOOKUP(A9,Master_Customers!$A:$D,4,FALSE()),"❌ Not Found")) | C9: =IF(A9="","",IFERROR(VLOOKUP(A9,Master_Customers!$A:$O,15,FALSE()),"")) | F9: =IF(E9="","",IF(C9="","",IF(E9>C9,"INSUFFICIENT FUNDS",C9-E9)))
B10: =IF(A10="","",IFERROR(VLOOKUP(A10,Master_Customers!$A:$D,4,FALSE()),"❌ Not Found")) | C10: =IF(A10="","",IFERROR(VLOOKUP(A10,Master_Customers!$A:$O,15,FALSE()),"")) | F10: =IF(E10="","",IF(C10="","",IF(E10>C10,"INSUFFICIENT FUNDS",C10-E10)))
B11: =IF(A11="","",IFERROR(VLOOKUP(A11,Master_Customers!$A:$D,4,FALSE()),"❌ Not Found")) | C11: =IF(A11="","",IFERROR(VLOOKUP(A11,Master_Customers!$A:$O,15,FALSE()),"")) | F11: =IF(E11="","",IF(C11="","",IF(E11>C11,"INSUFFICIENT FUNDS",C11-E11)))
B12: =IF(A12="","",IFERROR(VLOOKUP(A12,Master_Customers!$A:$D,4,FALSE()),"❌ Not Found")) | C12: =IF(A12="","",IFERROR(VLOOKUP(A12,Master_Customers!$A:$O,15,FALSE()),"")) | F12: =IF(E12="","",IF(C12="","",IF(E12>C12,"INSUFFICIENT FUNDS",C12-E12)))
B13: =IF(A13="","",IFERROR(VLOOKUP(A13,Master_Customers!$A:$D,4,FALSE()),"❌ Not Found")) | C13: =IF(A13="","",IFERROR(VLOOKUP(A13,Master_Customers!$A:$O,15,FALSE()),"")) | F13: =IF(E13="","",IF(C13="","",IF(E13>C13,"INSUFFICIENT FUNDS",C13-E13)))
B14: =IF(A14="","",IFERROR(VLOOKUP(A14,Master_Customers!$A:$D,4,FALSE()),"❌ Not Found")) | C14: =IF(A14="","",IFERROR(VLOOKUP(A14,Master_Customers!$A:$O,15,FALSE()),"")) | F14: =IF(E14="","",IF(C14="","",IF(E14>C14,"INSUFFICIENT FUNDS",C14-E14)))
B15: =IF(A15="","",IFERROR(VLOOKUP(A15,Master_Customers!$A:$D,4,FALSE()),"❌ Not Found")) | C15: =IF(A15="","",IFERROR(VLOOKUP(A15,Master_Customers!$A:$O,15,FALSE()),"")) | F15: =IF(E15="","",IF(C15="","",IF(E15>C15,"INSUFFICIENT FUNDS",C15-E15)))
B16: =IF(A16="","",IFERROR(VLOOKUP(A16,Master_Customers!$A:$D,4,FALSE()),"❌ Not Found")) | C16: =IF(A16="","",IFERROR(VLOOKUP(A16,Master_Customers!$A:$O,15,FALSE()),"")) | F16: =IF(E16="","",IF(C16="","",IF(E16>C16,"INSUFFICIENT FUNDS",C16-E16)))
B17: =IF(A17="","",IFERROR(VLOOKUP(A17,Master_Customers!$A:$D,4,FALSE()),"❌ Not Found")) | C17: =IF(A17="","",IFERROR(VLOOKUP(A17,Master_Customers!$A:$O,15,FALSE()),"")) | F17: =IF(E17="","",IF(C17="","",IF(E17>C17,"INSUFFICIENT FUNDS",C17-E17)))
B18: =IF(A18="","",IFERROR(VLOOKUP(A18,Master_Customers!$A:$D,4,FALSE()),"❌ Not Found")) | C18: =IF(A18="","",IFERROR(VLOOKUP(A18,Master_Customers!$A:$O,15,FALSE()),"")) | F18: =IF(E18="","",IF(C18="","",IF(E18>C18,"INSUFFICIENT FUNDS",C18-E18)))
B19: =IF(A19="","",IFERROR(VLOOKUP(A19,Master_Customers!$A:$D,4,FALSE()),"❌ Not Found")) | C19: =IF(A19="","",IFERROR(VLOOKUP(A19,Master_Customers!$A:$O,15,FALSE()),"")) | F19: =IF(E19="","",IF(C19="","",IF(E19>C19,"INSUFFICIENT FUNDS",C19-E19)))
B20: =IF(A20="","",IFERROR(VLOOKUP(A20,Master_Customers!$A:$D,4,FALSE()),"❌ Not Found")) | C20: =IF(A20="","",IFERROR(VLOOKUP(A20,Master_Customers!$A:$O,15,FALSE()),"")) | F20: =IF(E20="","",IF(C20="","",IF(E20>C20,"INSUFFICIENT FUNDS",C20-E20)))
... B1008: =IF(A1008="","",IFERROR(VLOOKUP(A1008,Master_Customers!$A:$D,4,FALSE()),"❌ Not Found")) | C1008: =IF(A1008="","",IFERROR(VLOOKUP(A1008,Master_Customers!$A:$O,15,FALSE()),"")) | F1008: =IF(E1008="","",IF(C1008="","",IF(E1008>C1008,"INSUFFICIENT FUNDS",C1008-E1008)))

Sheet Agent03_Loans
A1: 🏦 SAMICIOUS MICROFINANCE — AGENT03 LOAN REQUESTS
A2: Agent: Agent03 | Interest Rate: 2.5% p/m (flat) | Min: GHC 100 | Max: GHC 50,000
A4: 🔢 LOAN CALCULATOR
A5: Loan Amount (GHC):
A6: Repayment (months):
A7: Interest Rate (%/m): | B7: 2.5
A8: Total Interest (GHC): | B8: =IF(B5="","",B5*B7/100*B6)
A9: Total Repayable (GHC): | B9: =IF(B5="","",B5+B8)
A10: Monthly Installment (GHC): | B10: =IF(B5="","",B9/B6)
A12: 📋 LOAN REQUEST SUBMISSIONS — Enter details below to submit for manager approval
A13: Loan ID | B13: Account # | C13: Customer Name | D13: Request Date | E13: Loan Amount | F13: Purpose | G13: Months | H13: Rate % | I13: Total Repayable | J13: Monthly Install | K13: Status | L13: Notes
A14: LN202604120014 | B14: SAM20240200005 | C14: Yaw Darko | D14: 2026-04-12 | E14: 9211.09 | F14: Business | G14: 9 | H14: 2.5 | I14: 11283.59 | J14: 1253.73 | K14: Pending
A15: LN202604120015 | B15: SAM20240300006 | C15: Efua Kumi | D15: 2026-04-12 | E15: 9280.02 | F15: Business | G15: 12 | H15: 2.5 | I15: 12064.03 | J15: 1005.34 | K15: Pending
C16: =IF(B16="","",IFERROR(VLOOKUP(B16,Master_Customers!$A:$D,4,FALSE()),"❌ Not Found")) | I16: =IF(E16="","",E16+E16*H16/100*G16) | J16: =IFERROR(I16/G16,"")
C17: =IF(B17="","",IFERROR(VLOOKUP(B17,Master_Customers!$A:$D,4,FALSE()),"❌ Not Found")) | I17: =IF(E17="","",E17+E17*H17/100*G17) | J17: =IFERROR(I17/G17,"")
C18: =IF(B18="","",IFERROR(VLOOKUP(B18,Master_Customers!$A:$D,4,FALSE()),"❌ Not Found")) | I18: =IF(E18="","",E18+E18*H18/100*G18) | J18: =IFERROR(I18/G18,"")
C19: =IF(B19="","",IFERROR(VLOOKUP(B19,Master_Customers!$A:$D,4,FALSE()),"❌ Not Found")) | I19: =IF(E19="","",E19+E19*H19/100*G19) | J19: =IFERROR(I19/G19,"")
C20: =IF(B20="","",IFERROR(VLOOKUP(B20,Master_Customers!$A:$D,4,FALSE()),"❌ Not Found")) | I20: =IF(E20="","",E20+E20*H20/100*G20) | J20: =IFERROR(I20/G20,"")
C21: =IF(B21="","",IFERROR(VLOOKUP(B21,Master_Customers!$A:$D,4,FALSE()),"❌ Not Found")) | I21: =IF(E21="","",E21+E21*H21/100*G21) | J21: =IFERROR(I21/G21,"")
C22: =IF(B22="","",IFERROR(VLOOKUP(B22,Master_Customers!$A:$D,4,FALSE()),"❌ Not Found")) | I22: =IF(E22="","",E22+E22*H22/100*G22) | J22: =IFERROR(I22/G22,"")
C23: =IF(B23="","",IFERROR(VLOOKUP(B23,Master_Customers!$A:$D,4,FALSE()),"❌ Not Found")) | I23: =IF(E23="","",E23+E23*H23/100*G23) | J23: =IFERROR(I23/G23,"")
C24: =IF(B24="","",IFERROR(VLOOKUP(B24,Master_Customers!$A:$D,4,FALSE()),"❌ Not Found")) | I24: =IF(E24="","",E24+E24*H24/100*G24) | J24: =IFERROR(I24/G24,"")
C25: =IF(B25="","",IFERROR(VLOOKUP(B25,Master_Customers!$A:$D,4,FALSE()),"❌ Not Found")) | I25: =IF(E25="","",E25+E25*H25/100*G25) | J25: =IFERROR(I25/G25,"")
C26: =IF(B26="","",IFERROR(VLOOKUP(B26,Master_Customers!$A:$D,4,FALSE()),"❌ Not Found")) | I26: =IF(E26="","",E26+E26*H26/100*G26) | J26: =IFERROR(I26/G26,"")
C27: =IF(B27="","",IFERROR(VLOOKUP(B27,Master_Customers!$A:$D,4,FALSE()),"❌ Not Found")) | I27: =IF(E27="","",E27+E27*H27/100*G27) | J27: =IFERROR(I27/G27,"")
... C213: =IF(B213="","",IFERROR(VLOOKUP(B213,Master_Customers!$A:$D,4,FALSE()),"❌ Not Found")) | I213: =IF(E213="","",E213+E213*H213/100*G213) | J213: =IFERROR(I213/G213,"")

Sheet Agent04_Savings
A1: 💰 SAMICIOUS MICROFINANCE — AGENT04 SAVINGS
A2: Agent: Agent04 | Date: 2026-04-12 | Module: Daily Savings Collection
B3: Daily Target (GHC) | E3: Total Collected | H3: Remaining
B4: 5000 | E4: =SUMIF(I9:I1008,"SAVED",E9:E1008) -> 872.99 | H4: =IF(B4-E4<0,"TARGET MET!",B4-E4) -> 4127.01
A5: =IF(B4-E4<=0,"✅ DAILY TARGET ACHIEVED! Great work Agent04!","⏳ Collection in progress — Keep going!") -> ⏳ Collection in progress — Keep going!
A7: 📝 TRANSACTION ENTRY — Enter Account Number and Amount, then click RECORD or press Ctrl+S
A8: Account # | B8: Customer Name | C8: Current Balance | D8: Date | E8: Savings Amount | F8: New Balance | G8: Receipt # | H8: Agent | I8: Status | J8: Saved At
A9: SAM20240300007 | B9: =IF(A9="","",IFERROR(VLOOKUP(A9,Master_Customers!$A:$D,4,FALSE()),"❌ Not Found")) -> Kojo Amponsah | C9: =IF(A9="","",IFERROR(VLOOKUP(A9,Master_Customers!$A:$O,15,FALSE()),"")) -> 1701.52 | D9: 2026-04-12 | E9: 396.67 | F9: =IF(E9="","",IF(C9="","",C9+E9)) -> 2098.19 | H9: Agent04 | I9: SAVED | J9: 2026-04-12
A10: SAM20240300008 | B10: =IF(A10="","",IFERROR(VLOOKUP(A10,Master_Customers!$A:$D,4,FALSE()),"❌ Not Found")) -> Akosua Frimpong | C10: =IF(A10="","",IFERROR(VLOOKUP(A10,Master_Customers!$A:$O,15,FALSE()),"")) -> 2739.85 | D10: 2026-04-12 | E10: 476.32 | F10: =IF(E10="","",IF(C10="","",C10+E10)) -> 3216.17 | H10: Agent04 | I10: SAVED | J10: 2026-04-12
B11: =IF(A11="","",IFERROR(VLOOKUP(A11,Master_Customers!$A:$D,4,FALSE()),"❌ Not Found")) | C11: =IF(A11="","",IFERROR(VLOOKUP(A11,Master_Customers!$A:$O,15,FALSE()),"")) | F11: =IF(E11="","",IF(C11="","",C11+E11))
B12: =IF(A12="","",IFERROR(VLOOKUP(A12,Master_Customers!$A:$D,4,FALSE()),"❌ Not Found")) | C12: =IF(A12="","",IFERROR(VLOOKUP(A12,Master_Customers!$A:$O,15,FALSE()),"")) | F12: =IF(E12="","",IF(C12="","",C12+E12))
B13: =IF(A13="","",IFERROR(VLOOKUP(A13,Master_Customers!$A:$D,4,FALSE()),"❌ Not Found")) | C13: =IF(A13="","",IFERROR(VLOOKUP(A13,Master_Customers!$A:$O,15,FALSE()),"")) | F13: =IF(E13="","",IF(C13="","",C13+E13))
B14: =IF(A14="","",IFERROR(VLOOKUP(A14,Master_Customers!$A:$D,4,FALSE()),"❌ Not Found")) | C14: =IF(A14="","",IFERROR(VLOOKUP(A14,Master_Customers!$A:$O,15,FALSE()),"")) | F14: =IF(E14="","",IF(C14="","",C14+E14))
B15: =IF(A15="","",IFERROR(VLOOKUP(A15,Master_Customers!$A:$D,4,FALSE()),"❌ Not Found")) | C15: =IF(A15="","",IFERROR(VLOOKUP(A15,Master_Customers!$A:$O,15,FALSE()),"")) | F15: =IF(E15="","",IF(C15="","",C15+E15))
B16: =IF(A16="","",IFERROR(VLOOKUP(A16,Master_Customers!$A:$D,4,FALSE()),"❌ Not Found")) | C16: =IF(A16="","",IFERROR(VLOOKUP(A16,Master_Customers!$A:$O,15,FALSE()),"")) | F16: =IF(E16="","",IF(C16="","",C16+E16))
B17: =IF(A17="","",IFERROR(VLOOKUP(A17,Master_Customers!$A:$D,4,FALSE()),"❌ Not Found")) | C17: =IF(A17="","",IFERROR(VLOOKUP(A17,Master_Customers!$A:$O,15,FALSE()),"")) | F17: =IF(E17="","",IF(C17="","",C17+E17))
B18: =IF(A18="","",IFERROR(VLOOKUP(A18,Master_Customers!$A:$D,4,FALSE()),"❌ Not Found")) | C18: =IF(A18="","",IFERROR(VLOOKUP(A18,Master_Customers!$A:$O,15,FALSE()),"")) | F18: =IF(E18="","",IF(C18="","",C18+E18))
B19: =IF(A19="","",IFERROR(VLOOKUP(A19,Master_Customers!$A:$D,4,FALSE()),"❌ Not Found")) | C19: =IF(A19="","",IFERROR(VLOOKUP(A19,Master_Customers!$A:$O,15,FALSE()),"")) | F19: =IF(E19="","",IF(C19="","",C19+E19))
B20: =IF(A20="","",IFERROR(VLOOKUP(A20,Master_Customers!$A:$D,4,FALSE()),"❌ Not Found")) | C20: =IF(A20="","",IFERROR(VLOOKUP(A20,Master_Customers!$A:$O,15,FALSE()),"")) | F20: =IF(E20="","",IF(C20="","",C20+E20))
B21: =IF(A21="","",IFERROR(VLOOKUP(A21,Master_Customers!$A:$D,4,FALSE()),"❌ Not Found")) | C21: =IF(A21="","",IFERROR(VLOOKUP(A21,Master_Customers!$A:$O,15,FALSE()),"")) | F21: =IF(E21="","",IF(C21="","",C21+E21))
B22: =IF(A22="","",IFERROR(VLOOKUP(A22,Master_Customers!$A:$D,4,FALSE()),"❌ Not Found")) | C22: =IF(A22="","",IFERROR(VLOOKUP(A22,Master_Customers!$A:$O,15,FALSE()),"")) | F22: =IF(E22="","",IF(C22="","",C22+E22))
... B1008: =IF(A1008="","",IFERROR(VLOOKUP(A1008,Master_Customers!$A:$D,4,FALSE()),"❌ Not Found")) | C1008: =IF(A1008="","",IFERROR(VLOOKUP(A1008,Master_Customers!$A:$O,15,FALSE()),"")) | F1008: =IF(E1008="","",IF(C1008="","",C1008+E1008))

Sheet Agent04_Withdrawals
A1: 🏧 SAMICIOUS MICROFINANCE — AGENT04 WITHDRAWALS
A2: Agent: Agent04 | Date: 2026-04-12 | Module: Withdrawal Processing
B3: Total Withdrawals | E3: Transactions Count | H3: Avg Withdrawal
B4: =SUMIF(I9:I1008,"SAVED",E9:E1008) -> 0 | E4: =COUNTIF(I9:I1008,"SAVED") -> 0 | H4: =IFERROR(B4/E4,0) -> 0
A5: ⚠️ WITHDRAWALS MODULE — Insufficient balance will be flagged automatically
A7: 📝 TRANSACTION ENTRY — Enter Account Number and Withdrawal Amount
A8: Account # | B8: Customer Name | C8: Available Balance | D8: Date | E8: Withdrawal Amount | F8: New Balance | G8: Authorised By | H8: Agent | I8: Status | J8: Saved At
B9: =IF(A9="","",IFERROR(VLOOKUP(A9,Master_Customers!$A:$D,4,FALSE()),"❌ Not Found")) | C9: =IF(A9="","",IFERROR(VLOOKUP(A9,Master_Customers!$A:$O,15,FALSE()),"")) | F9: =IF(E9="","",IF(C9="","",IF(E9>C9,"INSUFFICIENT FUNDS",C9-E9)))
B10: =IF(A10="","",IFERROR(VLOOKUP(A10,Master_Customers!$A:$D,4,FALSE()),"❌ Not Found")) | C10: =IF(A10="","",IFERROR(VLOOKUP(A10,Master_Customers!$A:$O,15,FALSE()),"")) | F10: =IF(E10="","",IF(C10="","",IF(E10>C10,"INSUFFICIENT FUNDS",C10-E10)))
B11: =IF(A11="","",IFERROR(VLOOKUP(A11,Master_Customers!$A:$D,4,FALSE()),"❌ Not Found")) | C11: =IF(A11="","",IFERROR(VLOOKUP(A11,Master_Customers!$A:$O,15,FALSE()),"")) | F11: =IF(E11="","",IF(C11="","",IF(E11>C11,"INSUFFICIENT FUNDS",C11-E11)))
B12: =IF(A12="","",IFERROR(VLOOKUP(A12,Master_Customers!$A:$D,4,FALSE()),"❌ Not Found")) | C12: =IF(A12="","",IFERROR(VLOOKUP(A12,Master_Customers!$A:$O,15,FALSE()),"")) | F12: =IF(E12="","",IF(C12="","",IF(E12>C12,"INSUFFICIENT FUNDS",C12-E12)))
B13: =IF(A13="","",IFERROR(VLOOKUP(A13,Master_Customers!$A:$D,4,FALSE()),"❌ Not Found")) | C13: =IF(A13="","",IFERROR(VLOOKUP(A13,Master_Customers!$A:$O,15,FALSE()),"")) | F13: =IF(E13="","",IF(C13="","",IF(E13>C13,"INSUFFICIENT FUNDS",C13-E13)))
B14: =IF(A14="","",IFERROR(VLOOKUP(A14,Master_Customers!$A:$D,4,FALSE()),"❌ Not Found")) | C14: =IF(A14="","",IFERROR(VLOOKUP(A14,Master_Customers!$A:$O,15,FALSE()),"")) | F14: =IF(E14="","",IF(C14="","",IF(E14>C14,"INSUFFICIENT FUNDS",C14-E14)))
B15: =IF(A15="","",IFERROR(VLOOKUP(A15,Master_Customers!$A:$D,4,FALSE()),"❌ Not Found")) | C15: =IF(A15="","",IFERROR(VLOOKUP(A15,Master_Customers!$A:$O,15,FALSE()),"")) | F15: =IF(E15="","",IF(C15="","",IF(E15>C15,"INSUFFICIENT FUNDS",C15-E15)))
B16: =IF(A16="","",IFERROR(VLOOKUP(A16,Master_Customers!$A:$D,4,FALSE()),"❌ Not Found")) | C16: =IF(A16="","",IFERROR(VLOOKUP(A16,Master_Customers!$A:$O,15,FALSE()),"")) | F16: =IF(E16="","",IF(C16="","",IF(E16>C16,"INSUFFICIENT FUNDS",C16-E16)))
B17: =IF(A17="","",IFERROR(VLOOKUP(A17,Master_Customers!$A:$D,4,FALSE()),"❌ Not Found")) | C17: =IF(A17="","",IFERROR(VLOOKUP(A17,Master_Customers!$A:$O,15,FALSE()),"")) | F17: =IF(E17="","",IF(C17="","",IF(E17>C17,"INSUFFICIENT FUNDS",C17-E17)))
B18: =IF(A18="","",IFERROR(VLOOKUP(A18,Master_Customers!$A:$D,4,FALSE()),"❌ Not Found")) | C18: =IF(A18="","",IFERROR(VLOOKUP(A18,Master_Customers!$A:$O,15,FALSE()),"")) | F18: =IF(E18="","",IF(C18="","",IF(E18>C18,"INSUFFICIENT FUNDS",C18-E18)))
B19: =IF(A19="","",IFERROR(VLOOKUP(A19,Master_Customers!$A:$D,4,FALSE()),"❌ Not Found")) | C19: =IF(A19="","",IFERROR(VLOOKUP(A19,Master_Customers!$A:$O,15,FALSE()),"")) | F19: =IF(E19="","",IF(C19="","",IF(E19>C19,"INSUFFICIENT FUNDS",C19-E19)))
B20: =IF(A20="","",IFERROR(VLOOKUP(A20,Master_Customers!$A:$D,4,FALSE()),"❌ Not Found")) | C20: =IF(A20="","",IFERROR(VLOOKUP(A20,Master_Customers!$A:$O,15,FALSE()),"")) | F20: =IF(E20="","",IF(C20="","",IF(E20>C20,"INSUFFICIENT FUNDS",C20-E20)))
... B1008: =IF(A1008="","",IFERROR(VLOOKUP(A1008,Master_Customers!$A:$D,4,FALSE()),"❌ Not Found")) | C1008: =IF(A1008="","",IFERROR(VLOOKUP(A1008,Master_Customers!$A:$O,15,FALSE()),"")) | F1008: =IF(E1008="","",IF(C1008="","",IF(E1008>C1008,"INSUFFICIENT FUNDS",C1008-E1008)))

Sheet Agent04_Loans
A1: 🏦 SAMICIOUS MICROFINANCE — AGENT04 LOAN REQUESTS
A2: Agent: Agent04 | Interest Rate: 2.5% p/m (flat) | Min: GHC 100 | Max: GHC 50,000
A4: 🔢 LOAN CALCULATOR
A5: Loan Amount (GHC):
A6: Repayment (months):
A7: Interest Rate (%/m): | B7: 2.5
A8: Total Interest (GHC): | B8: =IF(B5="","",B5*B7/100*B6)
A9: Total Repayable (GHC): | B9: =IF(B5="","",B5+B8)
A10: Monthly Installment (GHC): | B10: =IF(B5="","",B9/B6)
A12: 📋 LOAN REQUEST SUBMISSIONS — Enter details below to submit for manager approval
A13: Loan ID | B13: Account # | C13: Customer Name | D13: Request Date | E13: Loan Amount | F13: Purpose | G13: Months | H13: Rate % | I13: Total Repayable | J13: Monthly Install | K13: Status | L13: Notes
A14: LN202604120014 | B14: SAM20240300007 | C14: Kojo Amponsah | D14: 2026-04-12 | E14: 9647.03 | F14: Business | G14: 12 | H14: 2.5 | I14: 12541.14 | J14: 1045.09 | K14: Pending
A15: LN202604120015 | B15: SAM20240300008 | C15: Akosua Frimpong | D15: 2026-04-12 | E15: 1051.63 | F15: Business | G15: 6 | H15: 2.5 | I15: 1209.37 | J15: 201.56 | K15: Pending
C16: =IF(B16="","",IFERROR(VLOOKUP(B16,Master_Customers!$A:$D,4,FALSE()),"❌ Not Found")) | I16: =IF(E16="","",E16+E16*H16/100*G16) | J16: =IFERROR(I16/G16,"")
C17: =IF(B17="","",IFERROR(VLOOKUP(B17,Master_Customers!$A:$D,4,FALSE()),"❌ Not Found")) | I17: =IF(E17="","",E17+E17*H17/100*G17) | J17: =IFERROR(I17/G17,"")
C18: =IF(B18="","",IFERROR(VLOOKUP(B18,Master_Customers!$A:$D,4,FALSE()),"❌ Not Found")) | I18: =IF(E18="","",E18+E18*H18/100*G18) | J18: =IFERROR(I18/G18,"")
C19: =IF(B19="","",IFERROR(VLOOKUP(B19,Master_Customers!$A:$D,4,FALSE()),"❌ Not Found")) | I19: =IF(E19="","",E19+E19*H19/100*G19) | J19: =IFERROR(I19/G19,"")
C20: =IF(B20="","",IFERROR(VLOOKUP(B20,Master_Customers!$A:$D,4,FALSE()),"❌ Not Found")) | I20: =IF(E20="","",E20+E20*H20/100*G20) | J20: =IFERROR(I20/G20,"")
C21: =IF(B21="","",IFERROR(VLOOKUP(B21,Master_Customers!$A:$D,4,FALSE()),"❌ Not Found")) | I21: =IF(E21="","",E21+E21*H21/100*G21) | J21: =IFERROR(I21/G21,"")
C22: =IF(B22="","",IFERROR(VLOOKUP(B22,Master_Customers!$A:$D,4,FALSE()),"❌ Not Found")) | I22: =IF(E22="","",E22+E22*H22/100*G22) | J22: =IFERROR(I22/G22,"")
C23: =IF(B23="","",IFERROR(VLOOKUP(B23,Master_Customers!$A:$D,4,FALSE()),"❌ Not Found")) | I23: =IF(E23="","",E23+E23*H23/100*G23) | J23: =IFERROR(I23/G23,"")
C24: =IF(B24="","",IFERROR(VLOOKUP(B24,Master_Customers!$A:$D,4,FALSE()),"❌ Not Found")) | I24: =IF(E24="","",E24+E24*H24/100*G24) | J24: =IFERROR(I24/G24,"")
C25: =IF(B25="","",IFERROR(VLOOKUP(B25,Master_Customers!$A:$D,4,FALSE()),"❌ Not Found")) | I25: =IF(E25="","",E25+E25*H25/100*G25) | J25: =IFERROR(I25/G25,"")
C26: =IF(B26="","",IFERROR(VLOOKUP(B26,Master_Customers!$A:$D,4,FALSE()),"❌ Not Found")) | I26: =IF(E26="","",E26+E26*H26/100*G26) | J26: =IFERROR(I26/G26,"")
C27: =IF(B27="","",IFERROR(VLOOKUP(B27,Master_Customers!$A:$D,4,FALSE()),"❌ Not Found")) | I27: =IF(E27="","",E27+E27*H27/100*G27) | J27: =IFERROR(I27/G27,"")
... C213: =IF(B213="","",IFERROR(VLOOKUP(B213,Master_Customers!$A:$D,4,FALSE()),"❌ Not Found")) | I213: =IF(E213="","",E213+E213*H213/100*G213) | J213: =IFERROR(I213/G213,"")

Sheet Agent05_Savings
A1: 💰 SAMICIOUS MICROFINANCE — AGENT05 SAVINGS
A2: Agent: Agent05 | Date: 2026-04-12 | Module: Daily Savings Collection
B3: Daily Target (GHC) | E3: Total Collected | H3: Remaining
B4: 5000 | E4: =SUMIF(I9:I1008,"SAVED",E9:E1008) -> 525.86 | H4: =IF(B4-E4<0,"TARGET MET!",B4-E4) -> 4474.14
A5: =IF(B4-E4<=0,"✅ DAILY TARGET ACHIEVED! Great work Agent05!","⏳ Collection in progress — Keep going!") -> ⏳ Collection in progress — Keep going!
A7: 📝 TRANSACTION ENTRY — Enter Account Number and Amount, then click RECORD or press Ctrl+S
A8: Account # | B8: Customer Name | C8: Current Balance | D8: Date | E8: Savings Amount | F8: New Balance | G8: Receipt # | H8: Agent | I8: Status | J8: Saved At
A9: SAM20240400009 | B9: =IF(A9="","",IFERROR(VLOOKUP(A9,Master_Customers!$A:$D,4,FALSE()),"❌ Not Found")) -> Kwabena Asante | C9: =IF(A9="","",IFERROR(VLOOKUP(A9,Master_Customers!$A:$O,15,FALSE()),"")) -> 3507.75 | D9: 2026-04-12 | E9: 179.84 | F9: =IF(E9="","",IF(C9="","",C9+E9)) -> 3687.59 | H9: Agent05 | I9: SAVED | J9: 2026-04-12
A10: SAM20240400010 | B10: =IF(A10="","",IFERROR(VLOOKUP(A10,Master_Customers!$A:$D,4,FALSE()),"❌ Not Found")) -> Adjoa Tetteh | C10: =IF(A10="","",IFERROR(VLOOKUP(A10,Master_Customers!$A:$O,15,FALSE()),"")) -> 3164.79 | D10: 2026-04-12 | E10: 346.02 | F10: =IF(E10="","",IF(C10="","",C10+E10)) -> 3510.81 | H10: Agent05 | I10: SAVED | J10: 2026-04-12
B11: =IF(A11="","",IFERROR(VLOOKUP(A11,Master_Customers!$A:$D,4,FALSE()),"❌ Not Found")) | C11: =IF(A11="","",IFERROR(VLOOKUP(A11,Master_Customers!$A:$O,15,FALSE()),"")) | F11: =IF(E11="","",IF(C11="","",C11+E11))
B12: =IF(A12="","",IFERROR(VLOOKUP(A12,Master_Customers!$A:$D,4,FALSE()),"❌ Not Found")) | C12: =IF(A12="","",IFERROR(VLOOKUP(A12,Master_Customers!$A:$O,15,FALSE()),"")) | F12: =IF(E12="","",IF(C12="","",C12+E12))
B13: =IF(A13="","",IFERROR(VLOOKUP(A13,Master_Customers!$A:$D,4,FALSE()),"❌ Not Found")) | C13: =IF(A13="","",IFERROR(VLOOKUP(A13,Master_Customers!$A:$O,15,FALSE()),"")) | F13: =IF(E13="","",IF(C13="","",C13+E13))
B14: =IF(A14="","",IFERROR(VLOOKUP(A14,Master_Customers!$A:$D,4,FALSE()),"❌ Not Found")) | C14: =IF(A14="","",IFERROR(VLOOKUP(A14,Master_Customers!$A:$O,15,FALSE()),"")) | F14: =IF(E14="","",IF(C14="","",C14+E14))
B15: =IF(A15="","",IFERROR(VLOOKUP(A15,Master_Customers!$A:$D,4,FALSE()),"❌ Not Found")) | C15: =IF(A15="","",IFERROR(VLOOKUP(A15,Master_Customers!$A:$O,15,FALSE()),"")) | F15: =IF(E15="","",IF(C15="","",C15+E15))
B16: =IF(A16="","",IFERROR(VLOOKUP(A16,Master_Customers!$A:$D,4,FALSE()),"❌ Not Found")) | C16: =IF(A16="","",IFERROR(VLOOKUP(A16,Master_Customers!$A:$O,15,FALSE()),"")) | F16: =IF(E16="","",IF(C16="","",C16+E16))
B17: =IF(A17="","",IFERROR(VLOOKUP(A17,Master_Customers!$A:$D,4,FALSE()),"❌ Not Found")) | C17: =IF(A17="","",IFERROR(VLOOKUP(A17,Master_Customers!$A:$O,15,FALSE()),"")) | F17: =IF(E17="","",IF(C17="","",C17+E17))
B18: =IF(A18="","",IFERROR(VLOOKUP(A18,Master_Customers!$A:$D,4,FALSE()),"❌ Not Found")) | C18: =IF(A18="","",IFERROR(VLOOKUP(A18,Master_Customers!$A:$O,15,FALSE()),"")) | F18: =IF(E18="","",IF(C18="","",C18+E18))
B19: =IF(A19="","",IFERROR(VLOOKUP(A19,Master_Customers!$A:$D,4,FALSE()),"❌ Not Found")) | C19: =IF(A19="","",IFERROR(VLOOKUP(A19,Master_Customers!$A:$O,15,FALSE()),"")) | F19: =IF(E19="","",IF(C19="","",C19+E19))
B20: =IF(A20="","",IFERROR(VLOOKUP(A20,Master_Customers!$A:$D,4,FALSE()),"❌ Not Found")) | C20: =IF(A20="","",IFERROR(VLOOKUP(A20,Master_Customers!$A:$O,15,FALSE()),"")) | F20: =IF(E20="","",IF(C20="","",C20+E20))
B21: =IF(A21="","",IFERROR(VLOOKUP(A21,Master_Customers!$A:$D,4,FALSE()),"❌ Not Found")) | C21: =IF(A21="","",IFERROR(VLOOKUP(A21,Master_Customers!$A:$O,15,FALSE()),"")) | F21: =IF(E21="","",IF(C21="","",C21+E21))
B22: =IF(A22="","",IFERROR(VLOOKUP(A22,Master_Customers!$A:$D,4,FALSE()),"❌ Not Found")) | C22: =IF(A22="","",IFERROR(VLOOKUP(A22,Master_Customers!$A:$O,15,FALSE()),"")) | F22: =IF(E22="","",IF(C22="","",C22+E22))
... B1008: =IF(A1008="","",IFERROR(VLOOKUP(A1008,Master_Customers!$A:$D,4,FALSE()),"❌ Not Found")) | C1008: =IF(A1008="","",IFERROR(VLOOKUP(A1008,Master_Customers!$A:$O,15,FALSE()),"")) | F1008: =IF(E1008="","",IF(C1008="","",C1008+E1008))

Sheet Agent05_Withdrawals
A1: 🏧 SAMICIOUS MICROFINANCE — AGENT05 WITHDRAWALS
A2: Agent: Agent05 | Date: 2026-04-12 | Module: Withdrawal Processing
B3: Total Withdrawals | E3: Transactions Count | H3: Avg Withdrawal
B4: =SUMIF(I9:I1008,"SAVED",E9:E1008) -> 0 | E4: =COUNTIF(I9:I1008,"SAVED") -> 0 | H4: =IFERROR(B4/E4,0) -> 0
A5: ⚠️ WITHDRAWALS MODULE — Insufficient balance will be flagged automatically
A7: 📝 TRANSACTION ENTRY — Enter Account Number and Withdrawal Amount
A8: Account # | B8: Customer Name | C8: Available Balance | D8: Date | E8: Withdrawal Amount | F8: New Balance | G8: Authorised By | H8: Agent | I8: Status | J8: Saved At
B9: =IF(A9="","",IFERROR(VLOOKUP(A9,Master_Customers!$A:$D,4,FALSE()),"❌ Not Found")) | C9: =IF(A9="","",IFERROR(VLOOKUP(A9,Master_Customers!$A:$O,15,FALSE()),"")) | F9: =IF(E9="","",IF(C9="","",IF(E9>C9,"INSUFFICIENT FUNDS",C9-E9)))
B10: =IF(A10="","",IFERROR(VLOOKUP(A10,Master_Customers!$A:$D,4,FALSE()),"❌ Not Found")) | C10: =IF(A10="","",IFERROR(VLOOKUP(A10,Master_Customers!$A:$O,15,FALSE()),"")) | F10: =IF(E10="","",IF(C10="","",IF(E10>C10,"INSUFFICIENT FUNDS",C10-E10)))
B11: =IF(A11="","",IFERROR(VLOOKUP(A11,Master_Customers!$A:$D,4,FALSE()),"❌ Not Found")) | C11: =IF(A11="","",IFERROR(VLOOKUP(A11,Master_Customers!$A:$O,15,FALSE()),"")) | F11: =IF(E11="","",IF(C11="","",IF(E11>C11,"INSUFFICIENT FUNDS",C11-E11)))
B12: =IF(A12="","",IFERROR(VLOOKUP(A12,Master_Customers!$A:$D,4,FALSE()),"❌ Not Found")) | C12: =IF(A12="","",IFERROR(VLOOKUP(A12,Master_Customers!$A:$O,15,FALSE()),"")) | F12: =IF(E12="","",IF(C12="","",IF(E12>C12,"INSUFFICIENT FUNDS",C12-E12)))
B13: =IF(A13="","",IFERROR(VLOOKUP(A13,Master_Customers!$A:$D,4,FALSE()),"❌ Not Found")) | C13: =IF(A13="","",IFERROR(VLOOKUP(A13,Master_Customers!$A:$O,15,FALSE()),"")) | F13: =IF(E13="","",IF(C13="","",IF(E13>C13,"INSUFFICIENT FUNDS",C13-E13)))
B14: =IF(A14="","",IFERROR(VLOOKUP(A14,Master_Customers!$A:$D,4,FALSE()),"❌ Not Found")) | C14: =IF(A14="","",IFERROR(VLOOKUP(A14,Master_Customers!$A:$O,15,FALSE()),"")) | F14: =IF(E14="","",IF(C14="","",IF(E14>C14,"INSUFFICIENT FUNDS",C14-E14)))
B15: =IF(A15="","",IFERROR(VLOOKUP(A15,Master_Customers!$A:$D,4,FALSE()),"❌ Not Found")) | C15: =IF(A15="","",IFERROR(VLOOKUP(A15,Master_Customers!$A:$O,15,FALSE()),"")) | F15: =IF(E15="","",IF(C15="","",IF(E15>C15,"INSUFFICIENT FUNDS",C15-E15)))
B16: =IF(A16="","",IFERROR(VLOOKUP(A16,Master_Customers!$A:$D,4,FALSE()),"❌ Not Found")) | C16: =IF(A16="","",IFERROR(VLOOKUP(A16,Master_Customers!$A:$O,15,FALSE()),"")) | F16: =IF(E16="","",IF(C16="","",IF(E16>C16,"INSUFFICIENT FUNDS",C16-E16)))
B17: =IF(A17="","",IFERROR(VLOOKUP(A17,Master_Customers!$A:$D,4,FALSE()),"❌ Not Found")) | C17: =IF(A17="","",IFERROR(VLOOKUP(A17,Master_Customers!$A:$O,15,FALSE()),"")) | F17: =IF(E17="","",IF(C17="","",IF(E17>C17,"INSUFFICIENT FUNDS",C17-E17)))
B18: =IF(A18="","",IFERROR(VLOOKUP(A18,Master_Customers!$A:$D,4,FALSE()),"❌ Not Found")) | C18: =IF(A18="","",IFERROR(VLOOKUP(A18,Master_Customers!$A:$O,15,FALSE()),"")) | F18: =IF(E18="","",IF(C18="","",IF(E18>C18,"INSUFFICIENT FUNDS",C18-E18)))
B19: =IF(A19="","",IFERROR(VLOOKUP(A19,Master_Customers!$A:$D,4,FALSE()),"❌ Not Found")) | C19: =IF(A19="","",IFERROR(VLOOKUP(A19,Master_Customers!$A:$O,15,FALSE()),"")) | F19: =IF(E19="","",IF(C19="","",IF(E19>C19,"INSUFFICIENT FUNDS",C19-E19)))
B20: =IF(A20="","",IFERROR(VLOOKUP(A20,Master_Customers!$A:$D,4,FALSE()),"❌ Not Found")) | C20: =IF(A20="","",IFERROR(VLOOKUP(A20,Master_Customers!$A:$O,15,FALSE()),"")) | F20: =IF(E20="","",IF(C20="","",IF(E20>C20,"INSUFFICIENT FUNDS",C20-E20)))
... B1008: =IF(A1008="","",IFERROR(VLOOKUP(A1008,Master_Customers!$A:$D,4,FALSE()),"❌ Not Found")) | C1008: =IF(A1008="","",IFERROR(VLOOKUP(A1008,Master_Customers!$A:$O,15,FALSE()),"")) | F1008: =IF(E1008="","",IF(C1008="","",IF(E1008>C1008,"INSUFFICIENT FUNDS",C1008-E1008)))

Sheet Agent05_Loans
A1: 🏦 SAMICIOUS MICROFINANCE — AGENT05 LOAN REQUESTS
A2: Agent: Agent05 | Interest Rate: 2.5% p/m (flat) | Min: GHC 100 | Max: GHC 50,000
A4: 🔢 LOAN CALCULATOR
A5: Loan Amount (GHC):
A6: Repayment (months):
A7: Interest Rate (%/m): | B7: 2.5
A8: Total Interest (GHC): | B8: =IF(B5="","",B5*B7/100*B6)
A9: Total Repayable (GHC): | B9: =IF(B5="","",B5+B8)
A10: Monthly Installment (GHC): | B10: =IF(B5="","",B9/B6)
A12: 📋 LOAN REQUEST SUBMISSIONS — Enter details below to submit for manager approval
A13: Loan ID | B13: Account # | C13: Customer Name | D13: Request Date | E13: Loan Amount | F13: Purpose | G13: Months | H13: Rate % | I13: Total Repayable | J13: Monthly Install | K13: Status | L13: Notes
A14: LN202604120014 | B14: SAM20240400009 | C14: Kwabena Asante | D14: 2026-04-12 | E14: 6227.98 | F14: Business | G14: 12 | H14: 2.5 | I14: 8096.37 | J14: 674.7 | K14: Pending
A15: LN202604120015 | B15: SAM20240400010 | C15: Adjoa Tetteh | D15: 2026-04-12 | E15: 9832.85 | F15: Business | G15: 9 | H15: 2.5 | I15: 12045.24 | J15: 1338.36 | K15: Pending
C16: =IF(B16="","",IFERROR(VLOOKUP(B16,Master_Customers!$A:$D,4,FALSE()),"❌ Not Found")) | I16: =IF(E16="","",E16+E16*H16/100*G16) | J16: =IFERROR(I16/G16,"")
C17: =IF(B17="","",IFERROR(VLOOKUP(B17,Master_Customers!$A:$D,4,FALSE()),"❌ Not Found")) | I17: =IF(E17="","",E17+E17*H17/100*G17) | J17: =IFERROR(I17/G17,"")
C18: =IF(B18="","",IFERROR(VLOOKUP(B18,Master_Customers!$A:$D,4,FALSE()),"❌ Not Found")) | I18: =IF(E18="","",E18+E18*H18/100*G18) | J18: =IFERROR(I18/G18,"")
C19: =IF(B19="","",IFERROR(VLOOKUP(B19,Master_Customers!$A:$D,4,FALSE()),"❌ Not Found")) | I19: =IF(E19="","",E19+E19*H19/100*G19) | J19: =IFERROR(I19/G19,"")
C20: =IF(B20="","",IFERROR(VLOOKUP(B20,Master_Customers!$A:$D,4,FALSE()),"❌ Not Found")) | I20: =IF(E20="","",E20+E20*H20/100*G20) | J20: =IFERROR(I20/G20,"")
C21: =IF(B21="","",IFERROR(VLOOKUP(B21,Master_Customers!$A:$D,4,FALSE()),"❌ Not Found")) | I21: =IF(E21="","",E21+E21*H21/100*G21) | J21: =IFERROR(I21/G21,"")
C22: =IF(B22="","",IFERROR(VLOOKUP(B22,Master_Customers!$A:$D,4,FALSE()),"❌ Not Found")) | I22: =IF(E22="","",E22+E22*H22/100*G22) | J22: =IFERROR(I22/G22,"")
C23: =IF(B23="","",IFERROR(VLOOKUP(B23,Master_Customers!$A:$D,4,FALSE()),"❌ Not Found")) | I23: =IF(E23="","",E23+E23*H23/100*G23) | J23: =IFERROR(I23/G23,"")
C24: =IF(B24="","",IFERROR(VLOOKUP(B24,Master_Customers!$A:$D,4,FALSE()),"❌ Not Found")) | I24: =IF(E24="","",E24+E24*H24/100*G24) | J24: =IFERROR(I24/G24,"")
C25: =IF(B25="","",IFERROR(VLOOKUP(B25,Master_Customers!$A:$D,4,FALSE()),"❌ Not Found")) | I25: =IF(E25="","",E25+E25*H25/100*G25) | J25: =IFERROR(I25/G25,"")
C26: =IF(B26="","",IFERROR(VLOOKUP(B26,Master_Customers!$A:$D,4,FALSE()),"❌ Not Found")) | I26: =IF(E26="","",E26+E26*H26/100*G26) | J26: =IFERROR(I26/G26,"")
C27: =IF(B27="","",IFERROR(VLOOKUP(B27,Master_Customers!$A:$D,4,FALSE()),"❌ Not Found")) | I27: =IF(E27="","",E27+E27*H27/100*G27) | J27: =IFERROR(I27/G27,"")
... C213: =IF(B213="","",IFERROR(VLOOKUP(B213,Master_Customers!$A:$D,4,FALSE()),"❌ Not Found")) | I213: =IF(E213="","",E213+E213*H213/100*G213) | J213: =IFERROR(I213/G213,"")

Sheet Agent06_Savings
A1: 💰 SAMICIOUS MICROFINANCE — AGENT06 SAVINGS
A2: Agent: Agent06 | Date: 2026-04-12 | Module: Daily Savings Collection
B3: Daily Target (GHC) | E3: Total Collected | H3: Remaining
B4: 5000 | E4: =SUMIF(I9:I1008,"SAVED",E9:E1008) -> 505.66 | H4: =IF(B4-E4<0,"TARGET MET!",B4-E4) -> 4494.34
A5: =IF(B4-E4<=0,"✅ DAILY TARGET ACHIEVED! Great work Agent06!","⏳ Collection in progress — Keep going!") -> ⏳ Collection in progress — Keep going!
A7: 📝 TRANSACTION ENTRY — Enter Account Number and Amount, then click RECORD or press Ctrl+S
A8: Account # | B8: Customer Name | C8: Current Balance | D8: Date | E8: Savings Amount | F8: New Balance | G8: Receipt # | H8: Agent | I8: Status | J8: Saved At
A9: SAM20240400011 | B9: =IF(A9="","",IFERROR(VLOOKUP(A9,Master_Customers!$A:$D,4,FALSE()),"❌ Not Found")) -> Nana Osei | C9: =IF(A9="","",IFERROR(VLOOKUP(A9,Master_Customers!$A:$O,15,FALSE()),"")) -> 3234.02 | D9: 2026-04-12 | E9: 159.27 | F9: =IF(E9="","",IF(C9="","",C9+E9)) -> 3393.29 | H9: Agent06 | I9: SAVED | J9: 2026-04-12
A10: SAM20240400012 | B10: =IF(A10="","",IFERROR(VLOOKUP(A10,Master_Customers!$A:$D,4,FALSE()),"❌ Not Found")) -> Adwoa Amoah | C10: =IF(A10="","",IFERROR(VLOOKUP(A10,Master_Customers!$A:$O,15,FALSE()),"")) -> 1673.16 | D10: 2026-04-12 | E10: 346.39 | F10: =IF(E10="","",IF(C10="","",C10+E10)) -> 2019.55 | H10: Agent06 | I10: SAVED | J10: 2026-04-12
B11: =IF(A11="","",IFERROR(VLOOKUP(A11,Master_Customers!$A:$D,4,FALSE()),"❌ Not Found")) | C11: =IF(A11="","",IFERROR(VLOOKUP(A11,Master_Customers!$A:$O,15,FALSE()),"")) | F11: =IF(E11="","",IF(C11="","",C11+E11))
B12: =IF(A12="","",IFERROR(VLOOKUP(A12,Master_Customers!$A:$D,4,FALSE()),"❌ Not Found")) | C12: =IF(A12="","",IFERROR(VLOOKUP(A12,Master_Customers!$A:$O,15,FALSE()),"")) | F12: =IF(E12="","",IF(C12="","",C12+E12))
B13: =IF(A13="","",IFERROR(VLOOKUP(A13,Master_Customers!$A:$D,4,FALSE()),"❌ Not Found")) | C13: =IF(A13="","",IFERROR(VLOOKUP(A13,Master_Customers!$A:$O,15,FALSE()),"")) | F13: =IF(E13="","",IF(C13="","",C13+E13))
B14: =IF(A14="","",IFERROR(VLOOKUP(A14,Master_Customers!$A:$D,4,FALSE()),"❌ Not Found")) | C14: =IF(A14="","",IFERROR(VLOOKUP(A14,Master_Customers!$A:$O,15,FALSE()),"")) | F14: =IF(E14="","",IF(C14="","",C14+E14))
B15: =IF(A15="","",IFERROR(VLOOKUP(A15,Master_Customers!$A:$D,4,FALSE()),"❌ Not Found")) | C15: =IF(A15="","",IFERROR(VLOOKUP(A15,Master_Customers!$A:$O,15,FALSE()),"")) | F15: =IF(E15="","",IF(C15="","",C15+E15))
B16: =IF(A16="","",IFERROR(VLOOKUP(A16,Master_Customers!$A:$D,4,FALSE()),"❌ Not Found")) | C16: =IF(A16="","",IFERROR(VLOOKUP(A16,Master_Customers!$A:$O,15,FALSE()),"")) | F16: =IF(E16="","",IF(C16="","",C16+E16))
B17: =IF(A17="","",IFERROR(VLOOKUP(A17,Master_Customers!$A:$D,4,FALSE()),"❌ Not Found")) | C17: =IF(A17="","",IFERROR(VLOOKUP(A17,Master_Customers!$A:$O,15,FALSE()),"")) | F17: =IF(E17="","",IF(C17="","",C17+E17))
B18: =IF(A18="","",IFERROR(VLOOKUP(A18,Master_Customers!$A:$D,4,FALSE()),"❌ Not Found")) | C18: =IF(A18="","",IFERROR(VLOOKUP(A18,Master_Customers!$A:$O,15,FALSE()),"")) | F18: =IF(E18="","",IF(C18="","",C18+E18))
B19: =IF(A19="","",IFERROR(VLOOKUP(A19,Master_Customers!$A:$D,4,FALSE()),"❌ Not Found")) | C19: =IF(A19="","",IFERROR(VLOOKUP(A19,Master_Customers!$A:$O,15,FALSE()),"")) | F19: =IF(E19="","",IF(C19="","",C19+E19))
B20: =IF(A20="","",IFERROR(VLOOKUP(A20,Master_Customers!$A:$D,4,FALSE()),"❌ Not Found")) | C20: =IF(A20="","",IFERROR(VLOOKUP(A20,Master_Customers!$A:$O,15,FALSE()),"")) | F20: =IF(E20="","",IF(C20="","",C20+E20))
B21: =IF(A21="","",IFERROR(VLOOKUP(A21,Master_Customers!$A:$D,4,FALSE()),"❌ Not Found")) | C21: =IF(A21="","",IFERROR(VLOOKUP(A21,Master_Customers!$A:$O,15,FALSE()),"")) | F21: =IF(E21="","",IF(C21="","",C21+E21))
B22: =IF(A22="","",IFERROR(VLOOKUP(A22,Master_Customers!$A:$D,4,FALSE()),"❌ Not Found")) | C22: =IF(A22="","",IFERROR(VLOOKUP(A22,Master_Customers!$A:$O,15,FALSE()),"")) | F22: =IF(E22="","",IF(C22="","",C22+E22))
... B1008: =IF(A1008="","",IFERROR(VLOOKUP(A1008,Master_Customers!$A:$D,4,FALSE()),"❌ Not Found")) | C1008: =IF(A1008="","",IFERROR(VLOOKUP(A1008,Master_Customers!$A:$O,15,FALSE()),"")) | F1008: =IF(E1008="","",IF(C1008="","",C1008+E1008))

Sheet Agent06_Withdrawals
A1: 🏧 SAMICIOUS MICROFINANCE — AGENT06 WITHDRAWALS
A2: Agent: Agent06 | Date: 2026-04-12 | Module: Withdrawal Processing
B3: Total Withdrawals | E3: Transactions Count | H3: Avg Withdrawal
B4: =SUMIF(I9:I1008,"SAVED",E9:E1008) -> 0 | E4: =COUNTIF(I9:I1008,"SAVED") -> 0 | H4: =IFERROR(B4/E4,0) -> 0
A5: ⚠️ WITHDRAWALS MODULE — Insufficient balance will be flagged automatically
A7: 📝 TRANSACTION ENTRY — Enter Account Number and Withdrawal Amount
A8: Account # | B8: Customer Name | C8: Available Balance | D8: Date | E8: Withdrawal Amount | F8: New Balance | G8: Authorised By | H8: Agent | I8: Status | J8: Saved At
B9: =IF(A9="","",IFERROR(VLOOKUP(A9,Master_Customers!$A:$D,4,FALSE()),"❌ Not Found")) | C9: =IF(A9="","",IFERROR(VLOOKUP(A9,Master_Customers!$A:$O,15,FALSE()),"")) | F9: =IF(E9="","",IF(C9="","",IF(E9>C9,"INSUFFICIENT FUNDS",C9-E9)))
B10: =IF(A10="","",IFERROR(VLOOKUP(A10,Master_Customers!$A:$D,4,FALSE()),"❌ Not Found")) | C10: =IF(A10="","",IFERROR(VLOOKUP(A10,Master_Customers!$A:$O,15,FALSE()),"")) | F10: =IF(E10="","",IF(C10="","",IF(E10>C10,"INSUFFICIENT FUNDS",C10-E10)))
B11: =IF(A11="","",IFERROR(VLOOKUP(A11,Master_Customers!$A:$D,4,FALSE()),"❌ Not Found")) | C11: =IF(A11="","",IFERROR(VLOOKUP(A11,Master_Customers!$A:$O,15,FALSE()),"")) | F11: =IF(E11="","",IF(C11="","",IF(E11>C11,"INSUFFICIENT FUNDS",C11-E11)))
B12: =IF(A12="","",IFERROR(VLOOKUP(A12,Master_Customers!$A:$D,4,FALSE()),"❌ Not Found")) | C12: =IF(A12="","",IFERROR(VLOOKUP(A12,Master_Customers!$A:$O,15,FALSE()),"")) | F12: =IF(E12="","",IF(C12="","",IF(E12>C12,"INSUFFICIENT FUNDS",C12-E12)))
B13: =IF(A13="","",IFERROR(VLOOKUP(A13,Master_Customers!$A:$D,4,FALSE()),"❌ Not Found")) | C13: =IF(A13="","",IFERROR(VLOOKUP(A13,Master_Customers!$A:$O,15,FALSE()),"")) | F13: =IF(E13="","",IF(C13="","",IF(E13>C13,"INSUFFICIENT FUNDS",C13-E13)))
B14: =IF(A14="","",IFERROR(VLOOKUP(A14,Master_Customers!$A:$D,4,FALSE()),"❌ Not Found")) | C14: =IF(A14="","",IFERROR(VLOOKUP(A14,Master_Customers!$A:$O,15,FALSE()),"")) | F14: =IF(E14="","",IF(C14="","",IF(E14>C14,"INSUFFICIENT FUNDS",C14-E14)))
B15: =IF(A15="","",IFERROR(VLOOKUP(A15,Master_Customers!$A:$D,4,FALSE()),"❌ Not Found")) | C15: =IF(A15="","",IFERROR(VLOOKUP(A15,Master_Customers!$A:$O,15,FALSE()),"")) | F15: =IF(E15="","",IF(C15="","",IF(E15>C15,"INSUFFICIENT FUNDS",C15-E15)))
B16: =IF(A16="","",IFERROR(VLOOKUP(A16,Master_Customers!$A:$D,4,FALSE()),"❌ Not Found")) | C16: =IF(A16="","",IFERROR(VLOOKUP(A16,Master_Customers!$A:$O,15,FALSE()),"")) | F16: =IF(E16="","",IF(C16="","",IF(E16>C16,"INSUFFICIENT FUNDS",C16-E16)))
B17: =IF(A17="","",IFERROR(VLOOKUP(A17,Master_Customers!$A:$D,4,FALSE()),"❌ Not Found")) | C17: =IF(A17="","",IFERROR(VLOOKUP(A17,Master_Customers!$A:$O,15,FALSE()),"")) | F17: =IF(E17="","",IF(C17="","",IF(E17>C17,"INSUFFICIENT FUNDS",C17-E17)))
B18: =IF(A18="","",IFERROR(VLOOKUP(A18,Master_Customers!$A:$D,4,FALSE()),"❌ Not Found")) | C18: =IF(A18="","",IFERROR(VLOOKUP(A18,Master_Customers!$A:$O,15,FALSE()),"")) | F18: =IF(E18="","",IF(C18="","",IF(E18>C18,"INSUFFICIENT FUNDS",C18-E18)))
B19: =IF(A19="","",IFERROR(VLOOKUP(A19,Master_Customers!$A:$D,4,FALSE()),"❌ Not Found")) | C19: =IF(A19="","",IFERROR(VLOOKUP(A19,Master_Customers!$A:$O,15,FALSE()),"")) | F19: =IF(E19="","",IF(C19="","",IF(E19>C19,"INSUFFICIENT FUNDS",C19-E19)))
B20: =IF(A20="","",IFERROR(VLOOKUP(A20,Master_Customers!$A:$D,4,FALSE()),"❌ Not Found")) | C20: =IF(A20="","",IFERROR(VLOOKUP(A20,Master_Customers!$A:$O,15,FALSE()),"")) | F20: =IF(E20="","",IF(C20="","",IF(E20>C20,"INSUFFICIENT FUNDS",C20-E20)))
... B1008: =IF(A1008="","",IFERROR(VLOOKUP(A1008,Master_Customers!$A:$D,4,FALSE()),"❌ Not Found")) | C1008: =IF(A1008="","",IFERROR(VLOOKUP(A1008,Master_Customers!$A:$O,15,FALSE()),"")) | F1008: =IF(E1008="","",IF(C1008="","",IF(E1008>C1008,"INSUFFICIENT FUNDS",C1008-E1008)))

Sheet Agent06_Loans
A1: 🏦 SAMICIOUS MICROFINANCE — AGENT06 LOAN REQUESTS
A2: Agent: Agent06 | Interest Rate: 2.5% p/m (flat) | Min: GHC 100 | Max: GHC 50,000
A4: 🔢 LOAN CALCULATOR
A5: Loan Amount (GHC):
A6: Repayment (months):
A7: Interest Rate (%/m): | B7: 2.5
A8: Total Interest (GHC): | B8: =IF(B5="","",B5*B7/100*B6)
A9: Total Repayable (GHC): | B9: =IF(B5="","",B5+B8)
A10: Monthly Installment (GHC): | B10: =IF(B5="","",B9/B6)
A12: 📋 LOAN REQUEST SUBMISSIONS — Enter details below to submit for manager approval
A13: Loan ID | B13: Account # | C13: Customer Name | D13: Request Date | E13: Loan Amount | F13: Purpose | G13: Months | H13: Rate % | I13: Total Repayable | J13: Monthly Install | K13: Status | L13: Notes
A14: LN202604120014 | B14: SAM20240400011 | C14: Nana Osei | D14: 2026-04-12 | E14: 4080.7 | F14: Business | G14: 9 | H14: 2.5 | I14: 4998.86 | J14: 555.43 | K14: Pending
A15: LN202604120015 | B15: SAM20240400012 | C15: Adwoa Amoah | D15: 2026-04-12 | E15: 8772.6 | F15: Business | G15: 9 | H15: 2.5 | I15: 10746.44 | J15: 1194.05 | K15: Pending
C16: =IF(B16="","",IFERROR(VLOOKUP(B16,Master_Customers!$A:$D,4,FALSE()),"❌ Not Found")) | I16: =IF(E16="","",E16+E16*H16/100*G16) | J16: =IFERROR(I16/G16,"")
C17: =IF(B17="","",IFERROR(VLOOKUP(B17,Master_Customers!$A:$D,4,FALSE()),"❌ Not Found")) | I17: =IF(E17="","",E17+E17*H17/100*G17) | J17: =IFERROR(I17/G17,"")
C18: =IF(B18="","",IFERROR(VLOOKUP(B18,Master_Customers!$A:$D,4,FALSE()),"❌ Not Found")) | I18: =IF(E18="","",E18+E18*H18/100*G18) | J18: =IFERROR(I18/G18,"")
C19: =IF(B19="","",IFERROR(VLOOKUP(B19,Master_Customers!$A:$D,4,FALSE()),"❌ Not Found")) | I19: =IF(E19="","",E19+E19*H19/100*G19) | J19: =IFERROR(I19/G19,"")
C20: =IF(B20="","",IFERROR(VLOOKUP(B20,Master_Customers!$A:$D,4,FALSE()),"❌ Not Found")) | I20: =IF(E20="","",E20+E20*H20/100*G20) | J20: =IFERROR(I20/G20,"")
C21: =IF(B21="","",IFERROR(VLOOKUP(B21,Master_Customers!$A:$D,4,FALSE()),"❌ Not Found")) | I21: =IF(E21="","",E21+E21*H21/100*G21) | J21: =IFERROR(I21/G21,"")
C22: =IF(B22="","",IFERROR(VLOOKUP(B22,Master_Customers!$A:$D,4,FALSE()),"❌ Not Found")) | I22: =IF(E22="","",E22+E22*H22/100*G22) | J22: =IFERROR(I22/G22,"")
C23: =IF(B23="","",IFERROR(VLOOKUP(B23,Master_Customers!$A:$D,4,FALSE()),"❌ Not Found")) | I23: =IF(E23="","",E23+E23*H23/100*G23) | J23: =IFERROR(I23/G23,"")
C24: =IF(B24="","",IFERROR(VLOOKUP(B24,Master_Customers!$A:$D,4,FALSE()),"❌ Not Found")) | I24: =IF(E24="","",E24+E24*H24/100*G24) | J24: =IFERROR(I24/G24,"")
C25: =IF(B25="","",IFERROR(VLOOKUP(B25,Master_Customers!$A:$D,4,FALSE()),"❌ Not Found")) | I25: =IF(E25="","",E25+E25*H25/100*G25) | J25: =IFERROR(I25/G25,"")
C26: =IF(B26="","",IFERROR(VLOOKUP(B26,Master_Customers!$A:$D,4,FALSE()),"❌ Not Found")) | I26: =IF(E26="","",E26+E26*H26/100*G26) | J26: =IFERROR(I26/G26,"")
C27: =IF(B27="","",IFERROR(VLOOKUP(B27,Master_Customers!$A:$D,4,FALSE()),"❌ Not Found")) | I27: =IF(E27="","",E27+E27*H27/100*G27) | J27: =IFERROR(I27/G27,"")
... C213: =IF(B213="","",IFERROR(VLOOKUP(B213,Master_Customers!$A:$D,4,FALSE()),"❌ Not Found")) | I213: =IF(E213="","",E213+E213*H213/100*G213) | J213: =IFERROR(I213/G213,"")

Sheet Agent07_Savings
A1: 💰 SAMICIOUS MICROFINANCE — AGENT07 SAVINGS
A2: Agent: Agent07 | Date: 2026-04-12 | Module: Daily Savings Collection
B3: Daily Target (GHC) | E3: Total Collected | H3: Remaining
B4: 5000 | E4: =SUMIF(I9:I1008,"SAVED",E9:E1008) -> 642.46 | H4: =IF(B4-E4<0,"TARGET MET!",B4-E4) -> 4357.54
A5: =IF(B4-E4<=0,"✅ DAILY TARGET ACHIEVED! Great work Agent07!","⏳ Collection in progress — Keep going!") -> ⏳ Collection in progress — Keep going!
A7: 📝 TRANSACTION ENTRY — Enter Account Number and Amount, then click RECORD or press Ctrl+S
A8: Account # | B8: Customer Name | C8: Current Balance | D8: Date | E8: Savings Amount | F8: New Balance | G8: Receipt # | H8: Agent | I8: Status | J8: Saved At
A9: SAM20240500013 | B9: =IF(A9="","",IFERROR(VLOOKUP(A9,Master_Customers!$A:$D,4,FALSE()),"❌ Not Found")) -> Kweku Nyarko | C9: =IF(A9="","",IFERROR(VLOOKUP(A9,Master_Customers!$A:$O,15,FALSE()),"")) -> 3582.59 | D9: 2026-04-12 | E9: 470.53 | F9: =IF(E9="","",IF(C9="","",C9+E9)) -> 4053.12 | H9: Agent07 | I9: SAVED | J9: 2026-04-12
A10: SAM20240500014 | B10: =IF(A10="","",IFERROR(VLOOKUP(A10,Master_Customers!$A:$D,4,FALSE()),"❌ Not Found")) -> Abiba Seidu | C10: =IF(A10="","",IFERROR(VLOOKUP(A10,Master_Customers!$A:$O,15,FALSE()),"")) -> 2587.85 | D10: 2026-04-12 | E10: 171.93 | F10: =IF(E10="","",IF(C10="","",C10+E10)) -> 2759.78 | H10: Agent07 | I10: SAVED | J10: 2026-04-12
B11: =IF(A11="","",IFERROR(VLOOKUP(A11,Master_Customers!$A:$D,4,FALSE()),"❌ Not Found")) | C11: =IF(A11="","",IFERROR(VLOOKUP(A11,Master_Customers!$A:$O,15,FALSE()),"")) | F11: =IF(E11="","",IF(C11="","",C11+E11))
B12: =IF(A12="","",IFERROR(VLOOKUP(A12,Master_Customers!$A:$D,4,FALSE()),"❌ Not Found")) | C12: =IF(A12="","",IFERROR(VLOOKUP(A12,Master_Customers!$A:$O,15,FALSE()),"")) | F12: =IF(E12="","",IF(C12="","",C12+E12))
B13: =IF(A13="","",IFERROR(VLOOKUP(A13,Master_Customers!$A:$D,4,FALSE()),"❌ Not Found")) | C13: =IF(A13="","",IFERROR(VLOOKUP(A13,Master_Customers!$A:$O,15,FALSE()),"")) | F13: =IF(E13="","",IF(C13="","",C13+E13))
B14: =IF(A14="","",IFERROR(VLOOKUP(A14,Master_Customers!$A:$D,4,FALSE()),"❌ Not Found")) | C14: =IF(A14="","",IFERROR(VLOOKUP(A14,Master_Customers!$A:$O,15,FALSE()),"")) | F14: =IF(E14="","",IF(C14="","",C14+E14))
B15: =IF(A15="","",IFERROR(VLOOKUP(A15,Master_Customers!$A:$D,4,FALSE()),"❌ Not Found")) | C15: =IF(A15="","",IFERROR(VLOOKUP(A15,Master_Customers!$A:$O,15,FALSE()),"")) | F15: =IF(E15="","",IF(C15="","",C15+E15))
B16: =IF(A16="","",IFERROR(VLOOKUP(A16,Master_Customers!$A:$D,4,FALSE()),"❌ Not Found")) | C16: =IF(A16="","",IFERROR(VLOOKUP(A16,Master_Customers!$A:$O,15,FALSE()),"")) | F16: =IF(E16="","",IF(C16="","",C16+E16))
B17: =IF(A17="","",IFERROR(VLOOKUP(A17,Master_Customers!$A:$D,4,FALSE()),"❌ Not Found")) | C17: =IF(A17="","",IFERROR(VLOOKUP(A17,Master_Customers!$A:$O,15,FALSE()),"")) | F17: =IF(E17="","",IF(C17="","",C17+E17))
B18: =IF(A18="","",IFERROR(VLOOKUP(A18,Master_Customers!$A:$D,4,FALSE()),"❌ Not Found")) | C18: =IF(A18="","",IFERROR(VLOOKUP(A18,Master_Customers!$A:$O,15,FALSE()),"")) | F18: =IF(E18="","",IF(C18="","",C18+E18))
B19: =IF(A19="","",IFERROR(VLOOKUP(A19,Master_Customers!$A:$D,4,FALSE()),"❌ Not Found")) | C19: =IF(A19="","",IFERROR(VLOOKUP(A19,Master_Customers!$A:$O,15,FALSE()),"")) | F19: =IF(E19="","",IF(C19="","",C19+E19))
B20: =IF(A20="","",IFERROR(VLOOKUP(A20,Master_Customers!$A:$D,4,FALSE()),"❌ Not Found")) | C20: =IF(A20="","",IFERROR(VLOOKUP(A20,Master_Customers!$A:$O,15,FALSE()),"")) | F20: =IF(E20="","",IF(C20="","",C20+E20))
B21: =IF(A21="","",IFERROR(VLOOKUP(A21,Master_Customers!$A:$D,4,FALSE()),"❌ Not Found")) | C21: =IF(A21="","",IFERROR(VLOOKUP(A21,Master_Customers!$A:$O,15,FALSE()),"")) | F21: =IF(E21="","",IF(C21="","",C21+E21))
B22: =IF(A22="","",IFERROR(VLOOKUP(A22,Master_Customers!$A:$D,4,FALSE()),"❌ Not Found")) | C22: =IF(A22="","",IFERROR(VLOOKUP(A22,Master_Customers!$A:$O,15,FALSE()),"")) | F22: =IF(E22="","",IF(C22="","",C22+E22))
... B1008: =IF(A1008="","",IFERROR(VLOOKUP(A1008,Master_Customers!$A:$D,4,FALSE()),"❌ Not Found")) | C1008: =IF(A1008="","",IFERROR(VLOOKUP(A1008,Master_Customers!$A:$O,15,FALSE()),"")) | F1008: =IF(E1008="","",IF(C1008="","",C1008+E1008))

Sheet Agent07_Withdrawals
A1: 🏧 SAMICIOUS MICROFINANCE — AGENT07 WITHDRAWALS
A2: Agent: Agent07 | Date: 2026-04-12 | Module: Withdrawal Processing
B3: Total Withdrawals | E3: Transactions Count | H3: Avg Withdrawal
B4: =SUMIF(I9:I1008,"SAVED",E9:E1008) -> 0 | E4: =COUNTIF(I9:I1008,"SAVED") -> 0 | H4: =IFERROR(B4/E4,0) -> 0
A5: ⚠️ WITHDRAWALS MODULE — Insufficient balance will be flagged automatically
A7: 📝 TRANSACTION ENTRY — Enter Account Number and Withdrawal Amount
A8: Account # | B8: Customer Name | C8: Available Balance | D8: Date | E8: Withdrawal Amount | F8: New Balance | G8: Authorised By | H8: Agent | I8: Status | J8: Saved At
B9: =IF(A9="","",IFERROR(VLOOKUP(A9,Master_Customers!$A:$D,4,FALSE()),"❌ Not Found")) | C9: =IF(A9="","",IFERROR(VLOOKUP(A9,Master_Customers!$A:$O,15,FALSE()),"")) | F9: =IF(E9="","",IF(C9="","",IF(E9>C9,"INSUFFICIENT FUNDS",C9-E9)))
B10: =IF(A10="","",IFERROR(VLOOKUP(A10,Master_Customers!$A:$D,4,FALSE()),"❌ Not Found")) | C10: =IF(A10="","",IFERROR(VLOOKUP(A10,Master_Customers!$A:$O,15,FALSE()),"")) | F10: =IF(E10="","",IF(C10="","",IF(E10>C10,"INSUFFICIENT FUNDS",C10-E10)))
B11: =IF(A11="","",IFERROR(VLOOKUP(A11,Master_Customers!$A:$D,4,FALSE()),"❌ Not Found")) | C11: =IF(A11="","",IFERROR(VLOOKUP(A11,Master_Customers!$A:$O,15,FALSE()),"")) | F11: =IF(E11="","",IF(C11="","",IF(E11>C11,"INSUFFICIENT FUNDS",C11-E11)))
B12: =IF(A12="","",IFERROR(VLOOKUP(A12,Master_Customers!$A:$D,4,FALSE()),"❌ Not Found")) | C12: =IF(A12="","",IFERROR(VLOOKUP(A12,Master_Customers!$A:$O,15,FALSE()),"")) | F12: =IF(E12="","",IF(C12="","",IF(E12>C12,"INSUFFICIENT FUNDS",C12-E12)))
B13: =IF(A13="","",IFERROR(VLOOKUP(A13,Master_Customers!$A:$D,4,FALSE()),"❌ Not Found")) | C13: =IF(A13="","",IFERROR(VLOOKUP(A13,Master_Customers!$A:$O,15,FALSE()),"")) | F13: =IF(E13="","",IF(C13="","",IF(E13>C13,"INSUFFICIENT FUNDS",C13-E13)))
B14: =IF(A14="","",IFERROR(VLOOKUP(A14,Master_Customers!$A:$D,4,FALSE()),"❌ Not Found")) | C14: =IF(A14="","",IFERROR(VLOOKUP(A14,Master_Customers!$A:$O,15,FALSE()),"")) | F14: =IF(E14="","",IF(C14="","",IF(E14>C14,"INSUFFICIENT FUNDS",C14-E14)))
B15: =IF(A15="","",IFERROR(VLOOKUP(A15,Master_Customers!$A:$D,4,FALSE()),"❌ Not Found")) | C15: =IF(A15="","",IFERROR(VLOOKUP(A15,Master_Customers!$A:$O,15,FALSE()),"")) | F15: =IF(E15="","",IF(C15="","",IF(E15>C15,"INSUFFICIENT FUNDS",C15-E15)))
B16: =IF(A16="","",IFERROR(VLOOKUP(A16,Master_Customers!$A:$D,4,FALSE()),"❌ Not Found")) | C16: =IF(A16="","",IFERROR(VLOOKUP(A16,Master_Customers!$A:$O,15,FALSE()),"")) | F16: =IF(E16="","",IF(C16="","",IF(E16>C16,"INSUFFICIENT FUNDS",C16-E16)))
B17: =IF(A17="","",IFERROR(VLOOKUP(A17,Master_Customers!$A:$D,4,FALSE()),"❌ Not Found")) | C17: =IF(A17="","",IFERROR(VLOOKUP(A17,Master_Customers!$A:$O,15,FALSE()),"")) | F17: =IF(E17="","",IF(C17="","",IF(E17>C17,"INSUFFICIENT FUNDS",C17-E17)))
B18: =IF(A18="","",IFERROR(VLOOKUP(A18,Master_Customers!$A:$D,4,FALSE()),"❌ Not Found")) | C18: =IF(A18="","",IFERROR(VLOOKUP(A18,Master_Customers!$A:$O,15,FALSE()),"")) | F18: =IF(E18="","",IF(C18="","",IF(E18>C18,"INSUFFICIENT FUNDS",C18-E18)))
B19: =IF(A19="","",IFERROR(VLOOKUP(A19,Master_Customers!$A:$D,4,FALSE()),"❌ Not Found")) | C19: =IF(A19="","",IFERROR(VLOOKUP(A19,Master_Customers!$A:$O,15,FALSE()),"")) | F19: =IF(E19="","",IF(C19="","",IF(E19>C19,"INSUFFICIENT FUNDS",C19-E19)))
B20: =IF(A20="","",IFERROR(VLOOKUP(A20,Master_Customers!$A:$D,4,FALSE()),"❌ Not Found")) | C20: =IF(A20="","",IFERROR(VLOOKUP(A20,Master_Customers!$A:$O,15,FALSE()),"")) | F20: =IF(E20="","",IF(C20="","",IF(E20>C20,"INSUFFICIENT FUNDS",C20-E20)))
... B1008: =IF(A1008="","",IFERROR(VLOOKUP(A1008,Master_Customers!$A:$D,4,FALSE()),"❌ Not Found")) | C1008: =IF(A1008="","",IFERROR(VLOOKUP(A1008,Master_Customers!$A:$O,15,FALSE()),"")) | F1008: =IF(E1008="","",IF(C1008="","",IF(E1008>C1008,"INSUFFICIENT FUNDS",C1008-E1008)))

Sheet Agent07_Loans
A1: 🏦 SAMICIOUS MICROFINANCE — AGENT07 LOAN REQUESTS
A2: Agent: Agent07 | Interest Rate: 2.5% p/m (flat) | Min: GHC 100 | Max: GHC 50,000
A4: 🔢 LOAN CALCULATOR
A5: Loan Amount (GHC):
A6: Repayment (months):
A7: Interest Rate (%/m): | B7: 2.5
A8: Total Interest (GHC): | B8: =IF(B5="","",B5*B7/100*B6)
A9: Total Repayable (GHC): | B9: =IF(B5="","",B5+B8)
A10: Monthly Installment (GHC): | B10: =IF(B5="","",B9/B6)
A12: 📋 LOAN REQUEST SUBMISSIONS — Enter details below to submit for manager approval
A13: Loan ID | B13: Account # | C13: Customer Name | D13: Request Date | E13: Loan Amount | F13: Purpose | G13: Months | H13: Rate % | I13: Total Repayable | J13: Monthly Install | K13: Status | L13: Notes
A14: LN202604120014 | B14: SAM20240500013 | C14: Kweku Nyarko | D14: 2026-04-12 | E14: 9642.93 | F14: Business | G14: 6 | H14: 2.5 | I14: 11089.37 | J14: 1848.23 | K14: Pending
A15: LN202604120015 | B15: SAM20240500014 | C15: Abiba Seidu | D15: 2026-04-12 | E15: 2660.43 | F15: Business | G15: 12 | H15: 2.5 | I15: 3458.56 | J15: 288.21 | K15: Pending
C16: =IF(B16="","",IFERROR(VLOOKUP(B16,Master_Customers!$A:$D,4,FALSE()),"❌ Not Found")) | I16: =IF(E16="","",E16+E16*H16/100*G16) | J16: =IFERROR(I16/G16,"")
C17: =IF(B17="","",IFERROR(VLOOKUP(B17,Master_Customers!$A:$D,4,FALSE()),"❌ Not Found")) | I17: =IF(E17="","",E17+E17*H17/100*G17) | J17: =IFERROR(I17/G17,"")
C18: =IF(B18="","",IFERROR(VLOOKUP(B18,Master_Customers!$A:$D,4,FALSE()),"❌ Not Found")) | I18: =IF(E18="","",E18+E18*H18/100*G18) | J18: =IFERROR(I18/G18,"")
C19: =IF(B19="","",IFERROR(VLOOKUP(B19,Master_Customers!$A:$D,4,FALSE()),"❌ Not Found")) | I19: =IF(E19="","",E19+E19*H19/100*G19) | J19: =IFERROR(I19/G19,"")
C20: =IF(B20="","",IFERROR(VLOOKUP(B20,Master_Customers!$A:$D,4,FALSE()),"❌ Not Found")) | I20: =IF(E20="","",E20+E20*H20/100*G20) | J20: =IFERROR(I20/G20,"")
C21: =IF(B21="","",IFERROR(VLOOKUP(B21,Master_Customers!$A:$D,4,FALSE()),"❌ Not Found")) | I21: =IF(E21="","",E21+E21*H21/100*G21) | J21: =IFERROR(I21/G21,"")
C22: =IF(B22="","",IFERROR(VLOOKUP(B22,Master_Customers!$A:$D,4,FALSE()),"❌ Not Found")) | I22: =IF(E22="","",E22+E22*H22/100*G22) | J22: =IFERROR(I22/G22,"")
C23: =IF(B23="","",IFERROR(VLOOKUP(B23,Master_Customers!$A:$D,4,FALSE()),"❌ Not Found")) | I23: =IF(E23="","",E23+E23*H23/100*G23) | J23: =IFERROR(I23/G23,"")
C24: =IF(B24="","",IFERROR(VLOOKUP(B24,Master_Customers!$A:$D,4,FALSE()),"❌ Not Found")) | I24: =IF(E24="","",E24+E24*H24/100*G24) | J24: =IFERROR(I24/G24,"")
C25: =IF(B25="","",IFERROR(VLOOKUP(B25,Master_Customers!$A:$D,4,FALSE()),"❌ Not Found")) | I25: =IF(E25="","",E25+E25*H25/100*G25) | J25: =IFERROR(I25/G25,"")
C26: =IF(B26="","",IFERROR(VLOOKUP(B26,Master_Customers!$A:$D,4,FALSE()),"❌ Not Found")) | I26: =IF(E26="","",E26+E26*H26/100*G26) | J26: =IFERROR(I26/G26,"")
C27: =IF(B27="","",IFERROR(VLOOKUP(B27,Master_Customers!$A:$D,4,FALSE()),"❌ Not Found")) | I27: =IF(E27="","",E27+E27*H27/100*G27) | J27: =IFERROR(I27/G27,"")
... C213: =IF(B213="","",IFERROR(VLOOKUP(B213,Master_Customers!$A:$D,4,FALSE()),"❌ Not Found")) | I213: =IF(E213="","",E213+E213*H213/100*G213) | J213: =IFERROR(I213/G213,"")

Sheet Agent08_Savings
A1: 💰 SAMICIOUS MICROFINANCE — AGENT08 SAVINGS
A2: Agent: Agent08 | Date: 2026-04-12 | Module: Daily Savings Collection
B3: Daily Target (GHC) | E3: Total Collected | H3: Remaining
B4: 5000 | E4: =SUMIF(I9:I1008,"SAVED",E9:E1008) -> 641.53 | H4: =IF(B4-E4<0,"TARGET MET!",B4-E4) -> 4358.47
A5: =IF(B4-E4<=0,"✅ DAILY TARGET ACHIEVED! Great work Agent08!","⏳ Collection in progress — Keep going!") -> ⏳ Collection in progress — Keep going!
A7: 📝 TRANSACTION ENTRY — Enter Account Number and Amount, then click RECORD or press Ctrl+S
A8: Account # | B8: Customer Name | C8: Current Balance | D8: Date | E8: Savings Amount | F8: New Balance | G8: Receipt # | H8: Agent | I8: Status | J8: Saved At
A9: SAM20240500015 | B9: =IF(A9="","",IFERROR(VLOOKUP(A9,Master_Customers!$A:$D,4,FALSE()),"❌ Not Found")) -> Fiifi Ghartey | C9: =IF(A9="","",IFERROR(VLOOKUP(A9,Master_Customers!$A:$O,15,FALSE()),"")) -> 5621.14 | D9: 2026-04-12 | E9: 330.29 | F9: =IF(E9="","",IF(C9="","",C9+E9)) -> 5951.43 | H9: Agent08 | I9: SAVED | J9: 2026-04-12
A10: SAM20240500016 | B10: =IF(A10="","",IFERROR(VLOOKUP(A10,Master_Customers!$A:$D,4,FALSE()),"❌ Not Found")) -> Akua Bonsu | C10: =IF(A10="","",IFERROR(VLOOKUP(A10,Master_Customers!$A:$O,15,FALSE()),"")) -> 3721.04 | D10: 2026-04-12 | E10: 311.24 | F10: =IF(E10="","",IF(C10="","",C10+E10)) -> 4032.28 | H10: Agent08 | I10: SAVED | J10: 2026-04-12
B11: =IF(A11="","",IFERROR(VLOOKUP(A11,Master_Customers!$A:$D,4,FALSE()),"❌ Not Found")) | C11: =IF(A11="","",IFERROR(VLOOKUP(A11,Master_Customers!$A:$O,15,FALSE()),"")) | F11: =IF(E11="","",IF(C11="","",C11+E11))
B12: =IF(A12="","",IFERROR(VLOOKUP(A12,Master_Customers!$A:$D,4,FALSE()),"❌ Not Found")) | C12: =IF(A12="","",IFERROR(VLOOKUP(A12,Master_Customers!$A:$O,15,FALSE()),"")) | F12: =IF(E12="","",IF(C12="","",C12+E12))
B13: =IF(A13="","",IFERROR(VLOOKUP(A13,Master_Customers!$A:$D,4,FALSE()),"❌ Not Found")) | C13: =IF(A13="","",IFERROR(VLOOKUP(A13,Master_Customers!$A:$O,15,FALSE()),"")) | F13: =IF(E13="","",IF(C13="","",C13+E13))
B14: =IF(A14="","",IFERROR(VLOOKUP(A14,Master_Customers!$A:$D,4,FALSE()),"❌ Not Found")) | C14: =IF(A14="","",IFERROR(VLOOKUP(A14,Master_Customers!$A:$O,15,FALSE()),"")) | F14: =IF(E14="","",IF(C14="","",C14+E14))
B15: =IF(A15="","",IFERROR(VLOOKUP(A15,Master_Customers!$A:$D,4,FALSE()),"❌ Not Found")) | C15: =IF(A15="","",IFERROR(VLOOKUP(A15,Master_Customers!$A:$O,15,FALSE()),"")) | F15: =IF(E15="","",IF(C15="","",C15+E15))
B16: =IF(A16="","",IFERROR(VLOOKUP(A16,Master_Customers!$A:$D,4,FALSE()),"❌ Not Found")) | C16: =IF(A16="","",IFERROR(VLOOKUP(A16,Master_Customers!$A:$O,15,FALSE()),"")) | F16: =IF(E16="","",IF(C16="","",C16+E16))
B17: =IF(A17="","",IFERROR(VLOOKUP(A17,Master_Customers!$A:$D,4,FALSE()),"❌ Not Found")) | C17: =IF(A17="","",IFERROR(VLOOKUP(A17,Master_Customers!$A:$O,15,FALSE()),"")) | F17: =IF(E17="","",IF(C17="","",C17+E17))
B18: =IF(A18="","",IFERROR(VLOOKUP(A18,Master_Customers!$A:$D,4,FALSE()),"❌ Not Found")) | C18: =IF(A18="","",IFERROR(VLOOKUP(A18,Master_Customers!$A:$O,15,FALSE()),"")) | F18: =IF(E18="","",IF(C18="","",C18+E18))
B19: =IF(A19="","",IFERROR(VLOOKUP(A19,Master_Customers!$A:$D,4,FALSE()),"❌ Not Found")) | C19: =IF(A19="","",IFERROR(VLOOKUP(A19,Master_Customers!$A:$O,15,FALSE()),"")) | F19: =IF(E19="","",IF(C19="","",C19+E19))
B20: =IF(A20="","",IFERROR(VLOOKUP(A20,Master_Customers!$A:$D,4,FALSE()),"❌ Not Found")) | C20: =IF(A20="","",IFERROR(VLOOKUP(A20,Master_Customers!$A:$O,15,FALSE()),"")) | F20: =IF(E20="","",IF(C20="","",C20+E20))
B21: =IF(A21="","",IFERROR(VLOOKUP(A21,Master_Customers!$A:$D,4,FALSE()),"❌ Not Found")) | C21: =IF(A21="","",IFERROR(VLOOKUP(A21,Master_Customers!$A:$O,15,FALSE()),"")) | F21: =IF(E21="","",IF(C21="","",C21+E21))
B22: =IF(A22="","",IFERROR(VLOOKUP(A22,Master_Customers!$A:$D,4,FALSE()),"❌ Not Found")) | C22: =IF(A22="","",IFERROR(VLOOKUP(A22,Master_Customers!$A:$O,15,FALSE()),"")) | F22: =IF(E22="","",IF(C22="","",C22+E22))
... B1008: =IF(A1008="","",IFERROR(VLOOKUP(A1008,Master_Customers!$A:$D,4,FALSE()),"❌ Not Found")) | C1008: =IF(A1008="","",IFERROR(VLOOKUP(A1008,Master_Customers!$A:$O,15,FALSE()),"")) | F1008: =IF(E1008="","",IF(C1008="","",C1008+E1008))

Sheet Agent08_Withdrawals
A1: 🏧 SAMICIOUS MICROFINANCE — AGENT08 WITHDRAWALS
A2: Agent: Agent08 | Date: 2026-04-12 | Module: Withdrawal Processing
B3: Total Withdrawals | E3: Transactions Count | H3: Avg Withdrawal
B4: =SUMIF(I9:I1008,"SAVED",E9:E1008) -> 0 | E4: =COUNTIF(I9:I1008,"SAVED") -> 0 | H4: =IFERROR(B4/E4,0) -> 0
A5: ⚠️ WITHDRAWALS MODULE — Insufficient balance will be flagged automatically
A7: 📝 TRANSACTION ENTRY — Enter Account Number and Withdrawal Amount
A8: Account # | B8: Customer Name | C8: Available Balance | D8: Date | E8: Withdrawal Amount | F8: New Balance | G8: Authorised By | H8: Agent | I8: Status | J8: Saved At
B9: =IF(A9="","",IFERROR(VLOOKUP(A9,Master_Customers!$A:$D,4,FALSE()),"❌ Not Found")) | C9: =IF(A9="","",IFERROR(VLOOKUP(A9,Master_Customers!$A:$O,15,FALSE()),"")) | F9: =IF(E9="","",IF(C9="","",IF(E9>C9,"INSUFFICIENT FUNDS",C9-E9)))
B10: =IF(A10="","",IFERROR(VLOOKUP(A10,Master_Customers!$A:$D,4,FALSE()),"❌ Not Found")) | C10: =IF(A10="","",IFERROR(VLOOKUP(A10,Master_Customers!$A:$O,15,FALSE()),"")) | F10: =IF(E10="","",IF(C10="","",IF(E10>C10,"INSUFFICIENT FUNDS",C10-E10)))
B11: =IF(A11="","",IFERROR(VLOOKUP(A11,Master_Customers!$A:$D,4,FALSE()),"❌ Not Found")) | C11: =IF(A11="","",IFERROR(VLOOKUP(A11,Master_Customers!$A:$O,15,FALSE()),"")) | F11: =IF(E11="","",IF(C11="","",IF(E11>C11,"INSUFFICIENT FUNDS",C11-E11)))
B12: =IF(A12="","",IFERROR(VLOOKUP(A12,Master_Customers!$A:$D,4,FALSE()),"❌ Not Found")) | C12: =IF(A12="","",IFERROR(VLOOKUP(A12,Master_Customers!$A:$O,15,FALSE()),"")) | F12: =IF(E12="","",IF(C12="","",IF(E12>C12,"INSUFFICIENT FUNDS",C12-E12)))
B13: =IF(A13="","",IFERROR(VLOOKUP(A13,Master_Customers!$A:$D,4,FALSE()),"❌ Not Found")) | C13: =IF(A13="","",IFERROR(VLOOKUP(A13,Master_Customers!$A:$O,15,FALSE()),"")) | F13: =IF(E13="","",IF(C13="","",IF(E13>C13,"INSUFFICIENT FUNDS",C13-E13)))
B14: =IF(A14="","",IFERROR(VLOOKUP(A14,Master_Customers!$A:$D,4,FALSE()),"❌ Not Found")) | C14: =IF(A14="","",IFERROR(VLOOKUP(A14,Master_Customers!$A:$O,15,FALSE()),"")) | F14: =IF(E14="","",IF(C14="","",IF(E14>C14,"INSUFFICIENT FUNDS",C14-E14)))
B15: =IF(A15="","",IFERROR(VLOOKUP(A15,Master_Customers!$A:$D,4,FALSE()),"❌ Not Found")) | C15: =IF(A15="","",IFERROR(VLOOKUP(A15,Master_Customers!$A:$O,15,FALSE()),"")) | F15: =IF(E15="","",IF(C15="","",IF(E15>C15,"INSUFFICIENT FUNDS",C15-E15)))
B16: =IF(A16="","",IFERROR(VLOOKUP(A16,Master_Customers!$A:$D,4,FALSE()),"❌ Not Found")) | C16: =IF(A16="","",IFERROR(VLOOKUP(A16,Master_Customers!$A:$O,15,FALSE()),"")) | F16: =IF(E16="","",IF(C16="","",IF(E16>C16,"INSUFFICIENT FUNDS",C16-E16)))
B17: =IF(A17="","",IFERROR(VLOOKUP(A17,Master_Customers!$A:$D,4,FALSE()),"❌ Not Found")) | C17: =IF(A17="","",IFERROR(VLOOKUP(A17,Master_Customers!$A:$O,15,FALSE()),"")) | F17: =IF(E17="","",IF(C17="","",IF(E17>C17,"INSUFFICIENT FUNDS",C17-E17)))
B18: =IF(A18="","",IFERROR(VLOOKUP(A18,Master_Customers!$A:$D,4,FALSE()),"❌ Not Found")) | C18: =IF(A18="","",IFERROR(VLOOKUP(A18,Master_Customers!$A:$O,15,FALSE()),"")) | F18: =IF(E18="","",IF(C18="","",IF(E18>C18,"INSUFFICIENT FUNDS",C18-E18)))
B19: =IF(A19="","",IFERROR(VLOOKUP(A19,Master_Customers!$A:$D,4,FALSE()),"❌ Not Found")) | C19: =IF(A19="","",IFERROR(VLOOKUP(A19,Master_Customers!$A:$O,15,FALSE()),"")) | F19: =IF(E19="","",IF(C19="","",IF(E19>C19,"INSUFFICIENT FUNDS",C19-E19)))
B20: =IF(A20="","",IFERROR(VLOOKUP(A20,Master_Customers!$A:$D,4,FALSE()),"❌ Not Found")) | C20: =IF(A20="","",IFERROR(VLOOKUP(A20,Master_Customers!$A:$O,15,FALSE()),"")) | F20: =IF(E20="","",IF(C20="","",IF(E20>C20,"INSUFFICIENT FUNDS",C20-E20)))
... B1008: =IF(A1008="","",IFERROR(VLOOKUP(A1008,Master_Customers!$A:$D,4,FALSE()),"❌ Not Found")) | C1008: =IF(A1008="","",IFERROR(VLOOKUP(A1008,Master_Customers!$A:$O,15,FALSE()),"")) | F1008: =IF(E1008="","",IF(C1008="","",IF(E1008>C1008,"INSUFFICIENT FUNDS",C1008-E1008)))

Sheet Agent08_Loans
A1: 🏦 SAMICIOUS MICROFINANCE — AGENT08 LOAN REQUESTS
A2: Agent: Agent08 | Interest Rate: 2.5% p/m (flat) | Min: GHC 100 | Max: GHC 50,000
A4: 🔢 LOAN CALCULATOR
A5: Loan Amount (GHC):
A6: Repayment (months):
A7: Interest Rate (%/m): | B7: 2.5
A8: Total Interest (GHC): | B8: =IF(B5="","",B5*B7/100*B6)
A9: Total Repayable (GHC): | B9: =IF(B5="","",B5+B8)
A10: Monthly Installment (GHC): | B10: =IF(B5="","",B9/B6)
A12: 📋 LOAN REQUEST SUBMISSIONS — Enter details below to submit for manager approval
A13: Loan ID | B13: Account # | C13: Customer Name | D13: Request Date | E13: Loan Amount | F13: Purpose | G13: Months | H13: Rate % | I13: Total Repayable | J13: Monthly Install | K13: Status | L13: Notes
A14: LN202604120014 | B14: SAM20240500015 | C14: Fiifi Ghartey | D14: 2026-04-12 | E14: 8530.95 | F14: Business | G14: 12 | H14: 2.5 | I14: 11090.24 | J14: 924.19 | K14: Pending
A15: LN202604120015 | B15: SAM20240500016 | C15: Akua Bonsu | D15: 2026-04-12 | E15: 9334.84 | F15: Business | G15: 9 | H15: 2.5 | I15: 11435.18 | J15: 1270.58 | K15: Pending
C16: =IF(B16="","",IFERROR(VLOOKUP(B16,Master_Customers!$A:$D,4,FALSE()),"❌ Not Found")) | I16: =IF(E16="","",E16+E16*H16/100*G16) | J16: =IFERROR(I16/G16,"")
C17: =IF(B17="","",IFERROR(VLOOKUP(B17,Master_Customers!$A:$D,4,FALSE()),"❌ Not Found")) | I17: =IF(E17="","",E17+E17*H17/100*G17) | J17: =IFERROR(I17/G17,"")
C18: =IF(B18="","",IFERROR(VLOOKUP(B18,Master_Customers!$A:$D,4,FALSE()),"❌ Not Found")) | I18: =IF(E18="","",E18+E18*H18/100*G18) | J18: =IFERROR(I18/G18,"")
C19: =IF(B19="","",IFERROR(VLOOKUP(B19,Master_Customers!$A:$D,4,FALSE()),"❌ Not Found")) | I19: =IF(E19="","",E19+E19*H19/100*G19) | J19: =IFERROR(I19/G19,"")
C20: =IF(B20="","",IFERROR(VLOOKUP(B20,Master_Customers!$A:$D,4,FALSE()),"❌ Not Found")) | I20: =IF(E20="","",E20+E20*H20/100*G20) | J20: =IFERROR(I20/G20,"")
C21: =IF(B21="","",IFERROR(VLOOKUP(B21,Master_Customers!$A:$D,4,FALSE()),"❌ Not Found")) | I21: =IF(E21="","",E21+E21*H21/100*G21) | J21: =IFERROR(I21/G21,"")
C22: =IF(B22="","",IFERROR(VLOOKUP(B22,Master_Customers!$A:$D,4,FALSE()),"❌ Not Found")) | I22: =IF(E22="","",E22+E22*H22/100*G22) | J22: =IFERROR(I22/G22,"")
C23: =IF(B23="","",IFERROR(VLOOKUP(B23,Master_Customers!$A:$D,4,FALSE()),"❌ Not Found")) | I23: =IF(E23="","",E23+E23*H23/100*G23) | J23: =IFERROR(I23/G23,"")
C24: =IF(B24="","",IFERROR(VLOOKUP(B24,Master_Customers!$A:$D,4,FALSE()),"❌ Not Found")) | I24: =IF(E24="","",E24+E24*H24/100*G24) | J24: =IFERROR(I24/G24,"")
C25: =IF(B25="","",IFERROR(VLOOKUP(B25,Master_Customers!$A:$D,4,FALSE()),"❌ Not Found")) | I25: =IF(E25="","",E25+E25*H25/100*G25) | J25: =IFERROR(I25/G25,"")
C26: =IF(B26="","",IFERROR(VLOOKUP(B26,Master_Customers!$A:$D,4,FALSE()),"❌ Not Found")) | I26: =IF(E26="","",E26+E26*H26/100*G26) | J26: =IFERROR(I26/G26,"")
C27: =IF(B27="","",IFERROR(VLOOKUP(B27,Master_Customers!$A:$D,4,FALSE()),"❌ Not Found")) | I27: =IF(E27="","",E27+E27*H27/100*G27) | J27: =IFERROR(I27/G27,"")
... C213: =IF(B213="","",IFERROR(VLOOKUP(B213,Master_Customers!$A:$D,4,FALSE()),"❌ Not Found")) | I213: =IF(E213="","",E213+E213*H213/100*G213) | J213: =IFERROR(I213/G213,"")

Sheet Agent09_Savings
A1: 💰 SAMICIOUS MICROFINANCE — AGENT09 SAVINGS
A2: Agent: Agent09 | Date: 2026-04-12 | Module: Daily Savings Collection
B3: Daily Target (GHC) | E3: Total Collected | H3: Remaining
B4: 5000 | E4: =SUMIF(I9:I1008,"SAVED",E9:E1008) -> 627.62 | H4: =IF(B4-E4<0,"TARGET MET!",B4-E4) -> 4372.38
A5: =IF(B4-E4<=0,"✅ DAILY TARGET ACHIEVED! Great work Agent09!","⏳ Collection in progress — Keep going!") -> ⏳ Collection in progress — Keep going!
A7: 📝 TRANSACTION ENTRY — Enter Account Number and Amount, then click RECORD or press Ctrl+S
A8: Account # | B8: Customer Name | C8: Current Balance | D8: Date | E8: Savings Amount | F8: New Balance | G8: Receipt # | H8: Agent | I8: Status | J8: Saved At
A9: SAM20240600017 | B9: =IF(A9="","",IFERROR(VLOOKUP(A9,Master_Customers!$A:$D,4,FALSE()),"❌ Not Found")) -> Kwasi Adusei | C9: =IF(A9="","",IFERROR(VLOOKUP(A9,Master_Customers!$A:$O,15,FALSE()),"")) -> 2097.09 | D9: 2026-04-12 | E9: 497.35 | F9: =IF(E9="","",IF(C9="","",C9+E9)) -> 2594.44 | H9: Agent09 | I9: SAVED | J9: 2026-04-12
A10: SAM20240600018 | B10: =IF(A10="","",IFERROR(VLOOKUP(A10,Master_Customers!$A:$D,4,FALSE()),"❌ Not Found")) -> Esi Quaye | C10: =IF(A10="","",IFERROR(VLOOKUP(A10,Master_Customers!$A:$O,15,FALSE()),"")) -> 4320.19 | D10: 2026-04-12 | E10: 130.27 | F10: =IF(E10="","",IF(C10="","",C10+E10)) -> 4450.46 | H10: Agent09 | I10: SAVED | J10: 2026-04-12
B11: =IF(A11="","",IFERROR(VLOOKUP(A11,Master_Customers!$A:$D,4,FALSE()),"❌ Not Found")) | C11: =IF(A11="","",IFERROR(VLOOKUP(A11,Master_Customers!$A:$O,15,FALSE()),"")) | F11: =IF(E11="","",IF(C11="","",C11+E11))
B12: =IF(A12="","",IFERROR(VLOOKUP(A12,Master_Customers!$A:$D,4,FALSE()),"❌ Not Found")) | C12: =IF(A12="","",IFERROR(VLOOKUP(A12,Master_Customers!$A:$O,15,FALSE()),"")) | F12: =IF(E12="","",IF(C12="","",C12+E12))
B13: =IF(A13="","",IFERROR(VLOOKUP(A13,Master_Customers!$A:$D,4,FALSE()),"❌ Not Found")) | C13: =IF(A13="","",IFERROR(VLOOKUP(A13,Master_Customers!$A:$O,15,FALSE()),"")) | F13: =IF(E13="","",IF(C13="","",C13+E13))
B14: =IF(A14="","",IFERROR(VLOOKUP(A14,Master_Customers!$A:$D,4,FALSE()),"❌ Not Found")) | C14: =IF(A14="","",IFERROR(VLOOKUP(A14,Master_Customers!$A:$O,15,FALSE()),"")) | F14: =IF(E14="","",IF(C14="","",C14+E14))
B15: =IF(A15="","",IFERROR(VLOOKUP(A15,Master_Customers!$A:$D,4,FALSE()),"❌ Not Found")) | C15: =IF(A15="","",IFERROR(VLOOKUP(A15,Master_Customers!$A:$O,15,FALSE()),"")) | F15: =IF(E15="","",IF(C15="","",C15+E15))
B16: =IF(A16="","",IFERROR(VLOOKUP(A16,Master_Customers!$A:$D,4,FALSE()),"❌ Not Found")) | C16: =IF(A16="","",IFERROR(VLOOKUP(A16,Master_Customers!$A:$O,15,FALSE()),"")) | F16: =IF(E16="","",IF(C16="","",C16+E16))
B17: =IF(A17="","",IFERROR(VLOOKUP(A17,Master_Customers!$A:$D,4,FALSE()),"❌ Not Found")) | C17: =IF(A17="","",IFERROR(VLOOKUP(A17,Master_Customers!$A:$O,15,FALSE()),"")) | F17: =IF(E17="","",IF(C17="","",C17+E17))
B18: =IF(A18="","",IFERROR(VLOOKUP(A18,Master_Customers!$A:$D,4,FALSE()),"❌ Not Found")) | C18: =IF(A18="","",IFERROR(VLOOKUP(A18,Master_Customers!$A:$O,15,FALSE()),"")) | F18: =IF(E18="","",IF(C18="","",C18+E18))
B19: =IF(A19="","",IFERROR(VLOOKUP(A19,Master_Customers!$A:$D,4,FALSE()),"❌ Not Found")) | C19: =IF(A19="","",IFERROR(VLOOKUP(A19,Master_Customers!$A:$O,15,FALSE()),"")) | F19: =IF(E19="","",IF(C19="","",C19+E19))
B20: =IF(A20="","",IFERROR(VLOOKUP(A20,Master_Customers!$A:$D,4,FALSE()),"❌ Not Found")) | C20: =IF(A20="","",IFERROR(VLOOKUP(A20,Master_Customers!$A:$O,15,FALSE()),"")) | F20: =IF(E20="","",IF(C20="","",C20+E20))
B21: =IF(A21="","",IFERROR(VLOOKUP(A21,Master_Customers!$A:$D,4,FALSE()),"❌ Not Found")) | C21: =IF(A21="","",IFERROR(VLOOKUP(A21,Master_Customers!$A:$O,15,FALSE()),"")) | F21: =IF(E21="","",IF(C21="","",C21+E21))
B22: =IF(A22="","",IFERROR(VLOOKUP(A22,Master_Customers!$A:$D,4,FALSE()),"❌ Not Found")) | C22: =IF(A22="","",IFERROR(VLOOKUP(A22,Master_Customers!$A:$O,15,FALSE()),"")) | F22: =IF(E22="","",IF(C22="","",C22+E22))
... B1008: =IF(A1008="","",IFERROR(VLOOKUP(A1008,Master_Customers!$A:$D,4,FALSE()),"❌ Not Found")) | C1008: =IF(A1008="","",IFERROR(VLOOKUP(A1008,Master_Customers!$A:$O,15,FALSE()),"")) | F1008: =IF(E1008="","",IF(C1008="","",C1008+E1008))

Sheet Agent09_Withdrawals
A1: 🏧 SAMICIOUS MICROFINANCE — AGENT09 WITHDRAWALS
A2: Agent: Agent09 | Date: 2026-04-12 | Module: Withdrawal Processing
B3: Total Withdrawals | E3: Transactions Count | H3: Avg Withdrawal
B4: =SUMIF(I9:I1008,"SAVED",E9:E1008) -> 0 | E4: =COUNTIF(I9:I1008,"SAVED") -> 0 | H4: =IFERROR(B4/E4,0) -> 0
A5: ⚠️ WITHDRAWALS MODULE — Insufficient balance will be flagged automatically
A7: 📝 TRANSACTION ENTRY — Enter Account Number and Withdrawal Amount
A8: Account # | B8: Customer Name | C8: Available Balance | D8: Date | E8: Withdrawal Amount | F8: New Balance | G8: Authorised By | H8: Agent | I8: Status | J8: Saved At
B9: =IF(A9="","",IFERROR(VLOOKUP(A9,Master_Customers!$A:$D,4,FALSE()),"❌ Not Found")) | C9: =IF(A9="","",IFERROR(VLOOKUP(A9,Master_Customers!$A:$O,15,FALSE()),"")) | F9: =IF(E9="","",IF(C9="","",IF(E9>C9,"INSUFFICIENT FUNDS",C9-E9)))
B10: =IF(A10="","",IFERROR(VLOOKUP(A10,Master_Customers!$A:$D,4,FALSE()),"❌ Not Found")) | C10: =IF(A10="","",IFERROR(VLOOKUP(A10,Master_Customers!$A:$O,15,FALSE()),"")) | F10: =IF(E10="","",IF(C10="","",IF(E10>C10,"INSUFFICIENT FUNDS",C10-E10)))
B11: =IF(A11="","",IFERROR(VLOOKUP(A11,Master_Customers!$A:$D,4,FALSE()),"❌ Not Found")) | C11: =IF(A11="","",IFERROR(VLOOKUP(A11,Master_Customers!$A:$O,15,FALSE()),"")) | F11: =IF(E11="","",IF(C11="","",IF(E11>C11,"INSUFFICIENT FUNDS",C11-E11)))
B12: =IF(A12="","",IFERROR(VLOOKUP(A12,Master_Customers!$A:$D,4,FALSE()),"❌ Not Found")) | C12: =IF(A12="","",IFERROR(VLOOKUP(A12,Master_Customers!$A:$O,15,FALSE()),"")) | F12: =IF(E12="","",IF(C12="","",IF(E12>C12,"INSUFFICIENT FUNDS",C12-E12)))
B13: =IF(A13="","",IFERROR(VLOOKUP(A13,Master_Customers!$A:$D,4,FALSE()),"❌ Not Found")) | C13: =IF(A13="","",IFERROR(VLOOKUP(A13,Master_Customers!$A:$O,15,FALSE()),"")) | F13: =IF(E13="","",IF(C13="","",IF(E13>C13,"INSUFFICIENT FUNDS",C13-E13)))
B14: =IF(A14="","",IFERROR(VLOOKUP(A14,Master_Customers!$A:$D,4,FALSE()),"❌ Not Found")) | C14: =IF(A14="","",IFERROR(VLOOKUP(A14,Master_Customers!$A:$O,15,FALSE()),"")) | F14: =IF(E14="","",IF(C14="","",IF(E14>C14,"INSUFFICIENT FUNDS",C14-E14)))
B15: =IF(A15="","",IFERROR(VLOOKUP(A15,Master_Customers!$A:$D,4,FALSE()),"❌ Not Found")) | C15: =IF(A15="","",IFERROR(VLOOKUP(A15,Master_Customers!$A:$O,15,FALSE()),"")) | F15: =IF(E15="","",IF(C15="","",IF(E15>C15,"INSUFFICIENT FUNDS",C15-E15)))
B16: =IF(A16="","",IFERROR(VLOOKUP(A16,Master_Customers!$A:$D,4,FALSE()),"❌ Not Found")) | C16: =IF(A16="","",IFERROR(VLOOKUP(A16,Master_Customers!$A:$O,15,FALSE()),"")) | F16: =IF(E16="","",IF(C16="","",IF(E16>C16,"INSUFFICIENT FUNDS",C16-E16)))
B17: =IF(A17="","",IFERROR(VLOOKUP(A17,Master_Customers!$A:$D,4,FALSE()),"❌ Not Found")) | C17: =IF(A17="","",IFERROR(VLOOKUP(A17,Master_Customers!$A:$O,15,FALSE()),"")) | F17: =IF(E17="","",IF(C17="","",IF(E17>C17,"INSUFFICIENT FUNDS",C17-E17)))
B18: =IF(A18="","",IFERROR(VLOOKUP(A18,Master_Customers!$A:$D,4,FALSE()),"❌ Not Found")) | C18: =IF(A18="","",IFERROR(VLOOKUP(A18,Master_Customers!$A:$O,15,FALSE()),"")) | F18: =IF(E18="","",IF(C18="","",IF(E18>C18,"INSUFFICIENT FUNDS",C18-E18)))
B19: =IF(A19="","",IFERROR(VLOOKUP(A19,Master_Customers!$A:$D,4,FALSE()),"❌ Not Found")) | C19: =IF(A19="","",IFERROR(VLOOKUP(A19,Master_Customers!$A:$O,15,FALSE()),"")) | F19: =IF(E19="","",IF(C19="","",IF(E19>C19,"INSUFFICIENT FUNDS",C19-E19)))
B20: =IF(A20="","",IFERROR(VLOOKUP(A20,Master_Customers!$A:$D,4,FALSE()),"❌ Not Found")) | C20: =IF(A20="","",IFERROR(VLOOKUP(A20,Master_Customers!$A:$O,15,FALSE()),"")) | F20: =IF(E20="","",IF(C20="","",IF(E20>C20,"INSUFFICIENT FUNDS",C20-E20)))
... B1008: =IF(A1008="","",IFERROR(VLOOKUP(A1008,Master_Customers!$A:$D,4,FALSE()),"❌ Not Found")) | C1008: =IF(A1008="","",IFERROR(VLOOKUP(A1008,Master_Customers!$A:$O,15,FALSE()),"")) | F1008: =IF(E1008="","",IF(C1008="","",IF(E1008>C1008,"INSUFFICIENT FUNDS",C1008-E1008)))

Sheet Agent09_Loans
A1: 🏦 SAMICIOUS MICROFINANCE — AGENT09 LOAN REQUESTS
A2: Agent: Agent09 | Interest Rate: 2.5% p/m (flat) | Min: GHC 100 | Max: GHC 50,000
A4: 🔢 LOAN CALCULATOR
A5: Loan Amount (GHC):
A6: Repayment (months):
A7: Interest Rate (%/m): | B7: 2.5
A8: Total Interest (GHC): | B8: =IF(B5="","",B5*B7/100*B6)
A9: Total Repayable (GHC): | B9: =IF(B5="","",B5+B8)
A10: Monthly Installment (GHC): | B10: =IF(B5="","",B9/B6)
A12: 📋 LOAN REQUEST SUBMISSIONS — Enter details below to submit for manager approval
A13: Loan ID | B13: Account # | C13: Customer Name | D13: Request Date | E13: Loan Amount | F13: Purpose | G13: Months | H13: Rate % | I13: Total Repayable | J13: Monthly Install | K13: Status | L13: Notes
A14: LN202604120014 | B14: SAM20240600017 | C14: Kwasi Adusei | D14: 2026-04-12 | E14: 4693.98 | F14: Business | G14: 6 | H14: 2.5 | I14: 5398.08 | J14: 899.68 | K14: Pending
A15: LN202604120015 | B15: SAM20240600018 | C15: Esi Quaye | D15: 2026-04-12 | E15: 5411.77 | F15: Business | G15: 6 | H15: 2.5 | I15: 6223.54 | J15: 1037.26 | K15: Pending
C16: =IF(B16="","",IFERROR(VLOOKUP(B16,Master_Customers!$A:$D,4,FALSE()),"❌ Not Found")) | I16: =IF(E16="","",E16+E16*H16/100*G16) | J16: =IFERROR(I16/G16,"")
C17: =IF(B17="","",IFERROR(VLOOKUP(B17,Master_Customers!$A:$D,4,FALSE()),"❌ Not Found")) | I17: =IF(E17="","",E17+E17*H17/100*G17) | J17: =IFERROR(I17/G17,"")
C18: =IF(B18="","",IFERROR(VLOOKUP(B18,Master_Customers!$A:$D,4,FALSE()),"❌ Not Found")) | I18: =IF(E18="","",E18+E18*H18/100*G18) | J18: =IFERROR(I18/G18,"")
C19: =IF(B19="","",IFERROR(VLOOKUP(B19,Master_Customers!$A:$D,4,FALSE()),"❌ Not Found")) | I19: =IF(E19="","",E19+E19*H19/100*G19) | J19: =IFERROR(I19/G19,"")
C20: =IF(B20="","",IFERROR(VLOOKUP(B20,Master_Customers!$A:$D,4,FALSE()),"❌ Not Found")) | I20: =IF(E20="","",E20+E20*H20/100*G20) | J20: =IFERROR(I20/G20,"")
C21: =IF(B21="","",IFERROR(VLOOKUP(B21,Master_Customers!$A:$D,4,FALSE()),"❌ Not Found")) | I21: =IF(E21="","",E21+E21*H21/100*G21) | J21: =IFERROR(I21/G21,"")
C22: =IF(B22="","",IFERROR(VLOOKUP(B22,Master_Customers!$A:$D,4,FALSE()),"❌ Not Found")) | I22: =IF(E22="","",E22+E22*H22/100*G22) | J22: =IFERROR(I22/G22,"")
C23: =IF(B23="","",IFERROR(VLOOKUP(B23,Master_Customers!$A:$D,4,FALSE()),"❌ Not Found")) | I23: =IF(E23="","",E23+E23*H23/100*G23) | J23: =IFERROR(I23/G23,"")
C24: =IF(B24="","",IFERROR(VLOOKUP(B24,Master_Customers!$A:$D,4,FALSE()),"❌ Not Found")) | I24: =IF(E24="","",E24+E24*H24/100*G24) | J24: =IFERROR(I24/G24,"")
C25: =IF(B25="","",IFERROR(VLOOKUP(B25,Master_Customers!$A:$D,4,FALSE()),"❌ Not Found")) | I25: =IF(E25="","",E25+E25*H25/100*G25) | J25: =IFERROR(I25/G25,"")
C26: =IF(B26="","",IFERROR(VLOOKUP(B26,Master_Customers!$A:$D,4,FALSE()),"❌ Not Found")) | I26: =IF(E26="","",E26+E26*H26/100*G26) | J26: =IFERROR(I26/G26,"")
C27: =IF(B27="","",IFERROR(VLOOKUP(B27,Master_Customers!$A:$D,4,FALSE()),"❌ Not Found")) | I27: =IF(E27="","",E27+E27*H27/100*G27) | J27: =IFERROR(I27/G27,"")
... C213: =IF(B213="","",IFERROR(VLOOKUP(B213,Master_Customers!$A:$D,4,FALSE()),"❌ Not Found")) | I213: =IF(E213="","",E213+E213*H213/100*G213) | J213: =IFERROR(I213/G213,"")

Sheet Agent10_Savings
A1: 💰 SAMICIOUS MICROFINANCE — AGENT10 SAVINGS
A2: Agent: Agent10 | Date: 2026-04-12 | Module: Daily Savings Collection
B3: Daily Target (GHC) | E3: Total Collected | H3: Remaining
B4: 5000 | E4: =SUMIF(I9:I1008,"SAVED",E9:E1008) -> 878.92 | H4: =IF(B4-E4<0,"TARGET MET!",B4-E4) -> 4121.08
A5: =IF(B4-E4<=0,"✅ DAILY TARGET ACHIEVED! Great work Agent10!","⏳ Collection in progress — Keep going!") -> ⏳ Collection in progress — Keep going!
A7: 📝 TRANSACTION ENTRY — Enter Account Number and Amount, then click RECORD or press Ctrl+S
A8: Account # | B8: Customer Name | C8: Current Balance | D8: Date | E8: Savings Amount | F8: New Balance | G8: Receipt # | H8: Agent | I8: Status | J8: Saved At
A9: SAM20240600019 | B9: =IF(A9="","",IFERROR(VLOOKUP(A9,Master_Customers!$A:$D,4,FALSE()),"❌ Not Found")) -> Yaa Opoku | C9: =IF(A9="","",IFERROR(VLOOKUP(A9,Master_Customers!$A:$O,15,FALSE()),"")) -> 3180.59 | D9: 2026-04-12 | E9: 414.96 | F9: =IF(E9="","",IF(C9="","",C9+E9)) -> 3595.55 | H9: Agent10 | I9: SAVED | J9: 2026-04-12
A10: SAM20240600020 | B10: =IF(A10="","",IFERROR(VLOOKUP(A10,Master_Customers!$A:$D,4,FALSE()),"❌ Not Found")) -> Kwame Baffour | C10: =IF(A10="","",IFERROR(VLOOKUP(A10,Master_Customers!$A:$O,15,FALSE()),"")) -> 3129.99 | D10: 2026-04-12 | E10: 463.96 | F10: =IF(E10="","",IF(C10="","",C10+E10)) -> 3593.95 | H10: Agent10 | I10: SAVED | J10: 2026-04-12
B11: =IF(A11="","",IFERROR(VLOOKUP(A11,Master_Customers!$A:$D,4,FALSE()),"❌ Not Found")) | C11: =IF(A11="","",IFERROR(VLOOKUP(A11,Master_Customers!$A:$O,15,FALSE()),"")) | F11: =IF(E11="","",IF(C11="","",C11+E11))
B12: =IF(A12="","",IFERROR(VLOOKUP(A12,Master_Customers!$A:$D,4,FALSE()),"❌ Not Found")) | C12: =IF(A12="","",IFERROR(VLOOKUP(A12,Master_Customers!$A:$O,15,FALSE()),"")) | F12: =IF(E12="","",IF(C12="","",C12+E12))
B13: =IF(A13="","",IFERROR(VLOOKUP(A13,Master_Customers!$A:$D,4,FALSE()),"❌ Not Found")) | C13: =IF(A13="","",IFERROR(VLOOKUP(A13,Master_Customers!$A:$O,15,FALSE()),"")) | F13: =IF(E13="","",IF(C13="","",C13+E13))
B14: =IF(A14="","",IFERROR(VLOOKUP(A14,Master_Customers!$A:$D,4,FALSE()),"❌ Not Found")) | C14: =IF(A14="","",IFERROR(VLOOKUP(A14,Master_Customers!$A:$O,15,FALSE()),"")) | F14: =IF(E14="","",IF(C14="","",C14+E14))
B15: =IF(A15="","",IFERROR(VLOOKUP(A15,Master_Customers!$A:$D,4,FALSE()),"❌ Not Found")) | C15: =IF(A15="","",IFERROR(VLOOKUP(A15,Master_Customers!$A:$O,15,FALSE()),"")) | F15: =IF(E15="","",IF(C15="","",C15+E15))
B16: =IF(A16="","",IFERROR(VLOOKUP(A16,Master_Customers!$A:$D,4,FALSE()),"❌ Not Found")) | C16: =IF(A16="","",IFERROR(VLOOKUP(A16,Master_Customers!$A:$O,15,FALSE()),"")) | F16: =IF(E16="","",IF(C16="","",C16+E16))
B17: =IF(A17="","",IFERROR(VLOOKUP(A17,Master_Customers!$A:$D,4,FALSE()),"❌ Not Found")) | C17: =IF(A17="","",IFERROR(VLOOKUP(A17,Master_Customers!$A:$O,15,FALSE()),"")) | F17: =IF(E17="","",IF(C17="","",C17+E17))
B18: =IF(A18="","",IFERROR(VLOOKUP(A18,Master_Customers!$A:$D,4,FALSE()),"❌ Not Found")) | C18: =IF(A18="","",IFERROR(VLOOKUP(A18,Master_Customers!$A:$O,15,FALSE()),"")) | F18: =IF(E18="","",IF(C18="","",C18+E18))
B19: =IF(A19="","",IFERROR(VLOOKUP(A19,Master_Customers!$A:$D,4,FALSE()),"❌ Not Found")) | C19: =IF(A19="","",IFERROR(VLOOKUP(A19,Master_Customers!$A:$O,15,FALSE()),"")) | F19: =IF(E19="","",IF(C19="","",C19+E19))
B20: =IF(A20="","",IFERROR(VLOOKUP(A20,Master_Customers!$A:$D,4,FALSE()),"❌ Not Found")) | C20: =IF(A20="","",IFERROR(VLOOKUP(A20,Master_Customers!$A:$O,15,FALSE()),"")) | F20: =IF(E20="","",IF(C20="","",C20+E20))
B21: =IF(A21="","",IFERROR(VLOOKUP(A21,Master_Customers!$A:$D,4,FALSE()),"❌ Not Found")) | C21: =IF(A21="","",IFERROR(VLOOKUP(A21,Master_Customers!$A:$O,15,FALSE()),"")) | F21: =IF(E21="","",IF(C21="","",C21+E21))
B22: =IF(A22="","",IFERROR(VLOOKUP(A22,Master_Customers!$A:$D,4,FALSE()),"❌ Not Found")) | C22: =IF(A22="","",IFERROR(VLOOKUP(A22,Master_Customers!$A:$O,15,FALSE()),"")) | F22: =IF(E22="","",IF(C22="","",C22+E22))
... B1008: =IF(A1008="","",IFERROR(VLOOKUP(A1008,Master_Customers!$A:$D,4,FALSE()),"❌ Not Found")) | C1008: =IF(A1008="","",IFERROR(VLOOKUP(A1008,Master_Customers!$A:$O,15,FALSE()),"")) | F1008: =IF(E1008="","",IF(C1008="","",C1008+E1008))

Sheet Agent10_Withdrawals
A1: 🏧 SAMICIOUS MICROFINANCE — AGENT10 WITHDRAWALS
A2: Agent: Agent10 | Date: 2026-04-12 | Module: Withdrawal Processing
B3: Total Withdrawals | E3: Transactions Count | H3: Avg Withdrawal
B4: =SUMIF(I9:I1008,"SAVED",E9:E1008) -> 0 | E4: =COUNTIF(I9:I1008,"SAVED") -> 0 | H4: =IFERROR(B4/E4,0) -> 0
A5: ⚠️ WITHDRAWALS MODULE — Insufficient balance will be flagged automatically
A7: 📝 TRANSACTION ENTRY — Enter Account Number and Withdrawal Amount
A8: Account # | B8: Customer Name | C8: Available Balance | D8: Date | E8: Withdrawal Amount | F8: New Balance | G8: Authorised By | H8: Agent | I8: Status | J8: Saved At
B9: =IF(A9="","",IFERROR(VLOOKUP(A9,Master_Customers!$A:$D,4,FALSE()),"❌ Not Found")) | C9: =IF(A9="","",IFERROR(VLOOKUP(A9,Master_Customers!$A:$O,15,FALSE()),"")) | F9: =IF(E9="","",IF(C9="","",IF(E9>C9,"INSUFFICIENT FUNDS",C9-E9)))
B10: =IF(A10="","",IFERROR(VLOOKUP(A10,Master_Customers!$A:$D,4,FALSE()),"❌ Not Found")) | C10: =IF(A10="","",IFERROR(VLOOKUP(A10,Master_Customers!$A:$O,15,FALSE()),"")) | F10: =IF(E10="","",IF(C10="","",IF(E10>C10,"INSUFFICIENT FUNDS",C10-E10)))
B11: =IF(A11="","",IFERROR(VLOOKUP(A11,Master_Customers!$A:$D,4,FALSE()),"❌ Not Found")) | C11: =IF(A11="","",IFERROR(VLOOKUP(A11,Master_Customers!$A:$O,15,FALSE()),"")) | F11: =IF(E11="","",IF(C11="","",IF(E11>C11,"INSUFFICIENT FUNDS",C11-E11)))
B12: =IF(A12="","",IFERROR(VLOOKUP(A12,Master_Customers!$A:$D,4,FALSE()),"❌ Not Found")) | C12: =IF(A12="","",IFERROR(VLOOKUP(A12,Master_Customers!$A:$O,15,FALSE()),"")) | F12: =IF(E12="","",IF(C12="","",IF(E12>C12,"INSUFFICIENT FUNDS",C12-E12)))
B13: =IF(A13="","",IFERROR(VLOOKUP(A13,Master_Customers!$A:$D,4,FALSE()),"❌ Not Found")) | C13: =IF(A13="","",IFERROR(VLOOKUP(A13,Master_Customers!$A:$O,15,FALSE()),"")) | F13: =IF(E13="","",IF(C13="","",IF(E13>C13,"INSUFFICIENT FUNDS",C13-E13)))
B14: =IF(A14="","",IFERROR(VLOOKUP(A14,Master_Customers!$A:$D,4,FALSE()),"❌ Not Found")) | C14: =IF(A14="","",IFERROR(VLOOKUP(A14,Master_Customers!$A:$O,15,FALSE()),"")) | F14: =IF(E14="","",IF(C14="","",IF(E14>C14,"INSUFFICIENT FUNDS",C14-E14)))
B15: =IF(A15="","",IFERROR(VLOOKUP(A15,Master_Customers!$A:$D,4,FALSE()),"❌ Not Found")) | C15: =IF(A15="","",IFERROR(VLOOKUP(A15,Master_Customers!$A:$O,15,FALSE()),"")) | F15: =IF(E15="","",IF(C15="","",IF(E15>C15,"INSUFFICIENT FUNDS",C15-E15)))
B16: =IF(A16="","",IFERROR(VLOOKUP(A16,Master_Customers!$A:$D,4,FALSE()),"❌ Not Found")) | C16: =IF(A16="","",IFERROR(VLOOKUP(A16,Master_Customers!$A:$O,15,FALSE()),"")) | F16: =IF(E16="","",IF(C16="","",IF(E16>C16,"INSUFFICIENT FUNDS",C16-E16)))
B17: =IF(A17="","",IFERROR(VLOOKUP(A17,Master_Customers!$A:$D,4,FALSE()),"❌ Not Found")) | C17: =IF(A17="","",IFERROR(VLOOKUP(A17,Master_Customers!$A:$O,15,FALSE()),"")) | F17: =IF(E17="","",IF(C17="","",IF(E17>C17,"INSUFFICIENT FUNDS",C17-E17)))
B18: =IF(A18="","",IFERROR(VLOOKUP(A18,Master_Customers!$A:$D,4,FALSE()),"❌ Not Found")) | C18: =IF(A18="","",IFERROR(VLOOKUP(A18,Master_Customers!$A:$O,15,FALSE()),"")) | F18: =IF(E18="","",IF(C18="","",IF(E18>C18,"INSUFFICIENT FUNDS",C18-E18)))
B19: =IF(A19="","",IFERROR(VLOOKUP(A19,Master_Customers!$A:$D,4,FALSE()),"❌ Not Found")) | C19: =IF(A19="","",IFERROR(VLOOKUP(A19,Master_Customers!$A:$O,15,FALSE()),"")) | F19: =IF(E19="","",IF(C19="","",IF(E19>C19,"INSUFFICIENT FUNDS",C19-E19)))
B20: =IF(A20="","",IFERROR(VLOOKUP(A20,Master_Customers!$A:$D,4,FALSE()),"❌ Not Found")) | C20: =IF(A20="","",IFERROR(VLOOKUP(A20,Master_Customers!$A:$O,15,FALSE()),"")) | F20: =IF(E20="","",IF(C20="","",IF(E20>C20,"INSUFFICIENT FUNDS",C20-E20)))
... B1008: =IF(A1008="","",IFERROR(VLOOKUP(A1008,Master_Customers!$A:$D,4,FALSE()),"❌ Not Found")) | C1008: =IF(A1008="","",IFERROR(VLOOKUP(A1008,Master_Customers!$A:$O,15,FALSE()),"")) | F1008: =IF(E1008="","",IF(C1008="","",IF(E1008>C1008,"INSUFFICIENT FUNDS",C1008-E1008)))

Sheet Agent10_Loans
A1: 🏦 SAMICIOUS MICROFINANCE — AGENT10 LOAN REQUESTS
A2: Agent: Agent10 | Interest Rate: 2.5% p/m (flat) | Min: GHC 100 | Max: GHC 50,000
A4: 🔢 LOAN CALCULATOR
A5: Loan Amount (GHC):
A6: Repayment (months):
A7: Interest Rate (%/m): | B7: 2.5
A8: Total Interest (GHC): | B8: =IF(B5="","",B5*B7/100*B6)
A9: Total Repayable (GHC): | B9: =IF(B5="","",B5+B8)
A10: Monthly Installment (GHC): | B10: =IF(B5="","",B9/B6)
A12: 📋 LOAN REQUEST SUBMISSIONS — Enter details below to submit for manager approval
A13: Loan ID | B13: Account # | C13: Customer Name | D13: Request Date | E13: Loan Amount | F13: Purpose | G13: Months | H13: Rate % | I13: Total Repayable | J13: Monthly Install | K13: Status | L13: Notes
A14: LN202604120014 | B14: SAM20240600019 | C14: Yaa Opoku | D14: 2026-04-12 | E14: 5959.5 | F14: Business | G14: 6 | H14: 2.5 | I14: 6853.43 | J14: 1142.24 | K14: Pending
A15: LN202604120015 | B15: SAM20240600020 | C15: Kwame Baffour | D15: 2026-04-12 | E15: 6965.33 | F15: Business | G15: 6 | H15: 2.5 | I15: 8010.13 | J15: 1335.02 | K15: Pending
C16: =IF(B16="","",IFERROR(VLOOKUP(B16,Master_Customers!$A:$D,4,FALSE()),"❌ Not Found")) | I16: =IF(E16="","",E16+E16*H16/100*G16) | J16: =IFERROR(I16/G16,"")
C17: =IF(B17="","",IFERROR(VLOOKUP(B17,Master_Customers!$A:$D,4,FALSE()),"❌ Not Found")) | I17: =IF(E17="","",E17+E17*H17/100*G17) | J17: =IFERROR(I17/G17,"")
C18: =IF(B18="","",IFERROR(VLOOKUP(B18,Master_Customers!$A:$D,4,FALSE()),"❌ Not Found")) | I18: =IF(E18="","",E18+E18*H18/100*G18) | J18: =IFERROR(I18/G18,"")
C19: =IF(B19="","",IFERROR(VLOOKUP(B19,Master_Customers!$A:$D,4,FALSE()),"❌ Not Found")) | I19: =IF(E19="","",E19+E19*H19/100*G19) | J19: =IFERROR(I19/G19,"")
C20: =IF(B20="","",IFERROR(VLOOKUP(B20,Master_Customers!$A:$D,4,FALSE()),"❌ Not Found")) | I20: =IF(E20="","",E20+E20*H20/100*G20) | J20: =IFERROR(I20/G20,"")
C21: =IF(B21="","",IFERROR(VLOOKUP(B21,Master_Customers!$A:$D,4,FALSE()),"❌ Not Found")) | I21: =IF(E21="","",E21+E21*H21/100*G21) | J21: =IFERROR(I21/G21,"")
C22: =IF(B22="","",IFERROR(VLOOKUP(B22,Master_Customers!$A:$D,4,FALSE()),"❌ Not Found")) | I22: =IF(E22="","",E22+E22*H22/100*G22) | J22: =IFERROR(I22/G22,"")
C23: =IF(B23="","",IFERROR(VLOOKUP(B23,Master_Customers!$A:$D,4,FALSE()),"❌ Not Found")) | I23: =IF(E23="","",E23+E23*H23/100*G23) | J23: =IFERROR(I23/G23,"")
C24: =IF(B24="","",IFERROR(VLOOKUP(B24,Master_Customers!$A:$D,4,FALSE()),"❌ Not Found")) | I24: =IF(E24="","",E24+E24*H24/100*G24) | J24: =IFERROR(I24/G24,"")
C25: =IF(B25="","",IFERROR(VLOOKUP(B25,Master_Customers!$A:$D,4,FALSE()),"❌ Not Found")) | I25: =IF(E25="","",E25+E25*H25/100*G25) | J25: =IFERROR(I25/G25,"")
C26: =IF(B26="","",IFERROR(VLOOKUP(B26,Master_Customers!$A:$D,4,FALSE()),"❌ Not Found")) | I26: =IF(E26="","",E26+E26*H26/100*G26) | J26: =IFERROR(I26/G26,"")
C27: =IF(B27="","",IFERROR(VLOOKUP(B27,Master_Customers!$A:$D,4,FALSE()),"❌ Not Found")) | I27: =IF(E27="","",E27+E27*H27/100*G27) | J27: =IFERROR(I27/G27,"")
... C213: =IF(B213="","",IFERROR(VLOOKUP(B213,Master_Customers!$A:$D,4,FALSE()),"❌ Not Found")) | I213: =IF(E213="","",E213+E213*H213/100*G213) | J213: =IFERROR(I213/G213,"")

Sheet Daily_Balancing
A1: 📊 DAILY BALANCING REPORT — Sunday, 12 April 2026
A2: ⚡ Auto-calculated from all agent transaction sheets | Values update automatically
A3: Agent | B3: Total Savings (GHC) | C3: Total Withdrawals (GHC) | D3: Net Movement (GHC) | E3: Customers Served | F3: Transactions | G3: Performance
A4: Agent01 | B4: =IFERROR(SUMIF(Agent01_Savings!I9:I1008,"SAVED",Agent01_Savings!E9:E1008),0) -> 731.47 | C4: =IFERROR(SUMIF(Agent01_Withdrawals!I9:I1008,"SAVED",Agent01_Withdrawals!E9:E1008),0) -> 0 | D4: =B4-C4 -> 731.47 | E4: =IFERROR(COUNTIF(Agent01_Savings!I9:I1008,"SAVED")+COUNTIF(Agent01_Withdrawals!I9:I1008,"SAVED"),0) -> 2 | F4: =IFERROR(COUNTIF(Agent01_Savings!I9:I1008,"SAVED")+COUNTIF(Agent01_Withdrawals!I9:I1008,"SAVED"),0) -> 2 | G4: =IF(B4>=5000,"✅ On Track",IF(B4>=2500,"⚠️ Below Target","❌ Low")) -> ❌ Low
A5: Agent02 | B5: =IFERROR(SUMIF(Agent02_Savings!I9:I1008,"SAVED",Agent02_Savings!E9:E1008),0) -> 645.87 | C5: =IFERROR(SUMIF(Agent02_Withdrawals!I9:I1008,"SAVED",Agent02_Withdrawals!E9:E1008),0) -> 0 | D5: =B5-C5 -> 645.87 | E5: =IFERROR(COUNTIF(Agent02_Savings!I9:I1008,"SAVED")+COUNTIF(Agent02_Withdrawals!I9:I1008,"SAVED"),0) -> 2 | F5: =IFERROR(COUNTIF(Agent02_Savings!I9:I1008,"SAVED")+COUNTIF(Agent02_Withdrawals!I9:I1008,"SAVED"),0) -> 2 | G5: =IF(B5>=5000,"✅ On Track",IF(B5>=2500,"⚠️ Below Target","❌ Low")) -> ❌ Low
A6: Agent03 | B6: =IFERROR(SUMIF(Agent03_Savings!I9:I1008,"SAVED",Agent03_Savings!E9:E1008),0) -> 498.29 | C6: =IFERROR(SUMIF(Agent03_Withdrawals!I9:I1008,"SAVED",Agent03_Withdrawals!E9:E1008),0) -> 0 | D6: =B6-C6 -> 498.29 | E6: =IFERROR(COUNTIF(Agent03_Savings!I9:I1008,"SAVED")+COUNTIF(Agent03_Withdrawals!I9:I1008,"SAVED"),0) -> 2 | F6: =IFERROR(COUNTIF(Agent03_Savings!I9:I1008,"SAVED")+COUNTIF(Agent03_Withdrawals!I9:I1008,"SAVED"),0) -> 2 | G6: =IF(B6>=5000,"✅ On Track",IF(B6>=2500,"⚠️ Below Target","❌ Low")) -> ❌ Low
A7: Agent04 | B7: =IFERROR(SUMIF(Agent04_Savings!I9:I1008,"SAVED",Agent04_Savings!E9:E1008),0) -> 872.99 | C7: =IFERROR(SUMIF(Agent04_Withdrawals!I9:I1008,"SAVED",Agent04_Withdrawals!E9:E1008),0) -> 0 | D7: =B7-C7 -> 872.99 | E7: =IFERROR(COUNTIF(Agent04_Savings!I9:I1008,"SAVED")+COUNTIF(Agent04_Withdrawals!I9:I1008,"SAVED"),0) -> 2 | F7: =IFERROR(COUNTIF(Agent04_Savings!I9:I1008,"SAVED")+COUNTIF(Agent04_Withdrawals!I9:I1008,"SAVED"),0) -> 2 | G7: =IF(B7>=5000,"✅ On Track",IF(B7>=2500,"⚠️ Below Target","❌ Low")) -> ❌ Low
A8: Agent05 | B8: =IFERROR(SUMIF(Agent05_Savings!I9:I1008,"SAVED",Agent05_Savings!E9:E1008),0) -> 525.86 | C8: =IFERROR(SUMIF(Agent05_Withdrawals!I9:I1008,"SAVED",Agent05_Withdrawals!E9:E1008),0) -> 0 | D8: =B8-C8 -> 525.86 | E8: =IFERROR(COUNTIF(Agent05_Savings!I9:I1008,"SAVED")+COUNTIF(Agent05_Withdrawals!I9:I1008,"SAVED"),0) -> 2 | F8: =IFERROR(COUNTIF(Agent05_Savings!I9:I1008,"SAVED")+COUNTIF(Agent05_Withdrawals!I9:I1008,"SAVED"),0) -> 2 | G8: =IF(B8>=5000,"✅ On Track",IF(B8>=2500,"⚠️ Below Target","❌ Low")) -> ❌ Low
A9: Agent06 | B9: =IFERROR(SUMIF(Agent06_Savings!I9:I1008,"SAVED",Agent06_Savings!E9:E1008),0) -> 505.66 | C9: =IFERROR(SUMIF(Agent06_Withdrawals!I9:I1008,"SAVED",Agent06_Withdrawals!E9:E1008),0) -> 0 | D9: =B9-C9 -> 505.66 | E9: =IFERROR(COUNTIF(Agent06_Savings!I9:I1008,"SAVED")+COUNTIF(Agent06_Withdrawals!I9:I1008,"SAVED"),0) -> 2 | F9: =IFERROR(COUNTIF(Agent06_Savings!I9:I1008,"SAVED")+COUNTIF(Agent06_Withdrawals!I9:I1008,"SAVED"),0) -> 2 | G9: =IF(B9>=5000,"✅ On Track",IF(B9>=2500,"⚠️ Below Target","❌ Low")) -> ❌ Low
A10: Agent07 | B10: =IFERROR(SUMIF(Agent07_Savings!I9:I1008,"SAVED",Agent07_Savings!E9:E1008),0) -> 642.46 | C10: =IFERROR(SUMIF(Agent07_Withdrawals!I9:I1008,"SAVED",Agent07_Withdrawals!E9:E1008),0) -> 0 | D10: =B10-C10 -> 642.46 | E10: =IFERROR(COUNTIF(Agent07_Savings!I9:I1008,"SAVED")+COUNTIF(Agent07_Withdrawals!I9:I1008,"SAVED"),0) -> 2 | F10: =IFERROR(COUNTIF(Agent07_Savings!I9:I1008,"SAVED")+COUNTIF(Agent07_Withdrawals!I9:I1008,"SAVED"),0) -> 2 | G10: =IF(B10>=5000,"✅ On Track",IF(B10>=2500,"⚠️ Below Target","❌ Low")) -> ❌ Low
A11: Agent08 | B11: =IFERROR(SUMIF(Agent08_Savings!I9:I1008,"SAVED",Agent08_Savings!E9:E1008),0) -> 641.53 | C11: =IFERROR(SUMIF(Agent08_Withdrawals!I9:I1008,"SAVED",Agent08_Withdrawals!E9:E1008),0) -> 0 | D11: =B11-C11 -> 641.53 | E11: =IFERROR(COUNTIF(Agent08_Savings!I9:I1008,"SAVED")+COUNTIF(Agent08_Withdrawals!I9:I1008,"SAVED"),0) -> 2 | F11: =IFERROR(COUNTIF(Agent08_Savings!I9:I1008,"SAVED")+COUNTIF(Agent08_Withdrawals!I9:I1008,"SAVED"),0) -> 2 | G11: =IF(B11>=5000,"✅ On Track",IF(B11>=2500,"⚠️ Below Target","❌ Low")) -> ❌ Low
A12: Agent09 | B12: =IFERROR(SUMIF(Agent09_Savings!I9:I1008,"SAVED",Agent09_Savings!E9:E1008),0) -> 627.62 | C12: =IFERROR(SUMIF(Agent09_Withdrawals!I9:I1008,"SAVED",Agent09_Withdrawals!E9:E1008),0) -> 0 | D12: =B12-C12 -> 627.62 | E12: =IFERROR(COUNTIF(Agent09_Savings!I9:I1008,"SAVED")+COUNTIF(Agent09_Withdrawals!I9:I1008,"SAVED"),0) -> 2 | F12: =IFERROR(COUNTIF(Agent09_Savings!I9:I1008,"SAVED")+COUNTIF(Agent09_Withdrawals!I9:I1008,"SAVED"),0) -> 2 | G12: =IF(B12>=5000,"✅ On Track",IF(B12>=2500,"⚠️ Below Target","❌ Low")) -> ❌ Low
A13: Agent10 | B13: =IFERROR(SUMIF(Agent10_Savings!I9:I1008,"SAVED",Agent10_Savings!E9:E1008),0) -> 878.92 | C13: =IFERROR(SUMIF(Agent10_Withdrawals!I9:I1008,"SAVED",Agent10_Withdrawals!E9:E1008),0) -> 0 | D13: =B13-C13 -> 878.92 | E13: =IFERROR(COUNTIF(Agent10_Savings!I9:I1008,"SAVED")+COUNTIF(Agent10_Withdrawals!I9:I1008,"SAVED"),0) -> 2 | F13: =IFERROR(COUNTIF(Agent10_Savings!I9:I1008,"SAVED")+COUNTIF(Agent10_Withdrawals!I9:I1008,"SAVED"),0) -> 2 | G13: =IF(B13>=5000,"✅ On Track",IF(B13>=2500,"⚠️ Below Target","❌ Low")) -> ❌ Low
A14: GRAND TOTAL | B14: =SUM(B4:B13) -> 6570.67 | C14: =SUM(C4:C13) -> 0 | D14: =B14-C14 -> 6570.67 | E14: =SUM(E4:E13) -> 20 | F14: =SUM(F4:F13) -> 20 | G14: =IF(D14>0,"📈 Net Positive","📉 Net Negative") -> 📈 Net Positive
A16: 📊 AGENT PERFORMANCE COMPARISON

Sheet Weekly_Balancing
A1: 📅 WEEKLY BALANCING REPORT — Current Week
A2: =TEXT(TODAY()-WEEKDAY(TODAY(),2)+1,"DD MMM YYYY")&" to "&TEXT(TODAY()-WEEKDAY(TODAY(),2)+7,"DD MMM YYYY") -> 06 Apr 2026 to 12 Apr 2026
A4: Total Savings | B4: Total Withdrawals | C4: Net Movement | D4: Total Customers | E4: Avg Daily Savings | F4: Avg Daily Withdrawals
A5: =Daily_Balancing!B14 -> 6570.67 | B5: =Daily_Balancing!C14 -> 0 | C5: =Daily_Balancing!D14 -> 6570.67 | D5: =Daily_Balancing!E14 -> 20 | E5: =Daily_Balancing!B14/5 -> 1314.134 | F5: =Daily_Balancing!C14/5 -> 0
A7: 📋 WEEKLY SUMMARY BY AGENT
A8: Agent | B8: Mon | C8: Tue | D8: Wed | E8: Thu | F8: Fri | G8: Sat | H8: Weekly Total
A9: Agent01 | B9: =Daily_Balancing!B4/5 -> 146.294 | C9: =Daily_Balancing!B4/5 -> 146.294 | D9: =Daily_Balancing!B4/5 -> 146.294 | E9: =Daily_Balancing!B4/5 -> 146.294 | F9: =Daily_Balancing!B4/5 -> 146.294 | G9: =Daily_Balancing!B4/5 -> 146.294 | H9: =SUM(B9:G9) -> 877.764
A10: Agent02 | B10: =Daily_Balancing!B5/5 -> 129.174 | C10: =Daily_Balancing!B5/5 -> 129.174 | D10: =Daily_Balancing!B5/5 -> 129.174 | E10: =Daily_Balancing!B5/5 -> 129.174 | F10: =Daily_Balancing!B5/5 -> 129.174 | G10: =Daily_Balancing!B5/5 -> 129.174 | H10: =SUM(B10:G10) -> 775.044
A11: Agent03 | B11: =Daily_Balancing!B6/5 -> 99.658 | C11: =Daily_Balancing!B6/5 -> 99.658 | D11: =Daily_Balancing!B6/5 -> 99.658 | E11: =Daily_Balancing!B6/5 -> 99.658 | F11: =Daily_Balancing!B6/5 -> 99.658 | G11: =Daily_Balancing!B6/5 -> 99.658 | H11: =SUM(B11:G11) -> 597.948
A12: Agent04 | B12: =Daily_Balancing!B7/5 -> 174.598 | C12: =Daily_Balancing!B7/5 -> 174.598 | D12: =Daily_Balancing!B7/5 -> 174.598 | E12: =Daily_Balancing!B7/5 -> 174.598 | F12: =Daily_Balancing!B7/5 -> 174.598 | G12: =Daily_Balancing!B7/5 -> 174.598 | H12: =SUM(B12:G12) -> 1047.588
A13: Agent05 | B13: =Daily_Balancing!B8/5 -> 105.172 | C13: =Daily_Balancing!B8/5 -> 105.172 | D13: =Daily_Balancing!B8/5 -> 105.172 | E13: =Daily_Balancing!B8/5 -> 105.172 | F13: =Daily_Balancing!B8/5 -> 105.172 | G13: =Daily_Balancing!B8/5 -> 105.172 | H13: =SUM(B13:G13) -> 631.032
A14: Agent06 | B14: =Daily_Balancing!B9/5 -> 101.132 | C14: =Daily_Balancing!B9/5 -> 101.132 | D14: =Daily_Balancing!B9/5 -> 101.132 | E14: =Daily_Balancing!B9/5 -> 101.132 | F14: =Daily_Balancing!B9/5 -> 101.132 | G14: =Daily_Balancing!B9/5 -> 101.132 | H14: =SUM(B14:G14) -> 606.792
A15: Agent07 | B15: =Daily_Balancing!B10/5 -> 128.492 | C15: =Daily_Balancing!B10/5 -> 128.492 | D15: =Daily_Balancing!B10/5 -> 128.492 | E15: =Daily_Balancing!B10/5 -> 128.492 | F15: =Daily_Balancing!B10/5 -> 128.492 | G15: =Daily_Balancing!B10/5 -> 128.492 | H15: =SUM(B15:G15) -> 770.952
A16: Agent08 | B16: =Daily_Balancing!B11/5 -> 128.306 | C16: =Daily_Balancing!B11/5 -> 128.306 | D16: =Daily_Balancing!B11/5 -> 128.306 | E16: =Daily_Balancing!B11/5 -> 128.306 | F16: =Daily_Balancing!B11/5 -> 128.306 | G16: =Daily_Balancing!B11/5 -> 128.306 | H16: =SUM(B16:G16) -> 769.836
A17: Agent09 | B17: =Daily_Balancing!B12/5 -> 125.524 | C17: =Daily_Balancing!B12/5 -> 125.524 | D17: =Daily_Balancing!B12/5 -> 125.524 | E17: =Daily_Balancing!B12/5 -> 125.524 | F17: =Daily_Balancing!B12/5 -> 125.524 | G17: =Daily_Balancing!B12/5 -> 125.524 | H17: =SUM(B17:G17) -> 753.144
A18: Agent10 | B18: =Daily_Balancing!B13/5 -> 175.784 | C18: =Daily_Balancing!B13/5 -> 175.784 | D18: =Daily_Balancing!B13/5 -> 175.784 | E18: =Daily_Balancing!B13/5 -> 175.784 | F18: =Daily_Balancing!B13/5 -> 175.784 | G18: =Daily_Balancing!B13/5 -> 175.784 | H18: =SUM(B18:G18) -> 1054.704
A19: WEEKLY TOTAL | B19: =SUM(B9:B18) -> 1314.134 | C19: =SUM(C9:C18) -> 1314.134 | D19: =SUM(D9:D18) -> 1314.134 | E19: =SUM(E9:E18) -> 1314.134 | F19: =SUM(F9:F18) -> 1314.134 | G19: =SUM(G9:G18) -> 1314.134 | H19: =SUM(H9:H18) -> 7884.804

Sheet Monthly_Balancing
A1: 📆 MONTHLY BALANCING REPORT — April 2026
A3: MTD Savings | B3: MTD Withdrawals | C3: MTD Net | D3: New Accounts | E3: Active Loans
A4: =Daily_Balancing!B14 -> 6570.67 | B4: =Daily_Balancing!C14 -> 0 | C4: =Daily_Balancing!D14 -> 6570.67 | D4: =COUNTIF(Master_Customers!K2:K1000,">="&DATE(YEAR(TODAY()),MONTH(TODAY()),1)) -> 0 | E4: =COUNTIF(Active_Loans!K3:K200,"Approved")+COUNTIF(Active_Loans!K3:K200,"Disbursed") -> 3
A6: 📊 MONTH-BY-MONTH PERFORMANCE TRACKER
A7: Month | B7: Savings (GHC) | C7: Withdrawals (GHC) | D7: Net (GHC) | E7: New Accounts | F7: Active Loans | G7: Interest Income (GHC) | H7: Growth % | I7: Target Met?
A8: Jan | B8: 107824.22 | C8: 38477.45 | D8: 69346.77 | E8: 10 | F8: 13 | G8: 2695.61 | H8: -4.6% | I8: YES
A9: Feb | B9: 133790.85 | C9: 40450.89 | D9: 93339.96 | E9: 15 | F9: 13 | G9: 3344.77 | H9: 6.6% | I9: YES
A10: Mar | B10: 95687.1 | C10: 56036.07 | D10: 39651.03 | E10: 9 | F10: 12 | G10: 2392.18 | H10: -0.7% | I10: NO
A11: Apr | B11: 108714.02 | C11: 54460.14 | D11: 54253.88 | E11: 9 | F11: 7 | G11: 2717.85 | H11: -0.9% | I11: YES
A12: May
A13: Jun
A14: Jul
A15: Aug
A16: Sep
A17: Oct
A18: Nov
A19: Dec
A20: YTD TOTAL | B20: =SUM(B8:B19) -> 446016.19 | C20: =SUM(C8:C19) -> 189424.55 | D20: =SUM(D8:D19) -> 256591.64 | E20: =SUM(E8:E19) -> 43 | F20: =SUM(F8:F19) -> 45 | G20: =SUM(G8:G19) -> 11150.41
A22: 📈 MONTHLY TREND CHART

Sheet Active_Loans
A1: 🏦 SAMICIOUS MICROFINANCE — ACTIVE LOAN REGISTRY
A2: Loan_ID | B2: Account_Number | C2: Customer_Name | D2: Request_Date | E2: Loan_Amount | F2: Purpose | G2: Months | H2: Rate_% | I2: Total_Repayable | J2: Monthly_Installment | K2: Status | L2: Agent | M2: Approved_By | N2: Approval_Date | O2: Disbursement_Date | P2: Next_Payment | Q2: Outstanding_Balance | R2: Amt_Repaid | S2: Months_Paid | T2: Months_Remaining | U2: Health | V2: Notes
A3: LN202604120001 | B3: SAM20240100001 | C3: Kwame Asare | D3: 2026-04-12 | E3: 2000 | F3: Business expansion | G3: 6 | H3: 2.5 | I3: 2300 | J3: 383.33 | K3: Approved | L3: Agent01 | M3: Manager | N3: 2026-04-12 | P3: 2026-05-12 | Q3: 2300 | R3: 0 | S3: 0 | T3: 6 | U3: Good
A4: LN202604120002 | B4: SAM20240200005 | C4: Yaw Darko | D4: 2026-04-12 | E4: 5000 | F4: School fees | G4: 12 | H4: 2.5 | I4: 6500 | J4: 541.67 | K4: Pending | L4: Agent03 | M4: Manager | P4: 2026-05-12 | Q4: 5958.33 | R4: 541.67 | S4: 1 | T4: 11 | U4: Good
A5: LN202604120003 | B5: SAM20240400009 | C5: Kwabena Asante | D5: 2026-04-12 | E5: 8000 | F5: Equipment purchase | G5: 18 | H5: 2.5 | I5: 11600 | J5: 644.44 | K5: Approved | L5: Agent05 | M5: Manager | N5: 2026-04-12 | P5: 2026-05-12 | Q5: 10955.56 | R5: 644.44 | S5: 0 | T5: 18 | U5: Good
A6: LN202604120004 | B6: SAM20240500013 | C6: Kweku Nyarko | D6: 2026-04-12 | E6: 1500 | F6: Medical expenses | G6: 3 | H6: 2.5 | I6: 1612.5 | J6: 537.5 | K6: Disbursed | L6: Agent07 | M6: Manager | N6: 2026-04-12 | O6: 2026-04-12 | P6: 2026-05-12 | Q6: 537.5 | R6: 1075 | S6: 2 | T6: 1 | U6: Good
A7: LN202604120005 | B7: SAM20240600017 | C7: Kwasi Adusei | D7: 2026-04-12 | E7: 3000 | F7: Home renovation | G7: 9 | H7: 2.5 | I7: 3675 | J7: 408.33 | K7: Pending | L7: Agent09 | M7: Manager | P7: 2026-05-12 | Q7: 3675 | R7: 0 | S7: 0 | T7: 9 | U7: Good

Sheet Transactions_Log
A1: 📋 SAMICIOUS MICROFINANCE — TRANSACTIONS LOG
A2: Timestamp | B2: Transaction_ID | C2: Account_Number | D2: Customer_Name | E2: Agent | F2: Type | G2: Amount | H2: Balance_After | I2: Notes | J2: Recorded_By
A3: 2026-03-31 | B3: TXN202603310003 | C3: SAM20240100001 | D3: Kwame Asare | E3: Agent01 | F3: SAVINGS | G3: 319.75 | H3: 819.75 | J3: System
A4: 2026-04-05 | B4: TXN202604050004 | C4: SAM20240100001 | D4: Kwame Asare | E4: Agent01 | F4: WITHDRAWAL | G4: 391.94 | H4: 427.81 | J4: System
A5: 2026-04-04 | B5: TXN202604040005 | C5: SAM20240100001 | D5: Kwame Asare | E5: Agent01 | F5: SAVINGS | G5: 288.87 | H5: 716.68 | J5: System
A6: 2026-03-21 | B6: TXN202603210006 | C6: SAM20240100002 | D6: Ama Mensah | E6: Agent01 | F6: SAVINGS | G6: 472.27 | H6: 1672.27 | J6: System
A7: 2026-03-28 | B7: TXN202603280007 | C7: SAM20240100002 | D7: Ama Mensah | E7: Agent01 | F7: WITHDRAWAL | G7: 375 | H7: 1297.27 | J7: System
A8: 2026-03-25 | B8: TXN202603250008 | C8: SAM20240100002 | D8: Ama Mensah | E8: Agent01 | F8: WITHDRAWAL | G8: 455.9 | H8: 841.37 | J8: System
A9: 2026-04-01 | B9: TXN202604010009 | C9: SAM20240200003 | D9: Kofi Boateng | E9: Agent02 | F9: SAVINGS | G9: 437.67 | H9: 1237.67 | J9: System
A10: 2026-04-06 | B10: TXN202604060010 | C10: SAM20240200003 | D10: Kofi Boateng | E10: Agent02 | F10: WITHDRAWAL | G10: 347.26 | H10: 890.41 | J10: System
A11: 2026-03-16 | B11: TXN202603160011 | C11: SAM20240200003 | D11: Kofi Boateng | E11: Agent02 | F11: SAVINGS | G11: 87.33 | H11: 977.74 | J11: System
A12: 2026-03-21 | B12: TXN202603210012 | C12: SAM20240200004 | D12: Abena Owusu | E12: Agent02 | F12: SAVINGS | G12: 398.51 | H12: 698.51 | J12: System
A13: 2026-03-28 | B13: TXN202603280013 | C13: SAM20240200004 | D13: Abena Owusu | E13: Agent02 | F13: SAVINGS | G13: 69.19 | H13: 767.7 | J13: System
A14: 2026-03-26 | B14: TXN202603260014 | C14: SAM20240200004 | D14: Abena Owusu | E14: Agent02 | F14: WITHDRAWAL | G14: 141.69 | H14: 626.01 | J14: System
... A62: 2026-03-16 | B62: TXN202603160062 | C62: SAM20240600020 | D62: Kwame Baffour | E62: Agent10 | F62: SAVINGS | G62: 345.45 | H62: 961.99 | J62: System

Sheet Master_Customers
A1: Account_Number | B1: First_Name | C1: Last_Name | D1: Full_Name | E1: Ghana_Card | F1: Phone | G1: Address | H1: Occupation | I1: Agent_Assigned | J1: Opening_Balance | K1: Opening_Date | L1: KYC_Status | M1: KYC_Verified_By | N1: KYC_Date | O1: Current_Balance | P1: Total_Savings | Q1: Total_Withdrawals | R1: Active_Loan_Count | S1: Total_Loan_Balance | T1: Status | U1: Last_Transaction | V1: Notes
A2: SAM20240100001 | B2: Kwame | C2: Asare | D2: Kwame Asare | E2: GHA-123456789-0 | F2: 0244123456 | G2: 12 Accra Rd, Accra | H2: Trader | I2: Agent01 | J2: 500 | K2: 2024-01-15 | L2: Verified | M2: Manager | N2: 2024-01-15 | O2: 2436.65 | P2: 1990.4 | Q2: 53.75 | R2: 0 | S2: 0 | T2: Active | U2: 2026-04-12
A3: SAM20240100002 | B3: Ama | C3: Mensah | D3: Ama Mensah | E3: GHA-234567890-1 | F3: 0554234567 | G3: 5 Kumasi Ave, Kumasi | H3: Nurse | I3: Agent01 | J3: 1200 | K3: 2024-01-20 | L3: Verified | M3: Manager | N3: 2024-01-20 | O3: 2024.1 | P3: 970.08 | Q3: 145.98 | R3: 0 | S3: 0 | T3: Active | U3: 2026-04-12
A4: SAM20240200003 | B4: Kofi | C4: Boateng | D4: Kofi Boateng | E4: GHA-345678901-2 | F4: 0244345678 | G4: Plot 7, Tema | H4: Carpenter | I4: Agent02 | J4: 800 | K4: 2024-02-01 | L4: Verified | M4: Manager | N4: 2024-02-01 | O4: 2829.41 | P4: 2262.12 | Q4: 232.71 | R4: 0 | S4: 0 | T4: Active | U4: 2026-04-12
A5: SAM20240200004 | B5: Abena | C5: Owusu | D5: Abena Owusu | E5: GHA-456789012-3 | F5: 0204456789 | G5: 88 Ring Rd, Accra | H5: Seamstress | I5: Agent02 | J5: 300 | K5: 2024-02-10 | L5: Verified | M5: Manager | N5: 2024-02-10 | O5: 2942.01 | P5: 2698.1 | Q5: 56.09 | R5: 0 | S5: 0 | T5: Active | U5: 2026-04-12
A6: SAM20240200005 | B6: Yaw | C6: Darko | D6: Yaw Darko | E6: GHA-567890123-4 | F6: 0553567890 | G6: Osu, Accra | H6: Driver | I6: Agent03 | J6: 2500 | K6: 2024-02-14 | L6: Verified | M6: Manager | N6: 2024-02-14 | O6: 3808.17 | P6: 1381.38 | Q6: 73.21 | R6: 0 | S6: 0 | T6: Active | U6: 2026-04-12
A7: SAM20240300006 | B7: Efua | C7: Kumi | D7: Efua Kumi | E7: GHA-678901234-5 | F7: 0244678901 | G7: Kasoa, Accra | H7: Farmer | I7: Agent03 | J7: 400 | K7: 2024-03-05 | L7: Verified | M7: Manager | N7: 2024-03-05 | O7: 1106.6 | P7: 812.19 | Q7: 105.59 | R7: 0 | S7: 0 | T7: Active | U7: 2026-04-12
A8: SAM20240300007 | B8: Kojo | C8: Amponsah | D8: Kojo Amponsah | E8: GHA-789012345-6 | F8: 0556789012 | G8: Bantama, Kumasi | H8: Mechanic | I8: Agent04 | J8: 1500 | K8: 2024-03-12 | L8: Verified | M8: Manager | N8: 2024-03-12 | O8: 1701.52 | P8: 274.3 | Q8: 72.78 | R8: 0 | S8: 0 | T8: Active | U8: 2026-04-12
A9: SAM20240300008 | B9: Akosua | C9: Frimpong | D9: Akosua Frimpong | E9: GHA-890123456-7 | F9: 0243890123 | G9: Nkawkaw, E/R | H9: Teacher | I9: Agent04 | J9: 950 | K9: 2024-03-20 | L9: Verified | M9: Manager | N9: 2024-03-20 | O9: 2739.85 | P9: 2019.68 | Q9: 229.83 | R9: 0 | S9: 0 | T9: Active | U9: 2026-04-12
A10: SAM20240400009 | B10: Kwabena | C10: Asante | D10: Kwabena Asante | E10: GHA-901234567-8 | F10: 0244901234 | G10: Sunyani, B/A | H10: Pharmacist | I10: Agent05 | J10: 3000 | K10: 2024-04-01 | L10: Verified | M10: Manager | N10: 2024-04-01 | O10: 3507.75 | P10: 817.23 | Q10: 309.48 | R10: 0 | S10: 0 | T10: Active | U10: 2026-04-12
A11: SAM20240400010 | B11: Adjoa | C11: Tetteh | D11: Adjoa Tetteh | E11: GHA-012345678-9 | F11: 0541012345 | G11: Dansoman, Accra | H11: Caterer | I11: Agent05 | J11: 750 | K11: 2024-04-08 | L11: Verified | M11: Manager | N11: 2024-04-08 | O11: 3164.79 | P11: 2466.41 | Q11: 51.62 | R11: 0 | S11: 0 | T11: Active | U11: 2026-04-12
A12: SAM20240400011 | B12: Nana | C12: Osei | D12: Nana Osei | E12: GHA-111222333-0 | F12: 0244111222 | G12: Madina, Accra | H12: Electrician | I12: Agent06 | J12: 1100 | K12: 2024-04-15 | L12: Verified | M12: Manager | N12: 2024-04-15 | O12: 3234.02 | P12: 2456.29 | Q12: 322.27 | R12: 0 | S12: 0 | T12: Active | U12: 2026-04-12
A13: SAM20240400012 | B13: Adwoa | C13: Amoah | D13: Adwoa Amoah | E13: GHA-222333444-1 | F13: 0504222333 | G13: Teshie, Accra | H13: Hairdresser | I13: Agent06 | J13: 600 | K13: 2024-04-22 | L13: Verified | M13: Manager | N13: 2024-04-22 | O13: 1673.16 | P13: 1152.7 | Q13: 79.54 | R13: 0 | S13: 0 | T13: Active | U13: 2026-04-12
... A21: SAM20240600020 | B21: Kwame | C21: Baffour | D21: Kwame Baffour | E21: GHA-000111222-9 | F21: 0550000111 | G21: Wa, U/W | H21: Farmer | I21: Agent10 | J21: 700 | K21: 2024-06-20 | L21: Verified | M21: Manager | N21: 2024-06-20 | O21: 3129.99 | P21: 2612.78 | Q21: 182.79 | R21: 0 | S21: 0 | T21: Active | U21: 2026-04-12

Sheet System_Config
A1: ⚙️ SAMICIOUS MICROFINANCE — SYSTEM CONFIGURATION
A3: Company Name | B3: SAMICIOUS MICROFINANCE
A4: Currency | B4: GHC
A5: Default Interest Rate | B5: 2.5% per month
A6: Maximum Loan Amount | B6: 50000
A7: Minimum Loan Amount | B7: 100
A8: Number of Agents | B8: 10
A9: System Version | B9: 1.0.0
A10: Setup Date | B10: 2026-04-12
A11: Manager Password | B11: SAM@Manager2026
A12: Total Customers | B12: 20

Sheet Audit_Log
A1: 🔒 AUDIT LOG — All System Actions
A2: Timestamp | B2: User | C2: Action | D2: Details
A3: 2026-04-12 22:10:54.781658 | B3: Manager | C3: SYSTEM_INIT | D3: SAMICIOUS workbook initialized
A4: 2026-04-12 22:10:54.781667 | B4: System | C4: SAMPLE_DATA | D4: 20 sample customers loaded
A5: 2026-04-12 22:10:54.781670 | B5: Manager | C5: CONFIG_SET | D5: Interest rate: 2.5%, Max loan: GHC 50,000

Sheet VBA_Macros
A1: 💻 VBA MACROS — Press Alt+F11, Insert > Module, paste all code below
A2: HOW TO ENABLE MACROS: 1) Open VBA Editor (Alt+F11) 2) Insert > Module 3) Paste all code from the lines below 4) Save as .xlsm 5) Enable macros when prompted on open
A5: ' ═══════════════════════════════════════════════════════════════════════════
A6: ' SAMICIOUS MICROFINANCE - Complete VBA Module
A7: ' Copy all code below into the VBA Editor (Alt+F11) → Insert → Module
A8: ' ═══════════════════════════════════════════════════════════════════════════
A10: ' ─── MODULE 1: DATABASE OPERATIONS ─────────────────────────────────────────
A12: Function GetNextAccountSeq(yearMonth As String) As Long
A13: Dim masterWS As Worksheet
A14: Set masterWS = ThisWorkbook.Sheets("Master_Customers")
A15: Dim lastRow As Long
A16: lastRow = masterWS.Cells(Rows.Count, 1).End(xlUp).Row
... A507: ' End Sub
